Workbook

Sheet COS coding
G1: id | H1: contributors | I1: date_entered | J1: date_updated | K1: notes_coder | L1: notes_validation | M1: ref_original | N1: doi_original | O1: study_original | R1: ref_replication | S1: doi_replication | T1: osf_link | U1: study_replication | Y1: exclusion | Z1: discipline | AA1: effect | AB1: tags | AC1: description | AD1: claim_text_orig | AE1: claim_text_orig_page | AF1: n_original | AG1: es_orig_value | AH1: es_orig_estype | AJ1: pval_value_o | AK1: pval_type_o | AL1: pval_tails_o | AO1: n_replication | AP1: es_rep_value | AQ1: es_rep_estype | AS1: pval_value_r | AT1: pval_type_r | AU1: pval_tails_r
A2: rowid | B2: status | C2: approach | D2: coder_1 | E2: coder_2 | F2: entry | G2: id | H2: contributors | I2: date_entered | J2: date_updated | K2: notes_coder | L2: notes_validation | M2: ref_o | N2: doi_o | O2: study_o | P2: file_o | Q2: link_o | R2: ref_r | S2: doi_r | T2: url_r | U2: study_r | V2: file_r | W2: label_r | X2: link_r | Y2: exclusion | Z2: discipline | AA2: effect | AB2: tags | AC2: description | AD2: claim_text_o | AE2: claim_page_o | AF2: n_o | AG2: es_value_o | AH2: es_type_o | AI2: es_repr_o | AJ2: pval_value_o | AK2: pval_type_o | AL2: pval_tails_o | AM2: nested_o | AN2: prereg_o | AO2: n_r | AP2: es_value_r | AQ2: es_type_r | AR2: es_repr_r | AS2: pval_value_r | AT2: pval_type_r | AU2: pval_tails_r | AV2: nested_r | AW2: prereg_r | AX2: closeness_r | AY2: outcome | AZ2: outcome_quote | BA2: out_quote_source | BB2: fred_id | BC2: feedback_for_coder | BD2: validator
A3: ENSURE THIS STAYS UNCHANGED AND ALIGNED! | B3: - assigned: the entry has been assigned to a coder - help needed: there is an unresolved conflict - validated - chosen: the entry has been validated and marked as the one to remain in the final dataset - validated - discarded: the entry has been used for validation and is now inferior or redundant to the chosen entry for the same finding - validated - FReD but not COS: applies to replication studies that do not contain statistical test (e.g., replications in the qualitative humanities) | F3: for data matching. DO NOT EDIT - keep blank for new rows | G3: Sample id. DO NOT CHANGE. If you add samples, copy and add _b, _c etc | H3: *Add* your name when you edit the row | I3: (dd/mm/yyyy) | J3: (dd/mm/yyyy) | K3: general data entry notes, e.g., re access issues or study selection | L3: only used by core team | M3: Copy APA style from Google Scholar (or similar), without DOI | N3: without URL prefix, so starting with 10.xx | O3: Number of study in paper, e.g., 1 or 2A | P3: file-name for O PDF - only edit if DOI is missing | R3: Copy APA style from Google Scholar (or similar), without DOI | S3: without URL prefix, so starting with 10.xx | T3: Link to R results - only when DOI missing or for aggregate report | U3: Number of study in paper, e.g., 1 or 2A | V3: file-name for R PDF - only edit if DOI is missing | W3: How does R identify as replication in title or abstract? Usually "replication" but report different wording if used | Y3: Reason for study exclusion (usually only if R is not a replication) | Z3: Which broad field does the finding come from - e.g., Social Psychology or Labor Economics | AA3: x | AB3: tags to increase findability - e.g. keywords from abstract | AC3: Description of the effect under investigation (e.g., x is associated with y, x leads to y), possibly a part of the original publication's title (abstract claim) | AD3: The authors’ key statistical result and its interpretation | AE3: Page number(s) for claim_text_o | AF3: O's sample size [used for the critical test, i.e., after exclusion criteria have been applied], must contain only one value and must not contain text | AG3: original effect size value, must contain only one value and must not contain text | AH3: original effect size type (e.g., d, r, r², etasq) | AI3: Reproducible origin/calculation method for es_value_o ("p. xx" when reported, link when available online - e.g., OSF, otherwise calculation process) | AJ3: The reported p-value associated with the original finding, must contain only one value and must not contain text | AK3: How is p-val reported? "=" (e) / "<" (l) / ">" (g) or combined (le, ge)? for example "p <= .05" should be coded as "le" | AL3: How many tails associated with the p-value, taking on values of one, two, or unknown one: 1 two: 2 unknown / not specified: NA missing: not coded | AM3: Is pval based on a test that accounts for dependence between observations (e.g., multilevel, repeated measures) | AN3: Link to preregistration of O (only search for "regist") | AO3: R's sample size [used for the critical test, i.e., after exclusion criteria have been applied], must contain only one value and must not contain text | AP3: replication effect size value, must contain only one value and must not contain text | AQ3: replication effect size type | AR3: Reproducible origin/calculation method for es_value_r ("p. xx" when reported, otherwise calculation process) | AS3: The reported p-value associated with the replication finding, must contain only one value and must not contain text | AT3: How is p-val reported? "=" (e) / "<" (l) / ">" (g) or combined (le, ge)? for example "p <= .05" should be coded as "le" | AU3: How many tails associated with the p-value, taking on values of one, two, or unknown one: 1 two: 2 unknown: NA missing: not coded | AV3: Is pval based on a test that accounts for dependence between observations (e.g., multilevel, repeated measures) | AW3: Link to preregistration of R (only search for "regist") | AX3: NA: unknown 1: internal: all central features are highly similar AND conducted by at least one of the original researchers 2: close/direct: central features are highly similar AND none of the original authors is involved 3: conceptual/constructive/extension: central features are different, theoretically relevant aspects are the same; authorship overlap is irrelevant | AY3: One of successful failed mixed uninformative statistically successful but flawed | AZ3: outcome statement by replication authors | BA3: source of the quote | BD3: name of the person who validated the entry
A4: 4 | B4: validated - discarded | C4: double | F4: 2zgf9_1 | G4: 2zgf9 | H4: Kateri McRae, Daniel Lumian, Mallory C. Kidwell, Johanna Cohoon, Lilian Hummer | I4: 1.1.2023 | J4: 45641 | K4: coding tasks 2zgf9_1, bth36_1, and 7vgkq_1 are similar; the partial-eta squared reported in the replication paper of 0.226 is different from the value in OSF registries of 0.313, hence requires validation; Psychological science has not been listed as one of the disciplines, hence categorizing them as political science | M4: Cunningham, W. A., Van Bavel, J. J., & Johnsen, I. R. (2008). Affective flexibility: evaluative processing goals shape amygdala activity. Psychological Science, 19(2), 152-160. | N4: 10.1111/j.1467-9280.2008.02061.x | O4: 1 | P4: 10.1111--j.1467-9280.2008.02061.x.pdf | Q4: {=if(iserror(MATCH(V4, 'File Links'!C:C, 0)), "N/A", HYPERLINK(INDEX('File Links'!B:B, MATCH(P4, 'File Links'!C:C, 0))))} -> https://drive.google.com/file/d/1HsW-lUSPFaIpISHQ1bNk6CKMtH3z9rau/view?usp=drivesdk | R4: McRae, K., & Lumian, D. S. (2023, September 28). Replication of WA Cunningham, JJ Van Bavel, IR Johnsen (2008, PS 19 (2)). https://doi.org/10.17605/OSF.IO/2ZGF9 | S4: 10.17605/OSF.IO/2ZGF9 | U4: 1 | V4: 10.17605--osf.io--2zgf9.pdf | W4: replication attempt | X4: {=if(iserror(MATCH(V4, 'File Links'!C:C, 0)), "N/A", HYPERLINK(INDEX('File Links'!B:B, MATCH(V4, 'File Links'!C:C, 0))))} -> https://drive.google.com/file/d/15dLELTosbF1NWFYI0UOSPLIC70dnGG5S/view?usp=drivesdk | Z4: Political Science | AB4: affective flexibility, amygdala, valence, stimulus | AC4: interaction between scanning condition (positive or negative) and stimulus valence | AD4: "results were consistent with the idea of affective flexibility. There was a significant interaction between scanning condition (positive or negative) and stimulus valence (postscan ratings of positivity or negativity), F(1, 11) = 9.67, p < .01, prep = .95" | AE4: p. 7 | AF4: 12 | AG4: F(1, 11) = 9.67 | AH4: test statistic | AI4: p. 7 | AJ4: 0.01 | AK4: l (<) | AL4: 2 (two) | AM4: no | AN4: NA | AO4: 39 | AP4: 0.226 | AQ4: etasq | AR4: p. 6 | AS4: 0.02 | AT4: l (<) | AU4: 2 (two) | AV4: yes | AW4: https://doi.org/10.17605/OSF.IO/2ZGF9 | AX4: 2 - close | AY4: =IFERROR(__xludf.DUMMYFUNCTION("vlookup(BB4,importrange(""https://docs.google.com/spreadsheets/d/1d2vevQ_7D_v35q4wCQ4RpQ_IPoTwEMB9Yp6ymwlPqew/edit?gid=984458430#gid=984458430"", ""'replication success'!A:K""), 11, FAlSE)"),"#N/A") -> #N/A | AZ4: =IFERROR(__xludf.DUMMYFUNCTION("vlookup(BB4,importrange(""https://docs.google.com/spreadsheets/d/1d2vevQ_7D_v35q4wCQ4RpQ_IPoTwEMB9Yp6ymwlPqew/edit?gid=984458430#gid=984458430"", ""'replication success'!A:M""), 12, FAlSE)"),"#N/A") -> #N/A | BA4: =IFERROR(__xludf.DUMMYFUNCTION("vlookup(BB4,importrange(""https://docs.google.com/spreadsheets/d/1d2vevQ_7D_v35q4wCQ4RpQ_IPoTwEMB9Yp6ymwlPqew/edit?gid=984458430#gid=984458430"", ""'replication success'!A:M""), 13, FAlSE)"),"#N/A") -> #N/A | BB4: =IFERROR(__xludf.DUMMYFUNCTION("REGEXREPLACE(G4, ""_[a-z]{1,2}$"", """")"),"2zgf9") -> 2zgf9 | BD4: LR
A5: 5 | B5: validated - discarded | C5: double | D5: Maureen | F5: 2zgf9_1 | G5: 2zgf9 | H5: Kateri McRae, Daniel Lumian, Mallory C. Kidwell, Johanna Cohoon, Lilian Hummer, Jyoti Bhogal | I5: 45108 | J5: 45644 | M5: Cunningham, W. A., Van Bavel, J. J., & Johnsen, I. R. (2008). Affective flexibility: evaluative processing goals shape amygdala activity. Psychological Science, 19(2), 152-160. | N5: 10.1111/j.1467-9280.2008.02061.x | O5: 1 | P5: 10.1111--j.1467-9280.2008.02061.x.pdf | Q5: {=if(iserror(MATCH(V5, 'File Links'!C:C, 0)), "N/A", HYPERLINK(INDEX('File Links'!B:B, MATCH(P5, 'File Links'!C:C, 0))))} -> https://drive.google.com/file/d/1HsW-lUSPFaIpISHQ1bNk6CKMtH3z9rau/view?usp=drivesdk | R5: McRae, K., & Lumian, D. S. (2023, September 28). Replication of WA Cunningham, JJ Van Bavel, IR Johnsen (2008, PS 19 (2)). https://doi.org/10.17605/OSF.IO/2ZGF9 | S5: 10.17605/OSF.IO/2ZGF9 | V5: 10.17605--osf.io--2zgf9.pdf | X5: {=if(iserror(MATCH(V5, 'File Links'!C:C, 0)), "N/A", HYPERLINK(INDEX('File Links'!B:B, MATCH(V5, 'File Links'!C:C, 0))))} -> https://drive.google.com/file/d/15dLELTosbF1NWFYI0UOSPLIC70dnGG5S/view?usp=drivesdk | Y5: no replication report available but only a post completion registration | Z5: Cognitive Psychology | AB5: affective flexibility, amygdala, positive names, negative names | AF5: 12 | AN5: NA | AP5: 0.313 | AS5: unavailable | AX5: 3 - conceptual | AY5: =IFERROR(__xludf.DUMMYFUNCTION("vlookup(BB5,importrange(""https://docs.google.com/spreadsheets/d/1d2vevQ_7D_v35q4wCQ4RpQ_IPoTwEMB9Yp6ymwlPqew/edit?gid=984458430#gid=984458430"", ""'replication success'!A:K""), 11, FAlSE)"),"#N/A") -> #N/A | AZ5: =IFERROR(__xludf.DUMMYFUNCTION("vlookup(BB5,importrange(""https://docs.google.com/spreadsheets/d/1d2vevQ_7D_v35q4wCQ4RpQ_IPoTwEMB9Yp6ymwlPqew/edit?gid=984458430#gid=984458430"", ""'replication success'!A:M""), 12, FAlSE)"),"#N/A") -> #N/A | BA5: =IFERROR(__xludf.DUMMYFUNCTION("vlookup(BB5,importrange(""https://docs.google.com/spreadsheets/d/1d2vevQ_7D_v35q4wCQ4RpQ_IPoTwEMB9Yp6ymwlPqew/edit?gid=984458430#gid=984458430"", ""'replication success'!A:M""), 13, FAlSE)"),"#N/A") -> #N/A | BB5: =IFERROR(__xludf.DUMMYFUNCTION("REGEXREPLACE(G5, ""_[a-z]{1,2}$"", """")"),"2zgf9") -> 2zgf9 | BD5: LR
A6: 6 | B6: validated - chosen | C6: double | D6: Nikita | F6: 39xuw_1 | G6: 39xuw | H6: Nikita | I6: 45638 | J6: 45680 | K6: 1. Values for the REPLICATION statistical inferences were taken from Files uploaded to OSF by a link: https://osf.io/39xuw/files/osfstorage. I merged them in the corresponding PDF | L6: corrected N from 150 to 137 | M6: Schaffer, J., & Knobe, J. (2012). Contrastive knowledge surveyed. Noûs, 46(4), 675-708. | N6: 10.1111/j.1468-0068.2010.00795.x | O6: 1 | P6: 10.1111--j.1468-0068.2010.00795.x.pdf | Q6: {=if(iserror(MATCH(V6, 'File Links'!C:C, 0)), "N/A", HYPERLINK(INDEX('File Links'!B:B, MATCH(P6, 'File Links'!C:C, 0))))} -> https://drive.google.com/file/d/1O4mjB0-ZSujMTJYtaAoIsXTPuhxgEF-0/view?usp=drivesdk | R6: Wilkenfeld, D. A., & Hernández-Conde, J. V. (2017, September 12). Schaffer and Knobe Replication. https://doi.org/10.17605/OSF.IO/39XUW | S6: osf.io/wru8c | U6: 1 | V6: osf.io--wru8c.pdf | W6: Replication | X6: {=if(iserror(MATCH(V6, 'File Links'!C:C, 0)), "N/A", HYPERLINK(INDEX('File Links'!B:B, MATCH(V6, 'File Links'!C:C, 0))))} -> https://drive.google.com/file/d/1Oux4UBwSd26986fxRHjyI5XNtU-07DOs/view?usp=drivesdk | Z6: Experimental Philosophy | AA6: Contrast sensitivity of knowledge ascription (contrastivism) | AB6: Contrastivism, knowledge, knowledge ascription, "rather than" clause, contrast, context | AC6: The two conditions of the experiment involve ascribing knowledge of the very same proposition ("rather than" clause) and they differ only in that they pick out two different contrasts to that proposition: subject or object. | AD6: "Participants in the thief contrast condition tended to agree with the knowledge ascription they received (mean rating: 4.6), while participants in the jewel contrast condition tended to disagree with the knowledge ascription they received (mean rating: 3.1)." | AE6: 16 | AF6: 100 | AG6: t(98) = 3.4 | AH6: test statistic | AI6: p.31 | AJ6: 0.001 | AK6: e (=) | AL6: 2 (two) | AM6: no | AN6: NA | AO6: 137 | AP6: 0.584 | AQ6: d | AR6: p.2 of https://osf.io/k2cna | AS6: 0.001 | AT6: l (<) | AU6: 2 (two) | AV6: no | AW6: https://osf.io/39xuw | AX6: 2 - close | AY6: =IFERROR(__xludf.DUMMYFUNCTION("vlookup(BB6,importrange(""https://docs.google.com/spreadsheets/d/1d2vevQ_7D_v35q4wCQ4RpQ_IPoTwEMB9Yp6ymwlPqew/edit?gid=984458430#gid=984458430"", ""'replication success'!A:K""), 11, FAlSE)"),"successful") -> successful | AZ6: =IFERROR(__xludf.DUMMYFUNCTION("vlookup(BB6,importrange(""https://docs.google.com/spreadsheets/d/1d2vevQ_7D_v35q4wCQ4RpQ_IPoTwEMB9Yp6ymwlPqew/edit?gid=984458430#gid=984458430"", ""'replication success'!A:M""), 12, FAlSE)"),"Success assessment:(Did you succeed in replicating the original result? If applicable, does the original teamagree with you?)Yes on both counts.") -> Success assessment:(Did you succeed in replicating the original result? If applicable, does the original teamagree with you?)Yes on both counts. | BA6: =IFERROR(__xludf.DUMMYFUNCTION("vlookup(BB6,importrange(""https://docs.google.com/spreadsheets/d/1d2vevQ_7D_v35q4wCQ4RpQ_IPoTwEMB9Yp6ymwlPqew/edit?gid=984458430#gid=984458430"", ""'replication success'!A:M""), 13, FAlSE)"),"pg.3 in https://osf.io/k2cna") -> pg.3 in https://osf.io/k2cna | BB6: =IFERROR(__xludf.DUMMYFUNCTION("REGEXREPLACE(G6, ""_[a-z]{1,2}$"", """")"),"39xuw") -> 39xuw | BD6: LR
A7: 7 | B7: validated - discarded | C7: double | D7: Husnain | F7: 39xuw_1 | G7: 39xuw | H7: Husnain | I7: 45641 | J7: 45680 | K7: 1. The tags are not given explicitly so I have inferred from the introduction of orignal paper. 2. The effect size is not reprted in the orignal study while replication has reported it's own and the effect size of replication study the infered effect size is cohen's d 0.687. 3. The replication paper has reported cohen's d for the replicated study without the p value, however, it presented p valur for test stastic without the value of t. | M7: Schaffer, J., & Knobe, J. (2012). Contrastive knowledge surveyed. Noûs, 46(4), 675-708. | N7: 10.1111/j.1468-0068.2010.00795.x | P7: 10.1111--j.1468-0068.2010.00795.x.pdf | Q7: {=if(iserror(MATCH(V7, 'File Links'!C:C, 0)), "N/A", HYPERLINK(INDEX('File Links'!B:B, MATCH(P7, 'File Links'!C:C, 0))))} -> https://drive.google.com/file/d/1O4mjB0-ZSujMTJYtaAoIsXTPuhxgEF-0/view?usp=drivesdk | R7: Wilkenfeld, D. A., & Hernández-Conde, J. V. (2017, September 12). Schaffer and Knobe Replication. https://doi.org/10.17605/OSF.IO/39XUW | S7: osf.io/wru8c | V7: osf.io--wru8c.pdf | W7: Replication | X7: {=if(iserror(MATCH(V7, 'File Links'!C:C, 0)), "N/A", HYPERLINK(INDEX('File Links'!B:B, MATCH(V7, 'File Links'!C:C, 0))))} -> https://drive.google.com/file/d/1Oux4UBwSd26986fxRHjyI5XNtU-07DOs/view?usp=drivesdk | Z7: Experimental Philosophy | AA7: contrastive knowledge | AB7: contrastive model, invariantist models, contextualist models, knowlege acriptions, conversational context | AC7: Thief contrast codition tend to agree more compared to jewel contrast condition with knowledge ascription | AD7: "N = 100 people spending time in the Canberra Centre Mall in Canberra, Australia, t (98) = 3.4, p = .001." | AE7: p. 16 | AF7: 100 | AG7: 3.4 | AH7: test statistic | AI7: p. 16, 31 | AJ7: 0.001 | AK7: e (=) | AL7: NA (not reported) | AM7: no | AN7: NA | AO7: 137 | AP7: 0.584 | AQ7: d | AR7: p. 1,2 | AW7: https://osf.io/39xuw | AX7: 2 - close | AY7: =IFERROR(__xludf.DUMMYFUNCTION("vlookup(BB7,importrange(""https://docs.google.com/spreadsheets/d/1d2vevQ_7D_v35q4wCQ4RpQ_IPoTwEMB9Yp6ymwlPqew/edit?gid=984458430#gid=984458430"", ""'replication success'!A:K""), 11, FAlSE)"),"successful") -> successful | AZ7: =IFERROR(__xludf.DUMMYFUNCTION("vlookup(BB7,importrange(""https://docs.google.com/spreadsheets/d/1d2vevQ_7D_v35q4wCQ4RpQ_IPoTwEMB9Yp6ymwlPqew/edit?gid=984458430#gid=984458430"", ""'replication success'!A:M""), 12, FAlSE)"),"Success assessment:(Did you succeed in replicating the original result? If applicable, does the original teamagree with you?)Yes on both counts.") -> Success assessment:(Did you succeed in replicating the original result? If applicable, does the original teamagree with you?)Yes on both counts. | BA7: =IFERROR(__xludf.DUMMYFUNCTION("vlookup(BB7,importrange(""https://docs.google.com/spreadsheets/d/1d2vevQ_7D_v35q4wCQ4RpQ_IPoTwEMB9Yp6ymwlPqew/edit?gid=984458430#gid=984458430"", ""'replication success'!A:M""), 13, FAlSE)"),"pg.3 in https://osf.io/k2cna") -> pg.3 in https://osf.io/k2cna | BB7: =IFERROR(__xludf.DUMMYFUNCTION("REGEXREPLACE(G7, ""_[a-z]{1,2}$"", """")"),"39xuw") -> 39xuw | BD7: LR
A8: 8 | B8: validated - discarded | C8: double | D8: Maureen | F8: 7vgkq_1 | G8: 7vgkq | H8: Kateri McRae, Mallory C. Kidwell, Johanna Cohoon, Daniel Lumian, Lilian Hummer, TESS-Experiments | I8: 1.1.2023 | J8: 45641 | K8: coding tasks 2zgf9_1, bth36_1, and 7vgkq_1 are similar; the partial-eta squared reported in the replication paper of 0.226 is different from the value in OSF registries of 0.313, hence requires validation; Psychological science has not been listed as one of the disciplines, hence categorizing them as political science | M8: Cunningham, W. A., Van Bavel, J. J., & Johnsen, I. R. (2008). Affective flexibility: evaluative processing goals shape amygdala activity. Psychological Science, 19(2), 152-160. | N8: 10.1111/j.1467-9280.2008.02061.x | O8: 1 | P8: 10.1111--j.1467-9280.2008.02061.x.pdf | Q8: {=if(iserror(MATCH(V8, 'File Links'!C:C, 0)), "N/A", HYPERLINK(INDEX('File Links'!B:B, MATCH(P8, 'File Links'!C:C, 0))))} -> https://drive.google.com/file/d/1HsW-lUSPFaIpISHQ1bNk6CKMtH3z9rau/view?usp=drivesdk | R8: McRae, K., Lumian, D. S., & T. (2023, September 28). Materials. https://doi.org/10.17605/OSF.IO/7VGKQ | S8: osf.io/x4v53 | V8: =hyperlink(vlookup(lower(S8),'File Links'!E:F, 2, FALSE), SUBSTITUTE(lower(S8), "/", "--") & ".pdf") -> osf.io--x4v53.pdf | W8: replication attempt | X8: {=if(iserror(MATCH(V8, 'File Links'!C:C, 0)), "N/A", HYPERLINK(INDEX('File Links'!B:B, MATCH(V8, 'File Links'!C:C, 0))))} -> https://drive.google.com/file/d/101OwdNXwjKk-CSJMDDNBxSMU_jnE0JGh/view?usp=drivesdk | Z8: Political Science | AB8: affective flexibility, amygdala, valence, stimulus | AE8: p. 7 | AF8: 12 | AG8: 9.67 | AH8: test statistic | AI8: p. 7 | AJ8: 0.01 | AK8: l (<) | AL8: 2 (two) | AM8: no | AN8: NA | AO8: 39 | AP8: 0.226 | AQ8: etasq | AR8: p. 6 | AS8: 0.02 | AT8: l (<) | AU8: 2 (two) | AV8: yes | AW8: https://doi.org/10.17605/OSF.IO/7VGKQ | AX8: 2 - close | AY8: =IFERROR(__xludf.DUMMYFUNCTION("vlookup(BB8,importrange(""https://docs.google.com/spreadsheets/d/1d2vevQ_7D_v35q4wCQ4RpQ_IPoTwEMB9Yp6ymwlPqew/edit?gid=984458430#gid=984458430"", ""'replication success'!A:K""), 11, FAlSE)"),"#N/A") -> #N/A | AZ8: =IFERROR(__xludf.DUMMYFUNCTION("vlookup(BB8,importrange(""https://docs.google.com/spreadsheets/d/1d2vevQ_7D_v35q4wCQ4RpQ_IPoTwEMB9Yp6ymwlPqew/edit?gid=984458430#gid=984458430"", ""'replication success'!A:M""), 12, FAlSE)"),"#N/A") -> #N/A | BA8: =IFERROR(__xludf.DUMMYFUNCTION("vlookup(BB8,importrange(""https://docs.google.com/spreadsheets/d/1d2vevQ_7D_v35q4wCQ4RpQ_IPoTwEMB9Yp6ymwlPqew/edit?gid=984458430#gid=984458430"", ""'replication success'!A:M""), 13, FAlSE)"),"#N/A") -> #N/A | BB8: =IFERROR(__xludf.DUMMYFUNCTION("REGEXREPLACE(G8, ""_[a-z]{1,2}$"", """")"),"7vgkq") -> 7vgkq | BD8: LR
A9: 9 | B9: validated - discarded | C9: double | D9: Jyoti | F9: 7vgkq_1 | G9: 7vgkq | H9: Kateri McRae, Mallory C. Kidwell, Johanna Cohoon, Daniel Lumian, Lilian Hummer, TESS-Experiments, Jyoti Bhogal | I9: 45170 | J9: 45644 | M9: Cunningham, W. A., Van Bavel, J. J., & Johnsen, I. R. (2008). Affective flexibility: evaluative processing goals shape amygdala activity. Psychological Science, 19(2), 152-160. | N9: 10.1111/j.1467-9280.2008.02061.x | O9: 1 | P9: 10.1111--j.1467-9280.2008.02061.x.pdf | Q9: NA | R9: McRae, K., Lumian, D. S., & T. (2023, September 28). Materials. https://doi.org/10.17605/OSF.IO/7VGKQ | S9: 10.17605/OSF.IO/7VGKQ | V9: 10.17605--osf.io--7vgkq.pdf | X9: {=if(iserror(MATCH(V9, 'File Links'!C:C, 0)), "N/A", HYPERLINK(INDEX('File Links'!B:B, MATCH(V9, 'File Links'!C:C, 0))))} -> N/A | Y9: no replication report available but only a post completion registration | Z9: Cognitive Psychology | AB9: affective flexibility, amygdala, positive names, negative names | AN9: NA | AP9: 0.313 | AS9: unavailable | AY9: =IFERROR(__xludf.DUMMYFUNCTION("vlookup(BB9,importrange(""https://docs.google.com/spreadsheets/d/1d2vevQ_7D_v35q4wCQ4RpQ_IPoTwEMB9Yp6ymwlPqew/edit?gid=984458430#gid=984458430"", ""'replication success'!A:K""), 11, FAlSE)"),"#N/A") -> #N/A | AZ9: =IFERROR(__xludf.DUMMYFUNCTION("vlookup(BB9,importrange(""https://docs.google.com/spreadsheets/d/1d2vevQ_7D_v35q4wCQ4RpQ_IPoTwEMB9Yp6ymwlPqew/edit?gid=984458430#gid=984458430"", ""'replication success'!A:M""), 12, FAlSE)"),"#N/A") -> #N/A | BA9: =IFERROR(__xludf.DUMMYFUNCTION("vlookup(BB9,importrange(""https://docs.google.com/spreadsheets/d/1d2vevQ_7D_v35q4wCQ4RpQ_IPoTwEMB9Yp6ymwlPqew/edit?gid=984458430#gid=984458430"", ""'replication success'!A:M""), 13, FAlSE)"),"#N/A") -> #N/A | BB9: =IFERROR(__xludf.DUMMYFUNCTION("REGEXREPLACE(G9, ""_[a-z]{1,2}$"", """")"),"7vgkq") -> 7vgkq | BD9: LR
A10: 10 | B10: validated - discarded | C10: double | D10: Nikolay | F10: acykd_1 | G10: acykd | H10: Nikolay Petrov | I10: 45639 | K10: original sample size is 42, but 1 was excluded afterwards (p. 137) | L10: - Please type "NA" if you could not find "regis" in the manuscript. - Good catch with the N = 41! - This is the preregistration: https://osf.io/8urxv It is linked at the top of the entry | M10: Mussweiler, T., & Englich, B. (2005). Subliminal anchoring: Judgmental consequences and underlying mechanisms. Organizational Behavior and Human Decision Processes, 98(2), 133-143. | N10: 10.1016/j.obhdp.2004.12.002 | O10: 2 | P10: =hyperlink(vlookup(lower(N10),'File Links'!A:B, 2, FALSE), SUBSTITUTE(lower(N10), "/", "--") & ".pdf") -> 10.1016--j.obhdp.2004.12.002.pdf | Q10: {=if(iserror(MATCH(V10, 'File Links'!C:C, 0)), "N/A", HYPERLINK(INDEX('File Links'!B:B, MATCH(P10, 'File Links'!C:C, 0))))} -> https://drive.google.com/file/d/1CZ8RmInPe2eqHwf-p8tl0IQxpn8_H_C5/view?usp=drivesdk | R10: Röseler, L., Schütz, A., Burlakovas, E., Dück, M., Fels, S., Janiczek, S., … Seida, C. (2022, September 15). Replication Mussweiler & Englich, 2005, Study 2. https://doi.org/10.17605/OSF.IO/ACYKD | S10: 10.1016/j.jesp.2020.104066 | V10: =hyperlink(vlookup(lower(S10),'File Links'!E:F, 2, FALSE), SUBSTITUTE(lower(S10), "/", "--") & ".pdf") -> 10.1016--j.jesp.2020.104066.pdf | W10: replication | X10: {=if(iserror(MATCH(V10, 'File Links'!C:C, 0)), "N/A", HYPERLINK(INDEX('File Links'!B:B, MATCH(V10, 'File Links'!C:C, 0))))} -> https://drive.google.com/file/d/1Q7xa-u3DEssueb6fBYD39BjDPub6xcHR/view?usp=drivesdk | Z10: Judgment and Decision Making | AA10: subliminal anchoring | AB10: anchoring, subliminal priming, judgment bias, decision-making | AC10: estimates for numeric judgments are assimilated toward anchor values, even when these anchors are presented subliminally and outside of conscious awareness | AD10: Participants who were presented with the high anchor value estimated the car price to be higher (M = 21,219 Euro) than those presented with the low anchor value (M = 17,150 Euro), t(39) = 2.02, p < .05, r = .31. | AE10: 137 | AF10: 41 | AG10: 0.31 | AH10: r | AI10: p. 137 | AJ10: 0.05 | AK10: l (<) | AL10: NA (not reported) | AM10: no | AN10: NA | AO10: 165 | AP10: -0.148 | AQ10: d | AR10: p. 3 | AS10: 0.83 | AT10: e (=) | AU10: 1 (one) | AV10: no | AW10: https://pdf.sciencedirectassets.com/272387/1-s2.0-S0022103120X00060/1-s2.0-S0022103120304066/main.pdf?X-Amz-Security-Token=IQoJb3JpZ2luX2VjEBgaCXVzLWVhc3QtMSJGMEQCICnHJqcNsP62IhJ5t%2BlQbccPwseA76qFfK6Rgkom8dtRAiB1LS%2BiM%2B0b%2BvwiyOom715iyNnHeXVQbXmSm95pdglacyq8BQjR%2F%2F%2F%2F%2F%2F%2F%2F%2F%2F8BEAUaDDA1OTAwMzU0Njg2NSIMmoze3y0Q1yERk%2B0lKpAF0gYTSXrqATr%2FlouJQrzfzrF%2B%2BHvghuPve%2FIY6N1xxaQBobJn18bDe0NKhRM4T2mvBEFjCOaVSqmUoM3%2F%2BmGL%2BTAQq6mB%2F5aQpDiqXVVnBGSq5%2F03UsrB78W9ZYcX3HuqmMRCwLpHPAIgIHd9zQtRRFGwk6RR%2ByNdrZ7EqjeWgcIKuyAr9%2Bj0JJ74pqGzqA1bFSaiBMqqZjviAxsq%2FjIO4yKprM2jCQw%2B%2FbZMITGLBdecPGFvQADAleUhJZgsYDQbMSkktZJ6E%2FJW5MtMzDJ3LrlhsdSqiHd28N4%2FJtYL8gNCs%2F9wK3a1s%2BQvM838pcLinkI8unVh1Gcvfxjbq6fYI6x4hCc7UZUEXs%2BEd%2Bo1x9GFvp3tcM%2BwJYlAa%2BEE%2FZcco8Dj58jnqzyOal0dDMeeWOjHL3y8xqwOE69icvonadJhHFVwONEoA1aox7vcITDF0spX53bm8Off4OeJ4bHC6QFHjIgBmUnwwVhqwcTI1CofN%2BPxww0zY3oNg4NrIO%2B5IVffRucPE9pztEeVHOdsmVPWyRlEFrjQ3aVJiYpL6TVfW3VfFLrAFifjveRxLAGB28CYsVXmTUz0Qxq6JRu7SlmaRNP2YnG7ipXXbiuZbwrorkm%2BxDc3uzBAI3Z82HTq1%2FmzxXw3SDN8%2FgQpgwWMXmWr%2F%2BckEKS7a7j2988ql%2B%2Fy%2BqfrHVJ5rVoDXKUgDUP6rR3X1ejf1UZwyc8ja5HXFbPfOefIT%2FsnbjIx3Ff255FID0Z6RGepP7orcagCAcWl7CBXLkbWM%2BaP6Oi1ITpYGOPrwvSeRMyKPH2NmAiiWZE5l0m%2FTJGJ0tND%2FrcK%2BOlvjkyuEOx33q4BZeSRwvKBTPBeeTtjgd9K%2BGRMok%2Fe5xEw28zvugY6sgH0sfyibldLqTratcbSkw7B9kA7YzvSU7Iyhc8zjvj18adk0B6r39A2zAda5VndB8QXUitJ8361WDPVPzGMTek%2Fl5bziH%2FtLRb2uo30VQ5T74JJWTp8l6Rs7L5pQAvE%2FQTclPBuc%2BZrz7CkEfVLz%2FJt0xicBVpzawZjnQzXuFBfBBbMr%2FWdBHYYpRqC6jMqh3zJIYsu9ZeQkzwiXFbF14t%2BITCuLmhK4klb9H3%2BQ4iKcUaK&X-Amz-Algorithm=AWS4-HMAC-SHA256&X-Amz-Date=20241213T084150Z&X-Amz-SignedHeaders=host&X-Amz-Expires=300&X-Amz-Credential=ASIAQ3PHCVTYUWRHKPES%2F20241213%2Fus-east-1%2Fs3%2Faws4_request&X-Amz-Signature=33924dc8199c3da89949ad504da4000be209df455000e1a7e4fee4140f60b1b1&hash=6979ab83d6e022fd52840830bb00b033291cf8235f9e721ac49f027cf55e995c&host=68042c943591013ac2b2430a89b270f6af2c76d8dfd086a07176afe7c76c2c61&pii=S0022103120304066&tid=spdf-0273d28f-03b4-4283-8694-d21fc2577d91&sid=18412b78662c794bb67b6200a74126f2bac9gxrqb&type=client&tsoh=d3d3LnNjaWVuY2VkaXJlY3QuY29t&ua=010859005455035b5a&rr=8f14a84b18840c73&cc=bg#link_ir0025 | AX10: 2 - close | AY10: =IFERROR(__xludf.DUMMYFUNCTION("vlookup(BB10,importrange(""https://docs.google.com/spreadsheets/d/1d2vevQ_7D_v35q4wCQ4RpQ_IPoTwEMB9Yp6ymwlPqew/edit?gid=984458430#gid=984458430"", ""'replication success'!A:K""), 11, FAlSE)"),"failed") -> failed | AZ10: =IFERROR(__xludf.DUMMYFUNCTION("vlookup(BB10,importrange(""https://docs.google.com/spreadsheets/d/1d2vevQ_7D_v35q4wCQ4RpQ_IPoTwEMB9Yp6ymwlPqew/edit?gid=984458430#gid=984458430"", ""'replication success'!A:M""), 12, FAlSE)"),"To sum up, due to the extremely high power, the anchoring effect should have occurred if it indeed existed. We interpret the fact that there was no sign of anchoring—even after we excluded outliers and controlled for whether participants saw the flicke"&"ring—as inconsistent with the claim that subliminal anchoring exists.") -> To sum up, due to the extremely high power, the anchoring effect should have occurred if it indeed existed. We interpret the fact that there was no sign of anchoring—even after we excluded outliers and controlled for whether participants saw the flickering—as inconsistent with the claim that subliminal anchoring exists. | BA10: =IFERROR(__xludf.DUMMYFUNCTION("vlookup(BB10,importrange(""https://docs.google.com/spreadsheets/d/1d2vevQ_7D_v35q4wCQ4RpQ_IPoTwEMB9Yp6ymwlPqew/edit?gid=984458430#gid=984458430"", ""'replication success'!A:M""), 13, FAlSE)"),"pg.3") -> pg.3 | BB10: =IFERROR(__xludf.DUMMYFUNCTION("REGEXREPLACE(G10, ""_[a-z]{1,2}$"", """")"),"acykd") -> acykd | BC10: - Please type "NA" if you could not find "regis" in the manuscript. - Good catch with the N = 41! - This is the preregistration: https://osf.io/8urxv It is linked at the top of the entry | BD10: LR
A11: 11 | B11: validated - chosen | C11: double | D11: Hakile | F11: acykd_1 | G11: acykd | H11: Hakile Resulbegoviq | I11: 45641 | J11: 45663 | K11: informative failure to replicate | L11: updated reference_r to report instead of the OSF page | M11: Mussweiler, T., & Englich, B. (2005). Subliminal anchoring: Judgmental consequences and underlying mechanisms. Organizational Behavior and Human Decision Processes, 98(2), 133-143. | N11: 10.1016/j.obhdp.2004.12.002 | O11: 2 | P11: =hyperlink(vlookup(lower(N11),'File Links'!A:B, 2, FALSE), SUBSTITUTE(lower(N11), "/", "--") & ".pdf") -> 10.1016--j.obhdp.2004.12.002.pdf | Q11: {=if(iserror(MATCH(V11, 'File Links'!C:C, 0)), "N/A", HYPERLINK(INDEX('File Links'!B:B, MATCH(P11, 'File Links'!C:C, 0))))} -> https://drive.google.com/file/d/1CZ8RmInPe2eqHwf-p8tl0IQxpn8_H_C5/view?usp=drivesdk | R11: Röseler, L., Schütz, A., Blank, P. A., Dück, M., Fels, S., Kupfer, J., ... & Seida, C. (2021). Evidence against subliminal anchoring: Two close, highly powered, preregistered, and failed replication attempts. Journal of Experimental Social Psychology, 92, 104066. https://doi.org/10.1016/j.jesp.2020.104066 | S11: 10.1016/j.jesp.2020.104066 | U11: 1 | V11: =hyperlink(vlookup(lower(S11),'File Links'!E:F, 2, FALSE), SUBSTITUTE(lower(S11), "/", "--") & ".pdf") -> 10.1016--j.jesp.2020.104066.pdf | W11: Replication | X11: {=if(iserror(MATCH(V11, 'File Links'!C:C, 0)), "N/A", HYPERLINK(INDEX('File Links'!B:B, MATCH(V11, 'File Links'!C:C, 0))))} -> https://drive.google.com/file/d/1Q7xa-u3DEssueb6fBYD39BjDPub6xcHR/view?usp=drivesdk | Z11: Social Psychology | AA11: Subliminal anchoring | AB11: Anchoring; Heuristics; Comparison; Selective accessibility; Assimilation | AC11: Subliminally presented numerical anchors influence judgment, causing estimates to shift toward the anchor values without participants being consciously aware of the anchors. | AD11: Participants who were presented with the high anchor value estimated the car price to be higher (M = 21,219 Euro) than those presented with the low anchor value (M = 17,150 Euro), t(39) = 2.02, p < .05, r = .31. | AE11: 137 | AF11: 41 | AG11: 0.31 | AH11: r | AI11: p. 137 | AJ11: 0.05 | AK11: l (<) | AL11: NA (not reported) | AM11: no | AN11: NA | AO11: 165 | AP11: -0.148 | AQ11: d | AR11: p. 3 | AS11: 0.83 | AT11: e (=) | AU11: 1 (one) | AV11: no | AW11: https://osf.io/8urxv | AX11: 2 - close | AY11: =IFERROR(__xludf.DUMMYFUNCTION("vlookup(BB11,importrange(""https://docs.google.com/spreadsheets/d/1d2vevQ_7D_v35q4wCQ4RpQ_IPoTwEMB9Yp6ymwlPqew/edit?gid=984458430#gid=984458430"", ""'replication success'!A:K""), 11, FAlSE)"),"failed") -> failed | AZ11: =IFERROR(__xludf.DUMMYFUNCTION("vlookup(BB11,importrange(""https://docs.google.com/spreadsheets/d/1d2vevQ_7D_v35q4wCQ4RpQ_IPoTwEMB9Yp6ymwlPqew/edit?gid=984458430#gid=984458430"", ""'replication success'!A:M""), 12, FAlSE)"),"To sum up, due to the extremely high power, the anchoring effect should have occurred if it indeed existed. We interpret the fact that there was no sign of anchoring—even after we excluded outliers and controlled for whether participants saw the flicke"&"ring—as inconsistent with the claim that subliminal anchoring exists.") -> To sum up, due to the extremely high power, the anchoring effect should have occurred if it indeed existed. We interpret the fact that there was no sign of anchoring—even after we excluded outliers and controlled for whether participants saw the flickering—as inconsistent with the claim that subliminal anchoring exists. | BA11: =IFERROR(__xludf.DUMMYFUNCTION("vlookup(BB11,importrange(""https://docs.google.com/spreadsheets/d/1d2vevQ_7D_v35q4wCQ4RpQ_IPoTwEMB9Yp6ymwlPqew/edit?gid=984458430#gid=984458430"", ""'replication success'!A:M""), 13, FAlSE)"),"pg.3") -> pg.3 | BB11: =IFERROR(__xludf.DUMMYFUNCTION("REGEXREPLACE(G11, ""_[a-z]{1,2}$"", """")"),"acykd") -> acykd | BC11: Feedback for Hakile: - The degreees of freedom for the t test are 39, indicating that N = 41 - the number of tails was actually not reported (it does not say anywhere whether it is one-tailed or two-tailed but was coded as 2) - I could not find the d = 0.71 on p. 137 or anywhere in the manuscript. - Please type "NA" if you could not find "regis" in the manuscript. - Please rather use text for the claim that includes statistical elements, such as the effect on p. 137 under "results and discussion" - This is the preregistration: https://osf.io/8urxv It is linked at the top of the entry. You linked the "post completion" registration. | BD11: LR
A12: 12 | B12: validated - chosen | C12: double | D12: Sarah | F12: additional_studies1_1 | G12: additional_studies1_a | H12: SAJ | I12: 45427 | J12: 45624 | M12: Rellensmann, J., & Schukajlow, S. (2017). Does students’ interest in a mathematical problem depend on the problem’s connection to reality? An analysis of students’ interest and pre-service teachers’ judgments of students’ interest in problems with and without a connection to reality. ZDM, 49, 367-378. https://doi.org/10.1007/s11858-016-0819-3 | N12: 10.1007/s11858-016-0819-3 | O12: 1 | P12: =hyperlink(vlookup(lower(N12),'File Links'!A:B, 2, FALSE), SUBSTITUTE(lower(N12), "/", "--") & ".pdf") -> 10.1007--s11858-016-0819-3.pdf | Q12: {=if(iserror(MATCH(V12, 'File Links'!C:C, 0)), "N/A", HYPERLINK(INDEX('File Links'!B:B, MATCH(P12, 'File Links'!C:C, 0))))} -> https://drive.google.com/file/d/1A3A0XWewbvFp536VbiCjIAYxdIJwVP-9/view?usp=drivesdk | R12: García-Cerdá, C., Segura, C., & Ferrando, I. (2024). Influence of the Type of Mathematical Problems on Students’ and Pre-service Teachers’ Interest and Performance. A Replication and Elaboration Study. Implementation and Replication Studies in Mathematics Education, 1(aop), 1-35. https://doi.org/10.1163/26670127-bja10017 | S12: 10.1163/26670127-bja10017 | U12: 1 | V12: =hyperlink(vlookup(lower(S12),'File Links'!E:F, 2, FALSE), SUBSTITUTE(lower(S12), "/", "--") & ".pdf") -> 10.1163--26670127-bja10017.pdf | W12: Title - "A replication and elaboration study" Abstract - "... the process of conceptual replication of Rellensmann and Schukajlow’s (2017) research..." | X12: {=if(iserror(MATCH(V12, 'File Links'!C:C, 0)), "N/A", HYPERLINK(INDEX('File Links'!B:B, MATCH(V12, 'File Links'!C:C, 0))))} -> https://drive.google.com/file/d/1u_oSZ0fEx8q87XxieN1axHREEr_kiGBE/view?usp=drivesdk | Z12: Education | AA12: interest in mathematics | AB12: mathematics, interest, students, pre-service teachers, diagnostic competence, real-world problems, performance, problem-solving | AC12: Influence of the Type of Mathematical Problems on Students’ Interest | AD12: A t-test for dependent samples indicated that the difference in students’ interest in the two problem types was statistically significant [t(99) = −2.96, p < 0.01]. | AE12: 7 | AF12: 100 | AG12: 0.3 | AH12: d | AI12: p. 7 | AJ12: 0.01 | AK12: l (<) | AL12: NA (not reported) | AM12: yes | AN12: NA | AO12: 80 | AP12: X2(2) = 9.99 | AQ12: test statistic | AR12: preprint p. 22 Kendells W = X2/N(K-1), X2 = 9.99, N = 80, K = 3 W = 9.99/ (80*(3-1)), W = 9.99/ (160), W ~ 0.06 | AS12: 0.01 | AT12: l (<) | AU12: NA (not reported) | AV12: no | AW12: NA | AX12: 2 - close | AY12: =IFERROR(__xludf.DUMMYFUNCTION("vlookup(BB12,importrange(""https://docs.google.com/spreadsheets/d/1d2vevQ_7D_v35q4wCQ4RpQ_IPoTwEMB9Yp6ymwlPqew/edit?gid=984458430#gid=984458430"", ""'replication success'!A:K""), 11, FAlSE)"),"successful") -> successful | AZ12: =IFERROR(__xludf.DUMMYFUNCTION("vlookup(BB12,importrange(""https://docs.google.com/spreadsheets/d/1d2vevQ_7D_v35q4wCQ4RpQ_IPoTwEMB9Yp6ymwlPqew/edit?gid=984458430#gid=984458430"", ""'replication success'!A:M""), 12, FAlSE)"),"This result is consistent with the replicated study (Rellensmann & Schukajlow, 2017), although, in that study, the interest values were adjusted to control the effect of task difficulty (in the present work that part corresponds to the study of perform"&"ance that will be discussed later).") -> This result is consistent with the replicated study (Rellensmann & Schukajlow, 2017), although, in that study, the interest values were adjusted to control the effect of task difficulty (in the present work that part corresponds to the study of performance that will be discussed later). | BA12: =IFERROR(__xludf.DUMMYFUNCTION("vlookup(BB12,importrange(""https://docs.google.com/spreadsheets/d/1d2vevQ_7D_v35q4wCQ4RpQ_IPoTwEMB9Yp6ymwlPqew/edit?gid=984458430#gid=984458430"", ""'replication success'!A:M""), 13, FAlSE)"),"pg.26") -> pg.26 | BB12: =IFERROR(__xludf.DUMMYFUNCTION("REGEXREPLACE(G12, ""_[a-z]{1,2}$"", """")"),"additional_studies1") -> additional_studies1 | BD12: LR
A13: 13 | B13: validated - discarded | C13: double | D13: Alexsandr | F13: additional_studies1_1 | G13: additional_studies1_a | H13: Aleksandr Pravednikov | I13: 45427 | J13: 45625 | K13: Claim text_r We observe that, in terms of means, there are no great differences in interest according to the type of problem. For students intramathematical problems were the most interesting (Mi = 2.77, SDi = 1.25), followed by word problems (Mw = 2.75, SDw = 1.18), and finally by modelling problems (Mm = 2.66, SDm = 1.26). - Table 1. To analyse whether the differences are significant, a hypothesis test was performed. Given that the means of interest did not follow, according to the results of the Shapiro-Wilk test, a normal distribution in any of the three types of problems, we applied Friedman’s non-parametric test. Thus, we obtained that there were differences between at least two types of problems (𝜒𝜒2(2)=9.99, p < 0.01). A post hoc analysis, using the Nemenyi test, ensured that there were significant differences in task-specific interest between word and modelling problems (p < 0.05), but not between the other combinations. [...] Page 21-22 | M13: Rellensmann, J., & Schukajlow, S. (2017). Does students’ interest in a mathematical problem depend on the problem’s connection to reality? An analysis of students’ interest and pre-service teachers’ judgments of students’ interest in problems with and without a connection to reality. ZDM, 49, 367-378. https://doi.org/10.1007/s11858-016-0819-3 | N13: 10.1007/s11858-016-0819-3 | P13: =hyperlink(vlookup(lower(N13),'File Links'!A:B, 2, FALSE), SUBSTITUTE(lower(N13), "/", "--") & ".pdf") -> 10.1007--s11858-016-0819-3.pdf | Q13: {=if(iserror(MATCH(V13, 'File Links'!C:C, 0)), "N/A", HYPERLINK(INDEX('File Links'!B:B, MATCH(P13, 'File Links'!C:C, 0))))} -> https://drive.google.com/file/d/1A3A0XWewbvFp536VbiCjIAYxdIJwVP-9/view?usp=drivesdk | R13: García-Cerdá, C., Segura, C., & Ferrando, I. (2024). Influence of the Type of Mathematical Problems on Students’ and Pre-service Teachers’ Interest and Performance. A Replication and Elaboration Study. Implementation and Replication Studies in Mathematics Education, 1(aop), 1-35. https://doi.org/10.1163/26670127-bja10017 | S13: 10.1163/26670127-bja10017 | V13: =hyperlink(vlookup(lower(S13),'File Links'!E:F, 2, FALSE), SUBSTITUTE(lower(S13), "/", "--") & ".pdf") -> 10.1163--26670127-bja10017.pdf | X13: {=if(iserror(MATCH(V13, 'File Links'!C:C, 0)), "N/A", HYPERLINK(INDEX('File Links'!B:B, MATCH(V13, 'File Links'!C:C, 0))))} -> https://drive.google.com/file/d/1u_oSZ0fEx8q87XxieN1axHREEr_kiGBE/view?usp=drivesdk | Z13: Educational Sciences | AB13: Students | AC13: Influence of the Type of Mathematical Problems on Students’ and Pre-service Teachers’ Interest and Performance | AD13: Students reported a mean level of interest of Madj = 2.71 (SDadj = 0.90) in solving problems with a connection to reality and Madj = 2.91 (SDadj = 1.00) in solving problems without a connection to reality when the impact of task difficulty was controlled for (Table 2). Means and standard errors for students’ interest are graphically displayed in Fig. 4. A t-test for dependent samples indicated that the difference in students’ interest in the two problem types was statistically significant [t(99) = −2.96, p < 0.01]. Cohen’s d = 0.30 indicated a small effect. This means that, contrary to our expectations, students reported more interest in solving problems without a connection to reality thann in problems with a connection to reality. | AE13: 7(373) | AF13: 100 | AG13: 0.3 | AH13: d | AJ13: 0.01 | AK13: l (<) | AL13: NA (not reported) | AN13: NA | AO13: 80 | AS13: p < 0.05 | AT13: l (<) | AU13: NA (not reported) | AX13: 2 - close | AY13: =IFERROR(__xludf.DUMMYFUNCTION("vlookup(BB13,importrange(""https://docs.google.com/spreadsheets/d/1d2vevQ_7D_v35q4wCQ4RpQ_IPoTwEMB9Yp6ymwlPqew/edit?gid=984458430#gid=984458430"", ""'replication success'!A:K""), 11, FAlSE)"),"successful") -> successful | AZ13: =IFERROR(__xludf.DUMMYFUNCTION("vlookup(BB13,importrange(""https://docs.google.com/spreadsheets/d/1d2vevQ_7D_v35q4wCQ4RpQ_IPoTwEMB9Yp6ymwlPqew/edit?gid=984458430#gid=984458430"", ""'replication success'!A:M""), 12, FAlSE)"),"This result is consistent with the replicated study (Rellensmann & Schukajlow, 2017), although, in that study, the interest values were adjusted to control the effect of task difficulty (in the present work that part corresponds to the study of perform"&"ance that will be discussed later).") -> This result is consistent with the replicated study (Rellensmann & Schukajlow, 2017), although, in that study, the interest values were adjusted to control the effect of task difficulty (in the present work that part corresponds to the study of performance that will be discussed later). | BA13: =IFERROR(__xludf.DUMMYFUNCTION("vlookup(BB13,importrange(""https://docs.google.com/spreadsheets/d/1d2vevQ_7D_v35q4wCQ4RpQ_IPoTwEMB9Yp6ymwlPqew/edit?gid=984458430#gid=984458430"", ""'replication success'!A:M""), 13, FAlSE)"),"pg.26") -> pg.26 | BB13: =IFERROR(__xludf.DUMMYFUNCTION("REGEXREPLACE(G13, ""_[a-z]{1,2}$"", """")"),"additional_studies1") -> additional_studies1 | BD13: LR
A14: 14 | B14: validated - chosen | C14: double | D14: Sarah | F14: additional_studies1_1 | G14: additional_studies1_b | H14: SAJ | I14: 45427 | J14: 45624 | K14: this effect was not explored in the original paper | M14: Rellensmann, J., & Schukajlow, S. (2017). Does students’ interest in a mathematical problem depend on the problem’s connection to reality? An analysis of students’ interest and pre-service teachers’ judgments of students’ interest in problems with and without a connection to reality. ZDM, 49, 367-378. https://doi.org/10.1007/s11858-016-0819-3 | N14: 10.1007/s11858-016-0819-3 | O14: 1 | P14: =hyperlink(vlookup(lower(N14),'File Links'!A:B, 2, FALSE), SUBSTITUTE(lower(N14), "/", "--") & ".pdf") -> 10.1007--s11858-016-0819-3.pdf | Q14: {=if(iserror(MATCH(V14, 'File Links'!C:C, 0)), "N/A", HYPERLINK(INDEX('File Links'!B:B, MATCH(P14, 'File Links'!C:C, 0))))} -> https://drive.google.com/file/d/1A3A0XWewbvFp536VbiCjIAYxdIJwVP-9/view?usp=drivesdk | R14: García-Cerdá, C., Segura, C., & Ferrando, I. (2024). Influence of the Type of Mathematical Problems on Students’ and Pre-service Teachers’ Interest and Performance. A Replication and Elaboration Study. Implementation and Replication Studies in Mathematics Education, 1(aop), 1-35. https://doi.org/10.1163/26670127-bja10017 | S14: 10.1163/26670127-bja10017 | U14: 1 | V14: =hyperlink(vlookup(lower(S14),'File Links'!E:F, 2, FALSE), SUBSTITUTE(lower(S14), "/", "--") & ".pdf") -> 10.1163--26670127-bja10017.pdf | W14: Title - "A replication and elaboration study" Abstract - "... the process of conceptual replication of Rellensmann and Schukajlow’s (2017) research..." | X14: {=if(iserror(MATCH(V14, 'File Links'!C:C, 0)), "N/A", HYPERLINK(INDEX('File Links'!B:B, MATCH(V14, 'File Links'!C:C, 0))))} -> https://drive.google.com/file/d/1u_oSZ0fEx8q87XxieN1axHREEr_kiGBE/view?usp=drivesdk | Z14: Education | AA14: interest in mathematics | AB14: mathematics, interest, students, pre-service teachers, diagnostic competence, real-world problems, performance, problem-solving | AC14: Influence of the Type of Mathematical Problems on Pre-service Teachers’ Interest | AD14: A t-test for dependent samples showed a significant difference in pre-service teachers’ judgments of students’ interest in solving the two types of problems [t(162) = 14.33, p < 0.01]. Cohen’s d = 1.12 | AE14: 7 | AF14: 163 | AG14: 1.12 | AH14: d | AI14: p. 7 | AJ14: 0.01 | AK14: l (<) | AL14: NA (not reported) | AM14: yes | AN14: NA | AO14: 80 | AP14: X2(2) = 16.54 | AQ14: test statistic | AR14: Kendells W = X2/N(K-1), X2 = 16.54, N = 80, K = 3 W = 16.54/ (80*(3-1)), W = 16.54/ (160), W ~ 0.1 | AS14: 0.01 | AT14: l (<) | AU14: NA (not reported) | AV14: no | AW14: NA | AX14: 2 - close | AY14: =IFERROR(__xludf.DUMMYFUNCTION("vlookup(BB14,importrange(""https://docs.google.com/spreadsheets/d/1d2vevQ_7D_v35q4wCQ4RpQ_IPoTwEMB9Yp6ymwlPqew/edit?gid=984458430#gid=984458430"", ""'replication success'!A:K""), 11, FAlSE)"),"successful") -> successful | AZ14: =IFERROR(__xludf.DUMMYFUNCTION("vlookup(BB14,importrange(""https://docs.google.com/spreadsheets/d/1d2vevQ_7D_v35q4wCQ4RpQ_IPoTwEMB9Yp6ymwlPqew/edit?gid=984458430#gid=984458430"", ""'replication success'!A:M""), 12, FAlSE)"),"This result is consistent with the replicated study (Rellensmann & Schukajlow, 2017), although, in that study, the interest values were adjusted to control the effect of task difficulty (in the present work that part corresponds to the study of perform"&"ance that will be discussed later).") -> This result is consistent with the replicated study (Rellensmann & Schukajlow, 2017), although, in that study, the interest values were adjusted to control the effect of task difficulty (in the present work that part corresponds to the study of performance that will be discussed later). | BA14: =IFERROR(__xludf.DUMMYFUNCTION("vlookup(BB14,importrange(""https://docs.google.com/spreadsheets/d/1d2vevQ_7D_v35q4wCQ4RpQ_IPoTwEMB9Yp6ymwlPqew/edit?gid=984458430#gid=984458430"", ""'replication success'!A:M""), 13, FAlSE)"),"pg.26") -> pg.26 | BB14: =IFERROR(__xludf.DUMMYFUNCTION("REGEXREPLACE(G14, ""_[a-z]{1,2}$"", """")"),"additional_studies1") -> additional_studies1 | BD14: LR
A15: 15 | B15: validated - discarded | C15: double | D15: Alexsandr | F15: additional_studies1_1 | G15: additional_studies1_b | H15: Aleksandr Pravednikov | I15: 45427 | J15: 45625 | K15: Claim text_r Table 2 shows the average situational interest of 80 pre-service teachers according to the connection to the reality of the problems. We observe that, for pre-service teachers, word problems were the most interesting (Mw = 3.28, SDw = 1.22), followed by modelling problems (Mm = 3.11, SDm = 1.25) and, finally, intramathematical problems (Mi = 2.92, SDi = 1.24). Again, we conducted a hypothesis test to analyse whether there were significant differences in interest according to the connection with the reality of the problems. The means of interest did not follow a normal distribution either, so we obtained that there are significant differences between at least two types of problems (𝜒𝜒2(2)=16.54, p < 0.01) by applying Friedman’s test. Nemenyi’s test ensured that there were significant differences in task-specific interest between word and modelling problems (p < 0.05), and between intramathematical and word problems (p < 0.01). There were no significant differences between intramathematical and modelling problems (p = 0.46), indicating that word problems were significantly more interesting for pre-service teachers. [...] Page 22-23 | M15: Rellensmann, J., & Schukajlow, S. (2017). Does students’ interest in a mathematical problem depend on the problem’s connection to reality? An analysis of students’ interest and pre-service teachers’ judgments of students’ interest in problems with and without a connection to reality. ZDM, 49, 367-378. https://doi.org/10.1007/s11858-016-0819-3 | N15: 10.1007/s11858-016-0819-3 | P15: =hyperlink(vlookup(lower(N15),'File Links'!A:B, 2, FALSE), SUBSTITUTE(lower(N15), "/", "--") & ".pdf") -> 10.1007--s11858-016-0819-3.pdf | Q15: {=if(iserror(MATCH(V15, 'File Links'!C:C, 0)), "N/A", HYPERLINK(INDEX('File Links'!B:B, MATCH(P15, 'File Links'!C:C, 0))))} -> https://drive.google.com/file/d/1A3A0XWewbvFp536VbiCjIAYxdIJwVP-9/view?usp=drivesdk | R15: García-Cerdá, C., Segura, C., & Ferrando, I. (2024). Influence of the Type of Mathematical Problems on Students’ and Pre-service Teachers’ Interest and Performance. A Replication and Elaboration Study. Implementation and Replication Studies in Mathematics Education, 1(aop), 1-35. https://doi.org/10.1163/26670127-bja10017 | S15: 10.1163/26670127-bja10017 | V15: =hyperlink(vlookup(lower(S15),'File Links'!E:F, 2, FALSE), SUBSTITUTE(lower(S15), "/", "--") & ".pdf") -> 10.1163--26670127-bja10017.pdf | X15: {=if(iserror(MATCH(V15, 'File Links'!C:C, 0)), "N/A", HYPERLINK(INDEX('File Links'!B:B, MATCH(V15, 'File Links'!C:C, 0))))} -> https://drive.google.com/file/d/1u_oSZ0fEx8q87XxieN1axHREEr_kiGBE/view?usp=drivesdk | Z15: Educational Sciences | AB15: Pre-service teachers | AC15: Influence of the Type of Mathematical Problems on Students’ and Pre-service Teachers’ Interest and Performance | AD15: Pre-service teachers predicted a mean of Madj = 3.18 (SDadj = 0.48) for students’ interest in problems with a connection to reality and Madj = 2.47 (SDadj = 0.60) for their interest in problems without a connection to reality (Table 2). Means and standard errors for pre-service teachers’ judgments are also graphically displayed in Fig. 4. A t-test for dependent samples showed a significant difference in pre-service teachers’ judgments of students’ interest in solving the two types of problems [t(162) = 14.33, p < 0.01]. Cohen’s d = 1.12 indicated a large effect. As hypothesized, this means that pre-service teachers believed that solving problems with a connection to reality triggered more interest in students than solving problems without a connection to reality. | AE15: 7(373) | AF15: 163 | AG15: 1.12 | AH15: d | AJ15: 0.01 | AK15: l (<) | AL15: NA (not reported) | AN15: NA | AO15: 80 | AS15: p < 0.01 | AT15: l (<) | AU15: NA (not reported) | AX15: 2 - close | AY15: =IFERROR(__xludf.DUMMYFUNCTION("vlookup(BB15,importrange(""https://docs.google.com/spreadsheets/d/1d2vevQ_7D_v35q4wCQ4RpQ_IPoTwEMB9Yp6ymwlPqew/edit?gid=984458430#gid=984458430"", ""'replication success'!A:K""), 11, FAlSE)"),"successful") -> successful | AZ15: =IFERROR(__xludf.DUMMYFUNCTION("vlookup(BB15,importrange(""https://docs.google.com/spreadsheets/d/1d2vevQ_7D_v35q4wCQ4RpQ_IPoTwEMB9Yp6ymwlPqew/edit?gid=984458430#gid=984458430"", ""'replication success'!A:M""), 12, FAlSE)"),"This result is consistent with the replicated study (Rellensmann & Schukajlow, 2017), although, in that study, the interest values were adjusted to control the effect of task difficulty (in the present work that part corresponds to the study of perform"&"ance that will be discussed later).") -> This result is consistent with the replicated study (Rellensmann & Schukajlow, 2017), although, in that study, the interest values were adjusted to control the effect of task difficulty (in the present work that part corresponds to the study of performance that will be discussed later). | BA15: =IFERROR(__xludf.DUMMYFUNCTION("vlookup(BB15,importrange(""https://docs.google.com/spreadsheets/d/1d2vevQ_7D_v35q4wCQ4RpQ_IPoTwEMB9Yp6ymwlPqew/edit?gid=984458430#gid=984458430"", ""'replication success'!A:M""), 13, FAlSE)"),"pg.26") -> pg.26 | BB15: =IFERROR(__xludf.DUMMYFUNCTION("REGEXREPLACE(G15, ""_[a-z]{1,2}$"", """")"),"additional_studies1") -> additional_studies1 | BD15: LR
A16: 16 | B16: validated - discarded | C16: double | D16: Sarah | F16: additional_studies1_1 | G16: additional_studies1_c | H16: SAJ | I16: 45427 | J16: 45624 | K16: this effect was not explored in the original paper | L16: discarded because this is an extension that cannot be paired up with an original finding | M16: Rellensmann, J., & Schukajlow, S. (2017). Does students’ interest in a mathematical problem depend on the problem’s connection to reality? An analysis of students’ interest and pre-service teachers’ judgments of students’ interest in problems with and without a connection to reality. ZDM, 49, 367-378. https://doi.org/10.1007/s11858-016-0819-3 | N16: 10.1007/s11858-016-0819-3 | O16: 1 | P16: =hyperlink(vlookup(lower(N16),'File Links'!A:B, 2, FALSE), SUBSTITUTE(lower(N16), "/", "--") & ".pdf") -> 10.1007--s11858-016-0819-3.pdf | Q16: {=if(iserror(MATCH(V16, 'File Links'!C:C, 0)), "N/A", HYPERLINK(INDEX('File Links'!B:B, MATCH(P16, 'File Links'!C:C, 0))))} -> https://drive.google.com/file/d/1A3A0XWewbvFp536VbiCjIAYxdIJwVP-9/view?usp=drivesdk | R16: García-Cerdá, C., Segura, C., & Ferrando, I. (2024). Influence of the Type of Mathematical Problems on Students’ and Pre-service Teachers’ Interest and Performance. A Replication and Elaboration Study. Implementation and Replication Studies in Mathematics Education, 1(aop), 1-35. https://doi.org/10.1163/26670127-bja10017 | S16: 10.1163/26670127-bja10017 | U16: 1 | V16: =hyperlink(vlookup(lower(S16),'File Links'!E:F, 2, FALSE), SUBSTITUTE(lower(S16), "/", "--") & ".pdf") -> 10.1163--26670127-bja10017.pdf | W16: Title - "A replication and elaboration study" Abstract - "... the process of conceptual replication of Rellensmann and Schukajlow’s (2017) research..." | X16: {=if(iserror(MATCH(V16, 'File Links'!C:C, 0)), "N/A", HYPERLINK(INDEX('File Links'!B:B, MATCH(V16, 'File Links'!C:C, 0))))} -> https://drive.google.com/file/d/1u_oSZ0fEx8q87XxieN1axHREEr_kiGBE/view?usp=drivesdk | Z16: Education | AA16: interest in mathematics | AB16: mathematics, interest, students, pre-service teachers, diagnostic competence, real-world problems, performance, problem-solving | AC16: Influence of the Type of Mathematical Problems on Student Performance | AN16: NA | AO16: 80 | AP16: 0.27 | AQ16: kendall's w | AR16: Kendells W = X2/N(K-1), X2 = 43.61, N = 80, K = 3 W = 43.61/ (80*(3-1)), W = 43.61/ (160), W ~ 0.27 | AS16: p < 0.01 | AT16: l (<) | AU16: NA (not reported) | AX16: extension | AY16: =IFERROR(__xludf.DUMMYFUNCTION("vlookup(BB16,importrange(""https://docs.google.com/spreadsheets/d/1d2vevQ_7D_v35q4wCQ4RpQ_IPoTwEMB9Yp6ymwlPqew/edit?gid=984458430#gid=984458430"", ""'replication success'!A:K""), 11, FAlSE)"),"successful") -> successful | AZ16: =IFERROR(__xludf.DUMMYFUNCTION("vlookup(BB16,importrange(""https://docs.google.com/spreadsheets/d/1d2vevQ_7D_v35q4wCQ4RpQ_IPoTwEMB9Yp6ymwlPqew/edit?gid=984458430#gid=984458430"", ""'replication success'!A:M""), 12, FAlSE)"),"This result is consistent with the replicated study (Rellensmann & Schukajlow, 2017), although, in that study, the interest values were adjusted to control the effect of task difficulty (in the present work that part corresponds to the study of perform"&"ance that will be discussed later).") -> This result is consistent with the replicated study (Rellensmann & Schukajlow, 2017), although, in that study, the interest values were adjusted to control the effect of task difficulty (in the present work that part corresponds to the study of performance that will be discussed later). | BA16: =IFERROR(__xludf.DUMMYFUNCTION("vlookup(BB16,importrange(""https://docs.google.com/spreadsheets/d/1d2vevQ_7D_v35q4wCQ4RpQ_IPoTwEMB9Yp6ymwlPqew/edit?gid=984458430#gid=984458430"", ""'replication success'!A:M""), 13, FAlSE)"),"pg.26") -> pg.26 | BB16: =IFERROR(__xludf.DUMMYFUNCTION("REGEXREPLACE(G16, ""_[a-z]{1,2}$"", """")"),"additional_studies1") -> additional_studies1 | BD16: LR
A17: 17 | B17: validated - discarded | C17: double | D17: Sarah | F17: additional_studies1_1 | G17: additional_studies1_d | H17: SAJ | I17: 45427 | J17: 45624 | K17: this effect was not explored in the original paper | L17: discarded because this is an extension that cannot be paired up with an original finding | M17: Rellensmann, J., & Schukajlow, S. (2017). Does students’ interest in a mathematical problem depend on the problem’s connection to reality? An analysis of students’ interest and pre-service teachers’ judgments of students’ interest in problems with and without a connection to reality. ZDM, 49, 367-378. https://doi.org/10.1007/s11858-016-0819-3 | N17: 10.1007/s11858-016-0819-3 | O17: 1 | P17: =hyperlink(vlookup(lower(N17),'File Links'!A:B, 2, FALSE), SUBSTITUTE(lower(N17), "/", "--") & ".pdf") -> 10.1007--s11858-016-0819-3.pdf | Q17: {=if(iserror(MATCH(V17, 'File Links'!C:C, 0)), "N/A", HYPERLINK(INDEX('File Links'!B:B, MATCH(P17, 'File Links'!C:C, 0))))} -> https://drive.google.com/file/d/1A3A0XWewbvFp536VbiCjIAYxdIJwVP-9/view?usp=drivesdk | R17: García-Cerdá, C., Segura, C., & Ferrando, I. (2024). Influence of the Type of Mathematical Problems on Students’ and Pre-service Teachers’ Interest and Performance. A Replication and Elaboration Study. Implementation and Replication Studies in Mathematics Education, 1(aop), 1-35. https://doi.org/10.1163/26670127-bja10017 | S17: 10.1163/26670127-bja10017 | U17: 1 | V17: =hyperlink(vlookup(lower(S17),'File Links'!E:F, 2, FALSE), SUBSTITUTE(lower(S17), "/", "--") & ".pdf") -> 10.1163--26670127-bja10017.pdf | W17: Title - "A replication and elaboration study" Abstract - "... the process of conceptual replication of Rellensmann and Schukajlow’s (2017) research..." | X17: {=if(iserror(MATCH(V17, 'File Links'!C:C, 0)), "N/A", HYPERLINK(INDEX('File Links'!B:B, MATCH(V17, 'File Links'!C:C, 0))))} -> https://drive.google.com/file/d/1u_oSZ0fEx8q87XxieN1axHREEr_kiGBE/view?usp=drivesdk | Z17: Education | AA17: interest in mathematics | AB17: mathematics, interest, students, pre-service teachers, diagnostic competence, real-world problems, performance, problem-solving | AC17: Influence of the Type of Mathematical Problems on Pre-service Teacher Performance | AN17: NA | AO17: 80 | AP17: 0.68 | AQ17: kendall's w | AR17: Kendells W = X2/N(K-1), X2 = 108.75, N = 80, K = 3 W = 108.75/ (80*(3-1)), W = 108.75/ (160), W ~ 0.68 | AS17: p < 0.01 | AT17: l (<) | AU17: NA (not reported) | AX17: extension | AY17: =IFERROR(__xludf.DUMMYFUNCTION("vlookup(BB17,importrange(""https://docs.google.com/spreadsheets/d/1d2vevQ_7D_v35q4wCQ4RpQ_IPoTwEMB9Yp6ymwlPqew/edit?gid=984458430#gid=984458430"", ""'replication success'!A:K""), 11, FAlSE)"),"successful") -> successful | AZ17: =IFERROR(__xludf.DUMMYFUNCTION("vlookup(BB17,importrange(""https://docs.google.com/spreadsheets/d/1d2vevQ_7D_v35q4wCQ4RpQ_IPoTwEMB9Yp6ymwlPqew/edit?gid=984458430#gid=984458430"", ""'replication success'!A:M""), 12, FAlSE)"),"This result is consistent with the replicated study (Rellensmann & Schukajlow, 2017), although, in that study, the interest values were adjusted to control the effect of task difficulty (in the present work that part corresponds to the study of perform"&"ance that will be discussed later).") -> This result is consistent with the replicated study (Rellensmann & Schukajlow, 2017), although, in that study, the interest values were adjusted to control the effect of task difficulty (in the present work that part corresponds to the study of performance that will be discussed later). | BA17: =IFERROR(__xludf.DUMMYFUNCTION("vlookup(BB17,importrange(""https://docs.google.com/spreadsheets/d/1d2vevQ_7D_v35q4wCQ4RpQ_IPoTwEMB9Yp6ymwlPqew/edit?gid=984458430#gid=984458430"", ""'replication success'!A:M""), 13, FAlSE)"),"pg.26") -> pg.26 | BB17: =IFERROR(__xludf.DUMMYFUNCTION("REGEXREPLACE(G17, ""_[a-z]{1,2}$"", """")"),"additional_studies1") -> additional_studies1 | BD17: LR
A18: 18 | B18: validated - discarded | C18: double | D18: Sarah | F18: additional_studies1_1 | G18: additional_studies1_e | H18: SAJ | I18: 45427 | J18: 45624 | K18: this effect was not explored in the original paper | L18: discarded because this is an extension that cannot be paired up with an original finding | M18: Rellensmann, J., & Schukajlow, S. (2017). Does students’ interest in a mathematical problem depend on the problem’s connection to reality? An analysis of students’ interest and pre-service teachers’ judgments of students’ interest in problems with and without a connection to reality. ZDM, 49, 367-378. https://doi.org/10.1007/s11858-016-0819-3 | N18: 10.1007/s11858-016-0819-3 | O18: 1 | P18: =hyperlink(vlookup(lower(N18),'File Links'!A:B, 2, FALSE), SUBSTITUTE(lower(N18), "/", "--") & ".pdf") -> 10.1007--s11858-016-0819-3.pdf | Q18: {=if(iserror(MATCH(V18, 'File Links'!C:C, 0)), "N/A", HYPERLINK(INDEX('File Links'!B:B, MATCH(P18, 'File Links'!C:C, 0))))} -> https://drive.google.com/file/d/1A3A0XWewbvFp536VbiCjIAYxdIJwVP-9/view?usp=drivesdk | R18: García-Cerdá, C., Segura, C., & Ferrando, I. (2024). Influence of the Type of Mathematical Problems on Students’ and Pre-service Teachers’ Interest and Performance. A Replication and Elaboration Study. Implementation and Replication Studies in Mathematics Education, 1(aop), 1-35. https://doi.org/10.1163/26670127-bja10017 | S18: 10.1163/26670127-bja10017 | U18: 1 | V18: =hyperlink(vlookup(lower(S18),'File Links'!E:F, 2, FALSE), SUBSTITUTE(lower(S18), "/", "--") & ".pdf") -> 10.1163--26670127-bja10017.pdf | W18: Title - "A replication and elaboration study" Abstract - "... the process of conceptual replication of Rellensmann and Schukajlow’s (2017) research..." | X18: {=if(iserror(MATCH(V18, 'File Links'!C:C, 0)), "N/A", HYPERLINK(INDEX('File Links'!B:B, MATCH(V18, 'File Links'!C:C, 0))))} -> https://drive.google.com/file/d/1u_oSZ0fEx8q87XxieN1axHREEr_kiGBE/view?usp=drivesdk | Z18: Education | AA18: interest in mathematics | AB18: mathematics, interest, students, pre-service teachers, diagnostic competence, real-world problems, performance, problem-solving | AC18: Influence of the Type of Mathematical Problems on Student Interest*Performance relationship | AN18: NA | AO18: 80 | AP18: intramathematical problem r = 0.25, word problem r = 0.29, modelling problem r = 0.31 | AQ18: r | AS18: intramathematical problem p < 0.05, word problem p < 0.01, modelling problem p < 0.01 | AT18: l (<) | AU18: NA (not reported) | AX18: extension | AY18: =IFERROR(__xludf.DUMMYFUNCTION("vlookup(BB18,importrange(""https://docs.google.com/spreadsheets/d/1d2vevQ_7D_v35q4wCQ4RpQ_IPoTwEMB9Yp6ymwlPqew/edit?gid=984458430#gid=984458430"", ""'replication success'!A:K""), 11, FAlSE)"),"successful") -> successful | AZ18: =IFERROR(__xludf.DUMMYFUNCTION("vlookup(BB18,importrange(""https://docs.google.com/spreadsheets/d/1d2vevQ_7D_v35q4wCQ4RpQ_IPoTwEMB9Yp6ymwlPqew/edit?gid=984458430#gid=984458430"", ""'replication success'!A:M""), 12, FAlSE)"),"This result is consistent with the replicated study (Rellensmann & Schukajlow, 2017), although, in that study, the interest values were adjusted to control the effect of task difficulty (in the present work that part corresponds to the study of perform"&"ance that will be discussed later).") -> This result is consistent with the replicated study (Rellensmann & Schukajlow, 2017), although, in that study, the interest values were adjusted to control the effect of task difficulty (in the present work that part corresponds to the study of performance that will be discussed later). | BA18: =IFERROR(__xludf.DUMMYFUNCTION("vlookup(BB18,importrange(""https://docs.google.com/spreadsheets/d/1d2vevQ_7D_v35q4wCQ4RpQ_IPoTwEMB9Yp6ymwlPqew/edit?gid=984458430#gid=984458430"", ""'replication success'!A:M""), 13, FAlSE)"),"pg.26") -> pg.26 | BB18: =IFERROR(__xludf.DUMMYFUNCTION("REGEXREPLACE(G18, ""_[a-z]{1,2}$"", """")"),"additional_studies1") -> additional_studies1 | BD18: LR
A19: 19 | B19: validated - discarded | C19: double | D19: Sarah | F19: additional_studies1_1 | G19: additional_studies1_f | H19: SAJ | I19: 45427 | J19: 45624 | K19: this effect was not explored in the original paper | L19: discarded because this is an extension that cannot be paired up with an original finding | M19: Rellensmann, J., & Schukajlow, S. (2017). Does students’ interest in a mathematical problem depend on the problem’s connection to reality? An analysis of students’ interest and pre-service teachers’ judgments of students’ interest in problems with and without a connection to reality. ZDM, 49, 367-378. https://doi.org/10.1007/s11858-016-0819-3 | N19: 10.1007/s11858-016-0819-3 | O19: 1 | P19: =hyperlink(vlookup(lower(N19),'File Links'!A:B, 2, FALSE), SUBSTITUTE(lower(N19), "/", "--") & ".pdf") -> 10.1007--s11858-016-0819-3.pdf | Q19: {=if(iserror(MATCH(V19, 'File Links'!C:C, 0)), "N/A", HYPERLINK(INDEX('File Links'!B:B, MATCH(P19, 'File Links'!C:C, 0))))} -> https://drive.google.com/file/d/1A3A0XWewbvFp536VbiCjIAYxdIJwVP-9/view?usp=drivesdk | R19: García-Cerdá, C., Segura, C., & Ferrando, I. (2024). Influence of the Type of Mathematical Problems on Students’ and Pre-service Teachers’ Interest and Performance. A Replication and Elaboration Study. Implementation and Replication Studies in Mathematics Education, 1(aop), 1-35. https://doi.org/10.1163/26670127-bja10017 | S19: 10.1163/26670127-bja10017 | U19: 1 | V19: =hyperlink(vlookup(lower(S19),'File Links'!E:F, 2, FALSE), SUBSTITUTE(lower(S19), "/", "--") & ".pdf") -> 10.1163--26670127-bja10017.pdf | W19: Title - "A replication and elaboration study" Abstract - "... the process of conceptual replication of Rellensmann and Schukajlow’s (2017) research..." | X19: {=if(iserror(MATCH(V19, 'File Links'!C:C, 0)), "N/A", HYPERLINK(INDEX('File Links'!B:B, MATCH(V19, 'File Links'!C:C, 0))))} -> https://drive.google.com/file/d/1u_oSZ0fEx8q87XxieN1axHREEr_kiGBE/view?usp=drivesdk | Z19: Education | AA19: interest in mathematics | AB19: mathematics, interest, students, pre-service teachers, diagnostic competence, real-world problems, performance, problem-solving | AC19: Influence of the Type of Mathematical Problems on Pre-service Teacher Interest*Performance relationship | AN19: NA | AO19: 80 | AP19: intramathematical problem r = 0.48, word problem r = 0.28, modelling problem r = 0.35 | AQ19: r | AS19: intramathematical problem p < 0.01, word problem p < 0.01, modelling problem p < 0.01 | AT19: l (<) | AU19: NA (not reported) | AX19: extension | AY19: =IFERROR(__xludf.DUMMYFUNCTION("vlookup(BB19,importrange(""https://docs.google.com/spreadsheets/d/1d2vevQ_7D_v35q4wCQ4RpQ_IPoTwEMB9Yp6ymwlPqew/edit?gid=984458430#gid=984458430"", ""'replication success'!A:K""), 11, FAlSE)"),"successful") -> successful | AZ19: =IFERROR(__xludf.DUMMYFUNCTION("vlookup(BB19,importrange(""https://docs.google.com/spreadsheets/d/1d2vevQ_7D_v35q4wCQ4RpQ_IPoTwEMB9Yp6ymwlPqew/edit?gid=984458430#gid=984458430"", ""'replication success'!A:M""), 12, FAlSE)"),"This result is consistent with the replicated study (Rellensmann & Schukajlow, 2017), although, in that study, the interest values were adjusted to control the effect of task difficulty (in the present work that part corresponds to the study of perform"&"ance that will be discussed later).") -> This result is consistent with the replicated study (Rellensmann & Schukajlow, 2017), although, in that study, the interest values were adjusted to control the effect of task difficulty (in the present work that part corresponds to the study of performance that will be discussed later). | BA19: =IFERROR(__xludf.DUMMYFUNCTION("vlookup(BB19,importrange(""https://docs.google.com/spreadsheets/d/1d2vevQ_7D_v35q4wCQ4RpQ_IPoTwEMB9Yp6ymwlPqew/edit?gid=984458430#gid=984458430"", ""'replication success'!A:M""), 13, FAlSE)"),"pg.26") -> pg.26 | BB19: =IFERROR(__xludf.DUMMYFUNCTION("REGEXREPLACE(G19, ""_[a-z]{1,2}$"", """")"),"additional_studies1") -> additional_studies1 | BD19: LR
A20: 20 | B20: assigned | C20: double | D20: Daniel | F20: additional_studies10 | G20: additional_studies10_d | H20: Daniel Manrique-Castano | J20: 45683 | K20: The coding of this study was extremely challenging for me and I could not complete it. I feel that the replication study is extremely unclear in describing what effects they are trying to replicate. Although the replication article provides the information for the original research article (DM&D column) in Tables 3 and 4 (p. 11), it is extremely difficult for me to track this information in the original research article. The replication does not specify which of the multiple comparisons they are referring to. In the lines I have filled in, I have been able to infer that the information refers only to the Spanish test. I spent several hours trying to decipher the information, but I am really frustrated because I would need much more time to read the article and the supplementary information to try to understand the issue. For this reason, I do not feel confident to complete the task. Sample size: The replication article reports a sample size of 19. This corresponds exclusively to the group of L2 Spanish speakers. However, my understanding is that the group of native Spanish speakers (n = 6) is also included in the comparisons. Again, it is extremely unclear which comparison the replication is trying to replicate. Therefore, I report 25 as the sample size in the lines I filled in. These entries, and the replication in general, need careful revision. | N20: 10.1111/lang.12161 | P20: =hyperlink(vlookup(lower(N20),'File Links'!A:B, 2, FALSE), SUBSTITUTE(lower(N20), "/", "--") & ".pdf") -> 10.1111--lang.12161.pdf | Q20: {=if(iserror(MATCH(V20, 'File Links'!C:C, 0)), "N/A", HYPERLINK(INDEX('File Links'!B:B, MATCH(P20, 'File Links'!C:C, 0))))} -> https://drive.google.com/file/d/1W_KvsfbanYWBQG9nzoDuqDlzFW_jUYH2/view?usp=drivesdk | R20: Huensch, A. (2024). Clarifying the role of inhibitory control in L2 phonological processing: A preregistered, close replication of Darcy et al.(2016). Studies in Second Language Acquisition, 1-21. https://doi.org/10.1017/S0272263124000238 | S20: 10.1017/S0272263124000238 | V20: =hyperlink(vlookup(lower(S20),'File Links'!E:F, 2, FALSE), SUBSTITUTE(lower(S20), "/", "--") & ".pdf") -> 10.1017--s0272263124000238.pdf | W20: A preregistered, close replication of Darcy et al. (2016) | X20: {=if(iserror(MATCH(V20, 'File Links'!C:C, 0)), "N/A", HYPERLINK(INDEX('File Links'!B:B, MATCH(V20, 'File Links'!C:C, 0))))} -> https://drive.google.com/file/d/1KQ2h_KjNuvgQPQ443vS97noydUJbOuPG/view?usp=drivesdk | Z20: Linguistics | AA20: Production accuracy - /e/ format | AB20: language processing, inhibitory control, second language, phonological processing | AC20: The study measured the production accuracy of /e/ format using a delayed sentence repetition task. | AN20: NA | AO20: 58 | AP20: 3.31 | AQ20: d | AR20: 1.26 / 0.38 | AV20: yes | AW20: https://osf.io/w4gj2 | AX20: 2 - close | AY20: =IFERROR(__xludf.DUMMYFUNCTION("vlookup(BB20,importrange(""https://docs.google.com/spreadsheets/d/1d2vevQ_7D_v35q4wCQ4RpQ_IPoTwEMB9Yp6ymwlPqew/edit?gid=984458430#gid=984458430"", ""'replication success'!A:K""), 11, FAlSE)"),"failed") -> failed | AZ20: =IFERROR(__xludf.DUMMYFUNCTION("vlookup(BB20,importrange(""https://docs.google.com/spreadsheets/d/1d2vevQ_7D_v35q4wCQ4RpQ_IPoTwEMB9Yp6ymwlPqew/edit?gid=984458430#gid=984458430"", ""'replication success'!A:M""), 12, FAlSE)"),"However, results of the partial correlation analyses in the current replication did not indicate clear relationships between phonological variables and inhibi- tory control.") -> However, results of the partial correlation analyses in the current replication did not indicate clear relationships between phonological variables and inhibi- tory control. | BA20: =IFERROR(__xludf.DUMMYFUNCTION("vlookup(BB20,importrange(""https://docs.google.com/spreadsheets/d/1d2vevQ_7D_v35q4wCQ4RpQ_IPoTwEMB9Yp6ymwlPqew/edit?gid=984458430#gid=984458430"", ""'replication success'!A:M""), 13, FAlSE)"),"abstract") -> abstract | BB20: =IFERROR(__xludf.DUMMYFUNCTION("REGEXREPLACE(G20, ""_[a-z]{1,2}$"", """")"),"additional_studies10") -> additional_studies10
A21: 21 | B21: assigned | C21: double | D21: Daniel | F21: additional_studies10 | G21: additional_studies10_e | H21: Daniel Manrique-Castano | J21: 45683 | K21: The coding of this study was extremely challenging for me and I could not complete it. I feel that the replication study is extremely unclear in describing what effects they are trying to replicate. Although the replication article provides the information for the original research article (DM&D column) in Tables 3 and 4 (p. 11), it is extremely difficult for me to track this information in the original research article. The replication does not specify which of the multiple comparisons they are referring to. In the lines I have filled in, I have been able to infer that the information refers only to the Spanish test. I spent several hours trying to decipher the information, but I am really frustrated because I would need much more time to read the article and the supplementary information to try to understand the issue. For this reason, I do not feel confident to complete the task. Sample size: The replication article reports a sample size of 19. This corresponds exclusively to the group of L2 Spanish speakers. However, my understanding is that the group of native Spanish speakers (n = 6) is also included in the comparisons. Again, it is extremely unclear which comparison the replication is trying to replicate. Therefore, I report 25 as the sample size in the lines I filled in. These entries, and the replication in general, need careful revision. | N21: 10.1111/lang.12161 | P21: =hyperlink(vlookup(lower(N21),'File Links'!A:B, 2, FALSE), SUBSTITUTE(lower(N21), "/", "--") & ".pdf") -> 10.1111--lang.12161.pdf | Q21: {=if(iserror(MATCH(V21, 'File Links'!C:C, 0)), "N/A", HYPERLINK(INDEX('File Links'!B:B, MATCH(P21, 'File Links'!C:C, 0))))} -> https://drive.google.com/file/d/1W_KvsfbanYWBQG9nzoDuqDlzFW_jUYH2/view?usp=drivesdk | R21: Huensch, A. (2024). Clarifying the role of inhibitory control in L2 phonological processing: A preregistered, close replication of Darcy et al.(2016). Studies in Second Language Acquisition, 1-21. https://doi.org/10.1017/S0272263124000238 | S21: 10.1017/S0272263124000238 | V21: =hyperlink(vlookup(lower(S21),'File Links'!E:F, 2, FALSE), SUBSTITUTE(lower(S21), "/", "--") & ".pdf") -> 10.1017--s0272263124000238.pdf | W21: A preregistered, close replication of Darcy et al. (2016) | X21: {=if(iserror(MATCH(V21, 'File Links'!C:C, 0)), "N/A", HYPERLINK(INDEX('File Links'!B:B, MATCH(V21, 'File Links'!C:C, 0))))} -> https://drive.google.com/file/d/1KQ2h_KjNuvgQPQ443vS97noydUJbOuPG/view?usp=drivesdk | Z21: Linguistics | AA21: Production accuracy - /ei̯/ ~ /e/ | AB21: language processing, inhibitory control, second language, phonological processing | AC21: The study measured the production accuracy of /ei/ ~ /e/ format using a delayed sentence repetition task. | AD21: Instead, they produced both vowels as a monophthongal /e/, with very little formant movement (1.18 for diphthongs vs. 0.92 for monophthongs, SD = 0.36), t(18) = 1.92, p = .071, r = .17, but distinguished them through duration. | AE21: p. 17 | AF21: 25 | AG21: 0.17 | AH21: r | AI21: t(18) = 1.92 | AJ21: 0.71 | AK21: e (=) | AL21: NA (not reported) | AM21: yes | AN21: NA | AO21: 58 | AP21: 0.64 | AQ21: d | AR21: p. 11 | AS21: 0.001 | AT21: l (<) | AU21: NA (not reported) | AV21: yes | AW21: https://osf.io/w4gj2 | AX21: 2 - close | AY21: =IFERROR(__xludf.DUMMYFUNCTION("vlookup(BB21,importrange(""https://docs.google.com/spreadsheets/d/1d2vevQ_7D_v35q4wCQ4RpQ_IPoTwEMB9Yp6ymwlPqew/edit?gid=984458430#gid=984458430"", ""'replication success'!A:K""), 11, FAlSE)"),"failed") -> failed | AZ21: =IFERROR(__xludf.DUMMYFUNCTION("vlookup(BB21,importrange(""https://docs.google.com/spreadsheets/d/1d2vevQ_7D_v35q4wCQ4RpQ_IPoTwEMB9Yp6ymwlPqew/edit?gid=984458430#gid=984458430"", ""'replication success'!A:M""), 12, FAlSE)"),"However, results of the partial correlation analyses in the current replication did not indicate clear relationships between phonological variables and inhibi- tory control.") -> However, results of the partial correlation analyses in the current replication did not indicate clear relationships between phonological variables and inhibi- tory control. | BA21: =IFERROR(__xludf.DUMMYFUNCTION("vlookup(BB21,importrange(""https://docs.google.com/spreadsheets/d/1d2vevQ_7D_v35q4wCQ4RpQ_IPoTwEMB9Yp6ymwlPqew/edit?gid=984458430#gid=984458430"", ""'replication success'!A:M""), 13, FAlSE)"),"abstract") -> abstract | BB21: =IFERROR(__xludf.DUMMYFUNCTION("REGEXREPLACE(G21, ""_[a-z]{1,2}$"", """")"),"additional_studies10") -> additional_studies10
A22: 22 | B22: assigned | C22: double | D22: Daniel | F22: additional_studies10 | G22: additional_studies10_f | H22: Daniel Manrique-Castano | J22: 45683 | K22: The coding of this study was extremely challenging for me and I could not complete it. I feel that the replication study is extremely unclear in describing what effects they are trying to replicate. Although the replication article provides the information for the original research article (DM&D column) in Tables 3 and 4 (p. 11), it is extremely difficult for me to track this information in the original research article. The replication does not specify which of the multiple comparisons they are referring to. In the lines I have filled in, I have been able to infer that the information refers only to the Spanish test. I spent several hours trying to decipher the information, but I am really frustrated because I would need much more time to read the article and the supplementary information to try to understand the issue. For this reason, I do not feel confident to complete the task. Sample size: The replication article reports a sample size of 19. This corresponds exclusively to the group of L2 Spanish speakers. However, my understanding is that the group of native Spanish speakers (n = 6) is also included in the comparisons. Again, it is extremely unclear which comparison the replication is trying to replicate. Therefore, I report 25 as the sample size in the lines I filled in. These entries, and the replication in general, need careful revision. | N22: 10.1111/lang.12161 | P22: =hyperlink(vlookup(lower(N22),'File Links'!A:B, 2, FALSE), SUBSTITUTE(lower(N22), "/", "--") & ".pdf") -> 10.1111--lang.12161.pdf | Q22: {=if(iserror(MATCH(V22, 'File Links'!C:C, 0)), "N/A", HYPERLINK(INDEX('File Links'!B:B, MATCH(P22, 'File Links'!C:C, 0))))} -> https://drive.google.com/file/d/1W_KvsfbanYWBQG9nzoDuqDlzFW_jUYH2/view?usp=drivesdk | R22: Huensch, A. (2024). Clarifying the role of inhibitory control in L2 phonological processing: A preregistered, close replication of Darcy et al.(2016). Studies in Second Language Acquisition, 1-21. https://doi.org/10.1017/S0272263124000238 | S22: 10.1017/S0272263124000238 | V22: =hyperlink(vlookup(lower(S22),'File Links'!E:F, 2, FALSE), SUBSTITUTE(lower(S22), "/", "--") & ".pdf") -> 10.1017--s0272263124000238.pdf | W22: A preregistered, close replication of Darcy et al. (2016) | X22: {=if(iserror(MATCH(V22, 'File Links'!C:C, 0)), "N/A", HYPERLINK(INDEX('File Links'!B:B, MATCH(V22, 'File Links'!C:C, 0))))} -> https://drive.google.com/file/d/1KQ2h_KjNuvgQPQ443vS97noydUJbOuPG/view?usp=drivesdk | Z22: Linguistics | AA22: Production accuracy - /ei̯/ z score | AB22: language processing, inhibitory control, second language, phonological processing | AC22: The study measured the production accuracy of /ei/ ~ z score format using a delayed sentence repetition task. | AN22: NA | AO22: 58 | AP22: -2.67 | AQ22: d | AR22: 2.27 / 0.85 | AW22: https://osf.io/w4gj2 | AX22: 2 - close | AY22: =IFERROR(__xludf.DUMMYFUNCTION("vlookup(BB22,importrange(""https://docs.google.com/spreadsheets/d/1d2vevQ_7D_v35q4wCQ4RpQ_IPoTwEMB9Yp6ymwlPqew/edit?gid=984458430#gid=984458430"", ""'replication success'!A:K""), 11, FAlSE)"),"failed") -> failed | AZ22: =IFERROR(__xludf.DUMMYFUNCTION("vlookup(BB22,importrange(""https://docs.google.com/spreadsheets/d/1d2vevQ_7D_v35q4wCQ4RpQ_IPoTwEMB9Yp6ymwlPqew/edit?gid=984458430#gid=984458430"", ""'replication success'!A:M""), 12, FAlSE)"),"However, results of the partial correlation analyses in the current replication did not indicate clear relationships between phonological variables and inhibi- tory control.") -> However, results of the partial correlation analyses in the current replication did not indicate clear relationships between phonological variables and inhibi- tory control. | BA22: =IFERROR(__xludf.DUMMYFUNCTION("vlookup(BB22,importrange(""https://docs.google.com/spreadsheets/d/1d2vevQ_7D_v35q4wCQ4RpQ_IPoTwEMB9Yp6ymwlPqew/edit?gid=984458430#gid=984458430"", ""'replication success'!A:M""), 13, FAlSE)"),"abstract") -> abstract | BB22: =IFERROR(__xludf.DUMMYFUNCTION("REGEXREPLACE(G22, ""_[a-z]{1,2}$"", """")"),"additional_studies10") -> additional_studies10
A23: 23 | B23: assigned | C23: double | D23: Daniel | F23: additional_studies10 | G23: additional_studies10_g | H23: Daniel Manrique-Castano | J23: 45683 | K23: The coding of this study was extremely challenging for me and I could not complete it. I feel that the replication study is extremely unclear in describing what effects they are trying to replicate. Although the replication article provides the information for the original research article (DM&D column) in Tables 3 and 4 (p. 11), it is extremely difficult for me to track this information in the original research article. The replication does not specify which of the multiple comparisons they are referring to. In the lines I have filled in, I have been able to infer that the information refers only to the Spanish test. I spent several hours trying to decipher the information, but I am really frustrated because I would need much more time to read the article and the supplementary information to try to understand the issue. For this reason, I do not feel confident to complete the task. Sample size: The replication article reports a sample size of 19. This corresponds exclusively to the group of L2 Spanish speakers. However, my understanding is that the group of native Spanish speakers (n = 6) is also included in the comparisons. Again, it is extremely unclear which comparison the replication is trying to replicate. Therefore, I report 25 as the sample size in the lines I filled in. These entries, and the replication in general, need careful revision. | N23: 10.1111/lang.12161 | P23: =hyperlink(vlookup(lower(N23),'File Links'!A:B, 2, FALSE), SUBSTITUTE(lower(N23), "/", "--") & ".pdf") -> 10.1111--lang.12161.pdf | Q23: {=if(iserror(MATCH(V23, 'File Links'!C:C, 0)), "N/A", HYPERLINK(INDEX('File Links'!B:B, MATCH(P23, 'File Links'!C:C, 0))))} -> https://drive.google.com/file/d/1W_KvsfbanYWBQG9nzoDuqDlzFW_jUYH2/view?usp=drivesdk | R23: Huensch, A. (2024). Clarifying the role of inhibitory control in L2 phonological processing: A preregistered, close replication of Darcy et al.(2016). Studies in Second Language Acquisition, 1-21. https://doi.org/10.1017/S0272263124000238 | S23: 10.1017/S0272263124000238 | V23: =hyperlink(vlookup(lower(S23),'File Links'!E:F, 2, FALSE), SUBSTITUTE(lower(S23), "/", "--") & ".pdf") -> 10.1017--s0272263124000238.pdf | W23: A preregistered, close replication of Darcy et al. (2016) | X23: {=if(iserror(MATCH(V23, 'File Links'!C:C, 0)), "N/A", HYPERLINK(INDEX('File Links'!B:B, MATCH(V23, 'File Links'!C:C, 0))))} -> https://drive.google.com/file/d/1KQ2h_KjNuvgQPQ443vS97noydUJbOuPG/view?usp=drivesdk | Z23: Linguistics | AA23: Production accuracy - Consonant accuracy | AB23: language processing, inhibitory control, second language, phonological processing | AC23: The study measured the production accuracy for consonants using a delayed sentence repetition task. | AN23: NA | AO23: 58 | AP23: 1.94 | AQ23: d | AR23: 4.50 / 2.31 | AW23: https://osf.io/w4gj2 | AX23: 2 - close | AY23: =IFERROR(__xludf.DUMMYFUNCTION("vlookup(BB23,importrange(""https://docs.google.com/spreadsheets/d/1d2vevQ_7D_v35q4wCQ4RpQ_IPoTwEMB9Yp6ymwlPqew/edit?gid=984458430#gid=984458430"", ""'replication success'!A:K""), 11, FAlSE)"),"failed") -> failed | AZ23: =IFERROR(__xludf.DUMMYFUNCTION("vlookup(BB23,importrange(""https://docs.google.com/spreadsheets/d/1d2vevQ_7D_v35q4wCQ4RpQ_IPoTwEMB9Yp6ymwlPqew/edit?gid=984458430#gid=984458430"", ""'replication success'!A:M""), 12, FAlSE)"),"However, results of the partial correlation analyses in the current replication did not indicate clear relationships between phonological variables and inhibi- tory control.") -> However, results of the partial correlation analyses in the current replication did not indicate clear relationships between phonological variables and inhibi- tory control. | BA23: =IFERROR(__xludf.DUMMYFUNCTION("vlookup(BB23,importrange(""https://docs.google.com/spreadsheets/d/1d2vevQ_7D_v35q4wCQ4RpQ_IPoTwEMB9Yp6ymwlPqew/edit?gid=984458430#gid=984458430"", ""'replication success'!A:M""), 13, FAlSE)"),"abstract") -> abstract | BB23: =IFERROR(__xludf.DUMMYFUNCTION("REGEXREPLACE(G23, ""_[a-z]{1,2}$"", """")"),"additional_studies10") -> additional_studies10
A24: 24 | B24: validated - discarded | C24: double | D24: Alexsandr | F24: additional_studies10_1 | G24: additional_studies10_a | H24: Aleksandr Pravednikov | I24: 45625 | J24: 45692 | K24: Claim text_r. Table 8, p. 14 Retrieval–induced inhibition: 1.02 (0.23), [...] Results of the current replication for the partial correlation analyses did not indicate statistically significant relationships, and effect sizes were small with 95% CIs crossing through zero. p. 16 | M24: Darcy, I., Mora, J. C., & Daidone, D. (2016). The role of inhibitory control in second language phonological processing. Language Learning, 66, 741–773. https://doi.org/10.1111/lang.12161 | N24: 10.1111/lang.12161 | O24: 1 | P24: =hyperlink(vlookup(lower(N24),'File Links'!A:B, 2, FALSE), SUBSTITUTE(lower(N24), "/", "--") & ".pdf") -> 10.1111--lang.12161.pdf | Q24: {=if(iserror(MATCH(V24, 'File Links'!C:C, 0)), "N/A", HYPERLINK(INDEX('File Links'!B:B, MATCH(P24, 'File Links'!C:C, 0))))} -> https://drive.google.com/file/d/1W_KvsfbanYWBQG9nzoDuqDlzFW_jUYH2/view?usp=drivesdk | R24: Huensch, A. (2024). Clarifying the role of inhibitory control in L2 phonological processing: A preregistered, close replication of Darcy et al.(2016). Studies in Second Language Acquisition, 1-21. https://doi.org/10.1017/S0272263124000238 | S24: 10.1017/S0272263124000238 | U24: 1 | V24: =hyperlink(vlookup(lower(S24),'File Links'!E:F, 2, FALSE), SUBSTITUTE(lower(S24), "/", "--") & ".pdf") -> 10.1017--s0272263124000238.pdf | W24: close replication | X24: {=if(iserror(MATCH(V24, 'File Links'!C:C, 0)), "N/A", HYPERLINK(INDEX('File Links'!B:B, MATCH(V24, 'File Links'!C:C, 0))))} -> https://drive.google.com/file/d/1KQ2h_KjNuvgQPQ443vS97noydUJbOuPG/view?usp=drivesdk | Z24: Linguistics | AA24: Second Language Phonological Processing | AB24: language processing, inhibitory control, second language, phonological processing | AC24: Role of inhibitory control in L2 phonological processing (Retrieval–induced inhibition) | AD24: Table 7 summarizes the results of correlation analyses between inhibition scores and the four phonological accuracy scores (controlling for proficiency). These correlations show that error rate and z scores in ABX perception were significantly negatively correlated with inhibition scores, which indicates that individuals with higher inhibition scores also obtained lower error rates and lower (more targetlike)zscores in vowel perception. | AE24: 21 | AF24: 18 | AK24: l (<) | AL24: NA (not reported) | AN24: NA | AO24: 58 | AU24: NA (not reported) | AX24: close | AY24: =IFERROR(__xludf.DUMMYFUNCTION("vlookup(BB24,importrange(""https://docs.google.com/spreadsheets/d/1d2vevQ_7D_v35q4wCQ4RpQ_IPoTwEMB9Yp6ymwlPqew/edit?gid=984458430#gid=984458430"", ""'replication success'!A:K""), 11, FAlSE)"),"failed") -> failed | AZ24: =IFERROR(__xludf.DUMMYFUNCTION("vlookup(BB24,importrange(""https://docs.google.com/spreadsheets/d/1d2vevQ_7D_v35q4wCQ4RpQ_IPoTwEMB9Yp6ymwlPqew/edit?gid=984458430#gid=984458430"", ""'replication success'!A:M""), 12, FAlSE)"),"However, results of the partial correlation analyses in the current replication did not indicate clear relationships between phonological variables and inhibi- tory control.") -> However, results of the partial correlation analyses in the current replication did not indicate clear relationships between phonological variables and inhibi- tory control. | BA24: =IFERROR(__xludf.DUMMYFUNCTION("vlookup(BB24,importrange(""https://docs.google.com/spreadsheets/d/1d2vevQ_7D_v35q4wCQ4RpQ_IPoTwEMB9Yp6ymwlPqew/edit?gid=984458430#gid=984458430"", ""'replication success'!A:M""), 13, FAlSE)"),"abstract") -> abstract | BB24: =IFERROR(__xludf.DUMMYFUNCTION("REGEXREPLACE(G24, ""_[a-z]{1,2}$"", """")"),"additional_studies10") -> additional_studies10 | BD24: LR
A25: 25 | B25: validated - chosen | C25: double | D25: Alexsandr | F25: additional_studies10_1 | G25: additional_studies10_b | H25: Aleksandr Pravednikov | I25: 45625 | J25: 45692 | K25: Claim text_r. Table 8, p. 14 ABX error (vowels) 19.2 (13.2) [...] Results of the current replication for the partial correlation analyses did not indicate statistically significant relationships, and effect sizes were small with 95% CIs crossing through zero. p. 16 | L25: coded as nested due to hierarchical regression; a fourth effect is reported for the replication but NA for the original study; p_val_tails_r coded as one because it says in the note "as reported in DM&D", where p-values are one-tailed. Note that in the table two-tailed CIs are reported | M25: Darcy, I., Mora, J. C., & Daidone, D. (2016). The role of inhibitory control in second language phonological processing. Language Learning, 66, 741–773. https://doi.org/10.1111/lang.12161 | N25: 10.1111/lang.12161 | O25: 1 | P25: =hyperlink(vlookup(lower(N25),'File Links'!A:B, 2, FALSE), SUBSTITUTE(lower(N25), "/", "--") & ".pdf") -> 10.1111--lang.12161.pdf | Q25: {=if(iserror(MATCH(V25, 'File Links'!C:C, 0)), "N/A", HYPERLINK(INDEX('File Links'!B:B, MATCH(P25, 'File Links'!C:C, 0))))} -> https://drive.google.com/file/d/1W_KvsfbanYWBQG9nzoDuqDlzFW_jUYH2/view?usp=drivesdk | R25: Huensch, A. (2024). Clarifying the role of inhibitory control in L2 phonological processing: A preregistered, close replication of Darcy et al.(2016). Studies in Second Language Acquisition, 1-21. https://doi.org/10.1017/S0272263124000238 | S25: 10.1017/S0272263124000238 | U25: 1 | V25: =hyperlink(vlookup(lower(S25),'File Links'!E:F, 2, FALSE), SUBSTITUTE(lower(S25), "/", "--") & ".pdf") -> 10.1017--s0272263124000238.pdf | W25: close replication | X25: {=if(iserror(MATCH(V25, 'File Links'!C:C, 0)), "N/A", HYPERLINK(INDEX('File Links'!B:B, MATCH(V25, 'File Links'!C:C, 0))))} -> https://drive.google.com/file/d/1KQ2h_KjNuvgQPQ443vS97noydUJbOuPG/view?usp=drivesdk | Z25: Linguistics | AA25: Second Language Phonological Processing | AB25: language processing, inhibitory control, second language, phonological processing | AC25: Role of inhibitory control in L2 phonological processing (ABX error (vowels)) | AD25: Table 7 summarizes the results of correlation analyses between inhibition scores and the four phonological accuracy scores (controlling for proficiency). These correlations show that error rate and z scores in ABX perception were significantly negatively correlated with inhibition scores, which indicates that individuals with higher inhibition scores also obtained lower error rates and lower (more targetlike)zscores in vowel perception. | AE25: 33 | AF25: 18 | AG25: -0.42 | AH25: partial r | AI25: p. 23 | AJ25: 0.01 | AK25: l (<) | AL25: 1 (one) | AM25: yes | AN25: NA | AO25: 58 | AP25: -0.13 | AQ25: partial r | AR25: p. 15, Table 10 | AS25: 0.379 | AT25: e (=) | AU25: 1 (one) | AV25: yes | AW25: https://osf.io/w4gj2 | AX25: close | AY25: =IFERROR(__xludf.DUMMYFUNCTION("vlookup(BB25,importrange(""https://docs.google.com/spreadsheets/d/1d2vevQ_7D_v35q4wCQ4RpQ_IPoTwEMB9Yp6ymwlPqew/edit?gid=984458430#gid=984458430"", ""'replication success'!A:K""), 11, FAlSE)"),"failed") -> failed | AZ25: =IFERROR(__xludf.DUMMYFUNCTION("vlookup(BB25,importrange(""https://docs.google.com/spreadsheets/d/1d2vevQ_7D_v35q4wCQ4RpQ_IPoTwEMB9Yp6ymwlPqew/edit?gid=984458430#gid=984458430"", ""'replication success'!A:M""), 12, FAlSE)"),"However, results of the partial correlation analyses in the current replication did not indicate clear relationships between phonological variables and inhibi- tory control.") -> However, results of the partial correlation analyses in the current replication did not indicate clear relationships between phonological variables and inhibi- tory control. | BA25: =IFERROR(__xludf.DUMMYFUNCTION("vlookup(BB25,importrange(""https://docs.google.com/spreadsheets/d/1d2vevQ_7D_v35q4wCQ4RpQ_IPoTwEMB9Yp6ymwlPqew/edit?gid=984458430#gid=984458430"", ""'replication success'!A:M""), 13, FAlSE)"),"abstract") -> abstract | BB25: =IFERROR(__xludf.DUMMYFUNCTION("REGEXREPLACE(G25, ""_[a-z]{1,2}$"", """")"),"additional_studies10") -> additional_studies10 | BD25: LR
A26: 26 | B26: validated - chosen | C26: double | D26: Alexsandr | F26: additional_studies10_1 | G26: additional_studies10_c | H26: Aleksandr Pravednikov | I26: 45625 | J26: 45692 | K26: Claim text_r. Table 8, p. 14 Vowel production z score: –2.27 (0.85)[...] Results of the current replication for the partial correlation analyses did not indicate statistically significant relationships, and effect sizes were small with 95% CIs crossing through zero. p. 16 | L26: coded as nested due to hierarchical regression; a fourth effect is reported for the replication but NA for the original study; p_val_tails_r coded as one because it says in the note "as reported in DM&D", where p-values are one-tailed. Note that in the table two-tailed CIs are reported | M26: Darcy, I., Mora, J. C., & Daidone, D. (2016). The role of inhibitory control in second language phonological processing. Language Learning, 66, 741–773. https://doi.org/10.1111/lang.12161 | N26: 10.1111/lang.12161 | O26: 1 | P26: =hyperlink(vlookup(lower(N26),'File Links'!A:B, 2, FALSE), SUBSTITUTE(lower(N26), "/", "--") & ".pdf") -> 10.1111--lang.12161.pdf | Q26: {=if(iserror(MATCH(V26, 'File Links'!C:C, 0)), "N/A", HYPERLINK(INDEX('File Links'!B:B, MATCH(P26, 'File Links'!C:C, 0))))} -> https://drive.google.com/file/d/1W_KvsfbanYWBQG9nzoDuqDlzFW_jUYH2/view?usp=drivesdk | R26: Huensch, A. (2024). Clarifying the role of inhibitory control in L2 phonological processing: A preregistered, close replication of Darcy et al.(2016). Studies in Second Language Acquisition, 1-21. https://doi.org/10.1017/S0272263124000238 | S26: 10.1017/S0272263124000238 | U26: 1 | V26: =hyperlink(vlookup(lower(S26),'File Links'!E:F, 2, FALSE), SUBSTITUTE(lower(S26), "/", "--") & ".pdf") -> 10.1017--s0272263124000238.pdf | W26: close replication | X26: {=if(iserror(MATCH(V26, 'File Links'!C:C, 0)), "N/A", HYPERLINK(INDEX('File Links'!B:B, MATCH(V26, 'File Links'!C:C, 0))))} -> https://drive.google.com/file/d/1KQ2h_KjNuvgQPQ443vS97noydUJbOuPG/view?usp=drivesdk | Z26: Linguistics | AA26: Second Language Phonological Processing | AB26: language processing, inhibitory control, second language, phonological processing | AC26: Role of inhibitory control in L2 phonological processing (Vowel production z score) | AD26: Table 7 summarizes the results of correlation analyses between inhibition scores and the four phonological accuracy scores (controlling for proficiency). These correlations show that error rate and z scores in ABX perception were significantly negatively correlated with inhibition scores, which indicates that individuals with higher inhibition scores also obtained lower error rates and lower (more targetlike)zscores in vowel perception. | AE26: 33 | AF26: 18 | AG26: -0.04 | AH26: partial r | AI26: p. 23 | AJ26: 0.05 | AK26: g (>) | AL26: 1 (one) | AM26: yes | AN26: NA | AO26: 58 | AP26: 0.09 | AQ26: partial r | AR26: p. 15, Table 10 | AS26: 0.529 | AT26: e (=) | AU26: 1 (one) | AV26: yes | AW26: https://osf.io/w4gj2 | AX26: close | AY26: =IFERROR(__xludf.DUMMYFUNCTION("vlookup(BB26,importrange(""https://docs.google.com/spreadsheets/d/1d2vevQ_7D_v35q4wCQ4RpQ_IPoTwEMB9Yp6ymwlPqew/edit?gid=984458430#gid=984458430"", ""'replication success'!A:K""), 11, FAlSE)"),"failed") -> failed | AZ26: =IFERROR(__xludf.DUMMYFUNCTION("vlookup(BB26,importrange(""https://docs.google.com/spreadsheets/d/1d2vevQ_7D_v35q4wCQ4RpQ_IPoTwEMB9Yp6ymwlPqew/edit?gid=984458430#gid=984458430"", ""'replication success'!A:M""), 12, FAlSE)"),"However, results of the partial correlation analyses in the current replication did not indicate clear relationships between phonological variables and inhibi- tory control.") -> However, results of the partial correlation analyses in the current replication did not indicate clear relationships between phonological variables and inhibi- tory control. | BA26: =IFERROR(__xludf.DUMMYFUNCTION("vlookup(BB26,importrange(""https://docs.google.com/spreadsheets/d/1d2vevQ_7D_v35q4wCQ4RpQ_IPoTwEMB9Yp6ymwlPqew/edit?gid=984458430#gid=984458430"", ""'replication success'!A:M""), 13, FAlSE)"),"abstract") -> abstract | BB26: =IFERROR(__xludf.DUMMYFUNCTION("REGEXREPLACE(G26, ""_[a-z]{1,2}$"", """")"),"additional_studies10") -> additional_studies10 | BD26: LR
A27: 27 | B27: validated - chosen | C27: double | D27: Alexsandr | F27: additional_studies10_1 | G27: additional_studies10_d | H27: Aleksandr Pravednikov | I27: 45625 | J27: 45692 | K27: Claim text_r. Table 8, p. 14 Consonant production (max. 8): 4.50 (2.31) [...] Results of the current replication for the partial correlation analyses did not indicate statistically significant relationships, and effect sizes were small with 95% CIs crossing through zero. p. 16 | L27: coded as nested due to hierarchical regression; a fourth effect is reported for the replication but NA for the original study; p_val_tails_r coded as one because it says in the note "as reported in DM&D", where p-values are one-tailed. Note that in the table two-tailed CIs are reported | M27: Darcy, I., Mora, J. C., & Daidone, D. (2016). The role of inhibitory control in second language phonological processing. Language Learning, 66, 741–773. https://doi.org/10.1111/lang.12161 | N27: 10.1111/lang.12161 | O27: 1 | P27: =hyperlink(vlookup(lower(N27),'File Links'!A:B, 2, FALSE), SUBSTITUTE(lower(N27), "/", "--") & ".pdf") -> 10.1111--lang.12161.pdf | Q27: {=if(iserror(MATCH(V27, 'File Links'!C:C, 0)), "N/A", HYPERLINK(INDEX('File Links'!B:B, MATCH(P27, 'File Links'!C:C, 0))))} -> https://drive.google.com/file/d/1W_KvsfbanYWBQG9nzoDuqDlzFW_jUYH2/view?usp=drivesdk | R27: Huensch, A. (2024). Clarifying the role of inhibitory control in L2 phonological processing: A preregistered, close replication of Darcy et al.(2016). Studies in Second Language Acquisition, 1-21. https://doi.org/10.1017/S0272263124000238 | S27: 10.1017/S0272263124000238 | U27: 1 | V27: =hyperlink(vlookup(lower(S27),'File Links'!E:F, 2, FALSE), SUBSTITUTE(lower(S27), "/", "--") & ".pdf") -> 10.1017--s0272263124000238.pdf | W27: close replication | X27: {=if(iserror(MATCH(V27, 'File Links'!C:C, 0)), "N/A", HYPERLINK(INDEX('File Links'!B:B, MATCH(V27, 'File Links'!C:C, 0))))} -> https://drive.google.com/file/d/1KQ2h_KjNuvgQPQ443vS97noydUJbOuPG/view?usp=drivesdk | Z27: Linguistics | AA27: Second Language Phonological Processing | AB27: language processing, inhibitory control, second language, phonological processing | AC27: Role of inhibitory control in L2 phonological processing (Consonant production (max. 8)) | AD27: Table 7 summarizes the results of correlation analyses between inhibition scores and the four phonological accuracy scores (controlling for proficiency). These correlations show that error rate and z scores in ABX perception were significantly negatively correlated with inhibition scores, which indicates that individuals with higher inhibition scores also obtained lower error rates and lower (more targetlike)zscores in vowel perception. | AE27: 33 | AF27: 18 | AG27: 0.34 | AH27: partial r | AI27: p. 23 | AJ27: 0.05 | AK27: l (<) | AL27: 1 (one) | AM27: yes | AN27: NA | AO27: 58 | AP27: 0.07 | AQ27: partial r | AR27: p. 15, Table 10 | AS27: 0.61 | AT27: e (=) | AU27: 1 (one) | AV27: yes | AW27: https://osf.io/w4gj2 | AX27: close | AY27: =IFERROR(__xludf.DUMMYFUNCTION("vlookup(BB27,importrange(""https://docs.google.com/spreadsheets/d/1d2vevQ_7D_v35q4wCQ4RpQ_IPoTwEMB9Yp6ymwlPqew/edit?gid=984458430#gid=984458430"", ""'replication success'!A:K""), 11, FAlSE)"),"failed") -> failed | AZ27: =IFERROR(__xludf.DUMMYFUNCTION("vlookup(BB27,importrange(""https://docs.google.com/spreadsheets/d/1d2vevQ_7D_v35q4wCQ4RpQ_IPoTwEMB9Yp6ymwlPqew/edit?gid=984458430#gid=984458430"", ""'replication success'!A:M""), 12, FAlSE)"),"However, results of the partial correlation analyses in the current replication did not indicate clear relationships between phonological variables and inhibi- tory control.") -> However, results of the partial correlation analyses in the current replication did not indicate clear relationships between phonological variables and inhibi- tory control. | BA27: =IFERROR(__xludf.DUMMYFUNCTION("vlookup(BB27,importrange(""https://docs.google.com/spreadsheets/d/1d2vevQ_7D_v35q4wCQ4RpQ_IPoTwEMB9Yp6ymwlPqew/edit?gid=984458430#gid=984458430"", ""'replication success'!A:M""), 13, FAlSE)"),"abstract") -> abstract | BB27: =IFERROR(__xludf.DUMMYFUNCTION("REGEXREPLACE(G27, ""_[a-z]{1,2}$"", """")"),"additional_studies10") -> additional_studies10 | BD27: LR
A28: 28 | B28: validated - discarded | C28: double | D28: Daniel | F28: additional_studies10_1 | G28: additional_studies10 | H28: Daniel Manrique-Castano | I28: 45683 | J28: 45692 | K28: The coding of this study was extremely challenging for me and I could not complete it. I feel that the replication study is extremely unclear in describing what effects they are trying to replicate. Although the replication article provides the information for the original research article (DM&D column) in Tables 3 and 4 (p. 11), it is extremely difficult for me to track this information in the original research article. The replication does not specify which of the multiple comparisons they are referring to. In the lines I have filled in, I have been able to infer that the information refers only to the Spanish test. I spent several hours trying to decipher the information, but I am really frustrated because I would need much more time to read the article and the supplementary information to try to understand the issue. For this reason, I do not feel confident to complete the task. Sample size: The replication article reports a sample size of 19. This corresponds exclusively to the group of L2 Spanish speakers. However, my understanding is that the group of native Spanish speakers (n = 6) is also included in the comparisons. Again, it is extremely unclear which comparison the replication is trying to replicate. Therefore, I report 25 as the sample size in the lines I filled in. These entries, and the replication in general, need careful revision. | M28: Darcy, I., Mora, J. C., & Daidone, D. (2016). The role of inhibitory control in second language phonological processing. Language Learning, 66, 741–773. https://doi.org/10.1111/lang.12161 | N28: 10.1111/lang.12161 | O28: 1 | P28: 10.1111--lang.12161.pdf | Q28: {=if(iserror(MATCH(V28, 'File Links'!C:C, 0)), "N/A", HYPERLINK(INDEX('File Links'!B:B, MATCH(P28, 'File Links'!C:C, 0))))} -> https://drive.google.com/file/d/1W_KvsfbanYWBQG9nzoDuqDlzFW_jUYH2/view?usp=drivesdk | R28: Huensch, A. (2024). Clarifying the role of inhibitory control in L2 phonological processing: A preregistered, close replication of Darcy et al.(2016). Studies in Second Language Acquisition, 1-21. https://doi.org/10.1017/S0272263124000238 | S28: 10.1017/S0272263124000238 | U28: 1 | V28: =hyperlink(vlookup(lower(S28),'File Links'!E:F, 2, FALSE), SUBSTITUTE(lower(S28), "/", "--") & ".pdf") -> 10.1017--s0272263124000238.pdf | W28: close replication | X28: {=if(iserror(MATCH(V28, 'File Links'!C:C, 0)), "N/A", HYPERLINK(INDEX('File Links'!B:B, MATCH(V28, 'File Links'!C:C, 0))))} -> https://drive.google.com/file/d/1KQ2h_KjNuvgQPQ443vS97noydUJbOuPG/view?usp=drivesdk | Z28: Linguistics | AA28: Second Language Phonological Processing | AB28: language processing, inhibitory control, second language, phonological processing | AC28: The study measured the perceptual processing of Spanish vowels using the speeded ABX categorization task. | AD28: The test subconditions consE and vowelE did not differ from each other (Merr = 4.6%, CI = 1.0–8.2; and Merr = 3.6%, CI = 0–7.2, respectively), but they triggered significantly fewer errors than the nonnative consS and vowelS subconditions (Merr = 24.0%, CI = 20.4–27.6; and Merr = 19.1%, CI = 15.5–22.7, respectively). p. 13, 14 25 0.955 d 19.1 / 20 0.1 l (<) NA (not reported) yes 58 1.45 d 19.2 / 13.2 yes https://osf.io/w4gj2 2 - close additional_studies10_b Daniel Manrique-Castano 26/01/2025 The coding of this study was extremely challenging for me and I could not complete it. I feel that the replication study is extremely unclear in describing what effects they are trying to replicate. Although the replication article provides the information for the original research article (DM&D column) in Tables 3 and 4 (p. 11), it is extremely difficult for me to track this information in the original research article. The replication does not specify which of the multiple comparisons they are referring to. In the lines I have filled in, I have been able to infer that the information refers only to the Spanish test. I spent several hours trying to decipher the information, but I am really frustrated because I would need much more time to read the article and the supplementary information to try to understand the issue. For this reason, I do not feel confident to complete the task. Sample size: The replication article reports a sample size of 19. This corresponds exclusively to the group of L2 Spanish speakers. However, my understanding is that the group of native Spanish speakers (n = 6) is also included in the comparisons. Again, it is extremely unclear which comparison the replication is trying to replicate. Therefore, I report 25 as the sample size in the lines I filled in. These entries, and the replication in general, need careful revision. 10.1111/lang.12161 A preregistered, close replication of Darcy et al. (2016)" | AF28: Linguistics | AG28: Perceptual processing - Spanish Consonant | AH28: NA | AI28: The study measured the perceptual processing of Spanish consonants using the speeded ABX categorization task. | AL28: Linguistics | AM28: Production accuracy - /ei/ format | AO28: The study measured the production accuracy of /ei/ format using a delayed sentence repetition task. | AP28: The two groups differed in the amount of formant movement during vowel production. The L2 Spanish learners were found to produce the Spanish diphthong /ei/ with much less formant movement (M = 1.18, SD = 0.55) than native controls (M = 3.19, SD = 0.71), as shown in Figure 2, Mann-Whitney U = 113.0, z = 3.56, p < .001, r = .71.. | AQ28: NA | AR28: 25 | AS28: 0.71 | AT28: r | AU28: p. 17 | AV28: 0.001 | AW28: l (<) | AX28: NA (not reported) | AY28: =IFERROR(__xludf.DUMMYFUNCTION("vlookup(BB28,importrange(""https://docs.google.com/spreadsheets/d/1d2vevQ_7D_v35q4wCQ4RpQ_IPoTwEMB9Yp6ymwlPqew/edit?gid=984458430#gid=984458430"", ""'replication success'!A:K""), 11, FAlSE)"),"failed") -> failed | AZ28: =IFERROR(__xludf.DUMMYFUNCTION("vlookup(BB28,importrange(""https://docs.google.com/spreadsheets/d/1d2vevQ_7D_v35q4wCQ4RpQ_IPoTwEMB9Yp6ymwlPqew/edit?gid=984458430#gid=984458430"", ""'replication success'!A:M""), 12, FAlSE)"),"However, results of the partial correlation analyses in the current replication did not indicate clear relationships between phonological variables and inhibi- tory control.") -> However, results of the partial correlation analyses in the current replication did not indicate clear relationships between phonological variables and inhibi- tory control. | BA28: =IFERROR(__xludf.DUMMYFUNCTION("vlookup(BB28,importrange(""https://docs.google.com/spreadsheets/d/1d2vevQ_7D_v35q4wCQ4RpQ_IPoTwEMB9Yp6ymwlPqew/edit?gid=984458430#gid=984458430"", ""'replication success'!A:M""), 13, FAlSE)"),"abstract") -> abstract | BB28: =IFERROR(__xludf.DUMMYFUNCTION("REGEXREPLACE(G28, ""_[a-z]{1,2}$"", """")"),"additional_studies10") -> additional_studies10 | BC28: yes | BD28: LR
A29: 29 | B29: validated - discarded | C29: double | D29: Fabienne | F29: additional_studies11_1 | G29: additional_studies11 | H29: Julia Fabienne Sandkühler | I29: 45637 | J29: 45692 | K29: replication N refers to number of couples | M29: Saxey, M. T., LeBaron-Black, A. B., & Curran, M. A. (2022). The Sooner, the Better? Couples' First Financial Discussion, Relationship Quality, and Financial Conflict in Emerging Adulthood. Journal of Financial Therapy, 13 (1) 2. https://doi.org/10.4148/1944-9771.1299 | N29: 10.4148/1944-9771.1299 | P29: 10.4148--1944-9771.1299.pdf | Q29: {=if(iserror(MATCH(V29, 'File Links'!C:C, 0)), "N/A", HYPERLINK(INDEX('File Links'!B:B, MATCH(P29, 'File Links'!C:C, 0))))} -> https://drive.google.com/file/d/1OByNKNsjZqSFHFFyt-o1mPqDkVmgruBu/view?usp=drivesdk | R29: Saxey, M. T., LeBaron‐Black, A. B., Inman, N. F., Yorgason, J. B., & Holmes, E. K. (2024). The earlier couples first discussed finances, the better? A dyadic, longitudinal replication and extension. Family Relations. https://doi.org/10.1111/fare.13030 | S29: 10.1111/fare.13030 | V29: =hyperlink(vlookup(lower(S29),'File Links'!E:F, 2, FALSE), SUBSTITUTE(lower(S29), "/", "--") & ".pdf") -> 10.1111--fare.13030.pdf | W29: dyadic, longitudinal replication and extension | X29: {=if(iserror(MATCH(V29, 'File Links'!C:C, 0)), "N/A", HYPERLINK(INDEX('File Links'!B:B, MATCH(V29, 'File Links'!C:C, 0))))} -> https://drive.google.com/file/d/1TGN_TAtoJI3jhMQTEG2wnN59FCyiXC2_/view?usp=drivesdk | Z29: Social Psychology | AB29: emerging adulthood; financial communication; financial conflict; financial discussion, relationship quality | AC29: Indirect effect present for relationship quality (replication: cross-sectional, wives' answers, effect on themselves) | AD29: Indirect effect present for relationship quality: “initiating financial discussion earlier in a romantic relationship may benefit relationship quality—through financial communication” (most emphasised claim in original) | AE29: 1 | AF29: 1950 | AG29: 0.13 | AH29: beta | AI29: p. 11 | AJ29: 0.001 | AK29: l (<) | AL29: NA (not reported) | AN29: NA | AO29: 1079 | AP29: 0.06 | AQ29: beta (std) | AR29: p. 2538 | AS29: 0.01 | AT29: l (<) | AU29: NA (not reported) | AW29: NA | AX29: 3 - conceptual | AY29: =IFERROR(__xludf.DUMMYFUNCTION("vlookup(BB29,importrange(""https://docs.google.com/spreadsheets/d/1d2vevQ_7D_v35q4wCQ4RpQ_IPoTwEMB9Yp6ymwlPqew/edit?gid=984458430#gid=984458430"", ""'replication success'!A:K""), 11, FAlSE)"),"mixed") -> mixed | AZ29: =IFERROR(__xludf.DUMMYFUNCTION("vlookup(BB29,importrange(""https://docs.google.com/spreadsheets/d/1d2vevQ_7D_v35q4wCQ4RpQ_IPoTwEMB9Yp6ymwlPqew/edit?gid=984458430#gid=984458430"", ""'replication success'!A:M""), 12, FAlSE)"),"Cross-sectionally, both husbands’ and wives’ reports of their first financial discussion predicted better marital satisfaction and fewer financial disagreements through their own report of healthy financial communication. Longitudinally, only husbands’ r"&"eport of the couple’s first financial discussion positively predicted between- person changes in both husbands’ and wives’ marital satifaction two waves later.") -> Cross-sectionally, both husbands’ and wives’ reports of their first financial discussion predicted better marital satisfaction and fewer financial disagreements through their own report of healthy financial communication. Longitudinally, only husbands’ report of the couple’s first financial discussion positively predicted between- person changes in both husbands’ and wives’ marital satifaction two waves later. | BA29: =IFERROR(__xludf.DUMMYFUNCTION("vlookup(BB29,importrange(""https://docs.google.com/spreadsheets/d/1d2vevQ_7D_v35q4wCQ4RpQ_IPoTwEMB9Yp6ymwlPqew/edit?gid=984458430#gid=984458430"", ""'replication success'!A:M""), 13, FAlSE)"),"abstract") -> abstract | BB29: =IFERROR(__xludf.DUMMYFUNCTION("REGEXREPLACE(G29, ""_[a-z]{1,2}$"", """")"),"additional_studies11") -> additional_studies11 | BD29: LR
A30: 30 | B30: validated - discarded | C30: double | D30: Fabienne | F30: additional_studies11_1 | G30: additional_studies11_b | H30: Julia Fabienne Sandkühler | I30: 45637 | J30: 45692 | K30: replication N refers to number of couples | M30: Saxey, M. T., LeBaron-Black, A. B., & Curran, M. A. (2022). The Sooner, the Better? Couples' First Financial Discussion, Relationship Quality, and Financial Conflict in Emerging Adulthood. Journal of Financial Therapy, 13 (1) 2. https://doi.org/10.4148/1944-9771.1299 | N30: 10.4148/1944-9771.1299 | P30: 10.4148--1944-9771.1299.pdf | Q30: {=if(iserror(MATCH(V30, 'File Links'!C:C, 0)), "N/A", HYPERLINK(INDEX('File Links'!B:B, MATCH(P30, 'File Links'!C:C, 0))))} -> https://drive.google.com/file/d/1OByNKNsjZqSFHFFyt-o1mPqDkVmgruBu/view?usp=drivesdk | R30: Saxey, M. T., LeBaron‐Black, A. B., Inman, N. F., Yorgason, J. B., & Holmes, E. K. (2024). The earlier couples first discussed finances, the better? A dyadic, longitudinal replication and extension. Family Relations. https://doi.org/10.1111/fare.13030 | S30: 10.1111/fare.13030 | V30: =hyperlink(vlookup(lower(S30),'File Links'!E:F, 2, FALSE), SUBSTITUTE(lower(S30), "/", "--") & ".pdf") -> 10.1111--fare.13030.pdf | W30: dyadic, longitudinal replication and extension | X30: {=if(iserror(MATCH(V30, 'File Links'!C:C, 0)), "N/A", HYPERLINK(INDEX('File Links'!B:B, MATCH(V30, 'File Links'!C:C, 0))))} -> https://drive.google.com/file/d/1TGN_TAtoJI3jhMQTEG2wnN59FCyiXC2_/view?usp=drivesdk | Z30: Social Psychology | AB30: emerging adulthood; financial communication; financial conflict; financial discussion, relationship quality | AC30: Indirect effect present for relationship quality (replication: cross-sectional, wives' answers, effect on partner) | AD30: Indirect effect present for relationship quality: “initiating financial discussion earlier in a romantic relationship may benefit relationship quality—through financial communication” (most emphasised claim in original) | AE30: 1 | AF30: 1950 | AG30: 0.13 | AH30: beta | AI30: p. 11 | AJ30: 0.001 | AK30: l (<) | AL30: NA (not reported) | AN30: NA | AO30: 1079 | AP30: 0.02 | AQ30: beta (std) | AR30: p. 2538 | AS30: 0.05 | AT30: l (<) | AU30: NA (not reported) | AW30: NA | AX30: 3 - conceptual | AY30: =IFERROR(__xludf.DUMMYFUNCTION("vlookup(BB30,importrange(""https://docs.google.com/spreadsheets/d/1d2vevQ_7D_v35q4wCQ4RpQ_IPoTwEMB9Yp6ymwlPqew/edit?gid=984458430#gid=984458430"", ""'replication success'!A:K""), 11, FAlSE)"),"mixed") -> mixed | AZ30: =IFERROR(__xludf.DUMMYFUNCTION("vlookup(BB30,importrange(""https://docs.google.com/spreadsheets/d/1d2vevQ_7D_v35q4wCQ4RpQ_IPoTwEMB9Yp6ymwlPqew/edit?gid=984458430#gid=984458430"", ""'replication success'!A:M""), 12, FAlSE)"),"Cross-sectionally, both husbands’ and wives’ reports of their first financial discussion predicted better marital satisfaction and fewer financial disagreements through their own report of healthy financial communication. Longitudinally, only husbands’ r"&"eport of the couple’s first financial discussion positively predicted between- person changes in both husbands’ and wives’ marital satifaction two waves later.") -> Cross-sectionally, both husbands’ and wives’ reports of their first financial discussion predicted better marital satisfaction and fewer financial disagreements through their own report of healthy financial communication. Longitudinally, only husbands’ report of the couple’s first financial discussion positively predicted between- person changes in both husbands’ and wives’ marital satifaction two waves later. | BA30: =IFERROR(__xludf.DUMMYFUNCTION("vlookup(BB30,importrange(""https://docs.google.com/spreadsheets/d/1d2vevQ_7D_v35q4wCQ4RpQ_IPoTwEMB9Yp6ymwlPqew/edit?gid=984458430#gid=984458430"", ""'replication success'!A:M""), 13, FAlSE)"),"abstract") -> abstract | BB30: =IFERROR(__xludf.DUMMYFUNCTION("REGEXREPLACE(G30, ""_[a-z]{1,2}$"", """")"),"additional_studies11") -> additional_studies11 | BD30: LR
A31: 31 | B31: validated - discarded | C31: double | D31: Fabienne | F31: additional_studies11_1 | G31: additional_studies11_c | H31: Julia Fabienne Sandkühler | I31: 45637 | J31: 45692 | K31: replication N refers to number of couples | M31: Saxey, M. T., LeBaron-Black, A. B., & Curran, M. A. (2022). The Sooner, the Better? Couples' First Financial Discussion, Relationship Quality, and Financial Conflict in Emerging Adulthood. Journal of Financial Therapy, 13 (1) 2. https://doi.org/10.4148/1944-9771.1299 | N31: 10.4148/1944-9771.1299 | P31: 10.4148--1944-9771.1299.pdf | Q31: {=if(iserror(MATCH(V31, 'File Links'!C:C, 0)), "N/A", HYPERLINK(INDEX('File Links'!B:B, MATCH(P31, 'File Links'!C:C, 0))))} -> https://drive.google.com/file/d/1OByNKNsjZqSFHFFyt-o1mPqDkVmgruBu/view?usp=drivesdk | R31: Saxey, M. T., LeBaron‐Black, A. B., Inman, N. F., Yorgason, J. B., & Holmes, E. K. (2024). The earlier couples first discussed finances, the better? A dyadic, longitudinal replication and extension. Family Relations. https://doi.org/10.1111/fare.13030 | S31: 10.1111/fare.13030 | V31: =hyperlink(vlookup(lower(S31),'File Links'!E:F, 2, FALSE), SUBSTITUTE(lower(S31), "/", "--") & ".pdf") -> 10.1111--fare.13030.pdf | W31: dyadic, longitudinal replication and extension | X31: {=if(iserror(MATCH(V31, 'File Links'!C:C, 0)), "N/A", HYPERLINK(INDEX('File Links'!B:B, MATCH(V31, 'File Links'!C:C, 0))))} -> https://drive.google.com/file/d/1TGN_TAtoJI3jhMQTEG2wnN59FCyiXC2_/view?usp=drivesdk | Z31: Social Psychology | AB31: emerging adulthood; financial communication; financial conflict; financial discussion, relationship quality | AC31: Indirect effect present for relationship quality (replication: cross-sectional, husbands' answers, effect on themselves) | AD31: Indirect effect present for relationship quality: “initiating financial discussion earlier in a romantic relationship may benefit relationship quality—through financial communication” (most emphasised claim in original) | AE31: 1 | AF31: 1950 | AG31: 0.13 | AH31: beta | AI31: p. 11 | AJ31: 0.001 | AK31: l (<) | AL31: NA (not reported) | AN31: NA | AO31: 1079 | AP31: 0.04 | AQ31: beta (std) | AR31: p. 2538 | AS31: 0.05 | AT31: l (<) | AU31: NA (not reported) | AW31: NA | AX31: 3 - conceptual | AY31: =IFERROR(__xludf.DUMMYFUNCTION("vlookup(BB31,importrange(""https://docs.google.com/spreadsheets/d/1d2vevQ_7D_v35q4wCQ4RpQ_IPoTwEMB9Yp6ymwlPqew/edit?gid=984458430#gid=984458430"", ""'replication success'!A:K""), 11, FAlSE)"),"mixed") -> mixed | AZ31: =IFERROR(__xludf.DUMMYFUNCTION("vlookup(BB31,importrange(""https://docs.google.com/spreadsheets/d/1d2vevQ_7D_v35q4wCQ4RpQ_IPoTwEMB9Yp6ymwlPqew/edit?gid=984458430#gid=984458430"", ""'replication success'!A:M""), 12, FAlSE)"),"Cross-sectionally, both husbands’ and wives’ reports of their first financial discussion predicted better marital satisfaction and fewer financial disagreements through their own report of healthy financial communication. Longitudinally, only husbands’ r"&"eport of the couple’s first financial discussion positively predicted between- person changes in both husbands’ and wives’ marital satifaction two waves later.") -> Cross-sectionally, both husbands’ and wives’ reports of their first financial discussion predicted better marital satisfaction and fewer financial disagreements through their own report of healthy financial communication. Longitudinally, only husbands’ report of the couple’s first financial discussion positively predicted between- person changes in both husbands’ and wives’ marital satifaction two waves later. | BA31: =IFERROR(__xludf.DUMMYFUNCTION("vlookup(BB31,importrange(""https://docs.google.com/spreadsheets/d/1d2vevQ_7D_v35q4wCQ4RpQ_IPoTwEMB9Yp6ymwlPqew/edit?gid=984458430#gid=984458430"", ""'replication success'!A:M""), 13, FAlSE)"),"abstract") -> abstract | BB31: =IFERROR(__xludf.DUMMYFUNCTION("REGEXREPLACE(G31, ""_[a-z]{1,2}$"", """")"),"additional_studies11") -> additional_studies11 | BD31: LR
A32: 32 | B32: validated - discarded | C32: double | D32: Fabienne | F32: additional_studies11_1 | G32: additional_studies11_d | H32: Julia Fabienne Sandkühler | I32: 45637 | J32: 45692 | K32: replication N refers to number of couples | M32: Saxey, M. T., LeBaron-Black, A. B., & Curran, M. A. (2022). The Sooner, the Better? Couples' First Financial Discussion, Relationship Quality, and Financial Conflict in Emerging Adulthood. Journal of Financial Therapy, 13 (1) 2. https://doi.org/10.4148/1944-9771.1299 | N32: 10.4148/1944-9771.1299 | P32: 10.4148--1944-9771.1299.pdf | Q32: {=if(iserror(MATCH(V32, 'File Links'!C:C, 0)), "N/A", HYPERLINK(INDEX('File Links'!B:B, MATCH(P32, 'File Links'!C:C, 0))))} -> https://drive.google.com/file/d/1OByNKNsjZqSFHFFyt-o1mPqDkVmgruBu/view?usp=drivesdk | R32: Saxey, M. T., LeBaron‐Black, A. B., Inman, N. F., Yorgason, J. B., & Holmes, E. K. (2024). The earlier couples first discussed finances, the better? A dyadic, longitudinal replication and extension. Family Relations. https://doi.org/10.1111/fare.13030 | S32: 10.1111/fare.13030 | V32: =hyperlink(vlookup(lower(S32),'File Links'!E:F, 2, FALSE), SUBSTITUTE(lower(S32), "/", "--") & ".pdf") -> 10.1111--fare.13030.pdf | W32: dyadic, longitudinal replication and extension | X32: {=if(iserror(MATCH(V32, 'File Links'!C:C, 0)), "N/A", HYPERLINK(INDEX('File Links'!B:B, MATCH(V32, 'File Links'!C:C, 0))))} -> https://drive.google.com/file/d/1TGN_TAtoJI3jhMQTEG2wnN59FCyiXC2_/view?usp=drivesdk | Z32: Social Psychology | AB32: emerging adulthood; financial communication; financial conflict; financial discussion, relationship quality | AC32: Indirect effect present for relationship quality (replication: cross-sectional, husbands' answers, effect on partner) | AD32: Indirect effect present for relationship quality: “initiating financial discussion earlier in a romantic relationship may benefit relationship quality—through financial communication” (most emphasised claim in original) | AE32: 1 | AF32: 1950 | AG32: 0.13 | AH32: beta | AI32: p. 11 | AJ32: 0.001 | AK32: l (<) | AL32: NA (not reported) | AN32: NA | AO32: 1079 | AQ32: beta (std) | AR32: p. 2538 | AS32: 0.05 | AT32: g (>) | AU32: NA (not reported) | AW32: NA | AX32: 3 - conceptual | AY32: =IFERROR(__xludf.DUMMYFUNCTION("vlookup(BB32,importrange(""https://docs.google.com/spreadsheets/d/1d2vevQ_7D_v35q4wCQ4RpQ_IPoTwEMB9Yp6ymwlPqew/edit?gid=984458430#gid=984458430"", ""'replication success'!A:K""), 11, FAlSE)"),"mixed") -> mixed | AZ32: =IFERROR(__xludf.DUMMYFUNCTION("vlookup(BB32,importrange(""https://docs.google.com/spreadsheets/d/1d2vevQ_7D_v35q4wCQ4RpQ_IPoTwEMB9Yp6ymwlPqew/edit?gid=984458430#gid=984458430"", ""'replication success'!A:M""), 12, FAlSE)"),"Cross-sectionally, both husbands’ and wives’ reports of their first financial discussion predicted better marital satisfaction and fewer financial disagreements through their own report of healthy financial communication. Longitudinally, only husbands’ r"&"eport of the couple’s first financial discussion positively predicted between- person changes in both husbands’ and wives’ marital satifaction two waves later.") -> Cross-sectionally, both husbands’ and wives’ reports of their first financial discussion predicted better marital satisfaction and fewer financial disagreements through their own report of healthy financial communication. Longitudinally, only husbands’ report of the couple’s first financial discussion positively predicted between- person changes in both husbands’ and wives’ marital satifaction two waves later. | BA32: =IFERROR(__xludf.DUMMYFUNCTION("vlookup(BB32,importrange(""https://docs.google.com/spreadsheets/d/1d2vevQ_7D_v35q4wCQ4RpQ_IPoTwEMB9Yp6ymwlPqew/edit?gid=984458430#gid=984458430"", ""'replication success'!A:M""), 13, FAlSE)"),"abstract") -> abstract | BB32: =IFERROR(__xludf.DUMMYFUNCTION("REGEXREPLACE(G32, ""_[a-z]{1,2}$"", """")"),"additional_studies11") -> additional_studies11 | BD32: LR
A33: 33 | B33: validated - discarded | C33: double | D33: Fabienne | F33: additional_studies11_1 | G33: additional_studies11_e | H33: Julia Fabienne Sandkühler | I33: 45637 | J33: 45692 | K33: replication N refers to number of couples | M33: Saxey, M. T., LeBaron-Black, A. B., & Curran, M. A. (2022). The Sooner, the Better? Couples' First Financial Discussion, Relationship Quality, and Financial Conflict in Emerging Adulthood. Journal of Financial Therapy, 13 (1) 2. https://doi.org/10.4148/1944-9771.1299 | N33: 10.4148/1944-9771.1299 | P33: 10.4148--1944-9771.1299.pdf | Q33: {=if(iserror(MATCH(V33, 'File Links'!C:C, 0)), "N/A", HYPERLINK(INDEX('File Links'!B:B, MATCH(P33, 'File Links'!C:C, 0))))} -> https://drive.google.com/file/d/1OByNKNsjZqSFHFFyt-o1mPqDkVmgruBu/view?usp=drivesdk | R33: Saxey, M. T., LeBaron‐Black, A. B., Inman, N. F., Yorgason, J. B., & Holmes, E. K. (2024). The earlier couples first discussed finances, the better? A dyadic, longitudinal replication and extension. Family Relations. https://doi.org/10.1111/fare.13030 | S33: 10.1111/fare.13030 | V33: =hyperlink(vlookup(lower(S33),'File Links'!E:F, 2, FALSE), SUBSTITUTE(lower(S33), "/", "--") & ".pdf") -> 10.1111--fare.13030.pdf | W33: dyadic, longitudinal replication and extension | X33: {=if(iserror(MATCH(V33, 'File Links'!C:C, 0)), "N/A", HYPERLINK(INDEX('File Links'!B:B, MATCH(V33, 'File Links'!C:C, 0))))} -> https://drive.google.com/file/d/1TGN_TAtoJI3jhMQTEG2wnN59FCyiXC2_/view?usp=drivesdk | Z33: Social Psychology | AB33: emerging adulthood; financial communication; financial conflict; financial discussion, relationship quality | AC33: Indirect effect present for relationship quality (replication: longitudinal, wives' answers, effect on themselves) | AD33: Indirect effect present for relationship quality: “initiating financial discussion earlier in a romantic relationship may benefit relationship quality—through financial communication” (most emphasised claim in original) | AE33: 1 | AF33: 1950 | AG33: 0.13 | AH33: beta | AI33: p. 11 | AJ33: 0.001 | AK33: l (<) | AL33: NA (not reported) | AN33: NA | AO33: 1079 | AQ33: beta (std) | AR33: p. 2538 | AS33: 0.05 | AT33: g (>) | AU33: NA (not reported) | AW33: NA | AX33: 3 - conceptual | AY33: =IFERROR(__xludf.DUMMYFUNCTION("vlookup(BB33,importrange(""https://docs.google.com/spreadsheets/d/1d2vevQ_7D_v35q4wCQ4RpQ_IPoTwEMB9Yp6ymwlPqew/edit?gid=984458430#gid=984458430"", ""'replication success'!A:K""), 11, FAlSE)"),"mixed") -> mixed | AZ33: =IFERROR(__xludf.DUMMYFUNCTION("vlookup(BB33,importrange(""https://docs.google.com/spreadsheets/d/1d2vevQ_7D_v35q4wCQ4RpQ_IPoTwEMB9Yp6ymwlPqew/edit?gid=984458430#gid=984458430"", ""'replication success'!A:M""), 12, FAlSE)"),"Cross-sectionally, both husbands’ and wives’ reports of their first financial discussion predicted better marital satisfaction and fewer financial disagreements through their own report of healthy financial communication. Longitudinally, only husbands’ r"&"eport of the couple’s first financial discussion positively predicted between- person changes in both husbands’ and wives’ marital satifaction two waves later.") -> Cross-sectionally, both husbands’ and wives’ reports of their first financial discussion predicted better marital satisfaction and fewer financial disagreements through their own report of healthy financial communication. Longitudinally, only husbands’ report of the couple’s first financial discussion positively predicted between- person changes in both husbands’ and wives’ marital satifaction two waves later. | BA33: =IFERROR(__xludf.DUMMYFUNCTION("vlookup(BB33,importrange(""https://docs.google.com/spreadsheets/d/1d2vevQ_7D_v35q4wCQ4RpQ_IPoTwEMB9Yp6ymwlPqew/edit?gid=984458430#gid=984458430"", ""'replication success'!A:M""), 13, FAlSE)"),"abstract") -> abstract | BB33: =IFERROR(__xludf.DUMMYFUNCTION("REGEXREPLACE(G33, ""_[a-z]{1,2}$"", """")"),"additional_studies11") -> additional_studies11 | BD33: LR
A34: 34 | B34: validated - discarded | C34: double | D34: Fabienne | F34: additional_studies11_1 | G34: additional_studies11_f | H34: Julia Fabienne Sandkühler | I34: 45637 | J34: 45692 | K34: replication N refers to number of couples | M34: Saxey, M. T., LeBaron-Black, A. B., & Curran, M. A. (2022). The Sooner, the Better? Couples' First Financial Discussion, Relationship Quality, and Financial Conflict in Emerging Adulthood. Journal of Financial Therapy, 13 (1) 2. https://doi.org/10.4148/1944-9771.1299 | N34: 10.4148/1944-9771.1299 | P34: 10.4148--1944-9771.1299.pdf | Q34: {=if(iserror(MATCH(V34, 'File Links'!C:C, 0)), "N/A", HYPERLINK(INDEX('File Links'!B:B, MATCH(P34, 'File Links'!C:C, 0))))} -> https://drive.google.com/file/d/1OByNKNsjZqSFHFFyt-o1mPqDkVmgruBu/view?usp=drivesdk | R34: Saxey, M. T., LeBaron‐Black, A. B., Inman, N. F., Yorgason, J. B., & Holmes, E. K. (2024). The earlier couples first discussed finances, the better? A dyadic, longitudinal replication and extension. Family Relations. https://doi.org/10.1111/fare.13030 | S34: 10.1111/fare.13030 | V34: =hyperlink(vlookup(lower(S34),'File Links'!E:F, 2, FALSE), SUBSTITUTE(lower(S34), "/", "--") & ".pdf") -> 10.1111--fare.13030.pdf | W34: dyadic, longitudinal replication and extension | X34: {=if(iserror(MATCH(V34, 'File Links'!C:C, 0)), "N/A", HYPERLINK(INDEX('File Links'!B:B, MATCH(V34, 'File Links'!C:C, 0))))} -> https://drive.google.com/file/d/1TGN_TAtoJI3jhMQTEG2wnN59FCyiXC2_/view?usp=drivesdk | Z34: Social Psychology | AB34: emerging adulthood; financial communication; financial conflict; financial discussion, relationship quality | AC34: Indirect effect present for relationship quality (replication: longitudinal, wives' answers, effect on partner) | AD34: Indirect effect present for relationship quality: “initiating financial discussion earlier in a romantic relationship may benefit relationship quality—through financial communication” (most emphasised claim in original) | AE34: 1 | AF34: 1950 | AG34: 0.13 | AH34: beta | AI34: p. 11 | AJ34: 0.001 | AK34: l (<) | AL34: NA (not reported) | AN34: NA | AO34: 1079 | AQ34: beta (std) | AR34: p. 2538 | AS34: 0.05 | AT34: g (>) | AU34: NA (not reported) | AW34: NA | AX34: 3 - conceptual | AY34: =IFERROR(__xludf.DUMMYFUNCTION("vlookup(BB34,importrange(""https://docs.google.com/spreadsheets/d/1d2vevQ_7D_v35q4wCQ4RpQ_IPoTwEMB9Yp6ymwlPqew/edit?gid=984458430#gid=984458430"", ""'replication success'!A:K""), 11, FAlSE)"),"mixed") -> mixed | AZ34: =IFERROR(__xludf.DUMMYFUNCTION("vlookup(BB34,importrange(""https://docs.google.com/spreadsheets/d/1d2vevQ_7D_v35q4wCQ4RpQ_IPoTwEMB9Yp6ymwlPqew/edit?gid=984458430#gid=984458430"", ""'replication success'!A:M""), 12, FAlSE)"),"Cross-sectionally, both husbands’ and wives’ reports of their first financial discussion predicted better marital satisfaction and fewer financial disagreements through their own report of healthy financial communication. Longitudinally, only husbands’ r"&"eport of the couple’s first financial discussion positively predicted between- person changes in both husbands’ and wives’ marital satifaction two waves later.") -> Cross-sectionally, both husbands’ and wives’ reports of their first financial discussion predicted better marital satisfaction and fewer financial disagreements through their own report of healthy financial communication. Longitudinally, only husbands’ report of the couple’s first financial discussion positively predicted between- person changes in both husbands’ and wives’ marital satifaction two waves later. | BA34: =IFERROR(__xludf.DUMMYFUNCTION("vlookup(BB34,importrange(""https://docs.google.com/spreadsheets/d/1d2vevQ_7D_v35q4wCQ4RpQ_IPoTwEMB9Yp6ymwlPqew/edit?gid=984458430#gid=984458430"", ""'replication success'!A:M""), 13, FAlSE)"),"abstract") -> abstract | BB34: =IFERROR(__xludf.DUMMYFUNCTION("REGEXREPLACE(G34, ""_[a-z]{1,2}$"", """")"),"additional_studies11") -> additional_studies11 | BD34: LR
A35: 35 | B35: validated - discarded | C35: double | D35: Fabienne | F35: additional_studies11_1 | G35: additional_studies11_g | H35: Julia Fabienne Sandkühler | I35: 45637 | J35: 45692 | K35: replication N refers to number of couples | M35: Saxey, M. T., LeBaron-Black, A. B., & Curran, M. A. (2022). The Sooner, the Better? Couples' First Financial Discussion, Relationship Quality, and Financial Conflict in Emerging Adulthood. Journal of Financial Therapy, 13 (1) 2. https://doi.org/10.4148/1944-9771.1299 | N35: 10.4148/1944-9771.1299 | P35: 10.4148--1944-9771.1299.pdf | Q35: {=if(iserror(MATCH(V35, 'File Links'!C:C, 0)), "N/A", HYPERLINK(INDEX('File Links'!B:B, MATCH(P35, 'File Links'!C:C, 0))))} -> https://drive.google.com/file/d/1OByNKNsjZqSFHFFyt-o1mPqDkVmgruBu/view?usp=drivesdk | R35: Saxey, M. T., LeBaron‐Black, A. B., Inman, N. F., Yorgason, J. B., & Holmes, E. K. (2024). The earlier couples first discussed finances, the better? A dyadic, longitudinal replication and extension. Family Relations. https://doi.org/10.1111/fare.13030 | S35: 10.1111/fare.13030 | V35: =hyperlink(vlookup(lower(S35),'File Links'!E:F, 2, FALSE), SUBSTITUTE(lower(S35), "/", "--") & ".pdf") -> 10.1111--fare.13030.pdf | W35: dyadic, longitudinal replication and extension | X35: {=if(iserror(MATCH(V35, 'File Links'!C:C, 0)), "N/A", HYPERLINK(INDEX('File Links'!B:B, MATCH(V35, 'File Links'!C:C, 0))))} -> https://drive.google.com/file/d/1TGN_TAtoJI3jhMQTEG2wnN59FCyiXC2_/view?usp=drivesdk | Z35: Social Psychology | AB35: emerging adulthood; financial communication; financial conflict; financial discussion, relationship quality | AC35: Indirect effect present for relationship quality (replication: longitudinal, husbands' answers, effect on themselves) | AD35: Indirect effect present for relationship quality: “initiating financial discussion earlier in a romantic relationship may benefit relationship quality—through financial communication” (most emphasised claim in original) | AE35: 1 | AF35: 1950 | AG35: 0.13 | AH35: beta | AI35: p. 11 | AJ35: 0.001 | AK35: l (<) | AL35: NA (not reported) | AN35: NA | AO35: 1079 | AQ35: beta (std) | AR35: p. 2538 | AS35: 0.05 | AT35: g (>) | AU35: NA (not reported) | AW35: NA | AX35: 3 - conceptual | AY35: =IFERROR(__xludf.DUMMYFUNCTION("vlookup(BB35,importrange(""https://docs.google.com/spreadsheets/d/1d2vevQ_7D_v35q4wCQ4RpQ_IPoTwEMB9Yp6ymwlPqew/edit?gid=984458430#gid=984458430"", ""'replication success'!A:K""), 11, FAlSE)"),"mixed") -> mixed | AZ35: =IFERROR(__xludf.DUMMYFUNCTION("vlookup(BB35,importrange(""https://docs.google.com/spreadsheets/d/1d2vevQ_7D_v35q4wCQ4RpQ_IPoTwEMB9Yp6ymwlPqew/edit?gid=984458430#gid=984458430"", ""'replication success'!A:M""), 12, FAlSE)"),"Cross-sectionally, both husbands’ and wives’ reports of their first financial discussion predicted better marital satisfaction and fewer financial disagreements through their own report of healthy financial communication. Longitudinally, only husbands’ r"&"eport of the couple’s first financial discussion positively predicted between- person changes in both husbands’ and wives’ marital satifaction two waves later.") -> Cross-sectionally, both husbands’ and wives’ reports of their first financial discussion predicted better marital satisfaction and fewer financial disagreements through their own report of healthy financial communication. Longitudinally, only husbands’ report of the couple’s first financial discussion positively predicted between- person changes in both husbands’ and wives’ marital satifaction two waves later. | BA35: =IFERROR(__xludf.DUMMYFUNCTION("vlookup(BB35,importrange(""https://docs.google.com/spreadsheets/d/1d2vevQ_7D_v35q4wCQ4RpQ_IPoTwEMB9Yp6ymwlPqew/edit?gid=984458430#gid=984458430"", ""'replication success'!A:M""), 13, FAlSE)"),"abstract") -> abstract | BB35: =IFERROR(__xludf.DUMMYFUNCTION("REGEXREPLACE(G35, ""_[a-z]{1,2}$"", """")"),"additional_studies11") -> additional_studies11 | BD35: LR
A36: 36 | B36: validated - discarded | C36: double | D36: Fabienne | F36: additional_studies11_1 | G36: additional_studies11_h | H36: Julia Fabienne Sandkühler | I36: 45637 | J36: 45692 | K36: replication N refers to number of couples | M36: Saxey, M. T., LeBaron-Black, A. B., & Curran, M. A. (2022). The Sooner, the Better? Couples' First Financial Discussion, Relationship Quality, and Financial Conflict in Emerging Adulthood. Journal of Financial Therapy, 13 (1) 2. https://doi.org/10.4148/1944-9771.1299 | N36: 10.4148/1944-9771.1299 | P36: 10.4148--1944-9771.1299.pdf | Q36: {=if(iserror(MATCH(V36, 'File Links'!C:C, 0)), "N/A", HYPERLINK(INDEX('File Links'!B:B, MATCH(P36, 'File Links'!C:C, 0))))} -> https://drive.google.com/file/d/1OByNKNsjZqSFHFFyt-o1mPqDkVmgruBu/view?usp=drivesdk | R36: Saxey, M. T., LeBaron‐Black, A. B., Inman, N. F., Yorgason, J. B., & Holmes, E. K. (2024). The earlier couples first discussed finances, the better? A dyadic, longitudinal replication and extension. Family Relations. https://doi.org/10.1111/fare.13030 | S36: 10.1111/fare.13030 | V36: =hyperlink(vlookup(lower(S36),'File Links'!E:F, 2, FALSE), SUBSTITUTE(lower(S36), "/", "--") & ".pdf") -> 10.1111--fare.13030.pdf | W36: dyadic, longitudinal replication and extension | X36: {=if(iserror(MATCH(V36, 'File Links'!C:C, 0)), "N/A", HYPERLINK(INDEX('File Links'!B:B, MATCH(V36, 'File Links'!C:C, 0))))} -> https://drive.google.com/file/d/1TGN_TAtoJI3jhMQTEG2wnN59FCyiXC2_/view?usp=drivesdk | Z36: Social Psychology | AB36: emerging adulthood; financial communication; financial conflict; financial discussion, relationship quality | AC36: Indirect effect present for relationship quality (replication: longitudinal, husbands' answers, effect on partner) | AD36: Indirect effect present for relationship quality: “initiating financial discussion earlier in a romantic relationship may benefit relationship quality—through financial communication” (most emphasised claim in original) | AE36: 1 | AF36: 1950 | AG36: 0.13 | AH36: beta | AI36: p. 11 | AJ36: 0.001 | AK36: l (<) | AL36: NA (not reported) | AN36: NA | AO36: 1079 | AQ36: beta (std) | AR36: p. 2538 | AS36: 0.05 | AT36: g (>) | AU36: NA (not reported) | AW36: NA | AX36: 3 - conceptual | AY36: =IFERROR(__xludf.DUMMYFUNCTION("vlookup(BB36,importrange(""https://docs.google.com/spreadsheets/d/1d2vevQ_7D_v35q4wCQ4RpQ_IPoTwEMB9Yp6ymwlPqew/edit?gid=984458430#gid=984458430"", ""'replication success'!A:K""), 11, FAlSE)"),"mixed") -> mixed | AZ36: =IFERROR(__xludf.DUMMYFUNCTION("vlookup(BB36,importrange(""https://docs.google.com/spreadsheets/d/1d2vevQ_7D_v35q4wCQ4RpQ_IPoTwEMB9Yp6ymwlPqew/edit?gid=984458430#gid=984458430"", ""'replication success'!A:M""), 12, FAlSE)"),"Cross-sectionally, both husbands’ and wives’ reports of their first financial discussion predicted better marital satisfaction and fewer financial disagreements through their own report of healthy financial communication. Longitudinally, only husbands’ r"&"eport of the couple’s first financial discussion positively predicted between- person changes in both husbands’ and wives’ marital satifaction two waves later.") -> Cross-sectionally, both husbands’ and wives’ reports of their first financial discussion predicted better marital satisfaction and fewer financial disagreements through their own report of healthy financial communication. Longitudinally, only husbands’ report of the couple’s first financial discussion positively predicted between- person changes in both husbands’ and wives’ marital satifaction two waves later. | BA36: =IFERROR(__xludf.DUMMYFUNCTION("vlookup(BB36,importrange(""https://docs.google.com/spreadsheets/d/1d2vevQ_7D_v35q4wCQ4RpQ_IPoTwEMB9Yp6ymwlPqew/edit?gid=984458430#gid=984458430"", ""'replication success'!A:M""), 13, FAlSE)"),"abstract") -> abstract | BB36: =IFERROR(__xludf.DUMMYFUNCTION("REGEXREPLACE(G36, ""_[a-z]{1,2}$"", """")"),"additional_studies11") -> additional_studies11 | BD36: LR
A37: 37 | B37: validated - discarded | C37: double | D37: Fabienne | F37: additional_studies11_1 | G37: additional_studies11_i | H37: Julia Fabienne Sandkühler | I37: 45637 | J37: 45692 | K37: replication N refers to number of couples | M37: Saxey, M. T., LeBaron-Black, A. B., & Curran, M. A. (2022). The Sooner, the Better? Couples' First Financial Discussion, Relationship Quality, and Financial Conflict in Emerging Adulthood. Journal of Financial Therapy, 13 (1) 2. https://doi.org/10.4148/1944-9771.1299 | N37: 10.4148/1944-9771.1299 | P37: 10.4148--1944-9771.1299.pdf | Q37: {=if(iserror(MATCH(V37, 'File Links'!C:C, 0)), "N/A", HYPERLINK(INDEX('File Links'!B:B, MATCH(P37, 'File Links'!C:C, 0))))} -> https://drive.google.com/file/d/1OByNKNsjZqSFHFFyt-o1mPqDkVmgruBu/view?usp=drivesdk | R37: Saxey, M. T., LeBaron‐Black, A. B., Inman, N. F., Yorgason, J. B., & Holmes, E. K. (2024). The earlier couples first discussed finances, the better? A dyadic, longitudinal replication and extension. Family Relations. https://doi.org/10.1111/fare.13030 | S37: 10.1111/fare.13030 | V37: =hyperlink(vlookup(lower(S37),'File Links'!E:F, 2, FALSE), SUBSTITUTE(lower(S37), "/", "--") & ".pdf") -> 10.1111--fare.13030.pdf | W37: dyadic, longitudinal replication and extension | X37: {=if(iserror(MATCH(V37, 'File Links'!C:C, 0)), "N/A", HYPERLINK(INDEX('File Links'!B:B, MATCH(V37, 'File Links'!C:C, 0))))} -> https://drive.google.com/file/d/1TGN_TAtoJI3jhMQTEG2wnN59FCyiXC2_/view?usp=drivesdk | Z37: Social Psychology | AB37: emerging adulthood; financial communication; financial conflict; financial discussion, relationship quality | AC37: No direct effect present for relationship quality (replication: cross-sectional, wives' answers, effect on themselves) | AD37: No direct effect present for relationship quality: “Nonetheless, couples’ first financial discussion was not directly associated with their relationship quality.” (however not emphasised in original) | AE37: 11 | AF37: 1950 | AH37: beta | AI37: p. 11 | AJ37: 0.05 | AK37: g (>) | AL37: NA (not reported) | AN37: NA | AO37: 1079 | AQ37: beta (std) | AR37: p. 2536 | AS37: 0.05 | AT37: g (>) | AU37: NA (not reported) | AW37: NA | AX37: 3 - conceptual | AY37: =IFERROR(__xludf.DUMMYFUNCTION("vlookup(BB37,importrange(""https://docs.google.com/spreadsheets/d/1d2vevQ_7D_v35q4wCQ4RpQ_IPoTwEMB9Yp6ymwlPqew/edit?gid=984458430#gid=984458430"", ""'replication success'!A:K""), 11, FAlSE)"),"mixed") -> mixed | AZ37: =IFERROR(__xludf.DUMMYFUNCTION("vlookup(BB37,importrange(""https://docs.google.com/spreadsheets/d/1d2vevQ_7D_v35q4wCQ4RpQ_IPoTwEMB9Yp6ymwlPqew/edit?gid=984458430#gid=984458430"", ""'replication success'!A:M""), 12, FAlSE)"),"Cross-sectionally, both husbands’ and wives’ reports of their first financial discussion predicted better marital satisfaction and fewer financial disagreements through their own report of healthy financial communication. Longitudinally, only husbands’ r"&"eport of the couple’s first financial discussion positively predicted between- person changes in both husbands’ and wives’ marital satifaction two waves later.") -> Cross-sectionally, both husbands’ and wives’ reports of their first financial discussion predicted better marital satisfaction and fewer financial disagreements through their own report of healthy financial communication. Longitudinally, only husbands’ report of the couple’s first financial discussion positively predicted between- person changes in both husbands’ and wives’ marital satifaction two waves later. | BA37: =IFERROR(__xludf.DUMMYFUNCTION("vlookup(BB37,importrange(""https://docs.google.com/spreadsheets/d/1d2vevQ_7D_v35q4wCQ4RpQ_IPoTwEMB9Yp6ymwlPqew/edit?gid=984458430#gid=984458430"", ""'replication success'!A:M""), 13, FAlSE)"),"abstract") -> abstract | BB37: =IFERROR(__xludf.DUMMYFUNCTION("REGEXREPLACE(G37, ""_[a-z]{1,2}$"", """")"),"additional_studies11") -> additional_studies11 | BD37: LR
A38: 38 | B38: validated - discarded | C38: double | D38: Fabienne | F38: additional_studies11_1 | G38: additional_studies11_j | H38: Julia Fabienne Sandkühler | I38: 45637 | J38: 45692 | K38: replication N refers to number of couples | M38: Saxey, M. T., LeBaron-Black, A. B., & Curran, M. A. (2022). The Sooner, the Better? Couples' First Financial Discussion, Relationship Quality, and Financial Conflict in Emerging Adulthood. Journal of Financial Therapy, 13 (1) 2. https://doi.org/10.4148/1944-9771.1299 | N38: 10.4148/1944-9771.1299 | P38: 10.4148--1944-9771.1299.pdf | Q38: {=if(iserror(MATCH(V38, 'File Links'!C:C, 0)), "N/A", HYPERLINK(INDEX('File Links'!B:B, MATCH(P38, 'File Links'!C:C, 0))))} -> https://drive.google.com/file/d/1OByNKNsjZqSFHFFyt-o1mPqDkVmgruBu/view?usp=drivesdk | R38: Saxey, M. T., LeBaron‐Black, A. B., Inman, N. F., Yorgason, J. B., & Holmes, E. K. (2024). The earlier couples first discussed finances, the better? A dyadic, longitudinal replication and extension. Family Relations. https://doi.org/10.1111/fare.13030 | S38: 10.1111/fare.13030 | V38: =hyperlink(vlookup(lower(S38),'File Links'!E:F, 2, FALSE), SUBSTITUTE(lower(S38), "/", "--") & ".pdf") -> 10.1111--fare.13030.pdf | W38: dyadic, longitudinal replication and extension | X38: {=if(iserror(MATCH(V38, 'File Links'!C:C, 0)), "N/A", HYPERLINK(INDEX('File Links'!B:B, MATCH(V38, 'File Links'!C:C, 0))))} -> https://drive.google.com/file/d/1TGN_TAtoJI3jhMQTEG2wnN59FCyiXC2_/view?usp=drivesdk | Z38: Social Psychology | AB38: emerging adulthood; financial communication; financial conflict; financial discussion, relationship quality | AC38: No direct effect present for relationship quality (replication: cross-sectional, wives' answers, effect on partner) | AD38: No direct effect present for relationship quality: “Nonetheless, couples’ first financial discussion was not directly associated with their relationship quality.” (however not emphasised in original) | AE38: 11 | AF38: 1950 | AH38: beta | AI38: p. 11 | AJ38: 0.05 | AK38: g (>) | AL38: NA (not reported) | AN38: NA | AO38: 1079 | AQ38: beta (std) | AR38: p. 2536 | AS38: 0.05 | AT38: g (>) | AU38: NA (not reported) | AW38: NA | AX38: 3 - conceptual | AY38: =IFERROR(__xludf.DUMMYFUNCTION("vlookup(BB38,importrange(""https://docs.google.com/spreadsheets/d/1d2vevQ_7D_v35q4wCQ4RpQ_IPoTwEMB9Yp6ymwlPqew/edit?gid=984458430#gid=984458430"", ""'replication success'!A:K""), 11, FAlSE)"),"mixed") -> mixed | AZ38: =IFERROR(__xludf.DUMMYFUNCTION("vlookup(BB38,importrange(""https://docs.google.com/spreadsheets/d/1d2vevQ_7D_v35q4wCQ4RpQ_IPoTwEMB9Yp6ymwlPqew/edit?gid=984458430#gid=984458430"", ""'replication success'!A:M""), 12, FAlSE)"),"Cross-sectionally, both husbands’ and wives’ reports of their first financial discussion predicted better marital satisfaction and fewer financial disagreements through their own report of healthy financial communication. Longitudinally, only husbands’ r"&"eport of the couple’s first financial discussion positively predicted between- person changes in both husbands’ and wives’ marital satifaction two waves later.") -> Cross-sectionally, both husbands’ and wives’ reports of their first financial discussion predicted better marital satisfaction and fewer financial disagreements through their own report of healthy financial communication. Longitudinally, only husbands’ report of the couple’s first financial discussion positively predicted between- person changes in both husbands’ and wives’ marital satifaction two waves later. | BA38: =IFERROR(__xludf.DUMMYFUNCTION("vlookup(BB38,importrange(""https://docs.google.com/spreadsheets/d/1d2vevQ_7D_v35q4wCQ4RpQ_IPoTwEMB9Yp6ymwlPqew/edit?gid=984458430#gid=984458430"", ""'replication success'!A:M""), 13, FAlSE)"),"abstract") -> abstract | BB38: =IFERROR(__xludf.DUMMYFUNCTION("REGEXREPLACE(G38, ""_[a-z]{1,2}$"", """")"),"additional_studies11") -> additional_studies11 | BD38: LR
A39: 39 | B39: validated - discarded | C39: double | D39: Fabienne | F39: additional_studies11_1 | G39: additional_studies11_k | H39: Julia Fabienne Sandkühler | I39: 45637 | J39: 45692 | K39: replication N refers to number of couples | M39: Saxey, M. T., LeBaron-Black, A. B., & Curran, M. A. (2022). The Sooner, the Better? Couples' First Financial Discussion, Relationship Quality, and Financial Conflict in Emerging Adulthood. Journal of Financial Therapy, 13 (1) 2. https://doi.org/10.4148/1944-9771.1299 | N39: 10.4148/1944-9771.1299 | P39: 10.4148--1944-9771.1299.pdf | Q39: {=if(iserror(MATCH(V39, 'File Links'!C:C, 0)), "N/A", HYPERLINK(INDEX('File Links'!B:B, MATCH(P39, 'File Links'!C:C, 0))))} -> https://drive.google.com/file/d/1OByNKNsjZqSFHFFyt-o1mPqDkVmgruBu/view?usp=drivesdk | R39: Saxey, M. T., LeBaron‐Black, A. B., Inman, N. F., Yorgason, J. B., & Holmes, E. K. (2024). The earlier couples first discussed finances, the better? A dyadic, longitudinal replication and extension. Family Relations. https://doi.org/10.1111/fare.13030 | S39: 10.1111/fare.13030 | V39: =hyperlink(vlookup(lower(S39),'File Links'!E:F, 2, FALSE), SUBSTITUTE(lower(S39), "/", "--") & ".pdf") -> 10.1111--fare.13030.pdf | W39: dyadic, longitudinal replication and extension | X39: {=if(iserror(MATCH(V39, 'File Links'!C:C, 0)), "N/A", HYPERLINK(INDEX('File Links'!B:B, MATCH(V39, 'File Links'!C:C, 0))))} -> https://drive.google.com/file/d/1TGN_TAtoJI3jhMQTEG2wnN59FCyiXC2_/view?usp=drivesdk | Z39: Social Psychology | AB39: emerging adulthood; financial communication; financial conflict; financial discussion, relationship quality | AC39: No direct effect present for relationship quality (replication: cross-sectional, husbands' answers, effect on themselves) | AD39: No direct effect present for relationship quality: “Nonetheless, couples’ first financial discussion was not directly associated with their relationship quality.” (however not emphasised in original) | AE39: 11 | AF39: 1950 | AH39: beta | AI39: p. 11 | AJ39: 0.05 | AK39: g (>) | AL39: NA (not reported) | AN39: NA | AO39: 1079 | AQ39: beta (std) | AR39: p. 2536 | AS39: 0.05 | AT39: g (>) | AU39: NA (not reported) | AW39: NA | AX39: 3 - conceptual | AY39: =IFERROR(__xludf.DUMMYFUNCTION("vlookup(BB39,importrange(""https://docs.google.com/spreadsheets/d/1d2vevQ_7D_v35q4wCQ4RpQ_IPoTwEMB9Yp6ymwlPqew/edit?gid=984458430#gid=984458430"", ""'replication success'!A:K""), 11, FAlSE)"),"mixed") -> mixed | AZ39: =IFERROR(__xludf.DUMMYFUNCTION("vlookup(BB39,importrange(""https://docs.google.com/spreadsheets/d/1d2vevQ_7D_v35q4wCQ4RpQ_IPoTwEMB9Yp6ymwlPqew/edit?gid=984458430#gid=984458430"", ""'replication success'!A:M""), 12, FAlSE)"),"Cross-sectionally, both husbands’ and wives’ reports of their first financial discussion predicted better marital satisfaction and fewer financial disagreements through their own report of healthy financial communication. Longitudinally, only husbands’ r"&"eport of the couple’s first financial discussion positively predicted between- person changes in both husbands’ and wives’ marital satifaction two waves later.") -> Cross-sectionally, both husbands’ and wives’ reports of their first financial discussion predicted better marital satisfaction and fewer financial disagreements through their own report of healthy financial communication. Longitudinally, only husbands’ report of the couple’s first financial discussion positively predicted between- person changes in both husbands’ and wives’ marital satifaction two waves later. | BA39: =IFERROR(__xludf.DUMMYFUNCTION("vlookup(BB39,importrange(""https://docs.google.com/spreadsheets/d/1d2vevQ_7D_v35q4wCQ4RpQ_IPoTwEMB9Yp6ymwlPqew/edit?gid=984458430#gid=984458430"", ""'replication success'!A:M""), 13, FAlSE)"),"abstract") -> abstract | BB39: =IFERROR(__xludf.DUMMYFUNCTION("REGEXREPLACE(G39, ""_[a-z]{1,2}$"", """")"),"additional_studies11") -> additional_studies11 | BD39: LR
A40: 40 | B40: validated - discarded | C40: double | D40: Fabienne | F40: additional_studies11_1 | G40: additional_studies11_l | H40: Julia Fabienne Sandkühler | I40: 45637 | J40: 45692 | K40: replication N refers to number of couples | M40: Saxey, M. T., LeBaron-Black, A. B., & Curran, M. A. (2022). The Sooner, the Better? Couples' First Financial Discussion, Relationship Quality, and Financial Conflict in Emerging Adulthood. Journal of Financial Therapy, 13 (1) 2. https://doi.org/10.4148/1944-9771.1299 | N40: 10.4148/1944-9771.1299 | P40: 10.4148--1944-9771.1299.pdf | Q40: {=if(iserror(MATCH(V40, 'File Links'!C:C, 0)), "N/A", HYPERLINK(INDEX('File Links'!B:B, MATCH(P40, 'File Links'!C:C, 0))))} -> https://drive.google.com/file/d/1OByNKNsjZqSFHFFyt-o1mPqDkVmgruBu/view?usp=drivesdk | R40: Saxey, M. T., LeBaron‐Black, A. B., Inman, N. F., Yorgason, J. B., & Holmes, E. K. (2024). The earlier couples first discussed finances, the better? A dyadic, longitudinal replication and extension. Family Relations. https://doi.org/10.1111/fare.13030 | S40: 10.1111/fare.13030 | V40: =hyperlink(vlookup(lower(S40),'File Links'!E:F, 2, FALSE), SUBSTITUTE(lower(S40), "/", "--") & ".pdf") -> 10.1111--fare.13030.pdf | W40: dyadic, longitudinal replication and extension | X40: {=if(iserror(MATCH(V40, 'File Links'!C:C, 0)), "N/A", HYPERLINK(INDEX('File Links'!B:B, MATCH(V40, 'File Links'!C:C, 0))))} -> https://drive.google.com/file/d/1TGN_TAtoJI3jhMQTEG2wnN59FCyiXC2_/view?usp=drivesdk | Z40: Social Psychology | AB40: emerging adulthood; financial communication; financial conflict; financial discussion, relationship quality | AC40: No direct effect present for relationship quality (replication: cross-sectional, husbands' answers, effect on partner) | AD40: No direct effect present for relationship quality: “Nonetheless, couples’ first financial discussion was not directly associated with their relationship quality.” (however not emphasised in original) | AE40: 11 | AF40: 1950 | AH40: beta | AI40: p. 11 | AJ40: 0.05 | AK40: g (>) | AL40: NA (not reported) | AN40: NA | AO40: 1079 | AQ40: beta (std) | AR40: p. 2536 | AS40: 0.05 | AT40: g (>) | AU40: NA (not reported) | AW40: NA | AX40: 3 - conceptual | AY40: =IFERROR(__xludf.DUMMYFUNCTION("vlookup(BB40,importrange(""https://docs.google.com/spreadsheets/d/1d2vevQ_7D_v35q4wCQ4RpQ_IPoTwEMB9Yp6ymwlPqew/edit?gid=984458430#gid=984458430"", ""'replication success'!A:K""), 11, FAlSE)"),"mixed") -> mixed | AZ40: =IFERROR(__xludf.DUMMYFUNCTION("vlookup(BB40,importrange(""https://docs.google.com/spreadsheets/d/1d2vevQ_7D_v35q4wCQ4RpQ_IPoTwEMB9Yp6ymwlPqew/edit?gid=984458430#gid=984458430"", ""'replication success'!A:M""), 12, FAlSE)"),"Cross-sectionally, both husbands’ and wives’ reports of their first financial discussion predicted better marital satisfaction and fewer financial disagreements through their own report of healthy financial communication. Longitudinally, only husbands’ r"&"eport of the couple’s first financial discussion positively predicted between- person changes in both husbands’ and wives’ marital satifaction two waves later.") -> Cross-sectionally, both husbands’ and wives’ reports of their first financial discussion predicted better marital satisfaction and fewer financial disagreements through their own report of healthy financial communication. Longitudinally, only husbands’ report of the couple’s first financial discussion positively predicted between- person changes in both husbands’ and wives’ marital satifaction two waves later. | BA40: =IFERROR(__xludf.DUMMYFUNCTION("vlookup(BB40,importrange(""https://docs.google.com/spreadsheets/d/1d2vevQ_7D_v35q4wCQ4RpQ_IPoTwEMB9Yp6ymwlPqew/edit?gid=984458430#gid=984458430"", ""'replication success'!A:M""), 13, FAlSE)"),"abstract") -> abstract | BB40: =IFERROR(__xludf.DUMMYFUNCTION("REGEXREPLACE(G40, ""_[a-z]{1,2}$"", """")"),"additional_studies11") -> additional_studies11 | BD40: LR
A41: 41 | B41: validated - discarded | C41: double | D41: Fabienne | F41: additional_studies11_1 | G41: additional_studies11_m | H41: Julia Fabienne Sandkühler | I41: 45637 | J41: 45692 | K41: replication N refers to number of couples | M41: Saxey, M. T., LeBaron-Black, A. B., & Curran, M. A. (2022). The Sooner, the Better? Couples' First Financial Discussion, Relationship Quality, and Financial Conflict in Emerging Adulthood. Journal of Financial Therapy, 13 (1) 2. https://doi.org/10.4148/1944-9771.1299 | N41: 10.4148/1944-9771.1299 | P41: 10.4148--1944-9771.1299.pdf | Q41: {=if(iserror(MATCH(V41, 'File Links'!C:C, 0)), "N/A", HYPERLINK(INDEX('File Links'!B:B, MATCH(P41, 'File Links'!C:C, 0))))} -> https://drive.google.com/file/d/1OByNKNsjZqSFHFFyt-o1mPqDkVmgruBu/view?usp=drivesdk | R41: Saxey, M. T., LeBaron‐Black, A. B., Inman, N. F., Yorgason, J. B., & Holmes, E. K. (2024). The earlier couples first discussed finances, the better? A dyadic, longitudinal replication and extension. Family Relations. https://doi.org/10.1111/fare.13030 | S41: 10.1111/fare.13030 | V41: =hyperlink(vlookup(lower(S41),'File Links'!E:F, 2, FALSE), SUBSTITUTE(lower(S41), "/", "--") & ".pdf") -> 10.1111--fare.13030.pdf | W41: dyadic, longitudinal replication and extension | X41: {=if(iserror(MATCH(V41, 'File Links'!C:C, 0)), "N/A", HYPERLINK(INDEX('File Links'!B:B, MATCH(V41, 'File Links'!C:C, 0))))} -> https://drive.google.com/file/d/1TGN_TAtoJI3jhMQTEG2wnN59FCyiXC2_/view?usp=drivesdk | Z41: Social Psychology | AB41: emerging adulthood; financial communication; financial conflict; financial discussion, relationship quality | AC41: No direct effect present for relationship quality (replication: longitudinal, wives' answers, effect on themselves) | AD41: No direct effect present for relationship quality: “Nonetheless, couples’ first financial discussion was not directly associated with their relationship quality.” (however not emphasised in original) | AE41: 11 | AF41: 1950 | AH41: beta | AI41: p. 11 | AJ41: 0.05 | AK41: g (>) | AL41: NA (not reported) | AN41: NA | AO41: 1079 | AQ41: beta (std) | AR41: p. 2538 | AS41: 0.05 | AT41: g (>) | AU41: NA (not reported) | AW41: NA | AX41: 3 - conceptual | AY41: =IFERROR(__xludf.DUMMYFUNCTION("vlookup(BB41,importrange(""https://docs.google.com/spreadsheets/d/1d2vevQ_7D_v35q4wCQ4RpQ_IPoTwEMB9Yp6ymwlPqew/edit?gid=984458430#gid=984458430"", ""'replication success'!A:K""), 11, FAlSE)"),"mixed") -> mixed | AZ41: =IFERROR(__xludf.DUMMYFUNCTION("vlookup(BB41,importrange(""https://docs.google.com/spreadsheets/d/1d2vevQ_7D_v35q4wCQ4RpQ_IPoTwEMB9Yp6ymwlPqew/edit?gid=984458430#gid=984458430"", ""'replication success'!A:M""), 12, FAlSE)"),"Cross-sectionally, both husbands’ and wives’ reports of their first financial discussion predicted better marital satisfaction and fewer financial disagreements through their own report of healthy financial communication. Longitudinally, only husbands’ r"&"eport of the couple’s first financial discussion positively predicted between- person changes in both husbands’ and wives’ marital satifaction two waves later.") -> Cross-sectionally, both husbands’ and wives’ reports of their first financial discussion predicted better marital satisfaction and fewer financial disagreements through their own report of healthy financial communication. Longitudinally, only husbands’ report of the couple’s first financial discussion positively predicted between- person changes in both husbands’ and wives’ marital satifaction two waves later. | BA41: =IFERROR(__xludf.DUMMYFUNCTION("vlookup(BB41,importrange(""https://docs.google.com/spreadsheets/d/1d2vevQ_7D_v35q4wCQ4RpQ_IPoTwEMB9Yp6ymwlPqew/edit?gid=984458430#gid=984458430"", ""'replication success'!A:M""), 13, FAlSE)"),"abstract") -> abstract | BB41: =IFERROR(__xludf.DUMMYFUNCTION("REGEXREPLACE(G41, ""_[a-z]{1,2}$"", """")"),"additional_studies11") -> additional_studies11 | BD41: LR
A42: 42 | B42: validated - discarded | C42: double | D42: Fabienne | F42: additional_studies11_1 | G42: additional_studies11_n | H42: Julia Fabienne Sandkühler | I42: 45637 | J42: 45692 | K42: replication N refers to number of couples | M42: Saxey, M. T., LeBaron-Black, A. B., & Curran, M. A. (2022). The Sooner, the Better? Couples' First Financial Discussion, Relationship Quality, and Financial Conflict in Emerging Adulthood. Journal of Financial Therapy, 13 (1) 2. https://doi.org/10.4148/1944-9771.1299 | N42: 10.4148/1944-9771.1299 | P42: 10.4148--1944-9771.1299.pdf | Q42: {=if(iserror(MATCH(V42, 'File Links'!C:C, 0)), "N/A", HYPERLINK(INDEX('File Links'!B:B, MATCH(P42, 'File Links'!C:C, 0))))} -> https://drive.google.com/file/d/1OByNKNsjZqSFHFFyt-o1mPqDkVmgruBu/view?usp=drivesdk | R42: Saxey, M. T., LeBaron‐Black, A. B., Inman, N. F., Yorgason, J. B., & Holmes, E. K. (2024). The earlier couples first discussed finances, the better? A dyadic, longitudinal replication and extension. Family Relations. https://doi.org/10.1111/fare.13030 | S42: 10.1111/fare.13030 | V42: =hyperlink(vlookup(lower(S42),'File Links'!E:F, 2, FALSE), SUBSTITUTE(lower(S42), "/", "--") & ".pdf") -> 10.1111--fare.13030.pdf | W42: dyadic, longitudinal replication and extension | X42: {=if(iserror(MATCH(V42, 'File Links'!C:C, 0)), "N/A", HYPERLINK(INDEX('File Links'!B:B, MATCH(V42, 'File Links'!C:C, 0))))} -> https://drive.google.com/file/d/1TGN_TAtoJI3jhMQTEG2wnN59FCyiXC2_/view?usp=drivesdk | Z42: Social Psychology | AB42: emerging adulthood; financial communication; financial conflict; financial discussion, relationship quality | AC42: No direct effect present for relationship quality (replication: longitudinal, wives' answers, effect on partner) | AD42: No direct effect present for relationship quality: “Nonetheless, couples’ first financial discussion was not directly associated with their relationship quality.” (however not emphasised in original) | AE42: 11 | AF42: 1950 | AH42: beta | AI42: p. 11 | AJ42: 0.05 | AK42: g (>) | AL42: NA (not reported) | AN42: NA | AO42: 1079 | AQ42: beta (std) | AR42: p. 2538 | AS42: 0.05 | AT42: g (>) | AU42: NA (not reported) | AW42: NA | AX42: 3 - conceptual | AY42: =IFERROR(__xludf.DUMMYFUNCTION("vlookup(BB42,importrange(""https://docs.google.com/spreadsheets/d/1d2vevQ_7D_v35q4wCQ4RpQ_IPoTwEMB9Yp6ymwlPqew/edit?gid=984458430#gid=984458430"", ""'replication success'!A:K""), 11, FAlSE)"),"mixed") -> mixed | AZ42: =IFERROR(__xludf.DUMMYFUNCTION("vlookup(BB42,importrange(""https://docs.google.com/spreadsheets/d/1d2vevQ_7D_v35q4wCQ4RpQ_IPoTwEMB9Yp6ymwlPqew/edit?gid=984458430#gid=984458430"", ""'replication success'!A:M""), 12, FAlSE)"),"Cross-sectionally, both husbands’ and wives’ reports of their first financial discussion predicted better marital satisfaction and fewer financial disagreements through their own report of healthy financial communication. Longitudinally, only husbands’ r"&"eport of the couple’s first financial discussion positively predicted between- person changes in both husbands’ and wives’ marital satifaction two waves later.") -> Cross-sectionally, both husbands’ and wives’ reports of their first financial discussion predicted better marital satisfaction and fewer financial disagreements through their own report of healthy financial communication. Longitudinally, only husbands’ report of the couple’s first financial discussion positively predicted between- person changes in both husbands’ and wives’ marital satifaction two waves later. | BA42: =IFERROR(__xludf.DUMMYFUNCTION("vlookup(BB42,importrange(""https://docs.google.com/spreadsheets/d/1d2vevQ_7D_v35q4wCQ4RpQ_IPoTwEMB9Yp6ymwlPqew/edit?gid=984458430#gid=984458430"", ""'replication success'!A:M""), 13, FAlSE)"),"abstract") -> abstract | BB42: =IFERROR(__xludf.DUMMYFUNCTION("REGEXREPLACE(G42, ""_[a-z]{1,2}$"", """")"),"additional_studies11") -> additional_studies11 | BD42: LR
A43: 43 | B43: validated - discarded | C43: double | D43: Fabienne | F43: additional_studies11_1 | G43: additional_studies11_o | H43: Julia Fabienne Sandkühler | I43: 45637 | J43: 45692 | K43: replication N refers to number of couples | M43: Saxey, M. T., LeBaron-Black, A. B., & Curran, M. A. (2022). The Sooner, the Better? Couples' First Financial Discussion, Relationship Quality, and Financial Conflict in Emerging Adulthood. Journal of Financial Therapy, 13 (1) 2. https://doi.org/10.4148/1944-9771.1299 | N43: 10.4148/1944-9771.1299 | P43: 10.4148--1944-9771.1299.pdf | Q43: {=if(iserror(MATCH(V43, 'File Links'!C:C, 0)), "N/A", HYPERLINK(INDEX('File Links'!B:B, MATCH(P43, 'File Links'!C:C, 0))))} -> https://drive.google.com/file/d/1OByNKNsjZqSFHFFyt-o1mPqDkVmgruBu/view?usp=drivesdk | R43: Saxey, M. T., LeBaron‐Black, A. B., Inman, N. F., Yorgason, J. B., & Holmes, E. K. (2024). The earlier couples first discussed finances, the better? A dyadic, longitudinal replication and extension. Family Relations. https://doi.org/10.1111/fare.13030 | S43: 10.1111/fare.13030 | V43: =hyperlink(vlookup(lower(S43),'File Links'!E:F, 2, FALSE), SUBSTITUTE(lower(S43), "/", "--") & ".pdf") -> 10.1111--fare.13030.pdf | W43: dyadic, longitudinal replication and extension | X43: {=if(iserror(MATCH(V43, 'File Links'!C:C, 0)), "N/A", HYPERLINK(INDEX('File Links'!B:B, MATCH(V43, 'File Links'!C:C, 0))))} -> https://drive.google.com/file/d/1TGN_TAtoJI3jhMQTEG2wnN59FCyiXC2_/view?usp=drivesdk | Z43: Social Psychology | AB43: emerging adulthood; financial communication; financial conflict; financial discussion, relationship quality | AC43: No direct effect present for relationship quality (replication: longitudinal, husbands' answers, effect on themselves) | AD43: No direct effect present for relationship quality: “Nonetheless, couples’ first financial discussion was not directly associated with their relationship quality.” (however not emphasised in original) | AE43: 11 | AF43: 1950 | AH43: beta | AI43: p. 11 | AJ43: 0.05 | AK43: g (>) | AL43: NA (not reported) | AN43: NA | AO43: 1079 | AP43: 0.07 | AQ43: beta (std) | AR43: p. 2538 | AS43: 0.05 | AT43: l (<) | AU43: NA (not reported) | AW43: NA | AX43: 3 - conceptual | AY43: =IFERROR(__xludf.DUMMYFUNCTION("vlookup(BB43,importrange(""https://docs.google.com/spreadsheets/d/1d2vevQ_7D_v35q4wCQ4RpQ_IPoTwEMB9Yp6ymwlPqew/edit?gid=984458430#gid=984458430"", ""'replication success'!A:K""), 11, FAlSE)"),"mixed") -> mixed | AZ43: =IFERROR(__xludf.DUMMYFUNCTION("vlookup(BB43,importrange(""https://docs.google.com/spreadsheets/d/1d2vevQ_7D_v35q4wCQ4RpQ_IPoTwEMB9Yp6ymwlPqew/edit?gid=984458430#gid=984458430"", ""'replication success'!A:M""), 12, FAlSE)"),"Cross-sectionally, both husbands’ and wives’ reports of their first financial discussion predicted better marital satisfaction and fewer financial disagreements through their own report of healthy financial communication. Longitudinally, only husbands’ r"&"eport of the couple’s first financial discussion positively predicted between- person changes in both husbands’ and wives’ marital satifaction two waves later.") -> Cross-sectionally, both husbands’ and wives’ reports of their first financial discussion predicted better marital satisfaction and fewer financial disagreements through their own report of healthy financial communication. Longitudinally, only husbands’ report of the couple’s first financial discussion positively predicted between- person changes in both husbands’ and wives’ marital satifaction two waves later. | BA43: =IFERROR(__xludf.DUMMYFUNCTION("vlookup(BB43,importrange(""https://docs.google.com/spreadsheets/d/1d2vevQ_7D_v35q4wCQ4RpQ_IPoTwEMB9Yp6ymwlPqew/edit?gid=984458430#gid=984458430"", ""'replication success'!A:M""), 13, FAlSE)"),"abstract") -> abstract | BB43: =IFERROR(__xludf.DUMMYFUNCTION("REGEXREPLACE(G43, ""_[a-z]{1,2}$"", """")"),"additional_studies11") -> additional_studies11 | BD43: LR
A44: 44 | B44: validated - discarded | C44: double | D44: Fabienne | F44: additional_studies11_1 | G44: additional_studies11_p | H44: Julia Fabienne Sandkühler | I44: 45637 | J44: 45692 | K44: replication N refers to number of couples | M44: Saxey, M. T., LeBaron-Black, A. B., & Curran, M. A. (2022). The Sooner, the Better? Couples' First Financial Discussion, Relationship Quality, and Financial Conflict in Emerging Adulthood. Journal of Financial Therapy, 13 (1) 2. https://doi.org/10.4148/1944-9771.1299 | N44: 10.4148/1944-9771.1299 | P44: 10.4148--1944-9771.1299.pdf | Q44: {=if(iserror(MATCH(V44, 'File Links'!C:C, 0)), "N/A", HYPERLINK(INDEX('File Links'!B:B, MATCH(P44, 'File Links'!C:C, 0))))} -> https://drive.google.com/file/d/1OByNKNsjZqSFHFFyt-o1mPqDkVmgruBu/view?usp=drivesdk | R44: Saxey, M. T., LeBaron‐Black, A. B., Inman, N. F., Yorgason, J. B., & Holmes, E. K. (2024). The earlier couples first discussed finances, the better? A dyadic, longitudinal replication and extension. Family Relations. https://doi.org/10.1111/fare.13030 | S44: 10.1111/fare.13030 | V44: =hyperlink(vlookup(lower(S44),'File Links'!E:F, 2, FALSE), SUBSTITUTE(lower(S44), "/", "--") & ".pdf") -> 10.1111--fare.13030.pdf | W44: dyadic, longitudinal replication and extension | X44: {=if(iserror(MATCH(V44, 'File Links'!C:C, 0)), "N/A", HYPERLINK(INDEX('File Links'!B:B, MATCH(V44, 'File Links'!C:C, 0))))} -> https://drive.google.com/file/d/1TGN_TAtoJI3jhMQTEG2wnN59FCyiXC2_/view?usp=drivesdk | Z44: Social Psychology | AB44: emerging adulthood; financial communication; financial conflict; financial discussion, relationship quality | AC44: No direct effect present for relationship quality (replication: longitudinal, husbands' answers, effect on partner) | AD44: No direct effect present for relationship quality: “Nonetheless, couples’ first financial discussion was not directly associated with their relationship quality.” (however not emphasised in original) | AE44: 11 | AF44: 1950 | AH44: beta | AI44: p. 11 | AJ44: 0.05 | AK44: g (>) | AL44: NA (not reported) | AN44: NA | AO44: 1079 | AP44: 0.07 | AQ44: beta (std) | AR44: p. 2538 | AS44: 0.05 | AT44: l (<) | AU44: NA (not reported) | AW44: NA | AX44: 3 - conceptual | AY44: =IFERROR(__xludf.DUMMYFUNCTION("vlookup(BB44,importrange(""https://docs.google.com/spreadsheets/d/1d2vevQ_7D_v35q4wCQ4RpQ_IPoTwEMB9Yp6ymwlPqew/edit?gid=984458430#gid=984458430"", ""'replication success'!A:K""), 11, FAlSE)"),"mixed") -> mixed | AZ44: =IFERROR(__xludf.DUMMYFUNCTION("vlookup(BB44,importrange(""https://docs.google.com/spreadsheets/d/1d2vevQ_7D_v35q4wCQ4RpQ_IPoTwEMB9Yp6ymwlPqew/edit?gid=984458430#gid=984458430"", ""'replication success'!A:M""), 12, FAlSE)"),"Cross-sectionally, both husbands’ and wives’ reports of their first financial discussion predicted better marital satisfaction and fewer financial disagreements through their own report of healthy financial communication. Longitudinally, only husbands’ r"&"eport of the couple’s first financial discussion positively predicted between- person changes in both husbands’ and wives’ marital satifaction two waves later.") -> Cross-sectionally, both husbands’ and wives’ reports of their first financial discussion predicted better marital satisfaction and fewer financial disagreements through their own report of healthy financial communication. Longitudinally, only husbands’ report of the couple’s first financial discussion positively predicted between- person changes in both husbands’ and wives’ marital satifaction two waves later. | BA44: =IFERROR(__xludf.DUMMYFUNCTION("vlookup(BB44,importrange(""https://docs.google.com/spreadsheets/d/1d2vevQ_7D_v35q4wCQ4RpQ_IPoTwEMB9Yp6ymwlPqew/edit?gid=984458430#gid=984458430"", ""'replication success'!A:M""), 13, FAlSE)"),"abstract") -> abstract | BB44: =IFERROR(__xludf.DUMMYFUNCTION("REGEXREPLACE(G44, ""_[a-z]{1,2}$"", """")"),"additional_studies11") -> additional_studies11 | BD44: LR
A45: 45 | B45: validated - discarded | C45: double | D45: Fabienne | F45: additional_studies11_1 | G45: additional_studies11_q | H45: Julia Fabienne Sandkühler | I45: 45637 | J45: 45692 | K45: replication N refers to number of couples | M45: Saxey, M. T., LeBaron-Black, A. B., & Curran, M. A. (2022). The Sooner, the Better? Couples' First Financial Discussion, Relationship Quality, and Financial Conflict in Emerging Adulthood. Journal of Financial Therapy, 13 (1) 2. https://doi.org/10.4148/1944-9771.1299 | N45: 10.4148/1944-9771.1299 | P45: 10.4148--1944-9771.1299.pdf | Q45: {=if(iserror(MATCH(V45, 'File Links'!C:C, 0)), "N/A", HYPERLINK(INDEX('File Links'!B:B, MATCH(P45, 'File Links'!C:C, 0))))} -> https://drive.google.com/file/d/1OByNKNsjZqSFHFFyt-o1mPqDkVmgruBu/view?usp=drivesdk | R45: Saxey, M. T., LeBaron‐Black, A. B., Inman, N. F., Yorgason, J. B., & Holmes, E. K. (2024). The earlier couples first discussed finances, the better? A dyadic, longitudinal replication and extension. Family Relations. https://doi.org/10.1111/fare.13030 | S45: 10.1111/fare.13030 | V45: =hyperlink(vlookup(lower(S45),'File Links'!E:F, 2, FALSE), SUBSTITUTE(lower(S45), "/", "--") & ".pdf") -> 10.1111--fare.13030.pdf | W45: dyadic, longitudinal replication and extension | X45: {=if(iserror(MATCH(V45, 'File Links'!C:C, 0)), "N/A", HYPERLINK(INDEX('File Links'!B:B, MATCH(V45, 'File Links'!C:C, 0))))} -> https://drive.google.com/file/d/1TGN_TAtoJI3jhMQTEG2wnN59FCyiXC2_/view?usp=drivesdk | Z45: Social Psychology | AB45: emerging adulthood; financial communication; financial conflict; financial discussion, relationship quality | AC45: Indirect effect present for financial conflict (replication: cross-sectional, wives' answers, effect on themselves) | AD45: Indirect effect present for financial conflict: "The pathway from the first financial discussion to financial conflict through financial communication was significant (β = -.06; p < .001)" (however not emphasised in original) | AE45: 11 | AF45: 1950 | AG45: -0.06 | AH45: beta | AI45: p. 11 | AJ45: 0.001 | AK45: l (<) | AL45: NA (not reported) | AN45: NA | AO45: 1079 | AP45: -0.07 | AQ45: beta (std) | AR45: p. 2537 | AS45: 0.001 | AT45: l (<) | AU45: NA (not reported) | AW45: NA | AX45: 3 - conceptual | AY45: =IFERROR(__xludf.DUMMYFUNCTION("vlookup(BB45,importrange(""https://docs.google.com/spreadsheets/d/1d2vevQ_7D_v35q4wCQ4RpQ_IPoTwEMB9Yp6ymwlPqew/edit?gid=984458430#gid=984458430"", ""'replication success'!A:K""), 11, FAlSE)"),"mixed") -> mixed | AZ45: =IFERROR(__xludf.DUMMYFUNCTION("vlookup(BB45,importrange(""https://docs.google.com/spreadsheets/d/1d2vevQ_7D_v35q4wCQ4RpQ_IPoTwEMB9Yp6ymwlPqew/edit?gid=984458430#gid=984458430"", ""'replication success'!A:M""), 12, FAlSE)"),"Cross-sectionally, both husbands’ and wives’ reports of their first financial discussion predicted better marital satisfaction and fewer financial disagreements through their own report of healthy financial communication. Longitudinally, only husbands’ r"&"eport of the couple’s first financial discussion positively predicted between- person changes in both husbands’ and wives’ marital satifaction two waves later.") -> Cross-sectionally, both husbands’ and wives’ reports of their first financial discussion predicted better marital satisfaction and fewer financial disagreements through their own report of healthy financial communication. Longitudinally, only husbands’ report of the couple’s first financial discussion positively predicted between- person changes in both husbands’ and wives’ marital satifaction two waves later. | BA45: =IFERROR(__xludf.DUMMYFUNCTION("vlookup(BB45,importrange(""https://docs.google.com/spreadsheets/d/1d2vevQ_7D_v35q4wCQ4RpQ_IPoTwEMB9Yp6ymwlPqew/edit?gid=984458430#gid=984458430"", ""'replication success'!A:M""), 13, FAlSE)"),"abstract") -> abstract | BB45: =IFERROR(__xludf.DUMMYFUNCTION("REGEXREPLACE(G45, ""_[a-z]{1,2}$"", """")"),"additional_studies11") -> additional_studies11 | BD45: LR
A46: 46 | B46: validated - discarded | C46: double | D46: Fabienne | F46: additional_studies11_1 | G46: additional_studies11_r | H46: Julia Fabienne Sandkühler | I46: 45637 | J46: 45692 | K46: replication N refers to number of couples | M46: Saxey, M. T., LeBaron-Black, A. B., & Curran, M. A. (2022). The Sooner, the Better? Couples' First Financial Discussion, Relationship Quality, and Financial Conflict in Emerging Adulthood. Journal of Financial Therapy, 13 (1) 2. https://doi.org/10.4148/1944-9771.1299 | N46: 10.4148/1944-9771.1299 | P46: 10.4148--1944-9771.1299.pdf | Q46: {=if(iserror(MATCH(V46, 'File Links'!C:C, 0)), "N/A", HYPERLINK(INDEX('File Links'!B:B, MATCH(P46, 'File Links'!C:C, 0))))} -> https://drive.google.com/file/d/1OByNKNsjZqSFHFFyt-o1mPqDkVmgruBu/view?usp=drivesdk | R46: Saxey, M. T., LeBaron‐Black, A. B., Inman, N. F., Yorgason, J. B., & Holmes, E. K. (2024). The earlier couples first discussed finances, the better? A dyadic, longitudinal replication and extension. Family Relations. https://doi.org/10.1111/fare.13030 | S46: 10.1111/fare.13030 | V46: =hyperlink(vlookup(lower(S46),'File Links'!E:F, 2, FALSE), SUBSTITUTE(lower(S46), "/", "--") & ".pdf") -> 10.1111--fare.13030.pdf | W46: dyadic, longitudinal replication and extension | X46: {=if(iserror(MATCH(V46, 'File Links'!C:C, 0)), "N/A", HYPERLINK(INDEX('File Links'!B:B, MATCH(V46, 'File Links'!C:C, 0))))} -> https://drive.google.com/file/d/1TGN_TAtoJI3jhMQTEG2wnN59FCyiXC2_/view?usp=drivesdk | Z46: Social Psychology | AB46: emerging adulthood; financial communication; financial conflict; financial discussion, relationship quality | AC46: Indirect effect present for financial conflict (replication: cross-sectional, wives' answers, effect on partner) | AD46: Indirect effect present for financial conflict: "The pathway from the first financial discussion to financial conflict through financial communication was significant (β = -.06; p < .001)" (however not emphasised in original) | AE46: 11 | AF46: 1950 | AG46: -0.06 | AH46: beta | AI46: p. 11 | AJ46: 0.001 | AK46: l (<) | AL46: NA (not reported) | AN46: NA | AO46: 1079 | AP46: -0.03 | AQ46: beta (std) | AR46: p. 2537 | AS46: 0.01 | AT46: l (<) | AU46: NA (not reported) | AW46: NA | AX46: 3 - conceptual | AY46: =IFERROR(__xludf.DUMMYFUNCTION("vlookup(BB46,importrange(""https://docs.google.com/spreadsheets/d/1d2vevQ_7D_v35q4wCQ4RpQ_IPoTwEMB9Yp6ymwlPqew/edit?gid=984458430#gid=984458430"", ""'replication success'!A:K""), 11, FAlSE)"),"mixed") -> mixed | AZ46: =IFERROR(__xludf.DUMMYFUNCTION("vlookup(BB46,importrange(""https://docs.google.com/spreadsheets/d/1d2vevQ_7D_v35q4wCQ4RpQ_IPoTwEMB9Yp6ymwlPqew/edit?gid=984458430#gid=984458430"", ""'replication success'!A:M""), 12, FAlSE)"),"Cross-sectionally, both husbands’ and wives’ reports of their first financial discussion predicted better marital satisfaction and fewer financial disagreements through their own report of healthy financial communication. Longitudinally, only husbands’ r"&"eport of the couple’s first financial discussion positively predicted between- person changes in both husbands’ and wives’ marital satifaction two waves later.") -> Cross-sectionally, both husbands’ and wives’ reports of their first financial discussion predicted better marital satisfaction and fewer financial disagreements through their own report of healthy financial communication. Longitudinally, only husbands’ report of the couple’s first financial discussion positively predicted between- person changes in both husbands’ and wives’ marital satifaction two waves later. | BA46: =IFERROR(__xludf.DUMMYFUNCTION("vlookup(BB46,importrange(""https://docs.google.com/spreadsheets/d/1d2vevQ_7D_v35q4wCQ4RpQ_IPoTwEMB9Yp6ymwlPqew/edit?gid=984458430#gid=984458430"", ""'replication success'!A:M""), 13, FAlSE)"),"abstract") -> abstract | BB46: =IFERROR(__xludf.DUMMYFUNCTION("REGEXREPLACE(G46, ""_[a-z]{1,2}$"", """")"),"additional_studies11") -> additional_studies11 | BD46: LR
A47: 47 | B47: validated - discarded | C47: double | D47: Fabienne | F47: additional_studies11_1 | G47: additional_studies11_s | H47: Julia Fabienne Sandkühler | I47: 45637 | J47: 45692 | K47: replication N refers to number of couples | M47: Saxey, M. T., LeBaron-Black, A. B., & Curran, M. A. (2022). The Sooner, the Better? Couples' First Financial Discussion, Relationship Quality, and Financial Conflict in Emerging Adulthood. Journal of Financial Therapy, 13 (1) 2. https://doi.org/10.4148/1944-9771.1299 | N47: 10.4148/1944-9771.1299 | P47: 10.4148--1944-9771.1299.pdf | Q47: {=if(iserror(MATCH(V47, 'File Links'!C:C, 0)), "N/A", HYPERLINK(INDEX('File Links'!B:B, MATCH(P47, 'File Links'!C:C, 0))))} -> https://drive.google.com/file/d/1OByNKNsjZqSFHFFyt-o1mPqDkVmgruBu/view?usp=drivesdk | R47: Saxey, M. T., LeBaron‐Black, A. B., Inman, N. F., Yorgason, J. B., & Holmes, E. K. (2024). The earlier couples first discussed finances, the better? A dyadic, longitudinal replication and extension. Family Relations. https://doi.org/10.1111/fare.13030 | S47: 10.1111/fare.13030 | V47: =hyperlink(vlookup(lower(S47),'File Links'!E:F, 2, FALSE), SUBSTITUTE(lower(S47), "/", "--") & ".pdf") -> 10.1111--fare.13030.pdf | W47: dyadic, longitudinal replication and extension | X47: {=if(iserror(MATCH(V47, 'File Links'!C:C, 0)), "N/A", HYPERLINK(INDEX('File Links'!B:B, MATCH(V47, 'File Links'!C:C, 0))))} -> https://drive.google.com/file/d/1TGN_TAtoJI3jhMQTEG2wnN59FCyiXC2_/view?usp=drivesdk | Z47: Social Psychology | AB47: emerging adulthood; financial communication; financial conflict; financial discussion, relationship quality | AC47: Indirect effect present for financial conflict (replication: cross-sectional, husbands' answers, effect on themselves) | AD47: Indirect effect present for financial conflict: "The pathway from the first financial discussion to financial conflict through financial communication was significant (β = -.06; p < .001)" (however not emphasised in original) | AE47: 11 | AF47: 1950 | AG47: -0.06 | AH47: beta | AI47: p. 11 | AJ47: 0.001 | AK47: l (<) | AL47: NA (not reported) | AN47: NA | AO47: 1079 | AP47: -0.04 | AQ47: beta (std) | AR47: p. 2537 | AS47: 0.05 | AT47: l (<) | AU47: NA (not reported) | AW47: NA | AX47: 3 - conceptual | AY47: =IFERROR(__xludf.DUMMYFUNCTION("vlookup(BB47,importrange(""https://docs.google.com/spreadsheets/d/1d2vevQ_7D_v35q4wCQ4RpQ_IPoTwEMB9Yp6ymwlPqew/edit?gid=984458430#gid=984458430"", ""'replication success'!A:K""), 11, FAlSE)"),"mixed") -> mixed | AZ47: =IFERROR(__xludf.DUMMYFUNCTION("vlookup(BB47,importrange(""https://docs.google.com/spreadsheets/d/1d2vevQ_7D_v35q4wCQ4RpQ_IPoTwEMB9Yp6ymwlPqew/edit?gid=984458430#gid=984458430"", ""'replication success'!A:M""), 12, FAlSE)"),"Cross-sectionally, both husbands’ and wives’ reports of their first financial discussion predicted better marital satisfaction and fewer financial disagreements through their own report of healthy financial communication. Longitudinally, only husbands’ r"&"eport of the couple’s first financial discussion positively predicted between- person changes in both husbands’ and wives’ marital satifaction two waves later.") -> Cross-sectionally, both husbands’ and wives’ reports of their first financial discussion predicted better marital satisfaction and fewer financial disagreements through their own report of healthy financial communication. Longitudinally, only husbands’ report of the couple’s first financial discussion positively predicted between- person changes in both husbands’ and wives’ marital satifaction two waves later. | BA47: =IFERROR(__xludf.DUMMYFUNCTION("vlookup(BB47,importrange(""https://docs.google.com/spreadsheets/d/1d2vevQ_7D_v35q4wCQ4RpQ_IPoTwEMB9Yp6ymwlPqew/edit?gid=984458430#gid=984458430"", ""'replication success'!A:M""), 13, FAlSE)"),"abstract") -> abstract | BB47: =IFERROR(__xludf.DUMMYFUNCTION("REGEXREPLACE(G47, ""_[a-z]{1,2}$"", """")"),"additional_studies11") -> additional_studies11 | BD47: LR
A48: 48 | B48: validated - discarded | C48: double | D48: Fabienne | F48: additional_studies11_1 | G48: additional_studies11_t | H48: Julia Fabienne Sandkühler | I48: 45637 | J48: 45692 | K48: replication N refers to number of couples | M48: Saxey, M. T., LeBaron-Black, A. B., & Curran, M. A. (2022). The Sooner, the Better? Couples' First Financial Discussion, Relationship Quality, and Financial Conflict in Emerging Adulthood. Journal of Financial Therapy, 13 (1) 2. https://doi.org/10.4148/1944-9771.1299 | N48: 10.4148/1944-9771.1299 | P48: 10.4148--1944-9771.1299.pdf | Q48: {=if(iserror(MATCH(V48, 'File Links'!C:C, 0)), "N/A", HYPERLINK(INDEX('File Links'!B:B, MATCH(P48, 'File Links'!C:C, 0))))} -> https://drive.google.com/file/d/1OByNKNsjZqSFHFFyt-o1mPqDkVmgruBu/view?usp=drivesdk | R48: Saxey, M. T., LeBaron‐Black, A. B., Inman, N. F., Yorgason, J. B., & Holmes, E. K. (2024). The earlier couples first discussed finances, the better? A dyadic, longitudinal replication and extension. Family Relations. https://doi.org/10.1111/fare.13030 | S48: 10.1111/fare.13030 | V48: =hyperlink(vlookup(lower(S48),'File Links'!E:F, 2, FALSE), SUBSTITUTE(lower(S48), "/", "--") & ".pdf") -> 10.1111--fare.13030.pdf | W48: dyadic, longitudinal replication and extension | X48: {=if(iserror(MATCH(V48, 'File Links'!C:C, 0)), "N/A", HYPERLINK(INDEX('File Links'!B:B, MATCH(V48, 'File Links'!C:C, 0))))} -> https://drive.google.com/file/d/1TGN_TAtoJI3jhMQTEG2wnN59FCyiXC2_/view?usp=drivesdk | Z48: Social Psychology | AB48: emerging adulthood; financial communication; financial conflict; financial discussion, relationship quality | AC48: Indirect effect present for financial conflict (replication: cross-sectional, husbands' answers, effect on partner) | AD48: Indirect effect present for financial conflict: "The pathway from the first financial discussion to financial conflict through financial communication was significant (β = -.06; p < .001)" (however not emphasised in original) | AE48: 11 | AF48: 1950 | AG48: -0.06 | AH48: beta | AI48: p. 11 | AJ48: 0.001 | AK48: l (<) | AL48: NA (not reported) | AN48: NA | AO48: 1079 | AP48: -0.02 | AQ48: beta (std) | AR48: p. 2537 | AS48: 0.05 | AT48: l (<) | AU48: NA (not reported) | AW48: NA | AX48: 3 - conceptual | AY48: =IFERROR(__xludf.DUMMYFUNCTION("vlookup(BB48,importrange(""https://docs.google.com/spreadsheets/d/1d2vevQ_7D_v35q4wCQ4RpQ_IPoTwEMB9Yp6ymwlPqew/edit?gid=984458430#gid=984458430"", ""'replication success'!A:K""), 11, FAlSE)"),"mixed") -> mixed | AZ48: =IFERROR(__xludf.DUMMYFUNCTION("vlookup(BB48,importrange(""https://docs.google.com/spreadsheets/d/1d2vevQ_7D_v35q4wCQ4RpQ_IPoTwEMB9Yp6ymwlPqew/edit?gid=984458430#gid=984458430"", ""'replication success'!A:M""), 12, FAlSE)"),"Cross-sectionally, both husbands’ and wives’ reports of their first financial discussion predicted better marital satisfaction and fewer financial disagreements through their own report of healthy financial communication. Longitudinally, only husbands’ r"&"eport of the couple’s first financial discussion positively predicted between- person changes in both husbands’ and wives’ marital satifaction two waves later.") -> Cross-sectionally, both husbands’ and wives’ reports of their first financial discussion predicted better marital satisfaction and fewer financial disagreements through their own report of healthy financial communication. Longitudinally, only husbands’ report of the couple’s first financial discussion positively predicted between- person changes in both husbands’ and wives’ marital satifaction two waves later. | BA48: =IFERROR(__xludf.DUMMYFUNCTION("vlookup(BB48,importrange(""https://docs.google.com/spreadsheets/d/1d2vevQ_7D_v35q4wCQ4RpQ_IPoTwEMB9Yp6ymwlPqew/edit?gid=984458430#gid=984458430"", ""'replication success'!A:M""), 13, FAlSE)"),"abstract") -> abstract | BB48: =IFERROR(__xludf.DUMMYFUNCTION("REGEXREPLACE(G48, ""_[a-z]{1,2}$"", """")"),"additional_studies11") -> additional_studies11 | BD48: LR
A49: 49 | B49: validated - discarded | C49: double | D49: Fabienne | F49: additional_studies11_1 | G49: additional_studies11_u | H49: Julia Fabienne Sandkühler | I49: 45637 | J49: 45692 | K49: replication N refers to number of couples | M49: Saxey, M. T., LeBaron-Black, A. B., & Curran, M. A. (2022). The Sooner, the Better? Couples' First Financial Discussion, Relationship Quality, and Financial Conflict in Emerging Adulthood. Journal of Financial Therapy, 13 (1) 2. https://doi.org/10.4148/1944-9771.1299 | N49: 10.4148/1944-9771.1299 | P49: 10.4148--1944-9771.1299.pdf | Q49: {=if(iserror(MATCH(V49, 'File Links'!C:C, 0)), "N/A", HYPERLINK(INDEX('File Links'!B:B, MATCH(P49, 'File Links'!C:C, 0))))} -> https://drive.google.com/file/d/1OByNKNsjZqSFHFFyt-o1mPqDkVmgruBu/view?usp=drivesdk | R49: Saxey, M. T., LeBaron‐Black, A. B., Inman, N. F., Yorgason, J. B., & Holmes, E. K. (2024). The earlier couples first discussed finances, the better? A dyadic, longitudinal replication and extension. Family Relations. https://doi.org/10.1111/fare.13030 | S49: 10.1111/fare.13030 | V49: =hyperlink(vlookup(lower(S49),'File Links'!E:F, 2, FALSE), SUBSTITUTE(lower(S49), "/", "--") & ".pdf") -> 10.1111--fare.13030.pdf | W49: dyadic, longitudinal replication and extension | X49: {=if(iserror(MATCH(V49, 'File Links'!C:C, 0)), "N/A", HYPERLINK(INDEX('File Links'!B:B, MATCH(V49, 'File Links'!C:C, 0))))} -> https://drive.google.com/file/d/1TGN_TAtoJI3jhMQTEG2wnN59FCyiXC2_/view?usp=drivesdk | Z49: Social Psychology | AB49: emerging adulthood; financial communication; financial conflict; financial discussion, relationship quality | AC49: Indirect effect present for financial conflict (replication: longitudinal, wives' answers, effect on themselves) | AD49: Indirect effect present for financial conflict: "The pathway from the first financial discussion to financial conflict through financial communication was significant (β = -.06; p < .001)" (however not emphasised in original) | AE49: 11 | AF49: 1950 | AG49: -0.06 | AH49: beta | AI49: p. 11 | AJ49: 0.001 | AK49: l (<) | AL49: NA (not reported) | AN49: NA | AO49: 1079 | AQ49: beta (std) | AR49: p. 2538 | AS49: 0.05 | AT49: g (>) | AU49: NA (not reported) | AW49: NA | AX49: 3 - conceptual | AY49: =IFERROR(__xludf.DUMMYFUNCTION("vlookup(BB49,importrange(""https://docs.google.com/spreadsheets/d/1d2vevQ_7D_v35q4wCQ4RpQ_IPoTwEMB9Yp6ymwlPqew/edit?gid=984458430#gid=984458430"", ""'replication success'!A:K""), 11, FAlSE)"),"mixed") -> mixed | AZ49: =IFERROR(__xludf.DUMMYFUNCTION("vlookup(BB49,importrange(""https://docs.google.com/spreadsheets/d/1d2vevQ_7D_v35q4wCQ4RpQ_IPoTwEMB9Yp6ymwlPqew/edit?gid=984458430#gid=984458430"", ""'replication success'!A:M""), 12, FAlSE)"),"Cross-sectionally, both husbands’ and wives’ reports of their first financial discussion predicted better marital satisfaction and fewer financial disagreements through their own report of healthy financial communication. Longitudinally, only husbands’ r"&"eport of the couple’s first financial discussion positively predicted between- person changes in both husbands’ and wives’ marital satifaction two waves later.") -> Cross-sectionally, both husbands’ and wives’ reports of their first financial discussion predicted better marital satisfaction and fewer financial disagreements through their own report of healthy financial communication. Longitudinally, only husbands’ report of the couple’s first financial discussion positively predicted between- person changes in both husbands’ and wives’ marital satifaction two waves later. | BA49: =IFERROR(__xludf.DUMMYFUNCTION("vlookup(BB49,importrange(""https://docs.google.com/spreadsheets/d/1d2vevQ_7D_v35q4wCQ4RpQ_IPoTwEMB9Yp6ymwlPqew/edit?gid=984458430#gid=984458430"", ""'replication success'!A:M""), 13, FAlSE)"),"abstract") -> abstract | BB49: =IFERROR(__xludf.DUMMYFUNCTION("REGEXREPLACE(G49, ""_[a-z]{1,2}$"", """")"),"additional_studies11") -> additional_studies11 | BD49: LR
A50: 50 | B50: validated - discarded | C50: double | D50: Fabienne | F50: additional_studies11_1 | G50: additional_studies11_v | H50: Julia Fabienne Sandkühler | I50: 45637 | J50: 45692 | K50: replication N refers to number of couples | M50: Saxey, M. T., LeBaron-Black, A. B., & Curran, M. A. (2022). The Sooner, the Better? Couples' First Financial Discussion, Relationship Quality, and Financial Conflict in Emerging Adulthood. Journal of Financial Therapy, 13 (1) 2. https://doi.org/10.4148/1944-9771.1299 | N50: 10.4148/1944-9771.1299 | P50: 10.4148--1944-9771.1299.pdf | Q50: {=if(iserror(MATCH(V50, 'File Links'!C:C, 0)), "N/A", HYPERLINK(INDEX('File Links'!B:B, MATCH(P50, 'File Links'!C:C, 0))))} -> https://drive.google.com/file/d/1OByNKNsjZqSFHFFyt-o1mPqDkVmgruBu/view?usp=drivesdk | R50: Saxey, M. T., LeBaron‐Black, A. B., Inman, N. F., Yorgason, J. B., & Holmes, E. K. (2024). The earlier couples first discussed finances, the better? A dyadic, longitudinal replication and extension. Family Relations. https://doi.org/10.1111/fare.13030 | S50: 10.1111/fare.13030 | V50: =hyperlink(vlookup(lower(S50),'File Links'!E:F, 2, FALSE), SUBSTITUTE(lower(S50), "/", "--") & ".pdf") -> 10.1111--fare.13030.pdf | W50: dyadic, longitudinal replication and extension | X50: {=if(iserror(MATCH(V50, 'File Links'!C:C, 0)), "N/A", HYPERLINK(INDEX('File Links'!B:B, MATCH(V50, 'File Links'!C:C, 0))))} -> https://drive.google.com/file/d/1TGN_TAtoJI3jhMQTEG2wnN59FCyiXC2_/view?usp=drivesdk | Z50: Social Psychology | AB50: emerging adulthood; financial communication; financial conflict; financial discussion, relationship quality | AC50: Indirect effect present for financial conflict (replication: longitudinal, wives' answers, effect on partner) | AD50: Indirect effect present for financial conflict: "The pathway from the first financial discussion to financial conflict through financial communication was significant (β = -.06; p < .001)" (however not emphasised in original) | AE50: 11 | AF50: 1950 | AG50: -0.06 | AH50: beta | AI50: p. 11 | AJ50: 0.001 | AK50: l (<) | AL50: NA (not reported) | AN50: NA | AO50: 1079 | AQ50: beta (std) | AR50: p. 2538 | AS50: 0.05 | AT50: g (>) | AU50: NA (not reported) | AW50: NA | AX50: 3 - conceptual | AY50: =IFERROR(__xludf.DUMMYFUNCTION("vlookup(BB50,importrange(""https://docs.google.com/spreadsheets/d/1d2vevQ_7D_v35q4wCQ4RpQ_IPoTwEMB9Yp6ymwlPqew/edit?gid=984458430#gid=984458430"", ""'replication success'!A:K""), 11, FAlSE)"),"mixed") -> mixed | AZ50: =IFERROR(__xludf.DUMMYFUNCTION("vlookup(BB50,importrange(""https://docs.google.com/spreadsheets/d/1d2vevQ_7D_v35q4wCQ4RpQ_IPoTwEMB9Yp6ymwlPqew/edit?gid=984458430#gid=984458430"", ""'replication success'!A:M""), 12, FAlSE)"),"Cross-sectionally, both husbands’ and wives’ reports of their first financial discussion predicted better marital satisfaction and fewer financial disagreements through their own report of healthy financial communication. Longitudinally, only husbands’ r"&"eport of the couple’s first financial discussion positively predicted between- person changes in both husbands’ and wives’ marital satifaction two waves later.") -> Cross-sectionally, both husbands’ and wives’ reports of their first financial discussion predicted better marital satisfaction and fewer financial disagreements through their own report of healthy financial communication. Longitudinally, only husbands’ report of the couple’s first financial discussion positively predicted between- person changes in both husbands’ and wives’ marital satifaction two waves later. | BA50: =IFERROR(__xludf.DUMMYFUNCTION("vlookup(BB50,importrange(""https://docs.google.com/spreadsheets/d/1d2vevQ_7D_v35q4wCQ4RpQ_IPoTwEMB9Yp6ymwlPqew/edit?gid=984458430#gid=984458430"", ""'replication success'!A:M""), 13, FAlSE)"),"abstract") -> abstract | BB50: =IFERROR(__xludf.DUMMYFUNCTION("REGEXREPLACE(G50, ""_[a-z]{1,2}$"", """")"),"additional_studies11") -> additional_studies11 | BD50: LR
