Workbook

Sheet COS coding
F1: id | G1: contributors | H1: date_entered | I1: date_updated | J1: notes_coder | K1: notes_validation | L1: ref_original | M1: doi_original | N1: study_original | Q1: ref_replication | R1: doi_replication | S1: osf_link | T1: study_replication | X1: exclusion | Y1: discipline | Z1: effect | AA1: tags | AB1: description | AC1: claim_text_orig | AD1: claim_text_orig_page | AE1: n_original | AF1: es_orig_value | AG1: es_orig_estype | AI1: pval_value_o | AJ1: pval_type_o | AK1: pval_tails_o | AN1: n_replication | AO1: es_rep_value | AP1: es_rep_estype | AR1: pval_value_r | AS1: pval_type_r | AT1: pval_tails_r
A2: status | B2: approach | C2: coder_1 | D2: coder_2 | E2: entry | F2: id | G2: contributors | H2: date_entered | I2: date_updated | J2: notes_coder | K2: notes_validation | L2: ref_o | M2: doi_o | N2: study_o | O2: file_o | P2: link_o | Q2: ref_r | R2: doi_r | S2: url_r | T2: study_r | U2: file_r | V2: label_r | W2: link_r | X2: exclusion | Y2: discipline | Z2: effect | AA2: tags | AB2: description | AC2: claim_text_o | AD2: claim_page_o | AE2: n_o | AF2: es_value_o | AG2: es_type_o | AH2: es_repr_o | AI2: pval_value_o | AJ2: pval_type_o | AK2: pval_tails_o | AL2: nested_o | AM2: prereg_o | AN2: n_r | AO2: es_value_r | AP2: es_type_r | AQ2: es_repr_r | AR2: pval_value_r | AS2: pval_type_r | AT2: pval_tails_r | AU2: nested_r | AV2: prereg_r | AW2: closeness_r | AX2: feedback_for_coder | AY2: validator
A3: - assigned: the entry has been assigned to a coder - help needed: there is an unresolved conflict - validated - chosen: the entry has been validated and marked as the one to remain in the final dataset - validated - discarded: the entry has been used for validation and is now inferior or redundant to the chosen entry for the same finding - validated - FReD but not COS: applies to replication studies that do not contain statistical test (e.g., replications in the qualitative humanities) | E3: for data matching. DO NOT EDIT - keep blank for new rows | F3: Sample id. DO NOT CHANGE. If you add samples, copy and add _b, _c etc | G3: *Add* your name when you edit the row | H3: (dd/mm/yyyy) | I3: (dd/mm/yyyy) | J3: general data entry notes, e.g., re access issues or study selection | K3: only used by core team | L3: Copy APA style from Google Scholar (or similar), without DOI | M3: without URL prefix, so starting with 10.xx | N3: Number of study in paper, e.g., 1 or 2A | O3: file-name for O PDF - only edit if DOI is missing | Q3: Copy APA style from Google Scholar (or similar), without DOI | R3: without URL prefix, so starting with 10.xx | S3: Link to R results - only when DOI missing or for aggregate report | T3: Number of study in paper, e.g., 1 or 2A | U3: file-name for R PDF - only edit if DOI is missing | V3: How does R identify as replication in title or abstract? Usually "replication" but report different wording if used | X3: Reason for study exclusion (usually only if R is not a replication) | Y3: Which broad field does the finding come from - e.g., Social Psychology or Labor Economics | Z3: x | AA3: tags to increase findability - e.g. keywords from abstract | AB3: Description of the effect under investigation (e.g., x is associated with y, x leads to y), possibly a part of the original publication's title (abstract claim) | AC3: The authors’ key statistical result and its interpretation | AD3: Page number(s) for claim_text_o | AE3: O's sample size [used for the critical test, i.e., after exclusion criteria have been applied], must contain only one value and must not contain text | AF3: original effect size value, must contain only one value and must not contain text | AG3: original effect size type (e.g., d, r, r², etasq) | AH3: Reproducible origin/calculation method for es_value_o ("p. xx" when reported, link when available online - e.g., OSF, otherwise calculation process) | AI3: The reported p-value associated with the original finding, must contain only one value and must not contain text | AJ3: How is p-val reported? "=" (e) / "<" (l) / ">" (g) or combined (le, ge)? for example "p <= .05" should be coded as "le" | AK3: How many tails associated with the p-value, taking on values of one, two, or unknown one: 1 two: 2 unknown / not specified: NA missing: not coded | AL3: Is pval based on a test that accounts for dependence between observations (e.g., multilevel, repeated measures) | AM3: Link to preregistration of O (only search for "regist") | AN3: R's sample size [used for the critical test, i.e., after exclusion criteria have been applied], must contain only one value and must not contain text | AO3: replication effect size value, must contain only one value and must not contain text | AP3: replication effect size type | AQ3: Reproducible origin/calculation method for es_value_r ("p. xx" when reported, otherwise calculation process) | AR3: The reported p-value associated with the replication finding, must contain only one value and must not contain text | AS3: How is p-val reported? "=" (e) / "<" (l) / ">" (g) or combined (le, ge)? for example "p <= .05" should be coded as "le" | AT3: How many tails associated with the p-value, taking on values of one, two, or unknown one: 1 two: 2 unknown: NA missing: not coded | AU3: Is pval based on a test that accounts for dependence between observations (e.g., multilevel, repeated measures) | AV3: Link to preregistration of R (only search for "regist") | AW3: NA: unknown 1: internal: all central features are highly similar AND conducted by at least one of the original researchers 2: close/direct: central features are highly similar AND none of the original authors is involved 3: conceptual/constructive/extension: central features are different, theoretically relevant aspects are the same; authorship overlap is irrelevant | AY3: name of the person who validated the entry
A4: validated - discarded | B4: double | C4: Maureen | E4: 2zgf9_1 | F4: 2zgf9 | G4: Kateri McRae, Daniel Lumian, Mallory C. Kidwell, Johanna Cohoon, Lilian Hummer | H4: 1.1.2023 | I4: 45641 | J4: coding tasks 2zgf9_1, bth36_1, and 7vgkq_1 are similar; the partial-eta squared reported in the replication paper of 0.226 is different from the value in OSF registries of 0.313, hence requires validation; Psychological science has not been listed as one of the disciplines, hence categorizing them as political science | L4: Cunningham, W. A., Van Bavel, J. J., & Johnsen, I. R. (2008). Affective flexibility: evaluative processing goals shape amygdala activity. Psychological Science, 19(2), 152-160. | M4: 10.1111/j.1467-9280.2008.02061.x | N4: 1 | O4: 10.1111--j.1467-9280.2008.02061.x.pdf | P4: {=HYPERLINK(INDEX('File Links'!B:B, MATCH(O4, 'File Links'!C:C, 0)))} -> https://drive.google.com/file/d/140WKvPe6h8fNM79ffoPo5RX6uP0flGT4/view?usp=drivesdk | Q4: McRae, K., & Lumian, D. S. (2023, September 28). Replication of WA Cunningham, JJ Van Bavel, IR Johnsen (2008, PS 19 (2)). https://doi.org/10.17605/OSF.IO/2ZGF9 | R4: 10.17605/OSF.IO/2ZGF9 | T4: 1 | U4: 10.17605--osf.io--2zgf9.pdf | V4: replication attempt | W4: {=HYPERLINK(INDEX('File Links'!B:B, MATCH(U4, 'File Links'!C:C, 0)))} -> https://drive.google.com/file/d/15dLELTosbF1NWFYI0UOSPLIC70dnGG5S/view?usp=drivesdk | Y4: Political Science | AA4: affective flexibility, amygdala, valence, stimulus | AB4: interaction between scanning condition (positive or negative) and stimulus valence | AC4: "results were consistent with the idea of affective flexibility. There was a significant interaction between scanning condition (positive or negative) and stimulus valence (postscan ratings of positivity or negativity), F(1, 11) = 9.67, p < .01, prep = .95" | AD4: p. 7 | AE4: 12 | AF4: 9.67 | AG4: F test statistic | AH4: p. 7 | AI4: 0.01 | AJ4: l (<) | AK4: 2 (two) | AL4: no | AN4: 39 | AO4: 0.226 | AP4: etasq | AQ4: p. 6 | AR4: 0.02 | AS4: l (<) | AT4: 2 (two) | AU4: yes | AV4: https://doi.org/10.17605/OSF.IO/2ZGF9 | AW4: 2 - close | AY4: LR
A5: validated - discarded | B5: double | C5: Jyoti | E5: 2zgf9_1 | F5: 2zgf9 | G5: Kateri McRae, Daniel Lumian, Mallory C. Kidwell, Johanna Cohoon, Lilian Hummer, Jyoti Bhogal | H5: 45108 | I5: 45644 | L5: Cunningham, W. A., Van Bavel, J. J., & Johnsen, I. R. (2008). Affective flexibility: evaluative processing goals shape amygdala activity. Psychological Science, 19(2), 152-160. | M5: 10.1111/j.1467-9280.2008.02061.x | N5: 1 | O5: 10.1111--j.1467-9280.2008.02061.x.pdf | P5: {=HYPERLINK(INDEX('File Links'!B:B, MATCH(O5, 'File Links'!C:C, 0)))} -> https://drive.google.com/file/d/140WKvPe6h8fNM79ffoPo5RX6uP0flGT4/view?usp=drivesdk | Q5: McRae, K., & Lumian, D. S. (2023, September 28). Replication of WA Cunningham, JJ Van Bavel, IR Johnsen (2008, PS 19 (2)). https://doi.org/10.17605/OSF.IO/2ZGF9 | R5: 10.17605/OSF.IO/2ZGF9 | U5: 10.17605--osf.io--2zgf9.pdf | W5: {=HYPERLINK(INDEX('File Links'!B:B, MATCH(U5, 'File Links'!C:C, 0)))} -> https://drive.google.com/file/d/15dLELTosbF1NWFYI0UOSPLIC70dnGG5S/view?usp=drivesdk | X5: no replication report available but only a post completion registration | Y5: Cognitive Psychology | AA5: affective flexibility, amygdala, positive names, negative names | AE5: 12 | AO5: 0.313 | AR5: unavailable | AW5: 3 - conceptual | AY5: LR
A6: validated - chosen | B6: double | C6: Nikita | E6: 39xuw_1 | F6: 39xuw | G6: Nikita | H6: 45638 | I6: 45680 | J6: 1. Values for the REPLICATION statistical inferences were taken from Files uploaded to OSF by a link: https://osf.io/39xuw/files/osfstorage. I merged them in the corresponding PDF | K6: corrected N from 150 to 137 | L6: Schaffer, J., & Knobe, J. (2012). Contrastive knowledge surveyed. Noûs, 46(4), 675-708. | M6: 10.1111/j.1468-0068.2010.00795.x | N6: 1 | O6: 10.1111--j.1468-0068.2010.00795.x.pdf | P6: {=HYPERLINK(INDEX('File Links'!B:B, MATCH(O6, 'File Links'!C:C, 0)))} -> https://drive.google.com/file/d/1O4mjB0-ZSujMTJYtaAoIsXTPuhxgEF-0/view?usp=drivesdk | Q6: Wilkenfeld, D. A., & Hernández-Conde, J. V. (2017, September 12). Schaffer and Knobe Replication. https://doi.org/10.17605/OSF.IO/39XUW | R6: 10.17605/OSF.IO/39XUW | T6: 1 | U6: 10.17605--osf.io--39xuw.pdf | V6: Replication | W6: {=HYPERLINK(INDEX('File Links'!B:B, MATCH(U6, 'File Links'!C:C, 0)))} -> #N/A | Y6: Experimental Philosophy | Z6: Contrast sensitivity of knowledge ascription (contrastivism) | AA6: Contrastivism, knowledge, knowledge ascription, "rather than" clause, contrast, context | AB6: The two conditions of the experiment involve ascribing knowledge of the very same proposition ("rather than" clause) and they differ only in that they pick out two different contrasts to that proposition: subject or object. | AC6: "Participants in the thief contrast condition tended to agree with the knowledge ascription they received (mean rating: 4.6), while participants in the jewel contrast condition tended to disagree with the knowledge ascription they received (mean rating: 3.1)." | AD6: 16 | AE6: 100 | AF6: t(98) = 3.4 | AG6: test statistic | AH6: p.31 | AI6: 0.001 | AJ6: e (=) | AK6: 2 (two) | AL6: no | AM6: NA | AN6: 137 | AO6: 0.584 | AP6: d | AQ6: p.2 of https://osf.io/k2cna | AR6: 0.001 | AS6: l (<) | AT6: 2 (two) | AU6: no | AV6: https://osf.io/39xuw | AW6: 2 - close | AY6: LR
A7: validated - discarded | B7: double | C7: Husnain | E7: 39xuw_1 | F7: 39xuw | G7: Husnain | H7: 45641 | I7: 45680 | J7: 1. The tags are not given explicitly so I have inferred from the introduction of orignal paper. 2. The effect size is not reprted in the orignal study while replication has reported it's own and the effect size of replication study the infered effect size is cohen's d 0.687. 3. The replication paper has reported cohen's d for the replicated study without the p value, however, it presented p valur for test stastic without the value of t. | L7: Schaffer, J., & Knobe, J. (2012). Contrastive knowledge surveyed. Noûs, 46(4), 675-708. | M7: 10.1111/j.1468-0068.2010.00795.x | O7: 10.1111--j.1468-0068.2010.00795.x.pdf | P7: {=HYPERLINK(INDEX('File Links'!B:B, MATCH(O7, 'File Links'!C:C, 0)))} -> https://drive.google.com/file/d/1O4mjB0-ZSujMTJYtaAoIsXTPuhxgEF-0/view?usp=drivesdk | Q7: Wilkenfeld, D. A., & Hernández-Conde, J. V. (2017, September 12). Schaffer and Knobe Replication. https://doi.org/10.17605/OSF.IO/39XUW | R7: 10.17605/OSF.IO/39XUW | U7: 10.17605--osf.io--39xuw.pdf | V7: Replication | W7: {=HYPERLINK(INDEX('File Links'!B:B, MATCH(U7, 'File Links'!C:C, 0)))} -> #N/A | Y7: Experimental Philosophy | Z7: contrastive knowledge | AA7: contrastive model, invariantist models, contextualist models, knowlege acriptions, conversational context | AB7: Thief contrast codition tend to agree more compared to jewel contrast condition with knowledge ascription | AC7: "N = 100 people spending time in the Canberra Centre Mall in Canberra, Australia, t (98) = 3.4, p = .001." | AD7: p. 16 | AE7: 100 | AF7: 3.4 | AG7: test statistic | AH7: p. 16, 31 | AI7: 0.001 | AJ7: e (=) | AK7: NA (not reported) | AL7: no | AN7: 137 | AO7: 0.584 | AP7: Cohen's d | AQ7: p. 1,2 | AV7: https://osf.io/39xuw | AW7: 2 - close | AY7: LR
A8: validated - discarded | B8: double | C8: Maureen | E8: 7vgkq_1 | F8: 7vgkq | G8: Kateri McRae, Mallory C. Kidwell, Johanna Cohoon, Daniel Lumian, Lilian Hummer, TESS-Experiments | H8: 1.1.2023 | I8: 45641 | J8: coding tasks 2zgf9_1, bth36_1, and 7vgkq_1 are similar; the partial-eta squared reported in the replication paper of 0.226 is different from the value in OSF registries of 0.313, hence requires validation; Psychological science has not been listed as one of the disciplines, hence categorizing them as political science | L8: Cunningham, W. A., Van Bavel, J. J., & Johnsen, I. R. (2008). Affective flexibility: evaluative processing goals shape amygdala activity. Psychological Science, 19(2), 152-160. | M8: 10.1111/j.1467-9280.2008.02061.x | N8: 1 | O8: 10.1111--j.1467-9280.2008.02061.x.pdf | P8: {=HYPERLINK(INDEX('File Links'!B:B, MATCH(O8, 'File Links'!C:C, 0)))} -> https://drive.google.com/file/d/140WKvPe6h8fNM79ffoPo5RX6uP0flGT4/view?usp=drivesdk | Q8: McRae, K., Lumian, D. S., & T. (2023, September 28). Materials. https://doi.org/10.17605/OSF.IO/7VGKQ | R8: 10.17605/OSF.IO/7VGKQ | U8: 10.17605--osf.io--7vgkq.pdf | V8: replication attempt | W8: {=HYPERLINK(INDEX('File Links'!B:B, MATCH(U8, 'File Links'!C:C, 0)))} -> #N/A | Y8: Political Science | AA8: affective flexibility, amygdala, valence, stimulus | AD8: p. 7 | AE8: 12 | AF8: 9.67 | AG8: F test statistic | AH8: p. 7 | AI8: 0.01 | AJ8: l (<) | AK8: 2 (two) | AL8: no | AN8: 39 | AO8: 0.226 | AP8: etasq | AQ8: p. 6 | AR8: 0.02 | AS8: l (<) | AT8: 2 (two) | AU8: yes | AV8: https://doi.org/10.17605/OSF.IO/7VGKQ | AW8: 2 - close | AY8: LR
A9: validated - discarded | B9: double | C9: Jyoti | E9: 7vgkq_1 | F9: 7vgkq | G9: Kateri McRae, Mallory C. Kidwell, Johanna Cohoon, Daniel Lumian, Lilian Hummer, TESS-Experiments, Jyoti Bhogal | H9: 45170 | I9: 45644 | L9: Cunningham, W. A., Van Bavel, J. J., & Johnsen, I. R. (2008). Affective flexibility: evaluative processing goals shape amygdala activity. Psychological Science, 19(2), 152-160. | M9: 10.1111/j.1467-9280.2008.02061.x | N9: 1 | O9: 10.1111--j.1467-9280.2008.02061.x.pdf | P9: {=HYPERLINK(INDEX('File Links'!B:B, MATCH(O9, 'File Links'!C:C, 0)))} -> https://drive.google.com/file/d/140WKvPe6h8fNM79ffoPo5RX6uP0flGT4/view?usp=drivesdk | Q9: McRae, K., Lumian, D. S., & T. (2023, September 28). Materials. https://doi.org/10.17605/OSF.IO/7VGKQ | R9: 10.17605/OSF.IO/7VGKQ | U9: 10.17605--osf.io--7vgkq.pdf | W9: {=HYPERLINK(INDEX('File Links'!B:B, MATCH(U9, 'File Links'!C:C, 0)))} -> #N/A | X9: no replication report available but only a post completion registration | Y9: Cognitive Psychology | AA9: affective flexibility, amygdala, positive names, negative names | AO9: 0.313 | AR9: unavailable | AY9: LR
A10: validated - discarded | B10: double | C10: Nikolay | E10: acykd_1 | F10: acykd | G10: Nikolay Petrov | H10: 45639 | J10: original sample size is 42, but 1 was excluded afterwards (p. 137) | K10: - Please type "NA" if you could not find "regis" in the manuscript. - Good catch with the N = 41! - This is the preregistration: https://osf.io/8urxv It is linked at the top of the entry | L10: Mussweiler, T., & Englich, B. (2005). Subliminal anchoring: Judgmental consequences and underlying mechanisms. Organizational Behavior and Human Decision Processes, 98(2), 133-143. | M10: 10.1016/j.obhdp.2004.12.002 | N10: 2 | O10: =hyperlink(vlookup(lower(M10),'File Links'!A:B, 2, FALSE), SUBSTITUTE(lower(M10), "/", "--") & ".pdf") -> 10.1016--j.obhdp.2004.12.002.pdf | P10: {=HYPERLINK(INDEX('File Links'!B:B, MATCH(O10, 'File Links'!C:C, 0)))} -> https://drive.google.com/file/d/1CZ8RmInPe2eqHwf-p8tl0IQxpn8_H_C5/view?usp=drivesdk | Q10: Röseler, L., Schütz, A., Burlakovas, E., Dück, M., Fels, S., Janiczek, S., … Seida, C. (2022, September 15). Replication Mussweiler & Englich, 2005, Study 2. https://doi.org/10.17605/OSF.IO/ACYKD | R10: 10.17605/OSF.IO/ACYKD | U10: 10.17605--osf.io--acykd.pdf | V10: replication | W10: {=HYPERLINK(INDEX('File Links'!B:B, MATCH(U10, 'File Links'!C:C, 0)))} -> #N/A | Y10: Judgment and Decision Making | Z10: subliminal anchoring | AA10: anchoring, subliminal priming, judgment bias, decision-making | AB10: estimates for numeric judgments are assimilated toward anchor values, even when these anchors are presented subliminally and outside of conscious awareness | AC10: Participants who were presented with the high anchor value estimated the car price to be higher (M = 21,219 Euro) than those presented with the low anchor value (M = 17,150 Euro), t(39) = 2.02, p < .05, r = .31. | AD10: 137 | AE10: 41 | AF10: 0.31 | AG10: r | AH10: p. 137 | AI10: 0.05 | AJ10: l (<) | AK10: NA (not reported) | AL10: no | AN10: 165 | AO10: -0.148 | AP10: d | AQ10: p. 3 | AR10: 0.83 | AS10: e (=) | AT10: 1 (one) | AU10: no | AV10: https://pdf.sciencedirectassets.com/272387/1-s2.0-S0022103120X00060/1-s2.0-S0022103120304066/main.pdf?X-Amz-Security-Token=IQoJb3JpZ2luX2VjEBgaCXVzLWVhc3QtMSJGMEQCICnHJqcNsP62IhJ5t%2BlQbccPwseA76qFfK6Rgkom8dtRAiB1LS%2BiM%2B0b%2BvwiyOom715iyNnHeXVQbXmSm95pdglacyq8BQjR%2F%2F%2F%2F%2F%2F%2F%2F%2F%2F8BEAUaDDA1OTAwMzU0Njg2NSIMmoze3y0Q1yERk%2B0lKpAF0gYTSXrqATr%2FlouJQrzfzrF%2B%2BHvghuPve%2FIY6N1xxaQBobJn18bDe0NKhRM4T2mvBEFjCOaVSqmUoM3%2F%2BmGL%2BTAQq6mB%2F5aQpDiqXVVnBGSq5%2F03UsrB78W9ZYcX3HuqmMRCwLpHPAIgIHd9zQtRRFGwk6RR%2ByNdrZ7EqjeWgcIKuyAr9%2Bj0JJ74pqGzqA1bFSaiBMqqZjviAxsq%2FjIO4yKprM2jCQw%2B%2FbZMITGLBdecPGFvQADAleUhJZgsYDQbMSkktZJ6E%2FJW5MtMzDJ3LrlhsdSqiHd28N4%2FJtYL8gNCs%2F9wK3a1s%2BQvM838pcLinkI8unVh1Gcvfxjbq6fYI6x4hCc7UZUEXs%2BEd%2Bo1x9GFvp3tcM%2BwJYlAa%2BEE%2FZcco8Dj58jnqzyOal0dDMeeWOjHL3y8xqwOE69icvonadJhHFVwONEoA1aox7vcITDF0spX53bm8Off4OeJ4bHC6QFHjIgBmUnwwVhqwcTI1CofN%2BPxww0zY3oNg4NrIO%2B5IVffRucPE9pztEeVHOdsmVPWyRlEFrjQ3aVJiYpL6TVfW3VfFLrAFifjveRxLAGB28CYsVXmTUz0Qxq6JRu7SlmaRNP2YnG7ipXXbiuZbwrorkm%2BxDc3uzBAI3Z82HTq1%2FmzxXw3SDN8%2FgQpgwWMXmWr%2F%2BckEKS7a7j2988ql%2B%2Fy%2BqfrHVJ5rVoDXKUgDUP6rR3X1ejf1UZwyc8ja5HXFbPfOefIT%2FsnbjIx3Ff255FID0Z6RGepP7orcagCAcWl7CBXLkbWM%2BaP6Oi1ITpYGOPrwvSeRMyKPH2NmAiiWZE5l0m%2FTJGJ0tND%2FrcK%2BOlvjkyuEOx33q4BZeSRwvKBTPBeeTtjgd9K%2BGRMok%2Fe5xEw28zvugY6sgH0sfyibldLqTratcbSkw7B9kA7YzvSU7Iyhc8zjvj18adk0B6r39A2zAda5VndB8QXUitJ8361WDPVPzGMTek%2Fl5bziH%2FtLRb2uo30VQ5T74JJWTp8l6Rs7L5pQAvE%2FQTclPBuc%2BZrz7CkEfVLz%2FJt0xicBVpzawZjnQzXuFBfBBbMr%2FWdBHYYpRqC6jMqh3zJIYsu9ZeQkzwiXFbF14t%2BITCuLmhK4klb9H3%2BQ4iKcUaK&X-Amz-Algorithm=AWS4-HMAC-SHA256&X-Amz-Date=20241213T084150Z&X-Amz-SignedHeaders=host&X-Amz-Expires=300&X-Amz-Credential=ASIAQ3PHCVTYUWRHKPES%2F20241213%2Fus-east-1%2Fs3%2Faws4_request&X-Amz-Signature=33924dc8199c3da89949ad504da4000be209df455000e1a7e4fee4140f60b1b1&hash=6979ab83d6e022fd52840830bb00b033291cf8235f9e721ac49f027cf55e995c&host=68042c943591013ac2b2430a89b270f6af2c76d8dfd086a07176afe7c76c2c61&pii=S0022103120304066&tid=spdf-0273d28f-03b4-4283-8694-d21fc2577d91&sid=18412b78662c794bb67b6200a74126f2bac9gxrqb&type=client&tsoh=d3d3LnNjaWVuY2VkaXJlY3QuY29t&ua=010859005455035b5a&rr=8f14a84b18840c73&cc=bg#link_ir0025 | AW10: 2 - close | AX10: - Please type "NA" if you could not find "regis" in the manuscript. - Good catch with the N = 41! - This is the preregistration: https://osf.io/8urxv It is linked at the top of the entry | AY10: LR
A11: validated - chosen | B11: double | C11: Hakile | E11: acykd_1 | F11: acykd | G11: Hakile Resulbegoviq | H11: 45641 | I11: 45663 | J11: informative failure to replicate | K11: updated reference_r to report instead of the OSF page | L11: Mussweiler, T., & Englich, B. (2005). Subliminal anchoring: Judgmental consequences and underlying mechanisms. Organizational Behavior and Human Decision Processes, 98(2), 133-143. | M11: 10.1016/j.obhdp.2004.12.002 | N11: 2 | O11: =hyperlink(vlookup(lower(M11),'File Links'!A:B, 2, FALSE), SUBSTITUTE(lower(M11), "/", "--") & ".pdf") -> 10.1016--j.obhdp.2004.12.002.pdf | P11: {=HYPERLINK(INDEX('File Links'!B:B, MATCH(O11, 'File Links'!C:C, 0)))} -> https://drive.google.com/file/d/1CZ8RmInPe2eqHwf-p8tl0IQxpn8_H_C5/view?usp=drivesdk | Q11: Röseler, L., Schütz, A., Blank, P. A., Dück, M., Fels, S., Kupfer, J., ... & Seida, C. (2021). Evidence against subliminal anchoring: Two close, highly powered, preregistered, and failed replication attempts. Journal of Experimental Social Psychology, 92, 104066. https://doi.org/10.1016/j.jesp.2020.104066 | R11: 10.1016/j.jesp.2020.104066 | T11: 1 | U11: 10.17605--osf.io--acykd.pdf | V11: Replication | W11: {=HYPERLINK(INDEX('File Links'!B:B, MATCH(U11, 'File Links'!C:C, 0)))} -> #N/A | Y11: Social Psychology | Z11: Subliminal anchoring | AA11: Anchoring; Heuristics; Comparison; Selective accessibility; Assimilation | AB11: Subliminally presented numerical anchors influence judgment, causing estimates to shift toward the anchor values without participants being consciously aware of the anchors. | AC11: Participants who were presented with the high anchor value estimated the car price to be higher (M = 21,219 Euro) than those presented with the low anchor value (M = 17,150 Euro), t(39) = 2.02, p < .05, r = .31. | AD11: 137 | AE11: 41 | AF11: 0.31 | AG11: r | AH11: p. 137 | AI11: 0.05 | AJ11: l (<) | AK11: NA (not reported) | AL11: no | AM11: NA | AN11: 165 | AO11: -0.148 | AP11: d | AQ11: p. 3 | AR11: 0.83 | AS11: e (=) | AT11: 1 (one) | AU11: no | AV11: https://osf.io/8urxv | AW11: 2 - close | AX11: Feedback for Hakile: - The degreees of freedom for the t test are 39, indicating that N = 41 - the number of tails was actually not reported (it does not say anywhere whether it is one-tailed or two-tailed but was coded as 2) - I could not find the d = 0.71 on p. 137 or anywhere in the manuscript. - Please type "NA" if you could not find "regis" in the manuscript. - Please rather use text for the claim that includes statistical elements, such as the effect on p. 137 under "results and discussion" - This is the preregistration: https://osf.io/8urxv It is linked at the top of the entry. You linked the "post completion" registration. | AY11: LR
A12: validated - chosen | B12: double | C12: Sarah | E12: additional_studies1_1 | F12: additional_studies1_a | G12: SAJ | H12: 45427 | I12: 45624 | L12: Rellensmann, J., & Schukajlow, S. (2017). Does students’ interest in a mathematical problem depend on the problem’s connection to reality? An analysis of students’ interest and pre-service teachers’ judgments of students’ interest in problems with and without a connection to reality. ZDM, 49, 367-378. https://doi.org/10.1007/s11858-016-0819-3 | M12: 10.1007/s11858-016-0819-3 | N12: 1 | O12: =hyperlink(vlookup(lower(M12),'File Links'!A:B, 2, FALSE), SUBSTITUTE(lower(M12), "/", "--") & ".pdf") -> 10.1007--s11858-016-0819-3.pdf | P12: {=HYPERLINK(INDEX('File Links'!B:B, MATCH(O12, 'File Links'!C:C, 0)))} -> https://drive.google.com/file/d/1A3A0XWewbvFp536VbiCjIAYxdIJwVP-9/view?usp=drivesdk | Q12: García-Cerdá, C., Segura, C., & Ferrando, I. (2024). Influence of the Type of Mathematical Problems on Students’ and Pre-service Teachers’ Interest and Performance. A Replication and Elaboration Study. Implementation and Replication Studies in Mathematics Education, 1(aop), 1-35. https://doi.org/10.1163/26670127-bja10017 | R12: 10.1163/26670127-bja10017 | T12: 1 | U12: =hyperlink(vlookup(lower(R12),'File Links'!E:F, 2, FALSE), SUBSTITUTE(lower(R12), "/", "--") & ".pdf") -> 10.1163--26670127-bja10017.pdf | V12: Title - "A replication and elaboration study" Abstract - "... the process of conceptual replication of Rellensmann and Schukajlow’s (2017) research..." | W12: {=HYPERLINK(INDEX('File Links'!B:B, MATCH(U12, 'File Links'!C:C, 0)))} -> #N/A | Y12: Education | Z12: interest in mathematics | AA12: mathematics, interest, students, pre-service teachers, diagnostic competence, real-world problems, performance, problem-solving | AB12: Influence of the Type of Mathematical Problems on Students’ Interest | AC12: A t-test for dependent samples indicated that the difference in students’ interest in the two problem types was statistically significant [t(99) = −2.96, p < 0.01]. | AD12: 7 | AE12: 100 | AF12: 0.3 | AG12: d | AH12: p. 7 | AI12: p < 0.01 | AJ12: l (<) | AK12: NA (not reported) | AL12: yes | AM12: NA | AN12: 80 | AO12: 𝜒2(2) = 9.99 | AP12: test statistic | AQ12: preprint p. 22 Kendells W = X2/N(K-1), X2 = 9.99, N = 80, K = 3 W = 9.99/ (80*(3-1)), W = 9.99/ (160), W ~ 0.06 | AR12: 0.01 | AS12: l (<) | AT12: NA (not reported) | AU12: no | AV12: NA | AW12: 2 - close | AY12: LR
A13: validated - discarded | B13: double | C13: Alexsandr | E13: additional_studies1_1 | F13: additional_studies1_a | G13: Aleksandr Pravednikov | H13: 45427 | I13: 45625 | J13: Claim text_r We observe that, in terms of means, there are no great differences in interest according to the type of problem. For students intramathematical problems were the most interesting (Mi = 2.77, SDi = 1.25), followed by word problems (Mw = 2.75, SDw = 1.18), and finally by modelling problems (Mm = 2.66, SDm = 1.26). - Table 1. To analyse whether the differences are significant, a hypothesis test was performed. Given that the means of interest did not follow, according to the results of the Shapiro-Wilk test, a normal distribution in any of the three types of problems, we applied Friedman’s non-parametric test. Thus, we obtained that there were differences between at least two types of problems (𝜒𝜒2(2)=9.99, p < 0.01). A post hoc analysis, using the Nemenyi test, ensured that there were significant differences in task-specific interest between word and modelling problems (p < 0.05), but not between the other combinations. [...] Page 21-22 | L13: Rellensmann, J., & Schukajlow, S. (2017). Does students’ interest in a mathematical problem depend on the problem’s connection to reality? An analysis of students’ interest and pre-service teachers’ judgments of students’ interest in problems with and without a connection to reality. ZDM, 49, 367-378. https://doi.org/10.1007/s11858-016-0819-3 | M13: 10.1007/s11858-016-0819-3 | O13: =hyperlink(vlookup(lower(M13),'File Links'!A:B, 2, FALSE), SUBSTITUTE(lower(M13), "/", "--") & ".pdf") -> 10.1007--s11858-016-0819-3.pdf | P13: {=HYPERLINK(INDEX('File Links'!B:B, MATCH(O13, 'File Links'!C:C, 0)))} -> https://drive.google.com/file/d/1A3A0XWewbvFp536VbiCjIAYxdIJwVP-9/view?usp=drivesdk | Q13: García-Cerdá, C., Segura, C., & Ferrando, I. (2024). Influence of the Type of Mathematical Problems on Students’ and Pre-service Teachers’ Interest and Performance. A Replication and Elaboration Study. Implementation and Replication Studies in Mathematics Education, 1(aop), 1-35. https://doi.org/10.1163/26670127-bja10017 | R13: 10.1163/26670127-bja10017 | U13: =hyperlink(vlookup(lower(R13),'File Links'!E:F, 2, FALSE), SUBSTITUTE(lower(R13), "/", "--") & ".pdf") -> 10.1163--26670127-bja10017.pdf | W13: {=HYPERLINK(INDEX('File Links'!B:B, MATCH(U13, 'File Links'!C:C, 0)))} -> #N/A | Y13: Educational Sciences | AA13: Students | AB13: Influence of the Type of Mathematical Problems on Students’ and Pre-service Teachers’ Interest and Performance | AC13: Students reported a mean level of interest of Madj = 2.71 (SDadj = 0.90) in solving problems with a connection to reality and Madj = 2.91 (SDadj = 1.00) in solving problems without a connection to reality when the impact of task difficulty was controlled for (Table 2). Means and standard errors for students’ interest are graphically displayed in Fig. 4. A t-test for dependent samples indicated that the difference in students’ interest in the two problem types was statistically significant [t(99) = −2.96, p < 0.01]. Cohen’s d = 0.30 indicated a small effect. This means that, contrary to our expectations, students reported more interest in solving problems without a connection to reality thann in problems with a connection to reality. | AD13: 7(373) | AE13: 100 | AF13: 0.3 | AG13: d | AI13: < 0.01 | AJ13: l (<) | AK13: NA (not reported) | AN13: 80 | AR13: p < 0.05 | AS13: l (<) | AT13: NA (not reported) | AW13: 2 - close | AY13: LR
A14: validated - chosen | B14: double | C14: Sarah | E14: additional_studies1_1 | F14: additional_studies1_b | G14: SAJ | H14: 45427 | I14: 45624 | J14: this effect was not explored in the original paper | L14: Rellensmann, J., & Schukajlow, S. (2017). Does students’ interest in a mathematical problem depend on the problem’s connection to reality? An analysis of students’ interest and pre-service teachers’ judgments of students’ interest in problems with and without a connection to reality. ZDM, 49, 367-378. https://doi.org/10.1007/s11858-016-0819-3 | M14: 10.1007/s11858-016-0819-3 | N14: 1 | O14: =hyperlink(vlookup(lower(M14),'File Links'!A:B, 2, FALSE), SUBSTITUTE(lower(M14), "/", "--") & ".pdf") -> 10.1007--s11858-016-0819-3.pdf | P14: {=HYPERLINK(INDEX('File Links'!B:B, MATCH(O14, 'File Links'!C:C, 0)))} -> https://drive.google.com/file/d/1A3A0XWewbvFp536VbiCjIAYxdIJwVP-9/view?usp=drivesdk | Q14: García-Cerdá, C., Segura, C., & Ferrando, I. (2024). Influence of the Type of Mathematical Problems on Students’ and Pre-service Teachers’ Interest and Performance. A Replication and Elaboration Study. Implementation and Replication Studies in Mathematics Education, 1(aop), 1-35. https://doi.org/10.1163/26670127-bja10017 | R14: 10.1163/26670127-bja10017 | T14: 1 | U14: =hyperlink(vlookup(lower(R14),'File Links'!E:F, 2, FALSE), SUBSTITUTE(lower(R14), "/", "--") & ".pdf") -> 10.1163--26670127-bja10017.pdf | V14: Title - "A replication and elaboration study" Abstract - "... the process of conceptual replication of Rellensmann and Schukajlow’s (2017) research..." | W14: {=HYPERLINK(INDEX('File Links'!B:B, MATCH(U14, 'File Links'!C:C, 0)))} -> #N/A | Y14: Education | Z14: interest in mathematics | AA14: mathematics, interest, students, pre-service teachers, diagnostic competence, real-world problems, performance, problem-solving | AB14: Influence of the Type of Mathematical Problems on Pre-service Teachers’ Interest | AC14: A t-test for dependent samples showed a significant difference in pre-service teachers’ judgments of students’ interest in solving the two types of problems [t(162) = 14.33, p < 0.01]. Cohen’s d = 1.12 | AD14: 7 | AE14: 163 | AF14: 1.12 | AG14: d | AH14: p. 7 | AI14: < 0.01 | AJ14: l (<) | AK14: NA (not reported) | AL14: yes | AM14: NA | AN14: 80 | AO14: 𝜒2(2) = 16.54 | AP14: test statistic | AQ14: Kendells W = X2/N(K-1), X2 = 16.54, N = 80, K = 3 W = 16.54/ (80*(3-1)), W = 16.54/ (160), W ~ 0.1 | AR14: 0.01 | AS14: l (<) | AT14: NA (not reported) | AU14: no | AV14: NA | AW14: 2 - close | AY14: LR
A15: validated - discarded | B15: double | C15: Alexsandr | E15: additional_studies1_1 | F15: additional_studies1_b | G15: Aleksandr Pravednikov | H15: 45427 | I15: 45625 | J15: Claim text_r Table 2 shows the average situational interest of 80 pre-service teachers according to the connection to the reality of the problems. We observe that, for pre-service teachers, word problems were the most interesting (Mw = 3.28, SDw = 1.22), followed by modelling problems (Mm = 3.11, SDm = 1.25) and, finally, intramathematical problems (Mi = 2.92, SDi = 1.24). Again, we conducted a hypothesis test to analyse whether there were significant differences in interest according to the connection with the reality of the problems. The means of interest did not follow a normal distribution either, so we obtained that there are significant differences between at least two types of problems (𝜒𝜒2(2)=16.54, p < 0.01) by applying Friedman’s test. Nemenyi’s test ensured that there were significant differences in task-specific interest between word and modelling problems (p < 0.05), and between intramathematical and word problems (p < 0.01). There were no significant differences between intramathematical and modelling problems (p = 0.46), indicating that word problems were significantly more interesting for pre-service teachers. [...] Page 22-23 | L15: Rellensmann, J., & Schukajlow, S. (2017). Does students’ interest in a mathematical problem depend on the problem’s connection to reality? An analysis of students’ interest and pre-service teachers’ judgments of students’ interest in problems with and without a connection to reality. ZDM, 49, 367-378. https://doi.org/10.1007/s11858-016-0819-3 | M15: 10.1007/s11858-016-0819-3 | O15: =hyperlink(vlookup(lower(M15),'File Links'!A:B, 2, FALSE), SUBSTITUTE(lower(M15), "/", "--") & ".pdf") -> 10.1007--s11858-016-0819-3.pdf | P15: {=HYPERLINK(INDEX('File Links'!B:B, MATCH(O15, 'File Links'!C:C, 0)))} -> https://drive.google.com/file/d/1A3A0XWewbvFp536VbiCjIAYxdIJwVP-9/view?usp=drivesdk | Q15: García-Cerdá, C., Segura, C., & Ferrando, I. (2024). Influence of the Type of Mathematical Problems on Students’ and Pre-service Teachers’ Interest and Performance. A Replication and Elaboration Study. Implementation and Replication Studies in Mathematics Education, 1(aop), 1-35. https://doi.org/10.1163/26670127-bja10017 | R15: 10.1163/26670127-bja10017 | U15: =hyperlink(vlookup(lower(R15),'File Links'!E:F, 2, FALSE), SUBSTITUTE(lower(R15), "/", "--") & ".pdf") -> 10.1163--26670127-bja10017.pdf | W15: {=HYPERLINK(INDEX('File Links'!B:B, MATCH(U15, 'File Links'!C:C, 0)))} -> #N/A | Y15: Educational Sciences | AA15: Pre-service teachers | AB15: Influence of the Type of Mathematical Problems on Students’ and Pre-service Teachers’ Interest and Performance | AC15: Pre-service teachers predicted a mean of Madj = 3.18 (SDadj = 0.48) for students’ interest in problems with a connection to reality and Madj = 2.47 (SDadj = 0.60) for their interest in problems without a connection to reality (Table 2). Means and standard errors for pre-service teachers’ judgments are also graphically displayed in Fig. 4. A t-test for dependent samples showed a significant difference in pre-service teachers’ judgments of students’ interest in solving the two types of problems [t(162) = 14.33, p < 0.01]. Cohen’s d = 1.12 indicated a large effect. As hypothesized, this means that pre-service teachers believed that solving problems with a connection to reality triggered more interest in students than solving problems without a connection to reality. | AD15: 7(373) | AE15: 163 | AF15: 1.12 | AG15: d | AI15: < 0.01 | AJ15: l (<) | AK15: NA (not reported) | AN15: 80 | AR15: p < 0.01 | AS15: l (<) | AT15: NA (not reported) | AW15: 2 - close | AY15: LR
A16: validated - discarded | B16: double | C16: Sarah | E16: additional_studies1_1 | F16: additional_studies1_c | G16: SAJ | H16: 45427 | I16: 45624 | J16: this effect was not explored in the original paper | K16: discarded because this is an extension that cannot be paired up with an original finding | L16: Rellensmann, J., & Schukajlow, S. (2017). Does students’ interest in a mathematical problem depend on the problem’s connection to reality? An analysis of students’ interest and pre-service teachers’ judgments of students’ interest in problems with and without a connection to reality. ZDM, 49, 367-378. https://doi.org/10.1007/s11858-016-0819-3 | M16: 10.1007/s11858-016-0819-3 | N16: 1 | O16: =hyperlink(vlookup(lower(M16),'File Links'!A:B, 2, FALSE), SUBSTITUTE(lower(M16), "/", "--") & ".pdf") -> 10.1007--s11858-016-0819-3.pdf | P16: {=HYPERLINK(INDEX('File Links'!B:B, MATCH(O16, 'File Links'!C:C, 0)))} -> https://drive.google.com/file/d/1A3A0XWewbvFp536VbiCjIAYxdIJwVP-9/view?usp=drivesdk | Q16: García-Cerdá, C., Segura, C., & Ferrando, I. (2024). Influence of the Type of Mathematical Problems on Students’ and Pre-service Teachers’ Interest and Performance. A Replication and Elaboration Study. Implementation and Replication Studies in Mathematics Education, 1(aop), 1-35. https://doi.org/10.1163/26670127-bja10017 | R16: 10.1163/26670127-bja10017 | T16: 1 | U16: =hyperlink(vlookup(lower(R16),'File Links'!E:F, 2, FALSE), SUBSTITUTE(lower(R16), "/", "--") & ".pdf") -> 10.1163--26670127-bja10017.pdf | V16: Title - "A replication and elaboration study" Abstract - "... the process of conceptual replication of Rellensmann and Schukajlow’s (2017) research..." | W16: {=HYPERLINK(INDEX('File Links'!B:B, MATCH(U16, 'File Links'!C:C, 0)))} -> #N/A | Y16: Education | Z16: interest in mathematics | AA16: mathematics, interest, students, pre-service teachers, diagnostic competence, real-world problems, performance, problem-solving | AB16: Influence of the Type of Mathematical Problems on Student Performance | AN16: 80 | AO16: 0.27 | AP16: W | AQ16: Kendells W = X2/N(K-1), X2 = 43.61, N = 80, K = 3 W = 43.61/ (80*(3-1)), W = 43.61/ (160), W ~ 0.27 | AR16: p < 0.01 | AS16: l (<) | AT16: NA (not reported) | AW16: extension | AY16: LR
A17: validated - discarded | B17: double | C17: Sarah | E17: additional_studies1_1 | F17: additional_studies1_d | G17: SAJ | H17: 45427 | I17: 45624 | J17: this effect was not explored in the original paper | K17: discarded because this is an extension that cannot be paired up with an original finding | L17: Rellensmann, J., & Schukajlow, S. (2017). Does students’ interest in a mathematical problem depend on the problem’s connection to reality? An analysis of students’ interest and pre-service teachers’ judgments of students’ interest in problems with and without a connection to reality. ZDM, 49, 367-378. https://doi.org/10.1007/s11858-016-0819-3 | M17: 10.1007/s11858-016-0819-3 | N17: 1 | O17: =hyperlink(vlookup(lower(M17),'File Links'!A:B, 2, FALSE), SUBSTITUTE(lower(M17), "/", "--") & ".pdf") -> 10.1007--s11858-016-0819-3.pdf | P17: {=HYPERLINK(INDEX('File Links'!B:B, MATCH(O17, 'File Links'!C:C, 0)))} -> https://drive.google.com/file/d/1A3A0XWewbvFp536VbiCjIAYxdIJwVP-9/view?usp=drivesdk | Q17: García-Cerdá, C., Segura, C., & Ferrando, I. (2024). Influence of the Type of Mathematical Problems on Students’ and Pre-service Teachers’ Interest and Performance. A Replication and Elaboration Study. Implementation and Replication Studies in Mathematics Education, 1(aop), 1-35. https://doi.org/10.1163/26670127-bja10017 | R17: 10.1163/26670127-bja10017 | T17: 1 | U17: =hyperlink(vlookup(lower(R17),'File Links'!E:F, 2, FALSE), SUBSTITUTE(lower(R17), "/", "--") & ".pdf") -> 10.1163--26670127-bja10017.pdf | V17: Title - "A replication and elaboration study" Abstract - "... the process of conceptual replication of Rellensmann and Schukajlow’s (2017) research..." | W17: {=HYPERLINK(INDEX('File Links'!B:B, MATCH(U17, 'File Links'!C:C, 0)))} -> #N/A | Y17: Education | Z17: interest in mathematics | AA17: mathematics, interest, students, pre-service teachers, diagnostic competence, real-world problems, performance, problem-solving | AB17: Influence of the Type of Mathematical Problems on Pre-service Teacher Performance | AN17: 80 | AO17: 0.68 | AP17: W | AQ17: Kendells W = X2/N(K-1), X2 = 108.75, N = 80, K = 3 W = 108.75/ (80*(3-1)), W = 108.75/ (160), W ~ 0.68 | AR17: p < 0.01 | AS17: l (<) | AT17: NA (not reported) | AW17: extension | AY17: LR
A18: validated - discarded | B18: double | C18: Sarah | E18: additional_studies1_1 | F18: additional_studies1_e | G18: SAJ | H18: 45427 | I18: 45624 | J18: this effect was not explored in the original paper | K18: discarded because this is an extension that cannot be paired up with an original finding | L18: Rellensmann, J., & Schukajlow, S. (2017). Does students’ interest in a mathematical problem depend on the problem’s connection to reality? An analysis of students’ interest and pre-service teachers’ judgments of students’ interest in problems with and without a connection to reality. ZDM, 49, 367-378. https://doi.org/10.1007/s11858-016-0819-3 | M18: 10.1007/s11858-016-0819-3 | N18: 1 | O18: =hyperlink(vlookup(lower(M18),'File Links'!A:B, 2, FALSE), SUBSTITUTE(lower(M18), "/", "--") & ".pdf") -> 10.1007--s11858-016-0819-3.pdf | P18: {=HYPERLINK(INDEX('File Links'!B:B, MATCH(O18, 'File Links'!C:C, 0)))} -> https://drive.google.com/file/d/1A3A0XWewbvFp536VbiCjIAYxdIJwVP-9/view?usp=drivesdk | Q18: García-Cerdá, C., Segura, C., & Ferrando, I. (2024). Influence of the Type of Mathematical Problems on Students’ and Pre-service Teachers’ Interest and Performance. A Replication and Elaboration Study. Implementation and Replication Studies in Mathematics Education, 1(aop), 1-35. https://doi.org/10.1163/26670127-bja10017 | R18: 10.1163/26670127-bja10017 | T18: 1 | U18: =hyperlink(vlookup(lower(R18),'File Links'!E:F, 2, FALSE), SUBSTITUTE(lower(R18), "/", "--") & ".pdf") -> 10.1163--26670127-bja10017.pdf | V18: Title - "A replication and elaboration study" Abstract - "... the process of conceptual replication of Rellensmann and Schukajlow’s (2017) research..." | W18: {=HYPERLINK(INDEX('File Links'!B:B, MATCH(U18, 'File Links'!C:C, 0)))} -> #N/A | Y18: Education | Z18: interest in mathematics | AA18: mathematics, interest, students, pre-service teachers, diagnostic competence, real-world problems, performance, problem-solving | AB18: Influence of the Type of Mathematical Problems on Student Interest*Performance relationship | AN18: 80 | AO18: intramathematical problem r = 0.25, word problem r = 0.29, modelling problem r = 0.31 | AP18: r | AR18: intramathematical problem p < 0.05, word problem p < 0.01, modelling problem p < 0.01 | AS18: l (<) | AT18: NA (not reported) | AW18: extension | AY18: LR
A19: validated - discarded | B19: double | C19: Sarah | E19: additional_studies1_1 | F19: additional_studies1_f | G19: SAJ | H19: 45427 | I19: 45624 | J19: this effect was not explored in the original paper | K19: discarded because this is an extension that cannot be paired up with an original finding | L19: Rellensmann, J., & Schukajlow, S. (2017). Does students’ interest in a mathematical problem depend on the problem’s connection to reality? An analysis of students’ interest and pre-service teachers’ judgments of students’ interest in problems with and without a connection to reality. ZDM, 49, 367-378. https://doi.org/10.1007/s11858-016-0819-3 | M19: 10.1007/s11858-016-0819-3 | N19: 1 | O19: =hyperlink(vlookup(lower(M19),'File Links'!A:B, 2, FALSE), SUBSTITUTE(lower(M19), "/", "--") & ".pdf") -> 10.1007--s11858-016-0819-3.pdf | P19: {=HYPERLINK(INDEX('File Links'!B:B, MATCH(O19, 'File Links'!C:C, 0)))} -> https://drive.google.com/file/d/1A3A0XWewbvFp536VbiCjIAYxdIJwVP-9/view?usp=drivesdk | Q19: García-Cerdá, C., Segura, C., & Ferrando, I. (2024). Influence of the Type of Mathematical Problems on Students’ and Pre-service Teachers’ Interest and Performance. A Replication and Elaboration Study. Implementation and Replication Studies in Mathematics Education, 1(aop), 1-35. https://doi.org/10.1163/26670127-bja10017 | R19: 10.1163/26670127-bja10017 | T19: 1 | U19: =hyperlink(vlookup(lower(R19),'File Links'!E:F, 2, FALSE), SUBSTITUTE(lower(R19), "/", "--") & ".pdf") -> 10.1163--26670127-bja10017.pdf | V19: Title - "A replication and elaboration study" Abstract - "... the process of conceptual replication of Rellensmann and Schukajlow’s (2017) research..." | W19: {=HYPERLINK(INDEX('File Links'!B:B, MATCH(U19, 'File Links'!C:C, 0)))} -> #N/A | Y19: Education | Z19: interest in mathematics | AA19: mathematics, interest, students, pre-service teachers, diagnostic competence, real-world problems, performance, problem-solving | AB19: Influence of the Type of Mathematical Problems on Pre-service Teacher Interest*Performance relationship | AN19: 80 | AO19: intramathematical problem r = 0.48, word problem r = 0.28, modelling problem r = 0.35 | AP19: r | AR19: intramathematical problem p < 0.01, word problem p < 0.01, modelling problem p < 0.01 | AS19: l (<) | AT19: NA (not reported) | AW19: extension | AY19: LR
A20: assigned | B20: double | C20: Daniel | E20: additional_studies10 | F20: additional_studies10_d | G20: Daniel Manrique-Castano | I20: 45683 | J20: The coding of this study was extremely challenging for me and I could not complete it. I feel that the replication study is extremely unclear in describing what effects they are trying to replicate. Although the replication article provides the information for the original research article (DM&D column) in Tables 3 and 4 (p. 11), it is extremely difficult for me to track this information in the original research article. The replication does not specify which of the multiple comparisons they are referring to. In the lines I have filled in, I have been able to infer that the information refers only to the Spanish test. I spent several hours trying to decipher the information, but I am really frustrated because I would need much more time to read the article and the supplementary information to try to understand the issue. For this reason, I do not feel confident to complete the task. Sample size: The replication article reports a sample size of 19. This corresponds exclusively to the group of L2 Spanish speakers. However, my understanding is that the group of native Spanish speakers (n = 6) is also included in the comparisons. Again, it is extremely unclear which comparison the replication is trying to replicate. Therefore, I report 25 as the sample size in the lines I filled in. These entries, and the replication in general, need careful revision. | M20: 10.1111/lang.12161 | O20: =hyperlink(vlookup(lower(M20),'File Links'!A:B, 2, FALSE), SUBSTITUTE(lower(M20), "/", "--") & ".pdf") -> 10.1111--lang.12161.pdf | P20: {=HYPERLINK(INDEX('File Links'!B:B, MATCH(O20, 'File Links'!C:C, 0)))} -> https://drive.google.com/file/d/1W_KvsfbanYWBQG9nzoDuqDlzFW_jUYH2/view?usp=drivesdk | V20: A preregistered, close replication of Darcy et al. (2016) | W20: {=HYPERLINK(INDEX('File Links'!B:B, MATCH(U20, 'File Links'!C:C, 0)))} -> #N/A | Y20: Linguistics | Z20: Production accuracy - /e/ format | AA20: language processing, inhibitory control, second language, phonological processing | AB20: The study measured the production accuracy of /e/ format using a delayed sentence repetition task. | AN20: 58 | AO20: 3.31 | AP20: d | AQ20: 1.26 / 0.38 | AU20: yes | AV20: https://osf.io/w4gj2 | AW20: 2 - close
A21: assigned | B21: double | C21: Daniel | E21: additional_studies10 | F21: additional_studies10_e | G21: Daniel Manrique-Castano | I21: 45683 | J21: The coding of this study was extremely challenging for me and I could not complete it. I feel that the replication study is extremely unclear in describing what effects they are trying to replicate. Although the replication article provides the information for the original research article (DM&D column) in Tables 3 and 4 (p. 11), it is extremely difficult for me to track this information in the original research article. The replication does not specify which of the multiple comparisons they are referring to. In the lines I have filled in, I have been able to infer that the information refers only to the Spanish test. I spent several hours trying to decipher the information, but I am really frustrated because I would need much more time to read the article and the supplementary information to try to understand the issue. For this reason, I do not feel confident to complete the task. Sample size: The replication article reports a sample size of 19. This corresponds exclusively to the group of L2 Spanish speakers. However, my understanding is that the group of native Spanish speakers (n = 6) is also included in the comparisons. Again, it is extremely unclear which comparison the replication is trying to replicate. Therefore, I report 25 as the sample size in the lines I filled in. These entries, and the replication in general, need careful revision. | M21: 10.1111/lang.12161 | O21: =hyperlink(vlookup(lower(M21),'File Links'!A:B, 2, FALSE), SUBSTITUTE(lower(M21), "/", "--") & ".pdf") -> 10.1111--lang.12161.pdf | P21: {=HYPERLINK(INDEX('File Links'!B:B, MATCH(O21, 'File Links'!C:C, 0)))} -> https://drive.google.com/file/d/1W_KvsfbanYWBQG9nzoDuqDlzFW_jUYH2/view?usp=drivesdk | V21: A preregistered, close replication of Darcy et al. (2016) | W21: {=HYPERLINK(INDEX('File Links'!B:B, MATCH(U21, 'File Links'!C:C, 0)))} -> #N/A | Y21: Linguistics | Z21: Production accuracy - /ei̯/ ~ /e/ | AA21: language processing, inhibitory control, second language, phonological processing | AB21: The study measured the production accuracy of /ei/ ~ /e/ format using a delayed sentence repetition task. | AC21: Instead, they produced both vowels as a monophthongal /e/, with very little formant movement (1.18 for diphthongs vs. 0.92 for monophthongs, SD = 0.36), t(18) = 1.92, p = .071, r = .17, but distinguished them through duration. | AD21: p. 17 | AE21: 25 | AF21: 0.17 | AG21: r | AH21: t(18) = 1.92 | AI21: 0.71 | AJ21: e (=) | AK21: NA (not reported) | AL21: yes | AN21: 58 | AO21: 0.64 | AP21: d | AQ21: p. 11 | AR21: 0.001 | AS21: l (<) | AT21: NA (not reported) | AU21: yes | AV21: https://osf.io/w4gj2 | AW21: 2 - close
A22: assigned | B22: double | C22: Daniel | E22: additional_studies10 | F22: additional_studies10_f | G22: Daniel Manrique-Castano | I22: 45683 | J22: The coding of this study was extremely challenging for me and I could not complete it. I feel that the replication study is extremely unclear in describing what effects they are trying to replicate. Although the replication article provides the information for the original research article (DM&D column) in Tables 3 and 4 (p. 11), it is extremely difficult for me to track this information in the original research article. The replication does not specify which of the multiple comparisons they are referring to. In the lines I have filled in, I have been able to infer that the information refers only to the Spanish test. I spent several hours trying to decipher the information, but I am really frustrated because I would need much more time to read the article and the supplementary information to try to understand the issue. For this reason, I do not feel confident to complete the task. Sample size: The replication article reports a sample size of 19. This corresponds exclusively to the group of L2 Spanish speakers. However, my understanding is that the group of native Spanish speakers (n = 6) is also included in the comparisons. Again, it is extremely unclear which comparison the replication is trying to replicate. Therefore, I report 25 as the sample size in the lines I filled in. These entries, and the replication in general, need careful revision. | M22: 10.1111/lang.12161 | O22: =hyperlink(vlookup(lower(M22),'File Links'!A:B, 2, FALSE), SUBSTITUTE(lower(M22), "/", "--") & ".pdf") -> 10.1111--lang.12161.pdf | P22: {=HYPERLINK(INDEX('File Links'!B:B, MATCH(O22, 'File Links'!C:C, 0)))} -> https://drive.google.com/file/d/1W_KvsfbanYWBQG9nzoDuqDlzFW_jUYH2/view?usp=drivesdk | V22: A preregistered, close replication of Darcy et al. (2016) | W22: {=HYPERLINK(INDEX('File Links'!B:B, MATCH(U22, 'File Links'!C:C, 0)))} -> #N/A | Y22: Linguistics | Z22: Production accuracy - /ei̯/ z score | AA22: language processing, inhibitory control, second language, phonological processing | AB22: The study measured the production accuracy of /ei/ ~ z score format using a delayed sentence repetition task. | AN22: 58 | AO22: -2.67 | AP22: d | AQ22: 2.27 / 0.85 | AV22: https://osf.io/w4gj2 | AW22: 2 - close
A23: assigned | B23: double | C23: Daniel | E23: additional_studies10 | F23: additional_studies10_g | G23: Daniel Manrique-Castano | I23: 45683 | J23: The coding of this study was extremely challenging for me and I could not complete it. I feel that the replication study is extremely unclear in describing what effects they are trying to replicate. Although the replication article provides the information for the original research article (DM&D column) in Tables 3 and 4 (p. 11), it is extremely difficult for me to track this information in the original research article. The replication does not specify which of the multiple comparisons they are referring to. In the lines I have filled in, I have been able to infer that the information refers only to the Spanish test. I spent several hours trying to decipher the information, but I am really frustrated because I would need much more time to read the article and the supplementary information to try to understand the issue. For this reason, I do not feel confident to complete the task. Sample size: The replication article reports a sample size of 19. This corresponds exclusively to the group of L2 Spanish speakers. However, my understanding is that the group of native Spanish speakers (n = 6) is also included in the comparisons. Again, it is extremely unclear which comparison the replication is trying to replicate. Therefore, I report 25 as the sample size in the lines I filled in. These entries, and the replication in general, need careful revision. | M23: 10.1111/lang.12161 | O23: =hyperlink(vlookup(lower(M23),'File Links'!A:B, 2, FALSE), SUBSTITUTE(lower(M23), "/", "--") & ".pdf") -> 10.1111--lang.12161.pdf | P23: {=HYPERLINK(INDEX('File Links'!B:B, MATCH(O23, 'File Links'!C:C, 0)))} -> https://drive.google.com/file/d/1W_KvsfbanYWBQG9nzoDuqDlzFW_jUYH2/view?usp=drivesdk | V23: A preregistered, close replication of Darcy et al. (2016) | W23: {=HYPERLINK(INDEX('File Links'!B:B, MATCH(U23, 'File Links'!C:C, 0)))} -> #N/A | Y23: Linguistics | Z23: Production accuracy - Consonant accuracy | AA23: language processing, inhibitory control, second language, phonological processing | AB23: The study measured the production accuracy for consonants using a delayed sentence repetition task. | AN23: 58 | AO23: 1.94 | AP23: d | AQ23: 4.50 / 2.31 | AV23: https://osf.io/w4gj2 | AW23: 2 - close
A24: validated - discarded | B24: double | C24: Alexsandr | E24: additional_studies10_1 | F24: additional_studies10_a | G24: Aleksandr Pravednikov | H24: 45625 | I24: 45692 | J24: Claim text_r. Table 8, p. 14 Retrieval–induced inhibition: 1.02 (0.23), [...] Results of the current replication for the partial correlation analyses did not indicate statistically significant relationships, and effect sizes were small with 95% CIs crossing through zero. p. 16 | L24: Darcy, I., Mora, J. C., & Daidone, D. (2016). The role of inhibitory control in second language phonological processing. Language Learning, 66, 741–773. https://doi.org/10.1111/lang.12161 | M24: 10.1111/lang.12161 | N24: 1 | O24: =hyperlink(vlookup(lower(M24),'File Links'!A:B, 2, FALSE), SUBSTITUTE(lower(M24), "/", "--") & ".pdf") -> 10.1111--lang.12161.pdf | P24: {=HYPERLINK(INDEX('File Links'!B:B, MATCH(O24, 'File Links'!C:C, 0)))} -> https://drive.google.com/file/d/1W_KvsfbanYWBQG9nzoDuqDlzFW_jUYH2/view?usp=drivesdk | Q24: Huensch, A. (2024). Clarifying the role of inhibitory control in L2 phonological processing: A preregistered, close replication of Darcy et al.(2016). Studies in Second Language Acquisition, 1-21. https://doi.org/10.1017/S0272263124000238 | R24: 10.1017/S0272263124000238 | T24: 1 | U24: =hyperlink(vlookup(lower(R24),'File Links'!E:F, 2, FALSE), SUBSTITUTE(lower(R24), "/", "--") & ".pdf") -> 10.1017--s0272263124000238.pdf | V24: close replication | W24: {=HYPERLINK(INDEX('File Links'!B:B, MATCH(U24, 'File Links'!C:C, 0)))} -> #N/A | Y24: Linguistics | Z24: Second Language Phonological Processing | AA24: language processing, inhibitory control, second language, phonological processing | AB24: Role of inhibitory control in L2 phonological processing (Retrieval–induced inhibition) | AC24: Table 7 summarizes the results of correlation analyses between inhibition scores and the four phonological accuracy scores (controlling for proficiency). These correlations show that error rate and z scores in ABX perception were significantly negatively correlated with inhibition scores, which indicates that individuals with higher inhibition scores also obtained lower error rates and lower (more targetlike)zscores in vowel perception. | AD24: 21 | AE24: 18 | AJ24: l (<) | AK24: NA (not reported) | AN24: 58 | AT24: NA (not reported) | AW24: close | AY24: LR
A25: validated - chosen | B25: double | C25: Alexsandr | E25: additional_studies10_1 | F25: additional_studies10_b | G25: Aleksandr Pravednikov | H25: 45625 | I25: 45692 | J25: Claim text_r. Table 8, p. 14 ABX error (vowels) 19.2 (13.2) [...] Results of the current replication for the partial correlation analyses did not indicate statistically significant relationships, and effect sizes were small with 95% CIs crossing through zero. p. 16 | K25: coded as nested due to hierarchical regression; a fourth effect is reported for the replication but NA for the original study; p_val_tails_r coded as one because it says in the note "as reported in DM&D", where p-values are one-tailed. Note that in the table two-tailed CIs are reported | L25: Darcy, I., Mora, J. C., & Daidone, D. (2016). The role of inhibitory control in second language phonological processing. Language Learning, 66, 741–773. https://doi.org/10.1111/lang.12161 | M25: 10.1111/lang.12161 | N25: 1 | O25: =hyperlink(vlookup(lower(M25),'File Links'!A:B, 2, FALSE), SUBSTITUTE(lower(M25), "/", "--") & ".pdf") -> 10.1111--lang.12161.pdf | P25: {=HYPERLINK(INDEX('File Links'!B:B, MATCH(O25, 'File Links'!C:C, 0)))} -> https://drive.google.com/file/d/1W_KvsfbanYWBQG9nzoDuqDlzFW_jUYH2/view?usp=drivesdk | Q25: Huensch, A. (2024). Clarifying the role of inhibitory control in L2 phonological processing: A preregistered, close replication of Darcy et al.(2016). Studies in Second Language Acquisition, 1-21. https://doi.org/10.1017/S0272263124000238 | R25: 10.1017/S0272263124000238 | T25: 1 | U25: =hyperlink(vlookup(lower(R25),'File Links'!E:F, 2, FALSE), SUBSTITUTE(lower(R25), "/", "--") & ".pdf") -> 10.1017--s0272263124000238.pdf | V25: close replication | W25: {=HYPERLINK(INDEX('File Links'!B:B, MATCH(U25, 'File Links'!C:C, 0)))} -> #N/A | Y25: Linguistics | Z25: Second Language Phonological Processing | AA25: language processing, inhibitory control, second language, phonological processing | AB25: Role of inhibitory control in L2 phonological processing (ABX error (vowels)) | AC25: Table 7 summarizes the results of correlation analyses between inhibition scores and the four phonological accuracy scores (controlling for proficiency). These correlations show that error rate and z scores in ABX perception were significantly negatively correlated with inhibition scores, which indicates that individuals with higher inhibition scores also obtained lower error rates and lower (more targetlike)zscores in vowel perception. | AD25: 33 | AE25: 18 | AF25: -0.42 | AG25: partial r | AH25: p. 23 | AI25: 0.01 | AJ25: l (<) | AK25: 1 (one) | AL25: yes | AM25: NA | AN25: 58 | AO25: -0.13 | AP25: partial r | AQ25: p. 15, Table 10 | AR25: 0.379 | AS25: e (=) | AT25: 1 (one) | AU25: yes | AV25: https://osf.io/w4gj2 | AW25: close | AY25: LR
A26: validated - chosen | B26: double | C26: Alexsandr | E26: additional_studies10_1 | F26: additional_studies10_c | G26: Aleksandr Pravednikov | H26: 45625 | I26: 45692 | J26: Claim text_r. Table 8, p. 14 Vowel production z score: –2.27 (0.85)[...] Results of the current replication for the partial correlation analyses did not indicate statistically significant relationships, and effect sizes were small with 95% CIs crossing through zero. p. 16 | K26: coded as nested due to hierarchical regression; a fourth effect is reported for the replication but NA for the original study; p_val_tails_r coded as one because it says in the note "as reported in DM&D", where p-values are one-tailed. Note that in the table two-tailed CIs are reported | L26: Darcy, I., Mora, J. C., & Daidone, D. (2016). The role of inhibitory control in second language phonological processing. Language Learning, 66, 741–773. https://doi.org/10.1111/lang.12161 | M26: 10.1111/lang.12161 | N26: 1 | O26: =hyperlink(vlookup(lower(M26),'File Links'!A:B, 2, FALSE), SUBSTITUTE(lower(M26), "/", "--") & ".pdf") -> 10.1111--lang.12161.pdf | P26: {=HYPERLINK(INDEX('File Links'!B:B, MATCH(O26, 'File Links'!C:C, 0)))} -> https://drive.google.com/file/d/1W_KvsfbanYWBQG9nzoDuqDlzFW_jUYH2/view?usp=drivesdk | Q26: Huensch, A. (2024). Clarifying the role of inhibitory control in L2 phonological processing: A preregistered, close replication of Darcy et al.(2016). Studies in Second Language Acquisition, 1-21. https://doi.org/10.1017/S0272263124000238 | R26: 10.1017/S0272263124000238 | T26: 1 | U26: =hyperlink(vlookup(lower(R26),'File Links'!E:F, 2, FALSE), SUBSTITUTE(lower(R26), "/", "--") & ".pdf") -> 10.1017--s0272263124000238.pdf | V26: close replication | W26: {=HYPERLINK(INDEX('File Links'!B:B, MATCH(U26, 'File Links'!C:C, 0)))} -> #N/A | Y26: Linguistics | Z26: Second Language Phonological Processing | AA26: language processing, inhibitory control, second language, phonological processing | AB26: Role of inhibitory control in L2 phonological processing (Vowel production z score) | AC26: Table 7 summarizes the results of correlation analyses between inhibition scores and the four phonological accuracy scores (controlling for proficiency). These correlations show that error rate and z scores in ABX perception were significantly negatively correlated with inhibition scores, which indicates that individuals with higher inhibition scores also obtained lower error rates and lower (more targetlike)zscores in vowel perception. | AD26: 33 | AE26: 18 | AF26: -0.04 | AG26: partial r | AH26: p. 23 | AI26: 0.05 | AJ26: g (>) | AK26: 1 (one) | AL26: yes | AM26: NA | AN26: 58 | AO26: 0.09 | AP26: partial r | AQ26: p. 15, Table 10 | AR26: 0.529 | AS26: e (=) | AT26: 1 (one) | AU26: yes | AV26: https://osf.io/w4gj2 | AW26: close | AY26: LR
A27: validated - chosen | B27: double | C27: Alexsandr | E27: additional_studies10_1 | F27: additional_studies10_d | G27: Aleksandr Pravednikov | H27: 45625 | I27: 45692 | J27: Claim text_r. Table 8, p. 14 Consonant production (max. 8): 4.50 (2.31) [...] Results of the current replication for the partial correlation analyses did not indicate statistically significant relationships, and effect sizes were small with 95% CIs crossing through zero. p. 16 | K27: coded as nested due to hierarchical regression; a fourth effect is reported for the replication but NA for the original study; p_val_tails_r coded as one because it says in the note "as reported in DM&D", where p-values are one-tailed. Note that in the table two-tailed CIs are reported | L27: Darcy, I., Mora, J. C., & Daidone, D. (2016). The role of inhibitory control in second language phonological processing. Language Learning, 66, 741–773. https://doi.org/10.1111/lang.12161 | M27: 10.1111/lang.12161 | N27: 1 | O27: =hyperlink(vlookup(lower(M27),'File Links'!A:B, 2, FALSE), SUBSTITUTE(lower(M27), "/", "--") & ".pdf") -> 10.1111--lang.12161.pdf | P27: {=HYPERLINK(INDEX('File Links'!B:B, MATCH(O27, 'File Links'!C:C, 0)))} -> https://drive.google.com/file/d/1W_KvsfbanYWBQG9nzoDuqDlzFW_jUYH2/view?usp=drivesdk | Q27: Huensch, A. (2024). Clarifying the role of inhibitory control in L2 phonological processing: A preregistered, close replication of Darcy et al.(2016). Studies in Second Language Acquisition, 1-21. https://doi.org/10.1017/S0272263124000238 | R27: 10.1017/S0272263124000238 | T27: 1 | U27: =hyperlink(vlookup(lower(R27),'File Links'!E:F, 2, FALSE), SUBSTITUTE(lower(R27), "/", "--") & ".pdf") -> 10.1017--s0272263124000238.pdf | V27: close replication | W27: {=HYPERLINK(INDEX('File Links'!B:B, MATCH(U27, 'File Links'!C:C, 0)))} -> #N/A | Y27: Linguistics | Z27: Second Language Phonological Processing | AA27: language processing, inhibitory control, second language, phonological processing | AB27: Role of inhibitory control in L2 phonological processing (Consonant production (max. 8)) | AC27: Table 7 summarizes the results of correlation analyses between inhibition scores and the four phonological accuracy scores (controlling for proficiency). These correlations show that error rate and z scores in ABX perception were significantly negatively correlated with inhibition scores, which indicates that individuals with higher inhibition scores also obtained lower error rates and lower (more targetlike)zscores in vowel perception. | AD27: 33 | AE27: 18 | AF27: 0.34 | AG27: partial r | AH27: p. 23 | AI27: 0.05 | AJ27: l (<) | AK27: 1 (one) | AL27: yes | AM27: NA | AN27: 58 | AO27: 0.07 | AP27: partial r | AQ27: p. 15, Table 10 | AR27: 0.61 | AS27: e (=) | AT27: 1 (one) | AU27: yes | AV27: https://osf.io/w4gj2 | AW27: close | AY27: LR
A28: validated - discarded | B28: double | C28: Daniel | E28: additional_studies10_1 | F28: additional_studies10 | G28: Daniel Manrique-Castano | H28: 45683 | I28: 45692 | J28: The coding of this study was extremely challenging for me and I could not complete it. I feel that the replication study is extremely unclear in describing what effects they are trying to replicate. Although the replication article provides the information for the original research article (DM&D column) in Tables 3 and 4 (p. 11), it is extremely difficult for me to track this information in the original research article. The replication does not specify which of the multiple comparisons they are referring to. In the lines I have filled in, I have been able to infer that the information refers only to the Spanish test. I spent several hours trying to decipher the information, but I am really frustrated because I would need much more time to read the article and the supplementary information to try to understand the issue. For this reason, I do not feel confident to complete the task. Sample size: The replication article reports a sample size of 19. This corresponds exclusively to the group of L2 Spanish speakers. However, my understanding is that the group of native Spanish speakers (n = 6) is also included in the comparisons. Again, it is extremely unclear which comparison the replication is trying to replicate. Therefore, I report 25 as the sample size in the lines I filled in. These entries, and the replication in general, need careful revision. | L28: Darcy, I., Mora, J. C., & Daidone, D. (2016). The role of inhibitory control in second language phonological processing. Language Learning, 66, 741–773. https://doi.org/10.1111/lang.12161 | M28: 10.1111/lang.12161 | N28: 1 | O28: 10.1111--lang.12161.pdf | P28: {=HYPERLINK(INDEX('File Links'!B:B, MATCH(O28, 'File Links'!C:C, 0)))} -> https://drive.google.com/file/d/1W_KvsfbanYWBQG9nzoDuqDlzFW_jUYH2/view?usp=drivesdk | Q28: Huensch, A. (2024). Clarifying the role of inhibitory control in L2 phonological processing: A preregistered, close replication of Darcy et al.(2016). Studies in Second Language Acquisition, 1-21. https://doi.org/10.1017/S0272263124000238 | R28: 10.1017/S0272263124000238 | T28: 1 | U28: =hyperlink(vlookup(lower(R28),'File Links'!E:F, 2, FALSE), SUBSTITUTE(lower(R28), "/", "--") & ".pdf") -> 10.1017--s0272263124000238.pdf | V28: close replication | W28: {=HYPERLINK(INDEX('File Links'!B:B, MATCH(U28, 'File Links'!C:C, 0)))} -> #N/A | Y28: Linguistics | Z28: Second Language Phonological Processing | AA28: language processing, inhibitory control, second language, phonological processing | AB28: The study measured the perceptual processing of Spanish vowels using the speeded ABX categorization task. | AC28: The test subconditions consE and vowelE did not differ from each other (Merr = 4.6%, CI = 1.0–8.2; and Merr = 3.6%, CI = 0–7.2, respectively), but they triggered significantly fewer errors than the nonnative consS and vowelS subconditions (Merr = 24.0%, CI = 20.4–27.6; and Merr = 19.1%, CI = 15.5–22.7, respectively). p. 13, 14 25 0.955 d 19.1 / 20 0.1 l (<) NA (not reported) yes 58 1.45 d 19.2 / 13.2 yes https://osf.io/w4gj2 2 - close additional_studies10_b Daniel Manrique-Castano 26/01/2025 The coding of this study was extremely challenging for me and I could not complete it. I feel that the replication study is extremely unclear in describing what effects they are trying to replicate. Although the replication article provides the information for the original research article (DM&D column) in Tables 3 and 4 (p. 11), it is extremely difficult for me to track this information in the original research article. The replication does not specify which of the multiple comparisons they are referring to. In the lines I have filled in, I have been able to infer that the information refers only to the Spanish test. I spent several hours trying to decipher the information, but I am really frustrated because I would need much more time to read the article and the supplementary information to try to understand the issue. For this reason, I do not feel confident to complete the task. Sample size: The replication article reports a sample size of 19. This corresponds exclusively to the group of L2 Spanish speakers. However, my understanding is that the group of native Spanish speakers (n = 6) is also included in the comparisons. Again, it is extremely unclear which comparison the replication is trying to replicate. Therefore, I report 25 as the sample size in the lines I filled in. These entries, and the replication in general, need careful revision. 10.1111/lang.12161 A preregistered, close replication of Darcy et al. (2016)" | AE28: Linguistics | AF28: Perceptual processing - Spanish Consonant | AG28: language processing, inhibitory control, second language, phonological processing | AH28: The study measured the perceptual processing of Spanish consonants using the speeded ABX categorization task. | AI28: The test subconditions consE and vowelE did not differ from each other (Merr = 4.6%, CI = 1.0–8.2; and Merr = 3.6%, CI = 0–7.2, respectively), but they triggered significantly fewer errors than the nonnative consS and vowelS subconditions (Merr = 24.0%, CI = 20.4–27.6; and Merr = 19.1%, CI = 15.5–22.7, respectively). p. 13, 14 25 1.04 d 24.0 / 23.0 0.1 l (<) NA (not reported) yes 58 1.2 d 16.8 / 14 yes https://osf.io/w4gj2 2 - close additional_studies10_c Daniel Manrique-Castano 26/01/2025 The coding of this study was extremely challenging for me and I could not complete it. I feel that the replication study is extremely unclear in describing what effects they are trying to replicate. Although the replication article provides the information for the original research article (DM&D column) in Tables 3 and 4 (p. 11), it is extremely difficult for me to track this information in the original research article. The replication does not specify which of the multiple comparisons they are referring to. In the lines I have filled in, I have been able to infer that the information refers only to the Spanish test. I spent several hours trying to decipher the information, but I am really frustrated because I would need much more time to read the article and the supplementary information to try to understand the issue. For this reason, I do not feel confident to complete the task. Sample size: The replication article reports a sample size of 19. This corresponds exclusively to the group of L2 Spanish speakers. However, my understanding is that the group of native Spanish speakers (n = 6) is also included in the comparisons. Again, it is extremely unclear which comparison the replication is trying to replicate. Therefore, I report 25 as the sample size in the lines I filled in. These entries, and the replication in general, need careful revision. 10.1111/lang.12161 A preregistered, close replication of Darcy et al. (2016)" | AK28: Linguistics | AL28: Production accuracy - /ei/ format | AM28: language processing, inhibitory control, second language, phonological processing | AN28: The study measured the production accuracy of /ei/ format using a delayed sentence repetition task. | AO28: The two groups differed in the amount of formant movement during vowel production. The L2 Spanish learners were found to produce the Spanish diphthong /ei/ with much less formant movement (M = 1.18, SD = 0.55) than native controls (M = 3.19, SD = 0.71), as shown in Figure 2, Mann-Whitney U = 113.0, z = 3.56, p < .001, r = .71.. | AP28: p. 17 | AQ28: 25 | AR28: 0.71 | AS28: r | AT28: p. 17 | AU28: 0.001 | AV28: l (<) | AW28: NA (not reported) | AX28: yes | AY28: LR
A29: validated - discarded | B29: double | C29: Fabienne | E29: additional_studies11_1 | F29: additional_studies11 | G29: Julia Fabienne Sandkühler | H29: 45637 | I29: 45692 | J29: replication N refers to number of couples | L29: Saxey, M. T., LeBaron-Black, A. B., & Curran, M. A. (2022). The Sooner, the Better? Couples' First Financial Discussion, Relationship Quality, and Financial Conflict in Emerging Adulthood. Journal of Financial Therapy, 13 (1) 2. https://doi.org/10.4148/1944-9771.1299 | M29: 10.4148/1944-9771.1299 | O29: 10.4148--1944-9771.1299.pdf | P29: {=HYPERLINK(INDEX('File Links'!B:B, MATCH(O29, 'File Links'!C:C, 0)))} -> https://drive.google.com/file/d/1OByNKNsjZqSFHFFyt-o1mPqDkVmgruBu/view?usp=drivesdk | Q29: Saxey, M. T., LeBaron‐Black, A. B., Inman, N. F., Yorgason, J. B., & Holmes, E. K. (2024). The earlier couples first discussed finances, the better? A dyadic, longitudinal replication and extension. Family Relations. https://doi.org/10.1111/fare.13030 | R29: 10.1111/fare.13030 | U29: .pdf | V29: dyadic, longitudinal replication and extension | W29: {=HYPERLINK(INDEX('File Links'!B:B, MATCH(U29, 'File Links'!C:C, 0)))} -> #N/A | Y29: Social Psychology | AA29: emerging adulthood; financial communication; financial conflict; financial discussion, relationship quality | AB29: Indirect effect present for relationship quality (replication: cross-sectional, wives' answers, effect on themselves) | AC29: Indirect effect present for relationship quality: “initiating financial discussion earlier in a romantic relationship may benefit relationship quality—through financial communication” (most emphasised claim in original) | AD29: 1 | AE29: 1950 | AF29: 0.13 | AG29: beta | AH29: p. 11 | AI29: 0.001 | AJ29: l (<) | AK29: NA (not reported) | AM29: NA | AN29: 1079 | AO29: 0.06 | AP29: beta (std) | AQ29: p. 2538 | AR29: 0.01 | AS29: l (<) | AT29: NA (not reported) | AV29: NA | AW29: 3 - conceptual | AY29: LR
A30: validated - discarded | B30: double | C30: Fabienne | E30: additional_studies11_1 | F30: additional_studies11_b | G30: Julia Fabienne Sandkühler | H30: 45637 | I30: 45692 | J30: replication N refers to number of couples | L30: Saxey, M. T., LeBaron-Black, A. B., & Curran, M. A. (2022). The Sooner, the Better? Couples' First Financial Discussion, Relationship Quality, and Financial Conflict in Emerging Adulthood. Journal of Financial Therapy, 13 (1) 2. https://doi.org/10.4148/1944-9771.1299 | M30: 10.4148/1944-9771.1299 | O30: 10.4148--1944-9771.1299.pdf | P30: {=HYPERLINK(INDEX('File Links'!B:B, MATCH(O30, 'File Links'!C:C, 0)))} -> https://drive.google.com/file/d/1OByNKNsjZqSFHFFyt-o1mPqDkVmgruBu/view?usp=drivesdk | Q30: Saxey, M. T., LeBaron‐Black, A. B., Inman, N. F., Yorgason, J. B., & Holmes, E. K. (2024). The earlier couples first discussed finances, the better? A dyadic, longitudinal replication and extension. Family Relations. https://doi.org/10.1111/fare.13030 | R30: 10.1111/fare.13030 | U30: .pdf | V30: dyadic, longitudinal replication and extension | W30: {=HYPERLINK(INDEX('File Links'!B:B, MATCH(U30, 'File Links'!C:C, 0)))} -> #N/A | Y30: Social Psychology | AA30: emerging adulthood; financial communication; financial conflict; financial discussion, relationship quality | AB30: Indirect effect present for relationship quality (replication: cross-sectional, wives' answers, effect on partner) | AC30: Indirect effect present for relationship quality: “initiating financial discussion earlier in a romantic relationship may benefit relationship quality—through financial communication” (most emphasised claim in original) | AD30: 1 | AE30: 1950 | AF30: 0.13 | AG30: beta | AH30: p. 11 | AI30: 0.001 | AJ30: l (<) | AK30: NA (not reported) | AM30: NA | AN30: 1079 | AO30: 0.02 | AP30: beta (std) | AQ30: p. 2538 | AR30: 0.05 | AS30: l (<) | AT30: NA (not reported) | AV30: NA | AW30: 3 - conceptual | AY30: LR
A31: validated - discarded | B31: double | C31: Fabienne | E31: additional_studies11_1 | F31: additional_studies11_c | G31: Julia Fabienne Sandkühler | H31: 45637 | I31: 45692 | J31: replication N refers to number of couples | L31: Saxey, M. T., LeBaron-Black, A. B., & Curran, M. A. (2022). The Sooner, the Better? Couples' First Financial Discussion, Relationship Quality, and Financial Conflict in Emerging Adulthood. Journal of Financial Therapy, 13 (1) 2. https://doi.org/10.4148/1944-9771.1299 | M31: 10.4148/1944-9771.1299 | O31: 10.4148--1944-9771.1299.pdf | P31: {=HYPERLINK(INDEX('File Links'!B:B, MATCH(O31, 'File Links'!C:C, 0)))} -> https://drive.google.com/file/d/1OByNKNsjZqSFHFFyt-o1mPqDkVmgruBu/view?usp=drivesdk | Q31: Saxey, M. T., LeBaron‐Black, A. B., Inman, N. F., Yorgason, J. B., & Holmes, E. K. (2024). The earlier couples first discussed finances, the better? A dyadic, longitudinal replication and extension. Family Relations. https://doi.org/10.1111/fare.13030 | R31: 10.1111/fare.13030 | U31: .pdf | V31: dyadic, longitudinal replication and extension | W31: {=HYPERLINK(INDEX('File Links'!B:B, MATCH(U31, 'File Links'!C:C, 0)))} -> #N/A | Y31: Social Psychology | AA31: emerging adulthood; financial communication; financial conflict; financial discussion, relationship quality | AB31: Indirect effect present for relationship quality (replication: cross-sectional, husbands' answers, effect on themselves) | AC31: Indirect effect present for relationship quality: “initiating financial discussion earlier in a romantic relationship may benefit relationship quality—through financial communication” (most emphasised claim in original) | AD31: 1 | AE31: 1950 | AF31: 0.13 | AG31: beta | AH31: p. 11 | AI31: 0.001 | AJ31: l (<) | AK31: NA (not reported) | AM31: NA | AN31: 1079 | AO31: 0.04 | AP31: beta (std) | AQ31: p. 2538 | AR31: 0.05 | AS31: l (<) | AT31: NA (not reported) | AV31: NA | AW31: 3 - conceptual | AY31: LR
A32: validated - discarded | B32: double | C32: Fabienne | E32: additional_studies11_1 | F32: additional_studies11_d | G32: Julia Fabienne Sandkühler | H32: 45637 | I32: 45692 | J32: replication N refers to number of couples | L32: Saxey, M. T., LeBaron-Black, A. B., & Curran, M. A. (2022). The Sooner, the Better? Couples' First Financial Discussion, Relationship Quality, and Financial Conflict in Emerging Adulthood. Journal of Financial Therapy, 13 (1) 2. https://doi.org/10.4148/1944-9771.1299 | M32: 10.4148/1944-9771.1299 | O32: 10.4148--1944-9771.1299.pdf | P32: {=HYPERLINK(INDEX('File Links'!B:B, MATCH(O32, 'File Links'!C:C, 0)))} -> https://drive.google.com/file/d/1OByNKNsjZqSFHFFyt-o1mPqDkVmgruBu/view?usp=drivesdk | Q32: Saxey, M. T., LeBaron‐Black, A. B., Inman, N. F., Yorgason, J. B., & Holmes, E. K. (2024). The earlier couples first discussed finances, the better? A dyadic, longitudinal replication and extension. Family Relations. https://doi.org/10.1111/fare.13030 | R32: 10.1111/fare.13030 | U32: .pdf | V32: dyadic, longitudinal replication and extension | W32: {=HYPERLINK(INDEX('File Links'!B:B, MATCH(U32, 'File Links'!C:C, 0)))} -> #N/A | Y32: Social Psychology | AA32: emerging adulthood; financial communication; financial conflict; financial discussion, relationship quality | AB32: Indirect effect present for relationship quality (replication: cross-sectional, husbands' answers, effect on partner) | AC32: Indirect effect present for relationship quality: “initiating financial discussion earlier in a romantic relationship may benefit relationship quality—through financial communication” (most emphasised claim in original) | AD32: 1 | AE32: 1950 | AF32: 0.13 | AG32: beta | AH32: p. 11 | AI32: 0.001 | AJ32: l (<) | AK32: NA (not reported) | AM32: NA | AN32: 1079 | AP32: beta (std) | AQ32: p. 2538 | AR32: 0.05 | AS32: g (>) | AT32: NA (not reported) | AV32: NA | AW32: 3 - conceptual | AY32: LR
A33: validated - discarded | B33: double | C33: Fabienne | E33: additional_studies11_1 | F33: additional_studies11_e | G33: Julia Fabienne Sandkühler | H33: 45637 | I33: 45692 | J33: replication N refers to number of couples | L33: Saxey, M. T., LeBaron-Black, A. B., & Curran, M. A. (2022). The Sooner, the Better? Couples' First Financial Discussion, Relationship Quality, and Financial Conflict in Emerging Adulthood. Journal of Financial Therapy, 13 (1) 2. https://doi.org/10.4148/1944-9771.1299 | M33: 10.4148/1944-9771.1299 | O33: 10.4148--1944-9771.1299.pdf | P33: {=HYPERLINK(INDEX('File Links'!B:B, MATCH(O33, 'File Links'!C:C, 0)))} -> https://drive.google.com/file/d/1OByNKNsjZqSFHFFyt-o1mPqDkVmgruBu/view?usp=drivesdk | Q33: Saxey, M. T., LeBaron‐Black, A. B., Inman, N. F., Yorgason, J. B., & Holmes, E. K. (2024). The earlier couples first discussed finances, the better? A dyadic, longitudinal replication and extension. Family Relations. https://doi.org/10.1111/fare.13030 | R33: 10.1111/fare.13030 | U33: .pdf | V33: dyadic, longitudinal replication and extension | W33: {=HYPERLINK(INDEX('File Links'!B:B, MATCH(U33, 'File Links'!C:C, 0)))} -> #N/A | Y33: Social Psychology | AA33: emerging adulthood; financial communication; financial conflict; financial discussion, relationship quality | AB33: Indirect effect present for relationship quality (replication: longitudinal, wives' answers, effect on themselves) | AC33: Indirect effect present for relationship quality: “initiating financial discussion earlier in a romantic relationship may benefit relationship quality—through financial communication” (most emphasised claim in original) | AD33: 1 | AE33: 1950 | AF33: 0.13 | AG33: beta | AH33: p. 11 | AI33: 0.001 | AJ33: l (<) | AK33: NA (not reported) | AM33: NA | AN33: 1079 | AP33: beta (std) | AQ33: p. 2538 | AR33: 0.05 | AS33: g (>) | AT33: NA (not reported) | AV33: NA | AW33: 3 - conceptual | AY33: LR
A34: validated - discarded | B34: double | C34: Fabienne | E34: additional_studies11_1 | F34: additional_studies11_f | G34: Julia Fabienne Sandkühler | H34: 45637 | I34: 45692 | J34: replication N refers to number of couples | L34: Saxey, M. T., LeBaron-Black, A. B., & Curran, M. A. (2022). The Sooner, the Better? Couples' First Financial Discussion, Relationship Quality, and Financial Conflict in Emerging Adulthood. Journal of Financial Therapy, 13 (1) 2. https://doi.org/10.4148/1944-9771.1299 | M34: 10.4148/1944-9771.1299 | O34: 10.4148--1944-9771.1299.pdf | P34: {=HYPERLINK(INDEX('File Links'!B:B, MATCH(O34, 'File Links'!C:C, 0)))} -> https://drive.google.com/file/d/1OByNKNsjZqSFHFFyt-o1mPqDkVmgruBu/view?usp=drivesdk | Q34: Saxey, M. T., LeBaron‐Black, A. B., Inman, N. F., Yorgason, J. B., & Holmes, E. K. (2024). The earlier couples first discussed finances, the better? A dyadic, longitudinal replication and extension. Family Relations. https://doi.org/10.1111/fare.13030 | R34: 10.1111/fare.13030 | U34: .pdf | V34: dyadic, longitudinal replication and extension | W34: {=HYPERLINK(INDEX('File Links'!B:B, MATCH(U34, 'File Links'!C:C, 0)))} -> #N/A | Y34: Social Psychology | AA34: emerging adulthood; financial communication; financial conflict; financial discussion, relationship quality | AB34: Indirect effect present for relationship quality (replication: longitudinal, wives' answers, effect on partner) | AC34: Indirect effect present for relationship quality: “initiating financial discussion earlier in a romantic relationship may benefit relationship quality—through financial communication” (most emphasised claim in original) | AD34: 1 | AE34: 1950 | AF34: 0.13 | AG34: beta | AH34: p. 11 | AI34: 0.001 | AJ34: l (<) | AK34: NA (not reported) | AM34: NA | AN34: 1079 | AP34: beta (std) | AQ34: p. 2538 | AR34: 0.05 | AS34: g (>) | AT34: NA (not reported) | AV34: NA | AW34: 3 - conceptual | AY34: LR
A35: validated - discarded | B35: double | C35: Fabienne | E35: additional_studies11_1 | F35: additional_studies11_g | G35: Julia Fabienne Sandkühler | H35: 45637 | I35: 45692 | J35: replication N refers to number of couples | L35: Saxey, M. T., LeBaron-Black, A. B., & Curran, M. A. (2022). The Sooner, the Better? Couples' First Financial Discussion, Relationship Quality, and Financial Conflict in Emerging Adulthood. Journal of Financial Therapy, 13 (1) 2. https://doi.org/10.4148/1944-9771.1299 | M35: 10.4148/1944-9771.1299 | O35: 10.4148--1944-9771.1299.pdf | P35: {=HYPERLINK(INDEX('File Links'!B:B, MATCH(O35, 'File Links'!C:C, 0)))} -> https://drive.google.com/file/d/1OByNKNsjZqSFHFFyt-o1mPqDkVmgruBu/view?usp=drivesdk | Q35: Saxey, M. T., LeBaron‐Black, A. B., Inman, N. F., Yorgason, J. B., & Holmes, E. K. (2024). The earlier couples first discussed finances, the better? A dyadic, longitudinal replication and extension. Family Relations. https://doi.org/10.1111/fare.13030 | R35: 10.1111/fare.13030 | U35: .pdf | V35: dyadic, longitudinal replication and extension | W35: {=HYPERLINK(INDEX('File Links'!B:B, MATCH(U35, 'File Links'!C:C, 0)))} -> #N/A | Y35: Social Psychology | AA35: emerging adulthood; financial communication; financial conflict; financial discussion, relationship quality | AB35: Indirect effect present for relationship quality (replication: longitudinal, husbands' answers, effect on themselves) | AC35: Indirect effect present for relationship quality: “initiating financial discussion earlier in a romantic relationship may benefit relationship quality—through financial communication” (most emphasised claim in original) | AD35: 1 | AE35: 1950 | AF35: 0.13 | AG35: beta | AH35: p. 11 | AI35: 0.001 | AJ35: l (<) | AK35: NA (not reported) | AM35: NA | AN35: 1079 | AP35: beta (std) | AQ35: p. 2538 | AR35: 0.05 | AS35: g (>) | AT35: NA (not reported) | AV35: NA | AW35: 3 - conceptual | AY35: LR
A36: validated - discarded | B36: double | C36: Fabienne | E36: additional_studies11_1 | F36: additional_studies11_h | G36: Julia Fabienne Sandkühler | H36: 45637 | I36: 45692 | J36: replication N refers to number of couples | L36: Saxey, M. T., LeBaron-Black, A. B., & Curran, M. A. (2022). The Sooner, the Better? Couples' First Financial Discussion, Relationship Quality, and Financial Conflict in Emerging Adulthood. Journal of Financial Therapy, 13 (1) 2. https://doi.org/10.4148/1944-9771.1299 | M36: 10.4148/1944-9771.1299 | O36: 10.4148--1944-9771.1299.pdf | P36: {=HYPERLINK(INDEX('File Links'!B:B, MATCH(O36, 'File Links'!C:C, 0)))} -> https://drive.google.com/file/d/1OByNKNsjZqSFHFFyt-o1mPqDkVmgruBu/view?usp=drivesdk | Q36: Saxey, M. T., LeBaron‐Black, A. B., Inman, N. F., Yorgason, J. B., & Holmes, E. K. (2024). The earlier couples first discussed finances, the better? A dyadic, longitudinal replication and extension. Family Relations. https://doi.org/10.1111/fare.13030 | R36: 10.1111/fare.13030 | U36: .pdf | V36: dyadic, longitudinal replication and extension | W36: {=HYPERLINK(INDEX('File Links'!B:B, MATCH(U36, 'File Links'!C:C, 0)))} -> #N/A | Y36: Social Psychology | AA36: emerging adulthood; financial communication; financial conflict; financial discussion, relationship quality | AB36: Indirect effect present for relationship quality (replication: longitudinal, husbands' answers, effect on partner) | AC36: Indirect effect present for relationship quality: “initiating financial discussion earlier in a romantic relationship may benefit relationship quality—through financial communication” (most emphasised claim in original) | AD36: 1 | AE36: 1950 | AF36: 0.13 | AG36: beta | AH36: p. 11 | AI36: 0.001 | AJ36: l (<) | AK36: NA (not reported) | AM36: NA | AN36: 1079 | AP36: beta (std) | AQ36: p. 2538 | AR36: 0.05 | AS36: g (>) | AT36: NA (not reported) | AV36: NA | AW36: 3 - conceptual | AY36: LR
A37: validated - discarded | B37: double | C37: Fabienne | E37: additional_studies11_1 | F37: additional_studies11_i | G37: Julia Fabienne Sandkühler | H37: 45637 | I37: 45692 | J37: replication N refers to number of couples | L37: Saxey, M. T., LeBaron-Black, A. B., & Curran, M. A. (2022). The Sooner, the Better? Couples' First Financial Discussion, Relationship Quality, and Financial Conflict in Emerging Adulthood. Journal of Financial Therapy, 13 (1) 2. https://doi.org/10.4148/1944-9771.1299 | M37: 10.4148/1944-9771.1299 | O37: 10.4148--1944-9771.1299.pdf | P37: {=HYPERLINK(INDEX('File Links'!B:B, MATCH(O37, 'File Links'!C:C, 0)))} -> https://drive.google.com/file/d/1OByNKNsjZqSFHFFyt-o1mPqDkVmgruBu/view?usp=drivesdk | Q37: Saxey, M. T., LeBaron‐Black, A. B., Inman, N. F., Yorgason, J. B., & Holmes, E. K. (2024). The earlier couples first discussed finances, the better? A dyadic, longitudinal replication and extension. Family Relations. https://doi.org/10.1111/fare.13030 | R37: 10.1111/fare.13030 | U37: .pdf | V37: dyadic, longitudinal replication and extension | W37: {=HYPERLINK(INDEX('File Links'!B:B, MATCH(U37, 'File Links'!C:C, 0)))} -> #N/A | Y37: Social Psychology | AA37: emerging adulthood; financial communication; financial conflict; financial discussion, relationship quality | AB37: No direct effect present for relationship quality (replication: cross-sectional, wives' answers, effect on themselves) | AC37: No direct effect present for relationship quality: “Nonetheless, couples’ first financial discussion was not directly associated with their relationship quality.” (however not emphasised in original) | AD37: 11 | AE37: 1950 | AG37: beta | AH37: p. 11 | AI37: 0.05 | AJ37: g (>) | AK37: NA (not reported) | AM37: NA | AN37: 1079 | AP37: beta (std) | AQ37: p. 2536 | AR37: 0.05 | AS37: g (>) | AT37: NA (not reported) | AV37: NA | AW37: 3 - conceptual | AY37: LR
A38: validated - discarded | B38: double | C38: Fabienne | E38: additional_studies11_1 | F38: additional_studies11_j | G38: Julia Fabienne Sandkühler | H38: 45637 | I38: 45692 | J38: replication N refers to number of couples | L38: Saxey, M. T., LeBaron-Black, A. B., & Curran, M. A. (2022). The Sooner, the Better? Couples' First Financial Discussion, Relationship Quality, and Financial Conflict in Emerging Adulthood. Journal of Financial Therapy, 13 (1) 2. https://doi.org/10.4148/1944-9771.1299 | M38: 10.4148/1944-9771.1299 | O38: 10.4148--1944-9771.1299.pdf | P38: {=HYPERLINK(INDEX('File Links'!B:B, MATCH(O38, 'File Links'!C:C, 0)))} -> https://drive.google.com/file/d/1OByNKNsjZqSFHFFyt-o1mPqDkVmgruBu/view?usp=drivesdk | Q38: Saxey, M. T., LeBaron‐Black, A. B., Inman, N. F., Yorgason, J. B., & Holmes, E. K. (2024). The earlier couples first discussed finances, the better? A dyadic, longitudinal replication and extension. Family Relations. https://doi.org/10.1111/fare.13030 | R38: 10.1111/fare.13030 | U38: .pdf | V38: dyadic, longitudinal replication and extension | W38: {=HYPERLINK(INDEX('File Links'!B:B, MATCH(U38, 'File Links'!C:C, 0)))} -> #N/A | Y38: Social Psychology | AA38: emerging adulthood; financial communication; financial conflict; financial discussion, relationship quality | AB38: No direct effect present for relationship quality (replication: cross-sectional, wives' answers, effect on partner) | AC38: No direct effect present for relationship quality: “Nonetheless, couples’ first financial discussion was not directly associated with their relationship quality.” (however not emphasised in original) | AD38: 11 | AE38: 1950 | AG38: beta | AH38: p. 11 | AI38: 0.05 | AJ38: g (>) | AK38: NA (not reported) | AM38: NA | AN38: 1079 | AP38: beta (std) | AQ38: p. 2536 | AR38: 0.05 | AS38: g (>) | AT38: NA (not reported) | AV38: NA | AW38: 3 - conceptual | AY38: LR
A39: validated - discarded | B39: double | C39: Fabienne | E39: additional_studies11_1 | F39: additional_studies11_k | G39: Julia Fabienne Sandkühler | H39: 45637 | I39: 45692 | J39: replication N refers to number of couples | L39: Saxey, M. T., LeBaron-Black, A. B., & Curran, M. A. (2022). The Sooner, the Better? Couples' First Financial Discussion, Relationship Quality, and Financial Conflict in Emerging Adulthood. Journal of Financial Therapy, 13 (1) 2. https://doi.org/10.4148/1944-9771.1299 | M39: 10.4148/1944-9771.1299 | O39: 10.4148--1944-9771.1299.pdf | P39: {=HYPERLINK(INDEX('File Links'!B:B, MATCH(O39, 'File Links'!C:C, 0)))} -> https://drive.google.com/file/d/1OByNKNsjZqSFHFFyt-o1mPqDkVmgruBu/view?usp=drivesdk | Q39: Saxey, M. T., LeBaron‐Black, A. B., Inman, N. F., Yorgason, J. B., & Holmes, E. K. (2024). The earlier couples first discussed finances, the better? A dyadic, longitudinal replication and extension. Family Relations. https://doi.org/10.1111/fare.13030 | R39: 10.1111/fare.13030 | U39: .pdf | V39: dyadic, longitudinal replication and extension | W39: {=HYPERLINK(INDEX('File Links'!B:B, MATCH(U39, 'File Links'!C:C, 0)))} -> #N/A | Y39: Social Psychology | AA39: emerging adulthood; financial communication; financial conflict; financial discussion, relationship quality | AB39: No direct effect present for relationship quality (replication: cross-sectional, husbands' answers, effect on themselves) | AC39: No direct effect present for relationship quality: “Nonetheless, couples’ first financial discussion was not directly associated with their relationship quality.” (however not emphasised in original) | AD39: 11 | AE39: 1950 | AG39: beta | AH39: p. 11 | AI39: 0.05 | AJ39: g (>) | AK39: NA (not reported) | AM39: NA | AN39: 1079 | AP39: beta (std) | AQ39: p. 2536 | AR39: 0.05 | AS39: g (>) | AT39: NA (not reported) | AV39: NA | AW39: 3 - conceptual | AY39: LR
A40: validated - discarded | B40: double | C40: Fabienne | E40: additional_studies11_1 | F40: additional_studies11_l | G40: Julia Fabienne Sandkühler | H40: 45637 | I40: 45692 | J40: replication N refers to number of couples | L40: Saxey, M. T., LeBaron-Black, A. B., & Curran, M. A. (2022). The Sooner, the Better? Couples' First Financial Discussion, Relationship Quality, and Financial Conflict in Emerging Adulthood. Journal of Financial Therapy, 13 (1) 2. https://doi.org/10.4148/1944-9771.1299 | M40: 10.4148/1944-9771.1299 | O40: 10.4148--1944-9771.1299.pdf | P40: {=HYPERLINK(INDEX('File Links'!B:B, MATCH(O40, 'File Links'!C:C, 0)))} -> https://drive.google.com/file/d/1OByNKNsjZqSFHFFyt-o1mPqDkVmgruBu/view?usp=drivesdk | Q40: Saxey, M. T., LeBaron‐Black, A. B., Inman, N. F., Yorgason, J. B., & Holmes, E. K. (2024). The earlier couples first discussed finances, the better? A dyadic, longitudinal replication and extension. Family Relations. https://doi.org/10.1111/fare.13030 | R40: 10.1111/fare.13030 | U40: .pdf | V40: dyadic, longitudinal replication and extension | W40: {=HYPERLINK(INDEX('File Links'!B:B, MATCH(U40, 'File Links'!C:C, 0)))} -> #N/A | Y40: Social Psychology | AA40: emerging adulthood; financial communication; financial conflict; financial discussion, relationship quality | AB40: No direct effect present for relationship quality (replication: cross-sectional, husbands' answers, effect on partner) | AC40: No direct effect present for relationship quality: “Nonetheless, couples’ first financial discussion was not directly associated with their relationship quality.” (however not emphasised in original) | AD40: 11 | AE40: 1950 | AG40: beta | AH40: p. 11 | AI40: 0.05 | AJ40: g (>) | AK40: NA (not reported) | AM40: NA | AN40: 1079 | AP40: beta (std) | AQ40: p. 2536 | AR40: 0.05 | AS40: g (>) | AT40: NA (not reported) | AV40: NA | AW40: 3 - conceptual | AY40: LR
A41: validated - discarded | B41: double | C41: Fabienne | E41: additional_studies11_1 | F41: additional_studies11_m | G41: Julia Fabienne Sandkühler | H41: 45637 | I41: 45692 | J41: replication N refers to number of couples | L41: Saxey, M. T., LeBaron-Black, A. B., & Curran, M. A. (2022). The Sooner, the Better? Couples' First Financial Discussion, Relationship Quality, and Financial Conflict in Emerging Adulthood. Journal of Financial Therapy, 13 (1) 2. https://doi.org/10.4148/1944-9771.1299 | M41: 10.4148/1944-9771.1299 | O41: 10.4148--1944-9771.1299.pdf | P41: {=HYPERLINK(INDEX('File Links'!B:B, MATCH(O41, 'File Links'!C:C, 0)))} -> https://drive.google.com/file/d/1OByNKNsjZqSFHFFyt-o1mPqDkVmgruBu/view?usp=drivesdk | Q41: Saxey, M. T., LeBaron‐Black, A. B., Inman, N. F., Yorgason, J. B., & Holmes, E. K. (2024). The earlier couples first discussed finances, the better? A dyadic, longitudinal replication and extension. Family Relations. https://doi.org/10.1111/fare.13030 | R41: 10.1111/fare.13030 | U41: .pdf | V41: dyadic, longitudinal replication and extension | W41: {=HYPERLINK(INDEX('File Links'!B:B, MATCH(U41, 'File Links'!C:C, 0)))} -> #N/A | Y41: Social Psychology | AA41: emerging adulthood; financial communication; financial conflict; financial discussion, relationship quality | AB41: No direct effect present for relationship quality (replication: longitudinal, wives' answers, effect on themselves) | AC41: No direct effect present for relationship quality: “Nonetheless, couples’ first financial discussion was not directly associated with their relationship quality.” (however not emphasised in original) | AD41: 11 | AE41: 1950 | AG41: beta | AH41: p. 11 | AI41: 0.05 | AJ41: g (>) | AK41: NA (not reported) | AM41: NA | AN41: 1079 | AP41: beta (std) | AQ41: p. 2538 | AR41: 0.05 | AS41: g (>) | AT41: NA (not reported) | AV41: NA | AW41: 3 - conceptual | AY41: LR
A42: validated - discarded | B42: double | C42: Fabienne | E42: additional_studies11_1 | F42: additional_studies11_n | G42: Julia Fabienne Sandkühler | H42: 45637 | I42: 45692 | J42: replication N refers to number of couples | L42: Saxey, M. T., LeBaron-Black, A. B., & Curran, M. A. (2022). The Sooner, the Better? Couples' First Financial Discussion, Relationship Quality, and Financial Conflict in Emerging Adulthood. Journal of Financial Therapy, 13 (1) 2. https://doi.org/10.4148/1944-9771.1299 | M42: 10.4148/1944-9771.1299 | O42: 10.4148--1944-9771.1299.pdf | P42: {=HYPERLINK(INDEX('File Links'!B:B, MATCH(O42, 'File Links'!C:C, 0)))} -> https://drive.google.com/file/d/1OByNKNsjZqSFHFFyt-o1mPqDkVmgruBu/view?usp=drivesdk | Q42: Saxey, M. T., LeBaron‐Black, A. B., Inman, N. F., Yorgason, J. B., & Holmes, E. K. (2024). The earlier couples first discussed finances, the better? A dyadic, longitudinal replication and extension. Family Relations. https://doi.org/10.1111/fare.13030 | R42: 10.1111/fare.13030 | U42: .pdf | V42: dyadic, longitudinal replication and extension | W42: {=HYPERLINK(INDEX('File Links'!B:B, MATCH(U42, 'File Links'!C:C, 0)))} -> #N/A | Y42: Social Psychology | AA42: emerging adulthood; financial communication; financial conflict; financial discussion, relationship quality | AB42: No direct effect present for relationship quality (replication: longitudinal, wives' answers, effect on partner) | AC42: No direct effect present for relationship quality: “Nonetheless, couples’ first financial discussion was not directly associated with their relationship quality.” (however not emphasised in original) | AD42: 11 | AE42: 1950 | AG42: beta | AH42: p. 11 | AI42: 0.05 | AJ42: g (>) | AK42: NA (not reported) | AM42: NA | AN42: 1079 | AP42: beta (std) | AQ42: p. 2538 | AR42: 0.05 | AS42: g (>) | AT42: NA (not reported) | AV42: NA | AW42: 3 - conceptual | AY42: LR
A43: validated - discarded | B43: double | C43: Fabienne | E43: additional_studies11_1 | F43: additional_studies11_o | G43: Julia Fabienne Sandkühler | H43: 45637 | I43: 45692 | J43: replication N refers to number of couples | L43: Saxey, M. T., LeBaron-Black, A. B., & Curran, M. A. (2022). The Sooner, the Better? Couples' First Financial Discussion, Relationship Quality, and Financial Conflict in Emerging Adulthood. Journal of Financial Therapy, 13 (1) 2. https://doi.org/10.4148/1944-9771.1299 | M43: 10.4148/1944-9771.1299 | O43: 10.4148--1944-9771.1299.pdf | P43: {=HYPERLINK(INDEX('File Links'!B:B, MATCH(O43, 'File Links'!C:C, 0)))} -> https://drive.google.com/file/d/1OByNKNsjZqSFHFFyt-o1mPqDkVmgruBu/view?usp=drivesdk | Q43: Saxey, M. T., LeBaron‐Black, A. B., Inman, N. F., Yorgason, J. B., & Holmes, E. K. (2024). The earlier couples first discussed finances, the better? A dyadic, longitudinal replication and extension. Family Relations. https://doi.org/10.1111/fare.13030 | R43: 10.1111/fare.13030 | U43: .pdf | V43: dyadic, longitudinal replication and extension | W43: {=HYPERLINK(INDEX('File Links'!B:B, MATCH(U43, 'File Links'!C:C, 0)))} -> #N/A | Y43: Social Psychology | AA43: emerging adulthood; financial communication; financial conflict; financial discussion, relationship quality | AB43: No direct effect present for relationship quality (replication: longitudinal, husbands' answers, effect on themselves) | AC43: No direct effect present for relationship quality: “Nonetheless, couples’ first financial discussion was not directly associated with their relationship quality.” (however not emphasised in original) | AD43: 11 | AE43: 1950 | AG43: beta | AH43: p. 11 | AI43: 0.05 | AJ43: g (>) | AK43: NA (not reported) | AM43: NA | AN43: 1079 | AO43: 0.07 | AP43: beta (std) | AQ43: p. 2538 | AR43: 0.05 | AS43: l (<) | AT43: NA (not reported) | AV43: NA | AW43: 3 - conceptual | AY43: LR
A44: validated - discarded | B44: double | C44: Fabienne | E44: additional_studies11_1 | F44: additional_studies11_p | G44: Julia Fabienne Sandkühler | H44: 45637 | I44: 45692 | J44: replication N refers to number of couples | L44: Saxey, M. T., LeBaron-Black, A. B., & Curran, M. A. (2022). The Sooner, the Better? Couples' First Financial Discussion, Relationship Quality, and Financial Conflict in Emerging Adulthood. Journal of Financial Therapy, 13 (1) 2. https://doi.org/10.4148/1944-9771.1299 | M44: 10.4148/1944-9771.1299 | O44: 10.4148--1944-9771.1299.pdf | P44: {=HYPERLINK(INDEX('File Links'!B:B, MATCH(O44, 'File Links'!C:C, 0)))} -> https://drive.google.com/file/d/1OByNKNsjZqSFHFFyt-o1mPqDkVmgruBu/view?usp=drivesdk | Q44: Saxey, M. T., LeBaron‐Black, A. B., Inman, N. F., Yorgason, J. B., & Holmes, E. K. (2024). The earlier couples first discussed finances, the better? A dyadic, longitudinal replication and extension. Family Relations. https://doi.org/10.1111/fare.13030 | R44: 10.1111/fare.13030 | U44: .pdf | V44: dyadic, longitudinal replication and extension | W44: {=HYPERLINK(INDEX('File Links'!B:B, MATCH(U44, 'File Links'!C:C, 0)))} -> #N/A | Y44: Social Psychology | AA44: emerging adulthood; financial communication; financial conflict; financial discussion, relationship quality | AB44: No direct effect present for relationship quality (replication: longitudinal, husbands' answers, effect on partner) | AC44: No direct effect present for relationship quality: “Nonetheless, couples’ first financial discussion was not directly associated with their relationship quality.” (however not emphasised in original) | AD44: 11 | AE44: 1950 | AG44: beta | AH44: p. 11 | AI44: 0.05 | AJ44: g (>) | AK44: NA (not reported) | AM44: NA | AN44: 1079 | AO44: 0.07 | AP44: beta (std) | AQ44: p. 2538 | AR44: 0.05 | AS44: l (<) | AT44: NA (not reported) | AV44: NA | AW44: 3 - conceptual | AY44: LR
A45: validated - discarded | B45: double | C45: Fabienne | E45: additional_studies11_1 | F45: additional_studies11_q | G45: Julia Fabienne Sandkühler | H45: 45637 | I45: 45692 | J45: replication N refers to number of couples | L45: Saxey, M. T., LeBaron-Black, A. B., & Curran, M. A. (2022). The Sooner, the Better? Couples' First Financial Discussion, Relationship Quality, and Financial Conflict in Emerging Adulthood. Journal of Financial Therapy, 13 (1) 2. https://doi.org/10.4148/1944-9771.1299 | M45: 10.4148/1944-9771.1299 | O45: 10.4148--1944-9771.1299.pdf | P45: {=HYPERLINK(INDEX('File Links'!B:B, MATCH(O45, 'File Links'!C:C, 0)))} -> https://drive.google.com/file/d/1OByNKNsjZqSFHFFyt-o1mPqDkVmgruBu/view?usp=drivesdk | Q45: Saxey, M. T., LeBaron‐Black, A. B., Inman, N. F., Yorgason, J. B., & Holmes, E. K. (2024). The earlier couples first discussed finances, the better? A dyadic, longitudinal replication and extension. Family Relations. https://doi.org/10.1111/fare.13030 | R45: 10.1111/fare.13030 | U45: .pdf | V45: dyadic, longitudinal replication and extension | W45: {=HYPERLINK(INDEX('File Links'!B:B, MATCH(U45, 'File Links'!C:C, 0)))} -> #N/A | Y45: Social Psychology | AA45: emerging adulthood; financial communication; financial conflict; financial discussion, relationship quality | AB45: Indirect effect present for financial conflict (replication: cross-sectional, wives' answers, effect on themselves) | AC45: Indirect effect present for financial conflict: "The pathway from the first financial discussion to financial conflict through financial communication was significant (β = -.06; p < .001)" (however not emphasised in original) | AD45: 11 | AE45: 1950 | AF45: -0.06 | AG45: beta | AH45: p. 11 | AI45: 0.001 | AJ45: l (<) | AK45: NA (not reported) | AM45: NA | AN45: 1079 | AO45: -0.07 | AP45: beta (std) | AQ45: p. 2537 | AR45: 0.001 | AS45: l (<) | AT45: NA (not reported) | AV45: NA | AW45: 3 - conceptual | AY45: LR
A46: validated - discarded | B46: double | C46: Fabienne | E46: additional_studies11_1 | F46: additional_studies11_r | G46: Julia Fabienne Sandkühler | H46: 45637 | I46: 45692 | J46: replication N refers to number of couples | L46: Saxey, M. T., LeBaron-Black, A. B., & Curran, M. A. (2022). The Sooner, the Better? Couples' First Financial Discussion, Relationship Quality, and Financial Conflict in Emerging Adulthood. Journal of Financial Therapy, 13 (1) 2. https://doi.org/10.4148/1944-9771.1299 | M46: 10.4148/1944-9771.1299 | O46: 10.4148--1944-9771.1299.pdf | P46: {=HYPERLINK(INDEX('File Links'!B:B, MATCH(O46, 'File Links'!C:C, 0)))} -> https://drive.google.com/file/d/1OByNKNsjZqSFHFFyt-o1mPqDkVmgruBu/view?usp=drivesdk | Q46: Saxey, M. T., LeBaron‐Black, A. B., Inman, N. F., Yorgason, J. B., & Holmes, E. K. (2024). The earlier couples first discussed finances, the better? A dyadic, longitudinal replication and extension. Family Relations. https://doi.org/10.1111/fare.13030 | R46: 10.1111/fare.13030 | U46: .pdf | V46: dyadic, longitudinal replication and extension | W46: {=HYPERLINK(INDEX('File Links'!B:B, MATCH(U46, 'File Links'!C:C, 0)))} -> #N/A | Y46: Social Psychology | AA46: emerging adulthood; financial communication; financial conflict; financial discussion, relationship quality | AB46: Indirect effect present for financial conflict (replication: cross-sectional, wives' answers, effect on partner) | AC46: Indirect effect present for financial conflict: "The pathway from the first financial discussion to financial conflict through financial communication was significant (β = -.06; p < .001)" (however not emphasised in original) | AD46: 11 | AE46: 1950 | AF46: -0.06 | AG46: beta | AH46: p. 11 | AI46: 0.001 | AJ46: l (<) | AK46: NA (not reported) | AM46: NA | AN46: 1079 | AO46: -0.03 | AP46: beta (std) | AQ46: p. 2537 | AR46: 0.01 | AS46: l (<) | AT46: NA (not reported) | AV46: NA | AW46: 3 - conceptual | AY46: LR
A47: validated - discarded | B47: double | C47: Fabienne | E47: additional_studies11_1 | F47: additional_studies11_s | G47: Julia Fabienne Sandkühler | H47: 45637 | I47: 45692 | J47: replication N refers to number of couples | L47: Saxey, M. T., LeBaron-Black, A. B., & Curran, M. A. (2022). The Sooner, the Better? Couples' First Financial Discussion, Relationship Quality, and Financial Conflict in Emerging Adulthood. Journal of Financial Therapy, 13 (1) 2. https://doi.org/10.4148/1944-9771.1299 | M47: 10.4148/1944-9771.1299 | O47: 10.4148--1944-9771.1299.pdf | P47: {=HYPERLINK(INDEX('File Links'!B:B, MATCH(O47, 'File Links'!C:C, 0)))} -> https://drive.google.com/file/d/1OByNKNsjZqSFHFFyt-o1mPqDkVmgruBu/view?usp=drivesdk | Q47: Saxey, M. T., LeBaron‐Black, A. B., Inman, N. F., Yorgason, J. B., & Holmes, E. K. (2024). The earlier couples first discussed finances, the better? A dyadic, longitudinal replication and extension. Family Relations. https://doi.org/10.1111/fare.13030 | R47: 10.1111/fare.13030 | U47: .pdf | V47: dyadic, longitudinal replication and extension | W47: {=HYPERLINK(INDEX('File Links'!B:B, MATCH(U47, 'File Links'!C:C, 0)))} -> #N/A | Y47: Social Psychology | AA47: emerging adulthood; financial communication; financial conflict; financial discussion, relationship quality | AB47: Indirect effect present for financial conflict (replication: cross-sectional, husbands' answers, effect on themselves) | AC47: Indirect effect present for financial conflict: "The pathway from the first financial discussion to financial conflict through financial communication was significant (β = -.06; p < .001)" (however not emphasised in original) | AD47: 11 | AE47: 1950 | AF47: -0.06 | AG47: beta | AH47: p. 11 | AI47: 0.001 | AJ47: l (<) | AK47: NA (not reported) | AM47: NA | AN47: 1079 | AO47: -0.04 | AP47: beta (std) | AQ47: p. 2537 | AR47: 0.05 | AS47: l (<) | AT47: NA (not reported) | AV47: NA | AW47: 3 - conceptual | AY47: LR
A48: validated - discarded | B48: double | C48: Fabienne | E48: additional_studies11_1 | F48: additional_studies11_t | G48: Julia Fabienne Sandkühler | H48: 45637 | I48: 45692 | J48: replication N refers to number of couples | L48: Saxey, M. T., LeBaron-Black, A. B., & Curran, M. A. (2022). The Sooner, the Better? Couples' First Financial Discussion, Relationship Quality, and Financial Conflict in Emerging Adulthood. Journal of Financial Therapy, 13 (1) 2. https://doi.org/10.4148/1944-9771.1299 | M48: 10.4148/1944-9771.1299 | O48: 10.4148--1944-9771.1299.pdf | P48: {=HYPERLINK(INDEX('File Links'!B:B, MATCH(O48, 'File Links'!C:C, 0)))} -> https://drive.google.com/file/d/1OByNKNsjZqSFHFFyt-o1mPqDkVmgruBu/view?usp=drivesdk | Q48: Saxey, M. T., LeBaron‐Black, A. B., Inman, N. F., Yorgason, J. B., & Holmes, E. K. (2024). The earlier couples first discussed finances, the better? A dyadic, longitudinal replication and extension. Family Relations. https://doi.org/10.1111/fare.13030 | R48: 10.1111/fare.13030 | U48: .pdf | V48: dyadic, longitudinal replication and extension | W48: {=HYPERLINK(INDEX('File Links'!B:B, MATCH(U48, 'File Links'!C:C, 0)))} -> #N/A | Y48: Social Psychology | AA48: emerging adulthood; financial communication; financial conflict; financial discussion, relationship quality | AB48: Indirect effect present for financial conflict (replication: cross-sectional, husbands' answers, effect on partner) | AC48: Indirect effect present for financial conflict: "The pathway from the first financial discussion to financial conflict through financial communication was significant (β = -.06; p < .001)" (however not emphasised in original) | AD48: 11 | AE48: 1950 | AF48: -0.06 | AG48: beta | AH48: p. 11 | AI48: 0.001 | AJ48: l (<) | AK48: NA (not reported) | AM48: NA | AN48: 1079 | AO48: -0.02 | AP48: beta (std) | AQ48: p. 2537 | AR48: 0.05 | AS48: l (<) | AT48: NA (not reported) | AV48: NA | AW48: 3 - conceptual | AY48: LR
A49: validated - discarded | B49: double | C49: Fabienne | E49: additional_studies11_1 | F49: additional_studies11_u | G49: Julia Fabienne Sandkühler | H49: 45637 | I49: 45692 | J49: replication N refers to number of couples | L49: Saxey, M. T., LeBaron-Black, A. B., & Curran, M. A. (2022). The Sooner, the Better? Couples' First Financial Discussion, Relationship Quality, and Financial Conflict in Emerging Adulthood. Journal of Financial Therapy, 13 (1) 2. https://doi.org/10.4148/1944-9771.1299 | M49: 10.4148/1944-9771.1299 | O49: 10.4148--1944-9771.1299.pdf | P49: {=HYPERLINK(INDEX('File Links'!B:B, MATCH(O49, 'File Links'!C:C, 0)))} -> https://drive.google.com/file/d/1OByNKNsjZqSFHFFyt-o1mPqDkVmgruBu/view?usp=drivesdk | Q49: Saxey, M. T., LeBaron‐Black, A. B., Inman, N. F., Yorgason, J. B., & Holmes, E. K. (2024). The earlier couples first discussed finances, the better? A dyadic, longitudinal replication and extension. Family Relations. https://doi.org/10.1111/fare.13030 | R49: 10.1111/fare.13030 | U49: .pdf | V49: dyadic, longitudinal replication and extension | W49: {=HYPERLINK(INDEX('File Links'!B:B, MATCH(U49, 'File Links'!C:C, 0)))} -> #N/A | Y49: Social Psychology | AA49: emerging adulthood; financial communication; financial conflict; financial discussion, relationship quality | AB49: Indirect effect present for financial conflict (replication: longitudinal, wives' answers, effect on themselves) | AC49: Indirect effect present for financial conflict: "The pathway from the first financial discussion to financial conflict through financial communication was significant (β = -.06; p < .001)" (however not emphasised in original) | AD49: 11 | AE49: 1950 | AF49: -0.06 | AG49: beta | AH49: p. 11 | AI49: 0.001 | AJ49: l (<) | AK49: NA (not reported) | AM49: NA | AN49: 1079 | AP49: beta (std) | AQ49: p. 2538 | AR49: 0.05 | AS49: g (>) | AT49: NA (not reported) | AV49: NA | AW49: 3 - conceptual | AY49: LR
A50: validated - discarded | B50: double | C50: Fabienne | E50: additional_studies11_1 | F50: additional_studies11_v | G50: Julia Fabienne Sandkühler | H50: 45637 | I50: 45692 | J50: replication N refers to number of couples | L50: Saxey, M. T., LeBaron-Black, A. B., & Curran, M. A. (2022). The Sooner, the Better? Couples' First Financial Discussion, Relationship Quality, and Financial Conflict in Emerging Adulthood. Journal of Financial Therapy, 13 (1) 2. https://doi.org/10.4148/1944-9771.1299 | M50: 10.4148/1944-9771.1299 | O50: 10.4148--1944-9771.1299.pdf | P50: {=HYPERLINK(INDEX('File Links'!B:B, MATCH(O50, 'File Links'!C:C, 0)))} -> https://drive.google.com/file/d/1OByNKNsjZqSFHFFyt-o1mPqDkVmgruBu/view?usp=drivesdk | Q50: Saxey, M. T., LeBaron‐Black, A. B., Inman, N. F., Yorgason, J. B., & Holmes, E. K. (2024). The earlier couples first discussed finances, the better? A dyadic, longitudinal replication and extension. Family Relations. https://doi.org/10.1111/fare.13030 | R50: 10.1111/fare.13030 | U50: .pdf | V50: dyadic, longitudinal replication and extension | W50: {=HYPERLINK(INDEX('File Links'!B:B, MATCH(U50, 'File Links'!C:C, 0)))} -> #N/A | Y50: Social Psychology | AA50: emerging adulthood; financial communication; financial conflict; financial discussion, relationship quality | AB50: Indirect effect present for financial conflict (replication: longitudinal, wives' answers, effect on partner) | AC50: Indirect effect present for financial conflict: "The pathway from the first financial discussion to financial conflict through financial communication was significant (β = -.06; p < .001)" (however not emphasised in original) | AD50: 11 | AE50: 1950 | AF50: -0.06 | AG50: beta | AH50: p. 11 | AI50: 0.001 | AJ50: l (<) | AK50: NA (not reported) | AM50: NA | AN50: 1079 | AP50: beta (std) | AQ50: p. 2538 | AR50: 0.05 | AS50: g (>) | AT50: NA (not reported) | AV50: NA | AW50: 3 - conceptual | AY50: LR
A51: validated - discarded | B51: double | C51: Fabienne | E51: additional_studies11_1 | F51: additional_studies11_w | G51: Julia Fabienne Sandkühler | H51: 45637 | I51: 45692 | J51: replication N refers to number of couples | L51: Saxey, M. T., LeBaron-Black, A. B., & Curran, M. A. (2022). The Sooner, the Better? Couples' First Financial Discussion, Relationship Quality, and Financial Conflict in Emerging Adulthood. Journal of Financial Therapy, 13 (1) 2. https://doi.org/10.4148/1944-9771.1299 | M51: 10.4148/1944-9771.1299 | O51: 10.4148--1944-9771.1299.pdf | P51: {=HYPERLINK(INDEX('File Links'!B:B, MATCH(O51, 'File Links'!C:C, 0)))} -> https://drive.google.com/file/d/1OByNKNsjZqSFHFFyt-o1mPqDkVmgruBu/view?usp=drivesdk | Q51: Saxey, M. T., LeBaron‐Black, A. B., Inman, N. F., Yorgason, J. B., & Holmes, E. K. (2024). The earlier couples first discussed finances, the better? A dyadic, longitudinal replication and extension. Family Relations. https://doi.org/10.1111/fare.13030 | R51: 10.1111/fare.13030 | U51: .pdf | V51: dyadic, longitudinal replication and extension | W51: {=HYPERLINK(INDEX('File Links'!B:B, MATCH(U51, 'File Links'!C:C, 0)))} -> #N/A | Y51: Social Psychology | AA51: emerging adulthood; financial communication; financial conflict; financial discussion, relationship quality | AB51: Indirect effect present for financial conflict (replication: longitudinal husbands' answers, effect on themselves) | AC51: Indirect effect present for financial conflict: "The pathway from the first financial discussion to financial conflict through financial communication was significant (β = -.06; p < .001)" (however not emphasised in original) | AD51: 11 | AE51: 1950 | AF51: -0.06 | AG51: beta | AH51: p. 11 | AI51: 0.001 | AJ51: l (<) | AK51: NA (not reported) | AM51: NA | AN51: 1079 | AP51: beta (std) | AQ51: p. 2538 | AR51: 0.05 | AS51: g (>) | AT51: NA (not reported) | AV51: NA | AW51: 3 - conceptual | AY51: LR
A52: validated - discarded | B52: double | C52: Fabienne | E52: additional_studies11_1 | F52: additional_studies11_x | G52: Julia Fabienne Sandkühler | H52: 45637 | I52: 45692 | J52: replication N refers to number of couples | L52: Saxey, M. T., LeBaron-Black, A. B., & Curran, M. A. (2022). The Sooner, the Better? Couples' First Financial Discussion, Relationship Quality, and Financial Conflict in Emerging Adulthood. Journal of Financial Therapy, 13 (1) 2. https://doi.org/10.4148/1944-9771.1299 | M52: 10.4148/1944-9771.1299 | O52: 10.4148--1944-9771.1299.pdf | P52: {=HYPERLINK(INDEX('File Links'!B:B, MATCH(O52, 'File Links'!C:C, 0)))} -> https://drive.google.com/file/d/1OByNKNsjZqSFHFFyt-o1mPqDkVmgruBu/view?usp=drivesdk | Q52: Saxey, M. T., LeBaron‐Black, A. B., Inman, N. F., Yorgason, J. B., & Holmes, E. K. (2024). The earlier couples first discussed finances, the better? A dyadic, longitudinal replication and extension. Family Relations. https://doi.org/10.1111/fare.13030 | R52: 10.1111/fare.13030 | U52: .pdf | V52: dyadic, longitudinal replication and extension | W52: {=HYPERLINK(INDEX('File Links'!B:B, MATCH(U52, 'File Links'!C:C, 0)))} -> #N/A | Y52: Social Psychology | AA52: emerging adulthood; financial communication; financial conflict; financial discussion, relationship quality | AB52: Indirect effect present for financial conflict (replication: longitudinal husbands' answers, effect on partner) | AC52: Indirect effect present for financial conflict: "The pathway from the first financial discussion to financial conflict through financial communication was significant (β = -.06; p < .001)" (however not emphasised in original) | AD52: 11 | AE52: 1950 | AF52: -0.06 | AG52: beta | AH52: p. 11 | AI52: 0.001 | AJ52: l (<) | AK52: NA (not reported) | AM52: NA | AN52: 1079 | AP52: beta (std) | AQ52: p. 2538 | AR52: 0.05 | AS52: g (>) | AT52: NA (not reported) | AV52: NA | AW52: 3 - conceptual | AY52: LR
A53: validated - discarded | B53: double | C53: Fabienne | E53: additional_studies11_1 | F53: additional_studies11_y | G53: Julia Fabienne Sandkühler | H53: 45637 | I53: 45692 | J53: replication N refers to number of couples | L53: Saxey, M. T., LeBaron-Black, A. B., & Curran, M. A. (2022). The Sooner, the Better? Couples' First Financial Discussion, Relationship Quality, and Financial Conflict in Emerging Adulthood. Journal of Financial Therapy, 13 (1) 2. https://doi.org/10.4148/1944-9771.1299 | M53: 10.4148/1944-9771.1299 | O53: 10.4148--1944-9771.1299.pdf | P53: {=HYPERLINK(INDEX('File Links'!B:B, MATCH(O53, 'File Links'!C:C, 0)))} -> https://drive.google.com/file/d/1OByNKNsjZqSFHFFyt-o1mPqDkVmgruBu/view?usp=drivesdk | Q53: Saxey, M. T., LeBaron‐Black, A. B., Inman, N. F., Yorgason, J. B., & Holmes, E. K. (2024). The earlier couples first discussed finances, the better? A dyadic, longitudinal replication and extension. Family Relations. https://doi.org/10.1111/fare.13030 | R53: 10.1111/fare.13030 | U53: .pdf | V53: dyadic, longitudinal replication and extension | W53: {=HYPERLINK(INDEX('File Links'!B:B, MATCH(U53, 'File Links'!C:C, 0)))} -> #N/A | Y53: Social Psychology | AA53: emerging adulthood; financial communication; financial conflict; financial discussion, relationship quality | AB53: Direct effect present for financial conflict (replication: cross-sectional, wives' answers, effect on themselves) | AC53: Direct effect present for financial conflict: “However, having an earlier first financial discussion as a couple was also positively associated with financial conflict.” (p. 1, emphasised in original) (also p. 11: "The pathway from the first financial discussion to financial conflict through financial communication was significant (β = -.06; p < .001), but the direct effect was also significant (p < .05).") | AD53: 1 | AE53: 1950 | AG53: beta | AH53: p. 11 | AI53: 0.05 | AJ53: g (>) | AK53: NA (not reported) | AM53: NA | AN53: 1079 | AP53: beta (std) | AQ53: p. 2536 | AR53: 0.05 | AS53: g (>) | AT53: NA (not reported) | AV53: NA | AW53: 3 - conceptual | AY53: LR
A54: validated - discarded | B54: double | C54: Fabienne | E54: additional_studies11_1 | F54: additional_studies11_z | G54: Julia Fabienne Sandkühler | H54: 45637 | I54: 45692 | J54: replication N refers to number of couples | L54: Saxey, M. T., LeBaron-Black, A. B., & Curran, M. A. (2022). The Sooner, the Better? Couples' First Financial Discussion, Relationship Quality, and Financial Conflict in Emerging Adulthood. Journal of Financial Therapy, 13 (1) 2. https://doi.org/10.4148/1944-9771.1299 | M54: 10.4148/1944-9771.1299 | O54: 10.4148--1944-9771.1299.pdf | P54: {=HYPERLINK(INDEX('File Links'!B:B, MATCH(O54, 'File Links'!C:C, 0)))} -> https://drive.google.com/file/d/1OByNKNsjZqSFHFFyt-o1mPqDkVmgruBu/view?usp=drivesdk | Q54: Saxey, M. T., LeBaron‐Black, A. B., Inman, N. F., Yorgason, J. B., & Holmes, E. K. (2024). The earlier couples first discussed finances, the better? A dyadic, longitudinal replication and extension. Family Relations. https://doi.org/10.1111/fare.13030 | R54: 10.1111/fare.13030 | U54: .pdf | V54: dyadic, longitudinal replication and extension | W54: {=HYPERLINK(INDEX('File Links'!B:B, MATCH(U54, 'File Links'!C:C, 0)))} -> #N/A | Y54: Social Psychology | AA54: emerging adulthood; financial communication; financial conflict; financial discussion, relationship quality | AB54: Direct effect present for financial conflict (replication: cross-sectional, wives' answers, effect on partner) | AC54: Direct effect present for financial conflict: “However, having an earlier first financial discussion as a couple was also positively associated with financial conflict.” (p. 1, emphasised in original) (also p. 11: "The pathway from the first financial discussion to financial conflict through financial communication was significant (β = -.06; p < .001), but the direct effect was also significant (p < .05).") | AD54: 1 | AE54: 1950 | AG54: beta | AH54: p. 11 | AI54: 0.05 | AJ54: g (>) | AK54: NA (not reported) | AM54: NA | AN54: 1079 | AP54: beta (std) | AQ54: p. 2536 | AR54: 0.05 | AS54: g (>) | AT54: NA (not reported) | AV54: NA | AW54: 3 - conceptual | AY54: LR
A55: validated - discarded | B55: double | C55: Fabienne | E55: additional_studies11_1 | F55: additional_studies11_za | G55: Julia Fabienne Sandkühler | H55: 45637 | I55: 45692 | J55: replication N refers to number of couples | L55: Saxey, M. T., LeBaron-Black, A. B., & Curran, M. A. (2022). The Sooner, the Better? Couples' First Financial Discussion, Relationship Quality, and Financial Conflict in Emerging Adulthood. Journal of Financial Therapy, 13 (1) 2. https://doi.org/10.4148/1944-9771.1299 | M55: 10.4148/1944-9771.1299 | O55: 10.4148--1944-9771.1299.pdf | P55: {=HYPERLINK(INDEX('File Links'!B:B, MATCH(O55, 'File Links'!C:C, 0)))} -> https://drive.google.com/file/d/1OByNKNsjZqSFHFFyt-o1mPqDkVmgruBu/view?usp=drivesdk | Q55: Saxey, M. T., LeBaron‐Black, A. B., Inman, N. F., Yorgason, J. B., & Holmes, E. K. (2024). The earlier couples first discussed finances, the better? A dyadic, longitudinal replication and extension. Family Relations. https://doi.org/10.1111/fare.13030 | R55: 10.1111/fare.13030 | U55: .pdf | V55: dyadic, longitudinal replication and extension | W55: {=HYPERLINK(INDEX('File Links'!B:B, MATCH(U55, 'File Links'!C:C, 0)))} -> #N/A | Y55: Social Psychology | AA55: emerging adulthood; financial communication; financial conflict; financial discussion, relationship quality | AB55: Direct effect present for financial conflict (replication: cross-sectional, husbands' answers, effect on themselves) | AC55: Direct effect present for financial conflict: “However, having an earlier first financial discussion as a couple was also positively associated with financial conflict.” (p. 1, emphasised in original) (also p. 11: "The pathway from the first financial discussion to financial conflict through financial communication was significant (β = -.06; p < .001), but the direct effect was also significant (p < .05).") | AD55: 1 | AE55: 1950 | AG55: beta | AH55: p. 11 | AI55: 0.05 | AJ55: g (>) | AK55: NA (not reported) | AM55: NA | AN55: 1079 | AP55: beta (std) | AQ55: p. 2536 | AR55: 0.05 | AS55: g (>) | AT55: NA (not reported) | AV55: NA | AW55: 3 - conceptual | AY55: LR
A56: validated - discarded | B56: double | C56: Fabienne | E56: additional_studies11_1 | F56: additional_studies11_zb | G56: Julia Fabienne Sandkühler | H56: 45637 | I56: 45692 | J56: replication N refers to number of couples | L56: Saxey, M. T., LeBaron-Black, A. B., & Curran, M. A. (2022). The Sooner, the Better? Couples' First Financial Discussion, Relationship Quality, and Financial Conflict in Emerging Adulthood. Journal of Financial Therapy, 13 (1) 2. https://doi.org/10.4148/1944-9771.1299 | M56: 10.4148/1944-9771.1299 | O56: 10.4148--1944-9771.1299.pdf | P56: {=HYPERLINK(INDEX('File Links'!B:B, MATCH(O56, 'File Links'!C:C, 0)))} -> https://drive.google.com/file/d/1OByNKNsjZqSFHFFyt-o1mPqDkVmgruBu/view?usp=drivesdk | Q56: Saxey, M. T., LeBaron‐Black, A. B., Inman, N. F., Yorgason, J. B., & Holmes, E. K. (2024). The earlier couples first discussed finances, the better? A dyadic, longitudinal replication and extension. Family Relations. https://doi.org/10.1111/fare.13030 | R56: 10.1111/fare.13030 | U56: .pdf | V56: dyadic, longitudinal replication and extension | W56: {=HYPERLINK(INDEX('File Links'!B:B, MATCH(U56, 'File Links'!C:C, 0)))} -> #N/A | Y56: Social Psychology | AA56: emerging adulthood; financial communication; financial conflict; financial discussion, relationship quality | AB56: Direct effect present for financial conflict (replication: cross-sectional, husbands' answers, effect on partner) | AC56: Direct effect present for financial conflict: “However, having an earlier first financial discussion as a couple was also positively associated with financial conflict.” (p. 1, emphasised in original) (also p. 11: "The pathway from the first financial discussion to financial conflict through financial communication was significant (β = -.06; p < .001), but the direct effect was also significant (p < .05).") | AD56: 1 | AE56: 1950 | AG56: beta | AH56: p. 11 | AI56: 0.05 | AJ56: g (>) | AK56: NA (not reported) | AM56: NA | AN56: 1079 | AP56: beta (std) | AQ56: p. 2536 | AR56: 0.05 | AS56: g (>) | AT56: NA (not reported) | AV56: NA | AW56: 3 - conceptual | AY56: LR
A57: validated - discarded | B57: double | C57: Fabienne | E57: additional_studies11_1 | F57: additional_studies11_zc | G57: Julia Fabienne Sandkühler | H57: 45637 | I57: 45692 | J57: replication N refers to number of couples | L57: Saxey, M. T., LeBaron-Black, A. B., & Curran, M. A. (2022). The Sooner, the Better? Couples' First Financial Discussion, Relationship Quality, and Financial Conflict in Emerging Adulthood. Journal of Financial Therapy, 13 (1) 2. https://doi.org/10.4148/1944-9771.1299 | M57: 10.4148/1944-9771.1299 | O57: 10.4148--1944-9771.1299.pdf | P57: {=HYPERLINK(INDEX('File Links'!B:B, MATCH(O57, 'File Links'!C:C, 0)))} -> https://drive.google.com/file/d/1OByNKNsjZqSFHFFyt-o1mPqDkVmgruBu/view?usp=drivesdk | Q57: Saxey, M. T., LeBaron‐Black, A. B., Inman, N. F., Yorgason, J. B., & Holmes, E. K. (2024). The earlier couples first discussed finances, the better? A dyadic, longitudinal replication and extension. Family Relations. https://doi.org/10.1111/fare.13030 | R57: 10.1111/fare.13030 | U57: .pdf | V57: dyadic, longitudinal replication and extension | W57: {=HYPERLINK(INDEX('File Links'!B:B, MATCH(U57, 'File Links'!C:C, 0)))} -> #N/A | Y57: Social Psychology | AA57: emerging adulthood; financial communication; financial conflict; financial discussion, relationship quality | AB57: Direct effect present for financial conflict (replication: longitudinal, wives' answers, effect on themselves) | AC57: Direct effect present for financial conflict: “However, having an earlier first financial discussion as a couple was also positively associated with financial conflict.” (p. 1, emphasised in original) (also p. 11: "The pathway from the first financial discussion to financial conflict through financial communication was significant (β = -.06; p < .001), but the direct effect was also significant (p < .05).") | AD57: 1 | AE57: 1950 | AG57: beta | AH57: p. 11 | AI57: 0.05 | AJ57: g (>) | AK57: NA (not reported) | AM57: NA | AN57: 1079 | AP57: beta (std) | AQ57: p. 2539 | AR57: 0.05 | AS57: g (>) | AT57: NA (not reported) | AV57: NA | AW57: 3 - conceptual | AY57: LR
A58: validated - discarded | B58: double | C58: Fabienne | E58: additional_studies11_1 | F58: additional_studies11_zd | G58: Julia Fabienne Sandkühler | H58: 45637 | I58: 45692 | J58: replication N refers to number of couples | L58: Saxey, M. T., LeBaron-Black, A. B., & Curran, M. A. (2022). The Sooner, the Better? Couples' First Financial Discussion, Relationship Quality, and Financial Conflict in Emerging Adulthood. Journal of Financial Therapy, 13 (1) 2. https://doi.org/10.4148/1944-9771.1299 | M58: 10.4148/1944-9771.1299 | O58: 10.4148--1944-9771.1299.pdf | P58: {=HYPERLINK(INDEX('File Links'!B:B, MATCH(O58, 'File Links'!C:C, 0)))} -> https://drive.google.com/file/d/1OByNKNsjZqSFHFFyt-o1mPqDkVmgruBu/view?usp=drivesdk | Q58: Saxey, M. T., LeBaron‐Black, A. B., Inman, N. F., Yorgason, J. B., & Holmes, E. K. (2024). The earlier couples first discussed finances, the better? A dyadic, longitudinal replication and extension. Family Relations. https://doi.org/10.1111/fare.13030 | R58: 10.1111/fare.13030 | U58: .pdf | V58: dyadic, longitudinal replication and extension | W58: {=HYPERLINK(INDEX('File Links'!B:B, MATCH(U58, 'File Links'!C:C, 0)))} -> #N/A | Y58: Social Psychology | AA58: emerging adulthood; financial communication; financial conflict; financial discussion, relationship quality | AB58: Direct effect present for financial conflict (replication: longitudinal, wives' answers, effect on partner) | AC58: Direct effect present for financial conflict: “However, having an earlier first financial discussion as a couple was also positively associated with financial conflict.” (p. 1, emphasised in original) (also p. 11: "The pathway from the first financial discussion to financial conflict through financial communication was significant (β = -.06; p < .001), but the direct effect was also significant (p < .05).") | AD58: 1 | AE58: 1950 | AG58: beta | AH58: p. 11 | AI58: 0.05 | AJ58: g (>) | AK58: NA (not reported) | AM58: NA | AN58: 1079 | AP58: beta (std) | AQ58: p. 2539 | AR58: 0.05 | AS58: g (>) | AT58: NA (not reported) | AV58: NA | AW58: 3 - conceptual | AY58: LR
A59: validated - discarded | B59: double | C59: Fabienne | E59: additional_studies11_1 | F59: additional_studies11_ze | G59: Julia Fabienne Sandkühler | H59: 45637 | I59: 45692 | J59: replication N refers to number of couples | L59: Saxey, M. T., LeBaron-Black, A. B., & Curran, M. A. (2022). The Sooner, the Better? Couples' First Financial Discussion, Relationship Quality, and Financial Conflict in Emerging Adulthood. Journal of Financial Therapy, 13 (1) 2. https://doi.org/10.4148/1944-9771.1299 | M59: 10.4148/1944-9771.1299 | O59: 10.4148--1944-9771.1299.pdf | P59: {=HYPERLINK(INDEX('File Links'!B:B, MATCH(O59, 'File Links'!C:C, 0)))} -> https://drive.google.com/file/d/1OByNKNsjZqSFHFFyt-o1mPqDkVmgruBu/view?usp=drivesdk | Q59: Saxey, M. T., LeBaron‐Black, A. B., Inman, N. F., Yorgason, J. B., & Holmes, E. K. (2024). The earlier couples first discussed finances, the better? A dyadic, longitudinal replication and extension. Family Relations. https://doi.org/10.1111/fare.13030 | R59: 10.1111/fare.13030 | U59: .pdf | V59: dyadic, longitudinal replication and extension | W59: {=HYPERLINK(INDEX('File Links'!B:B, MATCH(U59, 'File Links'!C:C, 0)))} -> #N/A | Y59: Social Psychology | AA59: emerging adulthood; financial communication; financial conflict; financial discussion, relationship quality | AB59: Direct effect present for financial conflict (replication: longitudinal, husbands' answers, effect on themselves) | AC59: Direct effect present for financial conflict: “However, having an earlier first financial discussion as a couple was also positively associated with financial conflict.” (p. 1, emphasised in original) (also p. 11: "The pathway from the first financial discussion to financial conflict through financial communication was significant (β = -.06; p < .001), but the direct effect was also significant (p < .05).") | AD59: 1 | AE59: 1950 | AG59: beta | AH59: p. 11 | AI59: 0.05 | AJ59: g (>) | AK59: NA (not reported) | AM59: NA | AN59: 1079 | AP59: beta (std) | AQ59: p. 2539 | AR59: 0.05 | AS59: g (>) | AT59: NA (not reported) | AV59: NA | AW59: 3 - conceptual | AY59: LR
A60: validated - discarded | B60: double | C60: Fabienne | E60: additional_studies11_1 | F60: additional_studies11_zf | G60: Julia Fabienne Sandkühler | H60: 45637 | I60: 45692 | J60: replication N refers to number of couples | L60: Saxey, M. T., LeBaron-Black, A. B., & Curran, M. A. (2022). The Sooner, the Better? Couples' First Financial Discussion, Relationship Quality, and Financial Conflict in Emerging Adulthood. Journal of Financial Therapy, 13 (1) 2. https://doi.org/10.4148/1944-9771.1299 | M60: 10.4148/1944-9771.1299 | O60: 10.4148--1944-9771.1299.pdf | P60: {=HYPERLINK(INDEX('File Links'!B:B, MATCH(O60, 'File Links'!C:C, 0)))} -> https://drive.google.com/file/d/1OByNKNsjZqSFHFFyt-o1mPqDkVmgruBu/view?usp=drivesdk | Q60: Saxey, M. T., LeBaron‐Black, A. B., Inman, N. F., Yorgason, J. B., & Holmes, E. K. (2024). The earlier couples first discussed finances, the better? A dyadic, longitudinal replication and extension. Family Relations. https://doi.org/10.1111/fare.13030 | R60: 10.1111/fare.13030 | U60: .pdf | V60: dyadic, longitudinal replication and extension | W60: {=HYPERLINK(INDEX('File Links'!B:B, MATCH(U60, 'File Links'!C:C, 0)))} -> #N/A | Y60: Social Psychology | AA60: emerging adulthood; financial communication; financial conflict; financial discussion, relationship quality | AB60: Direct effect present for financial conflict (replication: longitudinal, husbands' answers, effect on partner) | AC60: Direct effect present for financial conflict: “However, having an earlier first financial discussion as a couple was also positively associated with financial conflict.” (p. 1, emphasised in original) (also p. 11: "The pathway from the first financial discussion to financial conflict through financial communication was significant (β = -.06; p < .001), but the direct effect was also significant (p < .05).") | AD60: 1 | AE60: 1950 | AG60: beta | AH60: p. 11 | AI60: 0.05 | AJ60: g (>) | AK60: NA (not reported) | AM60: NA | AN60: 1079 | AP60: beta (std) | AQ60: p. 2539 | AR60: 0.05 | AS60: g (>) | AT60: NA (not reported) | AV60: NA | AW60: 3 - conceptual | AY60: LR
A61: validated - chosen | B61: double | C61: Hakile | E61: additional_studies11_1 | F61: additional_studies11_a | G61: Hakile | H61: 45686 | I61: 45692 | K61: many different effect sizes and models, I chose the first ones; also, R has dyads and also includes effects from one partner to the other | L61: Saxey, M. T., LeBaron-Black, A. B., & Curran, M. A. (2022). The Sooner, the Better? Couples' First Financial Discussion, Relationship Quality, and Financial Conflict in Emerging Adulthood. Journal of Financial Therapy, 13 (1) 2. https://doi.org/10.4148/1944-9771.1299 | M61: 10.4148/1944-9771.1299 | O61: 10.4148--1944-9771.1299.pdf | P61: {=HYPERLINK(INDEX('File Links'!B:B, MATCH(O61, 'File Links'!C:C, 0)))} -> https://drive.google.com/file/d/1OByNKNsjZqSFHFFyt-o1mPqDkVmgruBu/view?usp=drivesdk | Q61: Saxey, M. T., LeBaron‐Black, A. B., Inman, N. F., Yorgason, J. B., & Holmes, E. K. (2024). The earlier couples first discussed finances, the better? A dyadic, longitudinal replication and extension. Family Relations. https://doi.org/10.1111/fare.13030 | R61: 10.1111/fare.13030 | U61: .pdf | V61: dyadic, longitudinal replication and extension | W61: {=HYPERLINK(INDEX('File Links'!B:B, MATCH(U61, 'File Links'!C:C, 0)))} -> #N/A | Y61: Social Psychology | Z61: First Financial Discussion Effect | AA61: emerging adulthood; financial communication; financial conflict; financial discussion, relationship quality | AB61: Effect of Financial Communication on Relationship Satisfaction | AC61: couples’ first financial discussion was directly associated with their financial communication (β = .23; p < .001) | AD61: 13 | AE61: 1950 | AF61: 0.23 | AG61: beta (std) | AH61: p. 13 | AI61: 0.001 | AJ61: l (<) | AK61: NA (not reported) | AL61: no | AM61: NA | AN61: 1079 | AO61: 0.16 | AP61: beta (std) | AQ61: pp. 10-11 wives | AR61: 0.001 | AS61: l (<) | AT61: NA (not reported) | AU61: yes | AV61: NA | AW61: 1 - internal | AY61: LR
A62: validated - chosen | B62: double | C62: Hakile | E62: additional_studies11_1 | F62: additional_studies11_a | G62: Hakile | H62: 45686 | I62: 45692 | K62: many different effect sizes and models, I chose the first ones; also, R has dyads and also includes effects from one partner to the other | L62: Saxey, M. T., LeBaron-Black, A. B., & Curran, M. A. (2022). The Sooner, the Better? Couples' First Financial Discussion, Relationship Quality, and Financial Conflict in Emerging Adulthood. Journal of Financial Therapy, 13 (1) 2. https://doi.org/10.4148/1944-9771.1299 | M62: 10.4148/1944-9771.1299 | O62: 10.4148--1944-9771.1299.pdf | P62: {=HYPERLINK(INDEX('File Links'!B:B, MATCH(O62, 'File Links'!C:C, 0)))} -> https://drive.google.com/file/d/1OByNKNsjZqSFHFFyt-o1mPqDkVmgruBu/view?usp=drivesdk | Q62: Saxey, M. T., LeBaron‐Black, A. B., Inman, N. F., Yorgason, J. B., & Holmes, E. K. (2024). The earlier couples first discussed finances, the better? A dyadic, longitudinal replication and extension. Family Relations. https://doi.org/10.1111/fare.13030 | R62: 10.1111/fare.13030 | U62: .pdf | V62: dyadic, longitudinal replication and extension | W62: {=HYPERLINK(INDEX('File Links'!B:B, MATCH(U62, 'File Links'!C:C, 0)))} -> #N/A | Y62: Social Psychology | Z62: First Financial Discussion Effect | AA62: emerging adulthood; financial communication; financial conflict; financial discussion, relationship quality | AB62: Effect of Financial Communication on Relationship Satisfaction | AC62: couples’ first financial discussion was directly associated with their financial communication (β = .23; p < .001) | AD62: 13 | AE62: 1950 | AF62: 0.23 | AG62: beta (std) | AH62: p. 13 | AI62: 0.001 | AJ62: l (<) | AK62: NA (not reported) | AL62: no | AM62: NA | AN62: 1079 | AO62: 0.1 | AP62: beta (std) | AQ62: pp. 10-11 husbands | AR62: 0.05 | AS62: l (<) | AT62: NA (not reported) | AU62: yes | AV62: NA | AW62: 1 - internal | AY62: LR
A63: validated - chosen | B63: double | C63: Hakile | E63: additional_studies11_1 | F63: additional_studies11_b | G63: Hakile | H63: 45686 | I63: 45692 | K63: many different effect sizes and models, I chose the first ones; also, R has dyads and also includes effects from one partner to the other | L63: Saxey, M. T., LeBaron-Black, A. B., & Curran, M. A. (2022). The Sooner, the Better? Couples' First Financial Discussion, Relationship Quality, and Financial Conflict in Emerging Adulthood. Journal of Financial Therapy, 13 (1) 2. https://doi.org/10.4148/1944-9771.1299 | M63: 10.4148/1944-9771.1299 | O63: 10.4148--1944-9771.1299.pdf | P63: {=HYPERLINK(INDEX('File Links'!B:B, MATCH(O63, 'File Links'!C:C, 0)))} -> https://drive.google.com/file/d/1OByNKNsjZqSFHFFyt-o1mPqDkVmgruBu/view?usp=drivesdk | Q63: Saxey, M. T., LeBaron‐Black, A. B., Inman, N. F., Yorgason, J. B., & Holmes, E. K. (2024). The earlier couples first discussed finances, the better? A dyadic, longitudinal replication and extension. Family Relations. https://doi.org/10.1111/fare.13030 | R63: 10.1111/fare.13030 | U63: .pdf | V63: dyadic, longitudinal replication and extension | W63: {=HYPERLINK(INDEX('File Links'!B:B, MATCH(U63, 'File Links'!C:C, 0)))} -> #N/A | Y63: Social Psychology | Z63: First Financial Discussion Effect | AA63: emerging adulthood; financial communication; financial conflict; financial discussion, relationship quality | AB63: Effect of Financial Communication on Reducing Financial Disagreements | AC63: couples’ first financial discussion was directly associated with their ... financial conflict (β = .07; p < .05). | AD63: 13 | AE63: 1950 | AF63: 0.07 | AG63: beta (std) | AH63: p. 13 | AI63: 0.05 | AJ63: l (<) | AK63: NA (not reported) | AL63: no | AM63: NA | AN63: 1079 | AO63: -0.42 | AP63: beta (std) | AQ63: pp. 10-11 wives | AR63: 0.001 | AS63: l (<) | AT63: NA (not reported) | AU63: yes | AV63: NA | AW63: 1 - internal | AY63: LR
A64: validated - chosen | B64: double | C64: Hakile | E64: additional_studies11_1 | F64: additional_studies11_b | G64: Hakile | H64: 45686 | I64: 45692 | K64: many different effect sizes and models, I chose the first ones; also, R has dyads and also includes effects from one partner to the other | L64: Saxey, M. T., LeBaron-Black, A. B., & Curran, M. A. (2022). The Sooner, the Better? Couples' First Financial Discussion, Relationship Quality, and Financial Conflict in Emerging Adulthood. Journal of Financial Therapy, 13 (1) 2. https://doi.org/10.4148/1944-9771.1299 | M64: 10.4148/1944-9771.1299 | O64: 10.4148--1944-9771.1299.pdf | P64: {=HYPERLINK(INDEX('File Links'!B:B, MATCH(O64, 'File Links'!C:C, 0)))} -> https://drive.google.com/file/d/1OByNKNsjZqSFHFFyt-o1mPqDkVmgruBu/view?usp=drivesdk | Q64: Saxey, M. T., LeBaron‐Black, A. B., Inman, N. F., Yorgason, J. B., & Holmes, E. K. (2024). The earlier couples first discussed finances, the better? A dyadic, longitudinal replication and extension. Family Relations. https://doi.org/10.1111/fare.13030 | R64: 10.1111/fare.13030 | U64: .pdf | V64: dyadic, longitudinal replication and extension | W64: {=HYPERLINK(INDEX('File Links'!B:B, MATCH(U64, 'File Links'!C:C, 0)))} -> #N/A | Y64: Social Psychology | Z64: First Financial Discussion Effect | AA64: emerging adulthood; financial communication; financial conflict; financial discussion, relationship quality | AB64: Effect of Financial Communication on Reducing Financial Disagreements | AC64: couples’ first financial discussion was directly associated with their ... financial conflict (β = .07; p < .05). | AD64: 13 | AE64: 1950 | AF64: 0.07 | AG64: beta (std) | AH64: p. 13 | AI64: 0.05 | AJ64: l (<) | AK64: NA (not reported) | AL64: no | AM64: NA | AN64: 1079 | AO64: -0.41 | AP64: beta (std) | AQ64: pp. 10-11 husbands | AR64: 0.001 | AS64: l (<) | AT64: NA (not reported) | AU64: yes | AV64: NA | AW64: 1 - internal | AY64: LR
A65: validated - discarded | B65: double | C65: Antony | E65: additional_studies12_1 | F65: additional_studies12 | G65: Antony Casula | H65: 45636 | J65: Sample sizes extracted from df. | K65: - missed the study number - make sure to review and correct text that is copied (special characters were missing) | L65: Stellar, J. E., Gordon, A., Anderson, C. L., Piff, P. K., McNeil, G. D., & Keltner, D. (2018). Awe and humility. Journal of Personality and Social Psychology, 114(2), 258–269. https://doi.org/10.1037/pspi0000109 | M65: 10.1037/pspi0000109 | O65: 10.1037--pspi0000109.pdf | P65: {=HYPERLINK(INDEX('File Links'!B:B, MATCH(O65, 'File Links'!C:C, 0)))} -> https://drive.google.com/file/d/1DO937F2xhbz54X6xu8qtsy63K6O9mEYa/view?usp=drivesdk | Q65: Bertrand, A., Kimmel, J., Duhamel, S., Puel, H., Schifano, A., & Wood, É. (2024). A Replication Study to Evaluate the Effects of Awe on Humility. McGill Science Undergraduate Research Journal, 19(1), 39-45. https://doi.org/10.26443/msurj.v19i1.231 | R65: 10.26443/msurj.v19i1.231 | U65: 10.26443--msurj.v19i1.231.pdf | V65: Replication | W65: {=HYPERLINK(INDEX('File Links'!B:B, MATCH(U65, 'File Links'!C:C, 0)))} -> https://drive.google.com/file/d/12ZFslJnsSmpbIBYf9YKunwP3Ofv14HZ-/view?usp=drivesdk | Y65: Social Psychology | AA65: awe, humilty, vastness, world views | AB65: "Inducing awe led participants to present a more balanced view of their strengths and weaknesses to others (Study 3)." | AC65: "awe and neutral conditions had a different balance between disclosing their strengths and weaknesses, t(84) = 2.38, p = .02." | AD65: 263 | AE65: 86 | AF65: t(84) = 2.38 | AG65: test statistics | AH65: p. 263 | AI65: 0.02 | AJ65: e (=) | AK65: NA (not reported) | AL65: no | AN65: 71 | AO65: t(69) = –0.34 | AP65: test statistic | AQ65: p.41 | AR65: 0.438 | AS65: e (=) | AT65: NA (not reported) | AU65: no | AW65: 2 - close | AX65: - missed the study number - make sure to review and correct text that is copied (special characters were missing) | AY65: LR
A66: validated - chosen | B66: double | C66: Fabienne | E66: additional_studies12_1 | F66: additional_studies12 | G66: Julia Fabienne Sandkühler | H66: 45639 | I66: 45663 | J66: Replication might be preregistered, unclear. They mention that data exclusion was not preregistered, so they did not do it. However, I don't find a link to their preregistration. | K66: There is a reporting error in the paper: N = 85 but t(84) and df = N-2. Feedback for Fabienne - make sure to review and correct text that is copied (special characters were missing) - you entered N = 85 with t(84) and Ntotal = 85. I was about to correct it to N = 86 because N = t-2 for two sample t tests but there appears to be an error in the manuscript in the reporting of the DFs. - I could not find the effect size cohen's d that you entered (d = .57) in the original report so I replaced it with the test statistic. Please make sure to use only data from the original report for the _o variables - As you linked a website to calculate Cohen's d: We added a sheet to the spreadsheet which allows for effect size calculation that you can use next time, but test statistics would have been fine here, too! | L66: Stellar, J. E., Gordon, A., Anderson, C. L., Piff, P. K., McNeil, G. D., & Keltner, D. (2018). Awe and humility. Journal of Personality and Social Psychology, 114(2), 258–269. https://doi.org/10.1037/pspi0000109 | M66: 10.1037/pspi0000109 | N66: 3 | O66: 10.1037--pspi0000109.pdf | P66: {=HYPERLINK(INDEX('File Links'!B:B, MATCH(O66, 'File Links'!C:C, 0)))} -> https://drive.google.com/file/d/1DO937F2xhbz54X6xu8qtsy63K6O9mEYa/view?usp=drivesdk | Q66: Bertrand, A., Kimmel, J., Duhamel, S., Puel, H., Schifano, A., & Wood, É. (2024). A Replication Study to Evaluate the Effects of Awe on Humility. McGill Science Undergraduate Research Journal, 19(1), 39-45. https://doi.org/10.26443/msurj.v19i1.231 | R66: 10.26443/msurj.v19i1.231 | T66: 1 | U66: 10.26443--msurj.v19i1.231.pdf | V66: Replication | W66: {=HYPERLINK(INDEX('File Links'!B:B, MATCH(U66, 'File Links'!C:C, 0)))} -> https://drive.google.com/file/d/12ZFslJnsSmpbIBYf9YKunwP3Ofv14HZ-/view?usp=drivesdk | Y66: Social Psychology | AA66: humility, awe, emotion, self-concept | AB66: Awe leads to humility | AC66: "awe and neutral conditions had a different balance between disclosing their strengths and weaknesses, t(84) = 2.38, p = .02." | AD66: 263 | AE66: 85 | AF66: t(84) = 2.38 | AG66: test statistics | AH66: p. 263 | AI66: 0.02 | AJ66: e (=) | AK66: NA (not reported) | AL66: no | AM66: NA | AN66: 71 | AO66: t(69) = –0.34 | AP66: test statistic | AQ66: p.41 | AR66: 0.438 | AS66: e (=) | AT66: NA (not reported) | AU66: no | AV66: NA | AW66: 2 - close | AX66: Feedback for Fabienne - make sure to review and correct text that is copied (special characters were missing) - you entered N = 85 with t(84) and Ntotal = 85. I was about to correct it to N = 86 because N = t-2 for two sample t tests but there appears to be an error in the manuscript in the reporting of the DFs. - I could not find the effect size cohen's d that you entered (d = .57) in the original report so I replaced it with the test statistic. Please make sure to use only data from the original report for the _o variables - As you linked a website to calculate Cohen's d: We added a sheet to the spreadsheet which allows for effect size calculation that you can use next time, but test statistics would have been fine here, too! | AY66: LR
A67: validated - discarded | B67: double | C67: Antony | E67: additional_studies12_1 | F67: additional_studies12_b | G67: Antony Casula | H67: 45636 | J67: Sample sizes extracted from df. | L67: Stellar, J. E., Gordon, A., Anderson, C. L., Piff, P. K., McNeil, G. D., & Keltner, D. (2018). Awe and humility. Journal of Personality and Social Psychology, 114(2), 258–269. https://doi.org/10.1037/pspi0000109 | M67: 10.1037/pspi0000109 | O67: 10.1037--pspi0000109.pdf | P67: {=HYPERLINK(INDEX('File Links'!B:B, MATCH(O67, 'File Links'!C:C, 0)))} -> https://drive.google.com/file/d/1DO937F2xhbz54X6xu8qtsy63K6O9mEYa/view?usp=drivesdk | Q67: Bertrand, A., Kimmel, J., Duhamel, S., Puel, H., Schifano, A., & Wood, É. (2024). A Replication Study to Evaluate the Effects of Awe on Humility. McGill Science Undergraduate Research Journal, 19(1), 39-45. https://doi.org/10.26443/msurj.v19i1.231 | R67: 10.26443/msurj.v19i1.231 | U67: 10.26443--msurj.v19i1.231.pdf | V67: Replication | W67: {=HYPERLINK(INDEX('File Links'!B:B, MATCH(U67, 'File Links'!C:C, 0)))} -> https://drive.google.com/file/d/12ZFslJnsSmpbIBYf9YKunwP3Ofv14HZ-/view?usp=drivesdk | Y67: Social Psychology | AA67: awe, humilty, vastness, world views | AB67: "Inducing awe led participants to present a more balanced view of their strengths and weaknesses to others (Study 3)." | AC67: "More specific analyses revealed that participants in the awe condition discussed significantly fewer strengths (M=1.20, SD=.53) before choosing to write about their weaknesses than participants in the neutral condition (M =1.48, SD=.44), t(84)=2.64, p= .01,..." | AD67: 263 | AE67: 86 | AF67: t(84)=2.64 | AG67: test statistics | AH67: p. 263 | AI67: 0.01 | AJ67: e (=) | AK67: NA (not reported) | AL67: no | AN67: 93 | AO67: t(91) = 0.85, | AP67: test statistic | AQ67: p.41 | AR67: 0.397 | AS67: e (=) | AT67: NA (not reported) | AU67: no | AW67: 2 - close | AY67: LR
A68: validated - chosen | B68: double | C68: Fabienne | E68: additional_studies12_1 | F68: additional_studies12_b | G68: Julia Fabienne Sandkühler | H68: 45639 | I68: 45663 | J68: Replication might be preregistered, unclear. They mention that data exclusion was not preregistered, so they did not do it. However, I don't find a link to their preregistration. | L68: Stellar, J. E., Gordon, A., Anderson, C. L., Piff, P. K., McNeil, G. D., & Keltner, D. (2018). Awe and humility. Journal of Personality and Social Psychology, 114(2), 258–269. https://doi.org/10.1037/pspi0000109 | M68: 10.1037/pspi0000109 | N68: 3 | O68: 10.1037--pspi0000109.pdf | P68: {=HYPERLINK(INDEX('File Links'!B:B, MATCH(O68, 'File Links'!C:C, 0)))} -> https://drive.google.com/file/d/1DO937F2xhbz54X6xu8qtsy63K6O9mEYa/view?usp=drivesdk | Q68: Bertrand, A., Kimmel, J., Duhamel, S., Puel, H., Schifano, A., & Wood, É. (2024). A Replication Study to Evaluate the Effects of Awe on Humility. McGill Science Undergraduate Research Journal, 19(1), 39-45. https://doi.org/10.26443/msurj.v19i1.231 | R68: 10.26443/msurj.v19i1.231 | T68: 1 | U68: 10.26443--msurj.v19i1.231.pdf | V68: Replication | W68: {=HYPERLINK(INDEX('File Links'!B:B, MATCH(U68, 'File Links'!C:C, 0)))} -> https://drive.google.com/file/d/12ZFslJnsSmpbIBYf9YKunwP3Ofv14HZ-/view?usp=drivesdk | Y68: Social Psychology | AA68: humility, awe, emotion, self-concept | AB68: Awe leads to humility | AC68: "More specific analyses revealed that participants in the awe condition discussed significantly fewer strengths (M=1.20, SD=.53) before choosing to write about their weaknesses than participants in the neutral condition (M =1.48, SD=.44), t(84)=2.64, p= .01,..." | AD68: 263 | AE68: 85 | AF68: t(84)=2.64 | AG68: test statistics | AH68: p. 263 | AI68: 0.02 | AJ68: e (=) | AK68: NA (not reported) | AL68: no | AM68: NA | AN68: 93 | AO68: t(91) = 0.85, | AP68: test statistic | AQ68: p. 41: "The analyses showed that participants in the awe and the neutral conditiondid not significantly differ in their balance between strengths and weak-nesses disclosed (i.e., their humility score,t(69) = –0.34,p= 0.438); see Ap-pendix D for more information. This contradicts the original study, wherea significant difference was found,t(84) = 2.38,p= 0.02", Appendix D: "Humility scores in the awe condition (M= 0.16,SD= 0.16) when compared to the neutral condition (M= 0.17,SD= 0.16) were notsignificantly differentt(69) = –0.34,p= 0.438" https://www.socscistatistics.com/effectsize/default3.aspx. I assumed both groups were of equal size, i.e. had 70/2 = 35 participants. | AR68: 0.397 | AS68: e (=) | AT68: NA (not reported) | AU68: no | AV68: NA | AW68: 2 - close | AY68: LR
A69: validated - chosen | B69: double | C69: Antony | E69: additional_studies12_1 | F69: additional_studies12_c | G69: Antony Casula | H69: 45636 | I69: 45663 | J69: Sample sizes extracted from df. | L69: Stellar, J. E., Gordon, A., Anderson, C. L., Piff, P. K., McNeil, G. D., & Keltner, D. (2018). Awe and humility. Journal of Personality and Social Psychology, 114(2), 258–269. https://doi.org/10.1037/pspi0000109 | M69: 10.1037/pspi0000109 | N69: 3 | O69: 10.1037--pspi0000109.pdf | P69: {=HYPERLINK(INDEX('File Links'!B:B, MATCH(O69, 'File Links'!C:C, 0)))} -> https://drive.google.com/file/d/1DO937F2xhbz54X6xu8qtsy63K6O9mEYa/view?usp=drivesdk | Q69: Bertrand, A., Kimmel, J., Duhamel, S., Puel, H., Schifano, A., & Wood, É. (2024). A Replication Study to Evaluate the Effects of Awe on Humility. McGill Science Undergraduate Research Journal, 19(1), 39-45. https://doi.org/10.26443/msurj.v19i1.231 | R69: 10.26443/msurj.v19i1.231 | T69: 1 | U69: 10.26443--msurj.v19i1.231.pdf | V69: Replication | W69: {=HYPERLINK(INDEX('File Links'!B:B, MATCH(U69, 'File Links'!C:C, 0)))} -> https://drive.google.com/file/d/12ZFslJnsSmpbIBYf9YKunwP3Ofv14HZ-/view?usp=drivesdk | Y69: Social Psychology | AA69: awe, humilty, vastness, world views | AB69: "Inducing awe led participants to present a more balanced view of their strengths and weaknesses to others (Study 3)." | AC69: "...there was no effect of condition on the number of weaknesses participants listed (awe: M= .82, SD =.58; neutral: M = .79, SD=.49), t(84)=.27, p =.79." | AD69: 263 | AE69: 86 | AF69: t(84)=.27 | AG69: test statistics | AH69: p. 263 | AI69: 0.79 | AJ69: e (=) | AK69: NA (not reported) | AL69: no | AM69: NA | AN69: 84 | AO69: t(82)=0.5 | AP69: test statistic | AQ69: p.41 | AR69: 0.618 | AS69: e (=) | AT69: NA (not reported) | AU69: no | AV69: NA | AW69: 2 - close | AY69: LR
A70: validated - discarded | B70: double | C70: Husnain | E70: additional_studies125_1 | F70: additional_studies125 | G70: Husnain | H70: 45636 | I70: 45679 | J70: 1. In the orignal study, I have used claims from the page 1 because they were well summarised. However, I have reported results seprately for effect size and P value | K70: Changed label_r to "replication" instead of "Close Replication"; added tags that are also found in paper, changed n to 39; changed nested_o to yes, changed p_val_tails; changed pval_value_o to 0.025 | L70: Johnston, W., Dolan, K., Reid, N., Coughlan, G. F., & Caulfield, B. (2018). Investigating the effects of maximal anaerobic fatigue on dynamic postural control using the Y-Balance Test. Journal of science and medicine in sport, 21(1), 103-108. https://doi.org/10.1016/j.jsams.2017.06.007 | M70: 10.1016/j.jsams.2017.06.007 | N70: 1 | O70: 10.1016--j.jsams.2017.06.007.pdf | P70: {=HYPERLINK(INDEX('File Links'!B:B, MATCH(O70, 'File Links'!C:C, 0)))} -> https://drive.google.com/file/d/1bOamtHkDDCeR5rldqOBSgCXc_AFZb3yD/view?usp=drivesdk | Q70: Byrne, C., Murphy, J., & Warne, J. P. (2024). Replication Study: Investigating the effects of maximal anaerobic fatigue on dynamic postural control using the Y-Balance Test. Journal of Science and Medicine in Sport. https://doi.org/10.1016/j.jsams.2024.07.018 | R70: 10.1016/j.jsams.2024.07.018 | T70: 1 | U70: 10.1016--j.jsams.2024.07.018.pdf | V70: Replication | W70: {=HYPERLINK(INDEX('File Links'!B:B, MATCH(U70, 'File Links'!C:C, 0)))} -> https://drive.google.com/file/d/1iWxdhqxc4T6twXLJR2WbGMzAHqB2cMPh/view?usp=drivesdk | Y70: Science and Medicine in Sport | Z70: maximal anaerobic fatigue | AA70: Dynamic postural control, Dynamic balance, Y-Balance Test, Fatigue, Replication, Balance, Anterior reach direction, Posterolateral reach direction, Posteromedial reach direction | AB70: Maximal anaerobic fatigue significantly reduces Y-Balance Test scores in ANT | AC70: "Post-hoc paired sample t-tests demonstrated that all three reach directions demonstrated statistically significant differences between pre-fatigue and the first post-fatigue measurement (ANT: p = 0.019, PM: p = 0.004, PL: p = 0.003)" | AD70: p. 1, 3 | AE70: 20 | AF70: F(3, 57) = 3.818 | AG70: test statistic | AH70: p. 3 | AI70: 0.019 | AJ70: e (=) | AK70: NA (not reported) | AL70: yes | AN70: 39 | AO70: 0.159 | AP70: etasq | AQ70: p.4 | AR70: 0.002 | AS70: e (=) | AT70: NA (not reported) | AU70: no | AW70: 2 - close | AX70: - please report test statistics with all details: F(x, y) = value (and not just the value) | AY70: LR, Sophie
A71: validated - chosen | B71: double | C71: Nikita | E71: additional_studies125_1 | F71: additional_studies125_an | G71: Nikita | H71: 45638 | I71: 45679 | J71: 1. The initial registration of the protocol is under the link: https://osf.io/kqdpm 2. Since one-way rmANOVA was used, the Nested option is "Yes" 3. Degree of freedon for original study was calculated based on number of time measurements (4) and participants (20) | L71: Johnston, W., Dolan, K., Reid, N., Coughlan, G. F., & Caulfield, B. (2018). Investigating the effects of maximal anaerobic fatigue on dynamic postural control using the Y-Balance Test. Journal of science and medicine in sport, 21(1), 103-108. https://doi.org/10.1016/j.jsams.2017.06.007 | M71: 10.1016/j.jsams.2017.06.007 | N71: 1 | O71: 10.1016--j.jsams.2017.06.007.pdf | P71: {=HYPERLINK(INDEX('File Links'!B:B, MATCH(O71, 'File Links'!C:C, 0)))} -> https://drive.google.com/file/d/1bOamtHkDDCeR5rldqOBSgCXc_AFZb3yD/view?usp=drivesdk | Q71: Byrne, C., Murphy, J., & Warne, J. P. (2024). Replication Study: Investigating the effects of maximal anaerobic fatigue on dynamic postural control using the Y-Balance Test. Journal of Science and Medicine in Sport. https://doi.org/10.1016/j.jsams.2024.07.018 | R71: 10.1016/j.jsams.2024.07.018 | T71: 1 | U71: 10.1016--j.jsams.2024.07.018.pdf | V71: Replication | W71: {=HYPERLINK(INDEX('File Links'!B:B, MATCH(U71, 'File Links'!C:C, 0)))} -> https://drive.google.com/file/d/1iWxdhqxc4T6twXLJR2WbGMzAHqB2cMPh/view?usp=drivesdk | Y71: Medicine | Z71: Dynamic postural control | AA71: Dynamic postural control, Dynamic balance, Y-Balance Test, Fatigue, Replication, Balance, Anterior reach direction, Posterolateral reach direction, Posteromedial reach direction | AB71: Investigating the effects of maximal anaerobic fatigue on dynamic postural control with Y Balance test by comparing pre-fatigue and post-fatigue (0, 10, 20 min) in anterior direction | AC71: "A repeated measures ANOVA with a Greenhouse-Geisser correction determined that the mean reach distances for the anterior (F = 3.818, p = 0.025) reach directions were statistically significantly different between time points." | AD71: 3 | AE71: 20 | AF71: F(3, 57) = 3.818 | AG71: test statistic | AH71: p.3 | AI71: 0.025 | AJ71: e (=) | AK71: NA (not reported) | AL71: yes | AN71: 39 | AO71: 0.159 | AP71: etasq | AQ71: p.4 | AR71: 0.002 | AS71: e (=) | AT71: NA (not reported) | AU71: no | AV71: https://osf.io/5beqa | AW71: 2 - close | AX71: - please choose "NA" for pval_tails, when the paper does not clearly state it. Even if an F-Test is used | AY71: LR, Sophie
A72: validated - discarded | B72: double | C72: Husnain | E72: additional_studies125_1 | F72: additional_studies125_b | G72: Husnain | H72: 45636 | I72: 45679 | J72: 1. In the orignal study, I have used claims from the page 1 because they were well summarised. However, I have reported results seprately for effect size and P value | K72: changed pval_value_o to 0.0004 here it says not replicated, therefore other entry for this claim was chosen and this discarded | L72: Johnston, W., Dolan, K., Reid, N., Coughlan, G. F., & Caulfield, B. (2018). Investigating the effects of maximal anaerobic fatigue on dynamic postural control using the Y-Balance Test. Journal of science and medicine in sport, 21(1), 103-108. https://doi.org/10.1016/j.jsams.2017.06.008 | M72: 10.1016/j.jsams.2017.06.007 | N72: 1 | O72: 10.1016--j.jsams.2017.06.007.pdf | P72: {=HYPERLINK(INDEX('File Links'!B:B, MATCH(O72, 'File Links'!C:C, 0)))} -> https://drive.google.com/file/d/1bOamtHkDDCeR5rldqOBSgCXc_AFZb3yD/view?usp=drivesdk | Q72: Byrne, C., Murphy, J., & Warne, J. P. (2024). Replication Study: Investigating the effects of maximal anaerobic fatigue on dynamic postural control using the Y-Balance Test. Journal of Science and Medicine in Sport. https://doi.org/10.1016/j.jsams.2024.07.018 | R72: 10.1016/j.jsams.2024.07.018 | T72: 1 | U72: 10.1016--j.jsams.2024.07.018.pdf | V72: Replication | W72: {=HYPERLINK(INDEX('File Links'!B:B, MATCH(U72, 'File Links'!C:C, 0)))} -> https://drive.google.com/file/d/1iWxdhqxc4T6twXLJR2WbGMzAHqB2cMPh/view?usp=drivesdk | X72: Not replicated | Y72: Science and Medicine in Sport | Z72: maximal anaerobic fatigue | AA72: Dynamic postural control, Dynamic balance, Y-Balance Test, Fatigue | AB72: Maximal anaerobic fatigue significantly reduces Y-Balance Test scores in PM | AC72: "Post-hoc paired sample t-tests demonstrated that all three reach directions demonstrated statistically significant differences between pre-fatigue and the first post-fatigue measurement (ANT: p = 0.019, PM: p = 0.004, PL: p = 0.003)" | AD72: p. 1, 3 | AE72: 20 | AF72: 6503 | AG72: test statistic | AH72: p. 3 | AI72: 0.0004 | AJ72: e (=) | AK72: NA (not reported) | AL72: no | AX72: - please describe notes in more detail (e.g., what do you mean with "not replicated" - please do not code values for claims for which no replication finding exists - please look closely in the replication paper since here the finding was replicated | AY72: LR, Sophie
A73: validated - discarded | B73: double | C73: Husnain | E73: additional_studies125_1 | F73: additional_studies125_c | G73: Husnain | H73: 45636 | I73: 45679 | J73: 1. In the orignal study, I have used claims from the page 1 because they were well summarised. However, I have reported results seprately for effect size and P value | K73: I dont understand this claim, seems to be the same as above with a different p-value that I cannot find in the original paper. | L73: Johnston, W., Dolan, K., Reid, N., Coughlan, G. F., & Caulfield, B. (2018). Investigating the effects of maximal anaerobic fatigue on dynamic postural control using the Y-Balance Test. Journal of science and medicine in sport, 21(1), 103-108. https://doi.org/10.1016/j.jsams.2017.06.009 | M73: 10.1016/j.jsams.2017.06.007 | N73: 1 | O73: 10.1016--j.jsams.2017.06.007.pdf | P73: {=HYPERLINK(INDEX('File Links'!B:B, MATCH(O73, 'File Links'!C:C, 0)))} -> https://drive.google.com/file/d/1bOamtHkDDCeR5rldqOBSgCXc_AFZb3yD/view?usp=drivesdk | Q73: Byrne, C., Murphy, J., & Warne, J. P. (2024). Replication Study: Investigating the effects of maximal anaerobic fatigue on dynamic postural control using the Y-Balance Test. Journal of Science and Medicine in Sport. https://doi.org/10.1016/j.jsams.2024.07.018 | R73: 10.1016/j.jsams.2024.07.018 | T73: 1 | U73: 10.1016--j.jsams.2024.07.018.pdf | V73: Replication | W73: {=HYPERLINK(INDEX('File Links'!B:B, MATCH(U73, 'File Links'!C:C, 0)))} -> https://drive.google.com/file/d/1iWxdhqxc4T6twXLJR2WbGMzAHqB2cMPh/view?usp=drivesdk | X73: Not replicated | Y73: Science and Medicine in Sport | Z73: maximal anaerobic fatigue | AA73: Dynamic postural control, Dynamic balance, Y-Balance Test, Fatigue | AB73: Maximal anaerobic fatigue significantly reduces Y-Balance Test scores in PL | AC73: "Post-hoc paired sample t-tests demonstrated that all three reach directions demonstrated statistically significant differences between pre-fatigue and the first post-fatigue measurement (ANT: p = 0.019, PM: p = 0.004, PL: p = 0.003)" | AD73: p. 1, 3 | AE73: 20 | AF73: 6503 | AG73: test statistic | AH73: p. 3 | AI73: 0.003 | AJ73: e (=) | AK73: NA (not reported) | AL73: no | AY73: LR, Sophie
A74: awaiting validation | B74: double | C74: Husnain | E74: additional_studies125_1 | F74: additional_studies125_d | G74: Husnain | H74: 45636 | I74: 45679 | J74: 1. In the orignal study, I have used claims from the page 1 because they were well summarised. However, I have reported results seprately for effect size and P value | K74: changed n to 39 | L74: Johnston, W., Dolan, K., Reid, N., Coughlan, G. F., & Caulfield, B. (2018). Investigating the effects of maximal anaerobic fatigue on dynamic postural control using the Y-Balance Test. Journal of science and medicine in sport, 21(1), 103-108. https://doi.org/10.1016/j.jsams.2017.06.010 | M74: 10.1016/j.jsams.2017.06.007 | N74: 1 | O74: 10.1016--j.jsams.2017.06.007.pdf | P74: {=HYPERLINK(INDEX('File Links'!B:B, MATCH(O74, 'File Links'!C:C, 0)))} -> https://drive.google.com/file/d/1bOamtHkDDCeR5rldqOBSgCXc_AFZb3yD/view?usp=drivesdk | Q74: Byrne, C., Murphy, J., & Warne, J. P. (2024). Replication Study: Investigating the effects of maximal anaerobic fatigue on dynamic postural control using the Y-Balance Test. Journal of Science and Medicine in Sport. https://doi.org/10.1016/j.jsams.2024.07.018 | R74: 10.1016/j.jsams.2024.07.018 | T74: 1 | U74: 10.1016--j.jsams.2024.07.018.pdf | V74: Replication | W74: {=HYPERLINK(INDEX('File Links'!B:B, MATCH(U74, 'File Links'!C:C, 0)))} -> https://drive.google.com/file/d/1iWxdhqxc4T6twXLJR2WbGMzAHqB2cMPh/view?usp=drivesdk | Y74: Science and Medicine in Sport | Z74: maximal anaerobic fatigue | AA74: Dynamic postural control, Dynamic balance, Y-Balance Test, Fatigue | AB74: Dynamic postural control for ANT returned to pre-fatigue level with least significant | AC74: "The anterior reach direction returned to pre-fatigue levels within 10 min (p = 0.632). The posteromedial reach direction returned to pre-fatigue levels within 20 min (p = 0.236), while the posterolateral direction maintained a statistically significant difference at 20 min (p = 0.023)" | AD74: p. 1, 4 | AE74: 20 | AI74: 0.632 | AJ74: e (=) | AK74: NA (not reported) | AL74: no | AN74: 39 | AR74: 0.632 | AS74: e (=) | AT74: NA (not reported) | AU74: no | AW74: 2 - close | AX74: - please watch out for the n that was included in analysis and not the n before exclusions were made | AY74: LR, Sophie
A75: awaiting validation | B75: double | C75: Husnain | E75: additional_studies125_1 | F75: additional_studies125_e | G75: Husnain | H75: 45636 | I75: 45679 | J75: 1. In the orignal study, I have used claims from the page 1 because they were well summarised. However, I have reported results seprately for effect size and P value | L75: Johnston, W., Dolan, K., Reid, N., Coughlan, G. F., & Caulfield, B. (2018). Investigating the effects of maximal anaerobic fatigue on dynamic postural control using the Y-Balance Test. Journal of science and medicine in sport, 21(1), 103-108. https://doi.org/10.1016/j.jsams.2017.06.011 | M75: 10.1016/j.jsams.2017.06.007 | N75: 1 | O75: 10.1016--j.jsams.2017.06.007.pdf | P75: {=HYPERLINK(INDEX('File Links'!B:B, MATCH(O75, 'File Links'!C:C, 0)))} -> https://drive.google.com/file/d/1bOamtHkDDCeR5rldqOBSgCXc_AFZb3yD/view?usp=drivesdk | Q75: Byrne, C., Murphy, J., & Warne, J. P. (2024). Replication Study: Investigating the effects of maximal anaerobic fatigue on dynamic postural control using the Y-Balance Test. Journal of Science and Medicine in Sport. https://doi.org/10.1016/j.jsams.2024.07.018 | R75: 10.1016/j.jsams.2024.07.018 | T75: 1 | U75: 10.1016--j.jsams.2024.07.018.pdf | V75: Replication | W75: {=HYPERLINK(INDEX('File Links'!B:B, MATCH(U75, 'File Links'!C:C, 0)))} -> https://drive.google.com/file/d/1iWxdhqxc4T6twXLJR2WbGMzAHqB2cMPh/view?usp=drivesdk | X75: Not replicated | Y75: Science and Medicine in Sport | Z75: maximal anaerobic fatigue | AA75: Dynamic postural control, Dynamic balance, Y-Balance Test, Fatigue | AB75: Dynamic postural control for PM returned to pre-fatigue level with less | AC75: "The anterior reach direction returned to pre-fatigue levels within 10 min (p = 0.632). The posteromedial reach direction returned to pre-fatigue levels within 20 min (p = 0.236), while the posterolateral direction maintained a statistically significant difference at 20 min (p = 0.023)" | AD75: p. 1, 4 | AE75: 20 | AI75: 0.236 | AJ75: e (=) | AK75: NA (not reported) | AL75: no | AY75: LR, Sophie
A76: awaiting validation | B76: double | C76: Husnain | E76: additional_studies125_1 | F76: additional_studies125_f | G76: Husnain | H76: 45636 | I76: 45679 | J76: 1. In the orignal study, I have used claims from the page 1 because they were well summarised. However, I have reported results seprately for effect size and P value | L76: Johnston, W., Dolan, K., Reid, N., Coughlan, G. F., & Caulfield, B. (2018). Investigating the effects of maximal anaerobic fatigue on dynamic postural control using the Y-Balance Test. Journal of science and medicine in sport, 21(1), 103-108. https://doi.org/10.1016/j.jsams.2017.06.012 | M76: 10.1016/j.jsams.2017.06.007 | N76: 1 | O76: 10.1016--j.jsams.2017.06.007.pdf | P76: {=HYPERLINK(INDEX('File Links'!B:B, MATCH(O76, 'File Links'!C:C, 0)))} -> https://drive.google.com/file/d/1bOamtHkDDCeR5rldqOBSgCXc_AFZb3yD/view?usp=drivesdk | Q76: Byrne, C., Murphy, J., & Warne, J. P. (2024). Replication Study: Investigating the effects of maximal anaerobic fatigue on dynamic postural control using the Y-Balance Test. Journal of Science and Medicine in Sport. https://doi.org/10.1016/j.jsams.2024.07.018 | R76: 10.1016/j.jsams.2024.07.018 | T76: 1 | U76: 10.1016--j.jsams.2024.07.018.pdf | V76: Replication | W76: {=HYPERLINK(INDEX('File Links'!B:B, MATCH(U76, 'File Links'!C:C, 0)))} -> https://drive.google.com/file/d/1iWxdhqxc4T6twXLJR2WbGMzAHqB2cMPh/view?usp=drivesdk | X76: Not replicated | Y76: Science and Medicine in Sport | Z76: maximal anaerobic fatigue | AA76: Dynamic postural control, Dynamic balance, Y-Balance Test, Fatigue | AB76: Dynamic postural control for PL returned to pre-fatigue level with most | AC76: "The anterior reach direction returned to pre-fatigue levels within 10 min (p = 0.632). The posteromedial reach direction returned to pre-fatigue levels within 20 min (p = 0.236), while the posterolateral direction maintained a statistically significant difference at 20 min (p = 0.023)" | AD76: p. 1, 4 | AE76: 20 | AI76: 0.023 | AJ76: e (=) | AK76: NA (not reported) | AL76: no | AY76: LR, Sophie
A77: awaiting validation | B77: double | C77: Husnain | E77: additional_studies125_1 | F77: additional_studies125_g | G77: Husnain | H77: 45636 | I77: 45679 | J77: 1. In the orignal study, I have used claims from the page 1 because they were well summarised. However, I have reported results seprately for effect size and P value | L77: Johnston, W., Dolan, K., Reid, N., Coughlan, G. F., & Caulfield, B. (2018). Investigating the effects of maximal anaerobic fatigue on dynamic postural control using the Y-Balance Test. Journal of science and medicine in sport, 21(1), 103-108. https://doi.org/10.1016/j.jsams.2017.06.013 | M77: 10.1016/j.jsams.2017.06.007 | N77: 1 | O77: 10.1016--j.jsams.2017.06.007.pdf | P77: {=HYPERLINK(INDEX('File Links'!B:B, MATCH(O77, 'File Links'!C:C, 0)))} -> https://drive.google.com/file/d/1bOamtHkDDCeR5rldqOBSgCXc_AFZb3yD/view?usp=drivesdk | Q77: Byrne, C., Murphy, J., & Warne, J. P. (2024). Replication Study: Investigating the effects of maximal anaerobic fatigue on dynamic postural control using the Y-Balance Test. Journal of Science and Medicine in Sport. https://doi.org/10.1016/j.jsams.2024.07.018 | R77: 10.1016/j.jsams.2024.07.018 | T77: 1 | U77: 10.1016--j.jsams.2024.07.018.pdf | V77: Replication | W77: {=HYPERLINK(INDEX('File Links'!B:B, MATCH(U77, 'File Links'!C:C, 0)))} -> https://drive.google.com/file/d/1iWxdhqxc4T6twXLJR2WbGMzAHqB2cMPh/view?usp=drivesdk | X77: Not replicated | Y77: Science and Medicine in Sport | Z77: maximal anaerobic fatigue | AA77: Dynamic postural control, Dynamic balance, Y-Balance Test, Fatigue | AB77: Intraclass correlation coefficients for the Y-Balance Test indicate good intra-session reliability for ANT | AD77: p. 1, 4 | AE77: 20 | AK77: NA (not reported) | AL77: no | AY77: LR, Sophie
A78: awaiting validation | B78: double | C78: Husnain | E78: additional_studies125_1 | F78: additional_studies125_h | G78: Husnain | H78: 45636 | I78: 45679 | J78: 1. In the orignal study, I have used claims from the page 1 because they were well summarised. However, I have reported results seprately for effect size and P value | L78: Johnston, W., Dolan, K., Reid, N., Coughlan, G. F., & Caulfield, B. (2018). Investigating the effects of maximal anaerobic fatigue on dynamic postural control using the Y-Balance Test. Journal of science and medicine in sport, 21(1), 103-108. https://doi.org/10.1016/j.jsams.2017.06.014 | M78: 10.1016/j.jsams.2017.06.007 | N78: 1 | O78: 10.1016--j.jsams.2017.06.007.pdf | P78: {=HYPERLINK(INDEX('File Links'!B:B, MATCH(O78, 'File Links'!C:C, 0)))} -> https://drive.google.com/file/d/1bOamtHkDDCeR5rldqOBSgCXc_AFZb3yD/view?usp=drivesdk | Q78: Byrne, C., Murphy, J., & Warne, J. P. (2024). Replication Study: Investigating the effects of maximal anaerobic fatigue on dynamic postural control using the Y-Balance Test. Journal of Science and Medicine in Sport. https://doi.org/10.1016/j.jsams.2024.07.018 | R78: 10.1016/j.jsams.2024.07.018 | T78: 1 | U78: 10.1016--j.jsams.2024.07.018.pdf | V78: Replication | W78: {=HYPERLINK(INDEX('File Links'!B:B, MATCH(U78, 'File Links'!C:C, 0)))} -> https://drive.google.com/file/d/1iWxdhqxc4T6twXLJR2WbGMzAHqB2cMPh/view?usp=drivesdk | X78: Not replicated | Y78: Science and Medicine in Sport | Z78: maximal anaerobic fatigue | AA78: Dynamic postural control, Dynamic balance, Y-Balance Test, Fatigue | AB78: Intraclass correlation coefficients for the Y-Balance Test indicate best intra-session reliability for PM | AD78: p. 1, 4 | AE78: 20 | AK78: NA (not reported) | AL78: no | AY78: LR, Sophie
A79: awaiting validation | B79: double | C79: Husnain | E79: additional_studies125_1 | F79: additional_studies125_i | G79: Husnain | H79: 45636 | I79: 45679 | J79: 1. In the orignal study, I have used claims from the page 1 because they were well summarised. However, I have reported results seprately for effect size and P value | L79: Johnston, W., Dolan, K., Reid, N., Coughlan, G. F., & Caulfield, B. (2018). Investigating the effects of maximal anaerobic fatigue on dynamic postural control using the Y-Balance Test. Journal of science and medicine in sport, 21(1), 103-108. https://doi.org/10.1016/j.jsams.2017.06.015 | M79: 10.1016/j.jsams.2017.06.007 | N79: 1 | O79: 10.1016--j.jsams.2017.06.007.pdf | P79: {=HYPERLINK(INDEX('File Links'!B:B, MATCH(O79, 'File Links'!C:C, 0)))} -> https://drive.google.com/file/d/1bOamtHkDDCeR5rldqOBSgCXc_AFZb3yD/view?usp=drivesdk | Q79: Byrne, C., Murphy, J., & Warne, J. P. (2024). Replication Study: Investigating the effects of maximal anaerobic fatigue on dynamic postural control using the Y-Balance Test. Journal of Science and Medicine in Sport. https://doi.org/10.1016/j.jsams.2024.07.018 | R79: 10.1016/j.jsams.2024.07.018 | T79: 1 | U79: 10.1016--j.jsams.2024.07.018.pdf | V79: Replication | W79: {=HYPERLINK(INDEX('File Links'!B:B, MATCH(U79, 'File Links'!C:C, 0)))} -> https://drive.google.com/file/d/1iWxdhqxc4T6twXLJR2WbGMzAHqB2cMPh/view?usp=drivesdk | X79: Not replicated | Y79: Science and Medicine in Sport | Z79: maximal anaerobic fatigue | AA79: Dynamic postural control, Dynamic balance, Y-Balance Test, Fatigue | AB79: Intraclass correlation coefficients for the Y-Balance Test indicate least intra-session reliability PL | AD79: p. 1, 4 | AE79: 20 | AK79: NA (not reported) | AL79: no | AY79: LR, Sophie
A80: awaiting validation | B80: double | C80: Nikita | E80: additional_studies125_1 | F80: additional_studies125_pl | G80: Nikita | H80: 45638 | I80: 45679 | J80: 1. The initial registration of the protocol is under the link: https://osf.io/kqdpm 2. Since one-way rmANOVA was used, the Nested option is "Yes" 3. Degree of freedon for original study was calculated based on number of time measurements (4) and participants (20) | L80: Johnston, W., Dolan, K., Reid, N., Coughlan, G. F., & Caulfield, B. (2018). Investigating the effects of maximal anaerobic fatigue on dynamic postural control using the Y-Balance Test. Journal of science and medicine in sport, 21(1), 103-108. https://doi.org/10.1016/j.jsams.2017.06.007 | M80: 10.1016/j.jsams.2017.06.007 | N80: 1 | O80: 10.1016--j.jsams.2017.06.007.pdf | P80: {=HYPERLINK(INDEX('File Links'!B:B, MATCH(O80, 'File Links'!C:C, 0)))} -> https://drive.google.com/file/d/1bOamtHkDDCeR5rldqOBSgCXc_AFZb3yD/view?usp=drivesdk | Q80: Byrne, C., Murphy, J., & Warne, J. P. (2024). Replication Study: Investigating the effects of maximal anaerobic fatigue on dynamic postural control using the Y-Balance Test. Journal of Science and Medicine in Sport. https://doi.org/10.1016/j.jsams.2024.07.018 | R80: 10.1016/j.jsams.2024.07.018 | T80: 1 | U80: 10.1016--j.jsams.2024.07.018.pdf | V80: Replication | W80: {=HYPERLINK(INDEX('File Links'!B:B, MATCH(U80, 'File Links'!C:C, 0)))} -> https://drive.google.com/file/d/1iWxdhqxc4T6twXLJR2WbGMzAHqB2cMPh/view?usp=drivesdk | Y80: Medicine | Z80: Dynamic postural control | AA80: Dynamic postural control, Dynamic balance, Y-Balance Test, Fatigue, Replication, Balance, Anterior reach direction, Posterolateral reach direction, Posteromedial reach direction | AB80: Investigating the effects of maximal anaerobic fatigue on dynamic postural control with Y Balance test by comparing pre-fatigue and post-fatigue (0, 10, 20 min) in posteromedial direction | AC80: "The posteromedial reach direction was approaching significance (F = 2.215, p = 0.059)." | AD80: 3 | AE80: 20 | AF80: F(3, 57) = 2.215 | AG80: test statistic | AH80: p.3 | AI80: 0.059 | AJ80: e (=) | AK80: 1 (one) | AL80: yes | AN80: 39 | AO80: 0.052 | AP80: etasq | AQ80: p.4 | AR80: 0.122 | AS80: e (=) | AT80: NA (not reported) | AU80: no | AV80: https://osf.io/5beqa | AW80: 2 - close | AX80: - do not code tests as one-tailed unless it is explicitly said in the text (eg "one-tailed) | AY80: LR, Sophie
A81: validated - chosen | B81: double | C81: Nikita | E81: additional_studies125_1 | F81: additional_studies125_pm | G81: Nikita | H81: 45638 | I81: 45679 | J81: 1. The initial registration of the protocol is under the link: https://osf.io/kqdpm 2. Since one-way rmANOVA was used, the Nested option is "Yes" 3. Degree of freedon for original study was calculated based on number of time measurements (4) and participants (20) | K81: the values from the replication study that were put in are from a different finding, not replicating reach distance but reach direction | L81: Johnston, W., Dolan, K., Reid, N., Coughlan, G. F., & Caulfield, B. (2018). Investigating the effects of maximal anaerobic fatigue on dynamic postural control using the Y-Balance Test. Journal of science and medicine in sport, 21(1), 103-108. https://doi.org/10.1016/j.jsams.2017.06.007 | M81: 10.1016/j.jsams.2017.06.007 | N81: 1 | O81: 10.1016--j.jsams.2017.06.007.pdf | P81: {=HYPERLINK(INDEX('File Links'!B:B, MATCH(O81, 'File Links'!C:C, 0)))} -> https://drive.google.com/file/d/1bOamtHkDDCeR5rldqOBSgCXc_AFZb3yD/view?usp=drivesdk | Q81: Byrne, C., Murphy, J., & Warne, J. P. (2024). Replication Study: Investigating the effects of maximal anaerobic fatigue on dynamic postural control using the Y-Balance Test. Journal of Science and Medicine in Sport. https://doi.org/10.1016/j.jsams.2024.07.018 | R81: 10.1016/j.jsams.2024.07.018 | T81: 1 | U81: 10.1016--j.jsams.2024.07.018.pdf | V81: Replication | W81: {=HYPERLINK(INDEX('File Links'!B:B, MATCH(U81, 'File Links'!C:C, 0)))} -> https://drive.google.com/file/d/1iWxdhqxc4T6twXLJR2WbGMzAHqB2cMPh/view?usp=drivesdk | Y81: Medicine | Z81: Dynamic postural control | AA81: Dynamic postural control, Dynamic balance, Y-Balance Test, Fatigue, Replication, Balance, Anterior reach direction, Posterolateral reach direction, Posteromedial reach direction | AB81: Investigating the effects of maximal anaerobic fatigue on dynamic postural control with Y Balance test by comparing pre-fatigue and post-fatigue (0, 10, 20 min) in posterolateral direction | AC81: "A repeated measures ANOVA with a Greenhouse-Geisser correction determined that the mean reach distances for the posterolateral (F = 6.503, P = 0.0004) reach directions were statistically significantly different between time points." | AD81: 3 | AE81: 20 | AF81: F(3, 57) = 6.503 | AG81: test statistic | AH81: p. 3 | AI81: 0.0004 | AJ81: e (=) | AK81: 1 (one) | AL81: yes | AN81: 39 | AO81: 0.054 | AP81: etasq | AQ81: p.4 | AR81: 0.11 | AS81: e (=) | AT81: NA (not reported) | AU81: no | AV81: https://osf.io/5beqa | AW81: 2 - close | AY81: LR, Sophie
A82: validated - discarded | B82: double | C82: Alexsandr | E82: additional_studies13_1 | F82: additional_studies13 | G82: Aleksandr Pravednikov | H82: 45427 | I82: 45626 | J82: This is not a replication: original study relied on testing and neuropsychological performance (Visual Reproductions immediate recall/ Visual Reproductions delayed recall/ Verbal Paired Associates I /Verbal Paired Associates II/ Simple Reaction Time efficiency / Continuous Performance/ Test omissions) while newer one based on the APOE ε4 and ε2 presence in the brain. I extracted results, but didn't extract precise statistics. Claim text_r. Combat by APOE ε4. Table 2 shows the associations between PTSD symptom severity and combat exposure and covariates (age and sex; ancestry substructure PCs were also included in the model but are not shown in the table for simplicity) in each age group and ancestry cohort. As expected, PTSD severity was strongly associated with combat exposure. It was also negatively associated with age in the middle-age and old-age cohorts, but age was positively associated with PTSD in the young age group. Sex was not significantly related to PTSD severity, but this may be due to low power as the sample was primarily male. Table 2 also shows the main and interactive effects of combat and APOE ε4 on PTSD severity. There were no main effects of APOE ε4 on current PTSD severity in any of the cohorts (P > 0.07). There were no combat by APOE ε4 interactions in any of the age or ancestry cohorts (P ≥ 0.18). Head injury by APOE ε4. We next examined the potential role of head injury in place of combat in the APOE ε4 interaction models. Head injury was associated with current PTSD severity in every age group in both the AA and EUR cohorts (P ≤ 6.03 10–13; Table 2). There was one nominally significant interaction for head injury by ε4 in the young AA cohort (P = 0.042); however, this did not survive a multiple testing correction. [...] p.555 | L82: Vasterling, J. J., Aslan, M., Lee, L. O., Proctor, S. P., Ko, J., Jacob, S., & Concato, J. (2018). Longitudinal Associations among Posttraumatic Stress Disorder Symptoms, Traumatic Brain Injury, and Neurocognitive Functioning in Army Soldiers Deployed to the Iraq War. Journal of the International Neuropsychological Society, 24(4), 311–323. doi:10.1017/S1355617717001059 | M82: 10.1017/S1355617717001059 | O82: =hyperlink(vlookup(lower(M82),'File Links'!A:B, 2, FALSE), SUBSTITUTE(lower(M82), "/", "--") & ".pdf") -> 10.1017--s1355617717001059.pdf | P82: {=HYPERLINK(INDEX('File Links'!B:B, MATCH(O82, 'File Links'!C:C, 0)))} -> https://drive.google.com/file/d/1EKnIsw-dolmmk1-6Kle0hKb5-wtcqfmw/view?usp=drivesdk | Q82: Wolf, E. J., Miller, M. W., Zhang, R., Sherva, R., Harrington, K. M., Fonda, J. R., ... & Logue, M. W. (2024). No replication of Alzheimer’s disease genetics as a moderator of the association between combat exposure and PTSD risk in 138,592 combat veterans. Nature Mental Health, 1-9. https://doi.org/10.1038/s44220-024-00225-1 | R82: 10.1038/s44220-024-00225-1 | U82: =hyperlink(vlookup(lower(R82),'File Links'!E:F, 2, FALSE), SUBSTITUTE(lower(R82), "/", "--") & ".pdf") -> 10.1038--s44220-024-00225-1.pdf | W82: {=HYPERLINK(INDEX('File Links'!B:B, MATCH(U82, 'File Links'!C:C, 0)))} -> #N/A | X82: original study relied on testing and neuropsychological performance (Visual Reproductions immediate recall/ Visual Reproductions delayed recall/ Verbal Paired Associates I /Verbal Paired Associates II/ Simple Reaction Time efficiency / Continuous Performance/ Test omissions) while newer one based on the APOE ε4 and ε2 presence in the brain. I extracted results, but didn't extract precise statistics. | Y82: Medicine | AA82: Hypothesis 1, 2, 3 | AB82: Alzheimer’s disease genetics as a moderator of the association between combat exposure and PTSD risk | AC82: Results: Autoregressive analyses indicated that visual reproduction scores were inversely related to subsequent PTSD symptom severity at subsequent assessments. Conversely, increases in PTSD symptom severity over each measurement interval were associated with poorer verbal and/or visual recall at the end of each interval, and less efficient reaction time at post-deployment. TBI, primarily mild in this sample, was associated with adverse PTSD symptom outcomes at both post-deployment and long-term follow-up. [...] Table 3,4, and 5 | AD82: 1, 6, 7, 8, 9 | AE82: 272 | AW82: NA: unknown
A83: validated - discarded | B83: double | C83: Daniel | E83: additional_studies13_1 | F83: additional_studies13 | G83: Daniel Manrique-Castano | H83: 45427 | I83: 45684 | J83: The replication study is not a true replication of the original study. The replication study performs an analysis of APOE ε4 and ε2 genes (an Alzheimer’s disease polygenic risk score) in post-traumatic stress. The original study does not deal with this. Instead, it investigates the associations among PTSD, neurocognitive performance, and TBI following military deployment. | L83: Vasterling, J. J., Aslan, M., Lee, L. O., Proctor, S. P., Ko, J., Jacob, S., & Concato, J. (2018). Longitudinal Associations among Posttraumatic Stress Disorder Symptoms, Traumatic Brain Injury, and Neurocognitive Functioning in Army Soldiers Deployed to the Iraq War. Journal of the International Neuropsychological Society, 24(4), 311–323. doi:10.1017/S1355617717001059 | M83: 10.1017/S1355617717001059 | O83: 10.1017--s1355617717001059.pdf | P83: {=HYPERLINK(INDEX('File Links'!B:B, MATCH(O83, 'File Links'!C:C, 0)))} -> https://drive.google.com/file/d/1EKnIsw-dolmmk1-6Kle0hKb5-wtcqfmw/view?usp=drivesdk | Q83: Wolf, E. J., Miller, M. W., Zhang, R., Sherva, R., Harrington, K. M., Fonda, J. R., ... & Logue, M. W. (2024). No replication of Alzheimer’s disease genetics as a moderator of the association between combat exposure and PTSD risk in 138,592 combat veterans. Nature Mental Health, 1-9. https://doi.org/10.1038/s44220-024-00225-1 | U83: .pdf | W83: {=HYPERLINK(INDEX('File Links'!B:B, MATCH(U83, 'File Links'!C:C, 0)))} -> #N/A | X83: original study relied on testing and neuropsychological performance (Visual Reproductions immediate recall/ Visual Reproductions delayed recall/ Verbal Paired Associates I /Verbal Paired Associates II/ Simple Reaction Time efficiency / Continuous Performance/ Test omissions) while newer one based on the APOE ε4 and ε2 presence in the brain. I extracted results, but didn't extract precise statistics. | Y83: Cognitive Psychology
A84: awaiting validation | B84: double | C84: Alexsandr | E84: additional_studies14_1 | F84: additional_studies14 | G84: Aleksandr Pravednikov | H84: 45427 | I84: 45626 | J84: Claim text_r. Hypothesis testing. Table 5 and Fig. 4 show the Cramer’s V correlations between the covariates and the selected media collection. The variance stems from the 60 different parameter combinations tested. According to Cohen [41, 42], a correlation of 0.5 is high, 0.3 is medium, and 0.1 is small1. Hence, our results show a high correlation between the supervisor and the choice of media collection, but only a small correlation between the supervisor’s own choice of media collection and the worker’s choice. Consequently, the hypothesis on the supervisor’s social influence holds (H1a), whereas its particularization in the imitation hypothesis (H1b) does not hold. As coworkers and physical location show a small correlation with the media collection choice, the hypothesis about the coworkers’ social influence does not hold (H2), whereas the negligible association with the physical association does hold (H3). [...] p.9 | L84: Watson-Manheim, M. B., & Bélanger, F. (2007). Communication media repertoires: Dealing with the multiplicity of media choices. MIS quarterly, 267-293. https://doi.org/10.2307/25148791 | M84: 10.2307/25148791 | O84: =hyperlink(vlookup(lower(M84),'File Links'!A:B, 2, FALSE), SUBSTITUTE(lower(M84), "/", "--") & ".pdf") -> 10.2307--25148791.pdf | P84: {=HYPERLINK(INDEX('File Links'!B:B, MATCH(O84, 'File Links'!C:C, 0)))} -> https://drive.google.com/file/d/1R2VrRXYyejGfSg11kpe_vHbQr5DvYbiJ/view?usp=drivesdk | Q84: Hüllmann, J. A., & Krebber, S. (2021). Replication Study: Investigating Media Choice and Types of Media Collections of Distributed Workers Using Digital Traces. Available at SSRN 3816626. http://dx.doi.org/10.2139/ssrn.3816626 | R84: 10.2139/ssrn.3816626 | U84: =hyperlink(vlookup(lower(R84),'File Links'!E:F, 2, FALSE), SUBSTITUTE(lower(R84), "/", "--") & ".pdf") -> 10.2139--ssrn.3816626.pdf | W84: {=HYPERLINK(INDEX('File Links'!B:B, MATCH(U84, 'File Links'!C:C, 0)))} -> #N/A | X84: Even though theoretically relevant aspects of the studies are the same, the original study relied on qualitative methodology, hence there is no quantitative data to compare the studies. | Y84: Communication Science | AB84: Media Choice and Types of Media Collections | AW84: extension
A85: awaiting validation | B85: double | C85: Daniel | E85: additional_studies14_1 | F85: additional_studies14 | G85: Daniel Manrique-Castano | H85: 45427 | I85: 45684 | J85: The replication article is related to the original article. However, I do not believe that we can report a quantitative replication attempt. Although the original research article reports some rounded percentages for the use of communication media, I believe that this is a way of illustrating the qualitative information they present in the original research article. This is not comparable to the approach taken in the replication attempts. In other words, replication is a quantitative approach to replicating an original qualitative approach. | L85: Watson-Manheim, M. B., & Bélanger, F. (2007). Communication media repertoires: Dealing with the multiplicity of media choices. MIS quarterly, 267-293. https://doi.org/10.2307/25148791 | M85: 10.2307/25148791 | O85: 10.2307--25148791.pdf | P85: {=HYPERLINK(INDEX('File Links'!B:B, MATCH(O85, 'File Links'!C:C, 0)))} -> https://drive.google.com/file/d/1R2VrRXYyejGfSg11kpe_vHbQr5DvYbiJ/view?usp=drivesdk | Q85: Hüllmann, J. A., & Krebber, S. (2021). Replication Study: Investigating Media Choice and Types of Media Collections of Distributed Workers Using Digital Traces. Available at SSRN 3816626. http://dx.doi.org/10.2139/ssrn.3816626 | U85: .pdf | W85: {=HYPERLINK(INDEX('File Links'!B:B, MATCH(U85, 'File Links'!C:C, 0)))} -> #N/A | Y85: Communication Science
A86: help needed | B86: double | C86: Antony | E86: additional_studies15_1 | F86: additional_studies15 | G86: Antony Casula | H86: 45636 | I86: 45680 | K86: sample size unclear | L86: Gettinger, M., Kratochwill, T. R., Eubanks, A., Foy, A., & Levin, J. R. (2021). Academic and behavior combined support: Evaluation of an integrated supplemental intervention for early elementary students. Journal of School Psychology, 89, 1-19. https://doi.org/10.1016/j.jsp.2021.09.004 | M86: 10.1016/j.jsp.2021.09.004 | O86: 10.1016--j.jsp.2021.09.004.pdf | P86: {=HYPERLINK(INDEX('File Links'!B:B, MATCH(O86, 'File Links'!C:C, 0)))} -> https://drive.google.com/file/d/1RTiaFppoyqVSbs6ENCjo8xyaIVfjFhVI/view?usp=drivesdk | Q86: Gettinger, M., Kratochwill, T. R., Levin, J. R., Eubanks, A., & Foy, A. (2024). Academic and behavior combined support: A single-case practice-based replication study. Journal of School Psychology, 104, 101307. https://doi.org/10.1016/j.jsp.2024.101307 | R86: 10.1016/j.jsp.2024.101307 | U86: 10.1016--j.jsp.2024.101307.pdf | V86: Replication | W86: {=HYPERLINK(INDEX('File Links'!B:B, MATCH(U86, 'File Links'!C:C, 0)))} -> https://drive.google.com/file/d/1VAdnhoiJmdHbv1LbvyIfcfg3rNALrpkj/view?usp=drivesdk | Y86: Education | AA86: Academic and Behavior Combined Support, integrated supplemental intervention , Oral reading fluency outcomes, engaged behavior, disruptive behavior | AB86: "..integrated supplemental intervention for early elementary students [...] (produces) significant improvement from baseline to intervention for both reading and behavior outcomes." | AC86: "A randomization test conducted on these data revealed a statistically significant change in level across students following the introduction of the intervention (p = .001), from a baseline mean of 60.0 WCPM to an intervention mean of 91.2." | AD86: 25 | AE86: 6 | AF86: 1.21 | AG86: hedges' g | AH86: p.24-25 | AI86: 0.006 | AJ86: e (=) | AK86: NA (not reported) | AL86: yes | AN86: 4 | AO86: 2.06 | AP86: hedges' g | AQ86: p.8 | AR86: 0.25 | AS86: e (=) | AT86: NA (not reported) | AU86: yes | AW86: 1 - internal | AX86: The claim does not fit to the reported d, d should be 2.8 for this case | AY86: LR
A87: help needed | B87: double | C87: Fabienne | E87: additional_studies15_1 | F87: additional_studies15 | G87: Julia Fabienne Sandkühler | H87: 45639 | I87: 45680 | J87: Did not include followup, which is present in replication but not the original. | K87: sample size unclear | L87: Gettinger, M., Kratochwill, T. R., Eubanks, A., Foy, A., & Levin, J. R. (2021). Academic and behavior combined support: Evaluation of an integrated supplemental intervention for early elementary students. Journal of School Psychology, 89, 1-19. https://doi.org/10.1016/j.jsp.2021.09.004 | M87: 10.1016/j.jsp.2021.09.004 | O87: 10.1016--j.jsp.2021.09.004.pdf | P87: {=HYPERLINK(INDEX('File Links'!B:B, MATCH(O87, 'File Links'!C:C, 0)))} -> https://drive.google.com/file/d/1RTiaFppoyqVSbs6ENCjo8xyaIVfjFhVI/view?usp=drivesdk | Q87: Gettinger, M., Kratochwill, T. R., Levin, J. R., Eubanks, A., & Foy, A. (2024). Academic and behavior combined support: A single-case practice-based replication study. Journal of School Psychology, 104, 101307. https://doi.org/10.1016/j.jsp.2024.101307 | R87: 10.1016/j.jsp.2024.101307 | U87: .pdf | V87: "Replication" in title | W87: {=HYPERLINK(INDEX('File Links'!B:B, MATCH(U87, 'File Links'!C:C, 0)))} -> #N/A | Y87: Education | AA87: Supplemental support, Oral reading fluency, Engagement | AB87: Academic and Behavior Combined Support (ABC Support) | AC87: "Visual and statistical analyses revealed significant improvement from baseline to intervention for both reading and (...) outcomes.", Reading outcome, STANDARD reading passages: "The visual analysis was supported by a multiple-baseline randomization test that yielded a statistically significant increase in WCPM from baseline (M = 59.3) to intervention (M = 72.0), p = .006. The average effect-size d was 1.33, with an associated g of 1.21 and adjusted NAP of 0.57." | AD87: 1 and 12 | AE87: 6 | AF87: 1.33 | AG87: d | AH87: p. 12 | AI87: 0.006 | AJ87: e (=) | AK87: NA (not reported) | AM87: NA | AN87: 4 | AO87: 2.06 | AP87: hedges' g | AQ87: p. 8 | AR87: 0.25 | AS87: e (=) | AT87: NA (not reported) | AV87: NA | AW87: 1 - internal | AX87: Please only provide a numer for N (you wrote 1 and 12) and if you cannot, write an explanation into the notes variable or explain where it comes from. | AY87: LR
A88: help needed | B88: double | C88: Antony | E88: additional_studies15_1 | F88: additional_studies15_b | G88: Antony Casula | H88: 45636 | I88: 45680 | J88: Follow up (2 to 5 weeks after intervention) of preceding row's effect (compared to baseline-pre intervention) | K88: sample size unclear | L88: Gettinger, M., Kratochwill, T. R., Eubanks, A., Foy, A., & Levin, J. R. (2021). Academic and behavior combined support: Evaluation of an integrated supplemental intervention for early elementary students. Journal of School Psychology, 89, 1-19. https://doi.org/10.1016/j.jsp.2021.09.004 | M88: 10.1016/j.jsp.2021.09.004 | O88: 10.1016--j.jsp.2021.09.004.pdf | P88: {=HYPERLINK(INDEX('File Links'!B:B, MATCH(O88, 'File Links'!C:C, 0)))} -> https://drive.google.com/file/d/1RTiaFppoyqVSbs6ENCjo8xyaIVfjFhVI/view?usp=drivesdk | Q88: Gettinger, M., Kratochwill, T. R., Levin, J. R., Eubanks, A., & Foy, A. (2024). Academic and behavior combined support: A single-case practice-based replication study. Journal of School Psychology, 104, 101307. https://doi.org/10.1016/j.jsp.2024.101307 | R88: 10.1016/j.jsp.2024.101307 | U88: 10.1016--j.jsp.2024.101307.pdf | V88: Replication | W88: {=HYPERLINK(INDEX('File Links'!B:B, MATCH(U88, 'File Links'!C:C, 0)))} -> https://drive.google.com/file/d/1VAdnhoiJmdHbv1LbvyIfcfg3rNALrpkj/view?usp=drivesdk | Y88: Education | AA88: Academic and Behavior Combined Support, integrated supplemental intervention , Oral reading fluency outcomes, engaged behavior, disruptive behavior | AB88: "..integrated supplemental intervention for early elementary students [...] (produces) significant improvement from baseline to intervention for both reading and behavior outcomes." | AC88: "A randomization test conducted on these data revealed a statistically significant change in level across students following the introduction of the intervention (p = .001), from a baseline mean of 60.0 WCPM to an intervention mean of 91.2." | AD88: 25 | AE88: 6 | AF88: 1.21 | AG88: hedges' g | AH88: p.24-25 | AI88: 0.006 | AJ88: e (=) | AK88: NA (not reported) | AL88: yes | AN88: 4 | AO88: 1.5 | AP88: hedges' g | AQ88: p.8 | AR88: 0.042 | AS88: e (=) | AT88: NA (not reported) | AU88: yes | AW88: 1 - internal | AY88: LR
